Workbook

Sheet 01.2026
A1: Conta contábil | B1: Código Red. | C1: Descrição da Conta | D1: Saldo anterior | E1: Débito | F1: Crédito | G1: Movimento do Mês | H1: Saldo Atual
A2: 1 | C2: ATIVO | D2: 5330654 | E2: 2385665.3 | F2: 2788249.5 | H2: 4928069.7
A3: 1.1 | C3: ATIVO CIRCULANTE | D3: 2183243.4 | E3: 2201940.8 | F3: 2598441.2 | H3: 1786743
A4: 1.1.01 | C4: DISPONÍVEL | D4: 22157 | E4: 1411427.7 | F4: 1427037.4 | H4: 6547.21
A5: 1.1.01.01 | C5: CAIXA | D5: 0 | E5: 150694.49 | F5: 150694.49 | H5: 0
A6: 1.1.01.01.0010 | B6: 5 | C6: Entre Contas | D6: 0 | E6: 150694.49 | F6: 150694.49 | H6: 0
A7: 1.1.01.02 | C7: BANCOS CONTA MOVIMENTO | D7: 18003.95 | E7: 1260733.2 | F7: 1272189.9 | H7: 6547.21
A8: 1.1.01.02.0001 | B8: 27 | C8: Banco Itaú | D8: 1 | E8: 1076581.6 | F8: 1076582.6 | H8: 0
A9: 1.1.01.02.0002 | B9: 576 | C9: Banco Pag Útil | D9: 0 | E9: 3194.49 | F9: 1834.58 | H9: 1359.91
A10: 1.1.01.02.0101 | B10: 5444 | C10: Mercado Pago - Banco Digital | D10: 4760.31 | E10: 549.21 | F10: 122.22 | H10: 5187.3
A11: 1.1.01.02.0102 | B11: 5860 | C11: Banco Bradesco | D11: 13242.64 | E11: 180407.88 | F11: 193650.52 | H11: 0
A12: 1.1.01.03 | C12: APLICAÇÕES FINANCEIRAS | D12: 4153.05 | E12: 0 | F12: 4153.05 | H12: 0
A13: 1.1.01.03.0001 | B13: 35 | C13: Aplicações Banco Itaú | D13: 4153.05 | E13: 0 | F13: 4153.05 | H13: 0
A14: 1.1.02 | C14: CONTAS A RECEBER | D14: 857471.45 | E14: 710212.13 | F14: 953371.47 | H14: 614312.11
A15: 1.1.02.01 | C15: CLIENTES NACIONAIS | D15: 857471.45 | E15: 710212.13 | F15: 953371.47 | H15: 614312.11
A16: 1.1.02.01.0001 | B16: 43 | C16: Clientes Nacionais | D16: 513164.42 | E16: 651228.61 | F16: 765371.47 | H16: 399021.56
A17: 1.1.02.01.0002 | B17: 5347 | C17: Clientes B2B | D17: 344307.03 | E17: 58983.52 | F17: 188000 | H17: 215290.55
A18: 1.1.03 | C18: OUTROS CRÉDITOS | D18: 350507.25 | E18: 53317.65 | F18: 55870.19 | H18: 347954.71
A19: 1.1.03.01 | C19: CRÉDITOS DE FUNCIONÁRIOS | D19: 6071.56 | E19: 34747.35 | F19: 37600.01 | H19: 3218.9
A20: 1.1.03.01.0002 | B20: 60 | C20: Adiantamento de Férias | D20: 6071.56 | E20: 2972.89 | F20: 5825.55 | H20: 3218.9
A21: 1.1.03.01.0003 | B21: 3263 | C21: Adiantamento de Salários | D21: 0 | E21: 31774.46 | F21: 31774.46 | H21: 0
A22: 1.1.03.02 | C22: ADIANTAMENTO A FORNECEDORES | D22: 147010.2 | E22: 0 | F22: 0 | H22: 147010.2
A23: 1.1.03.02.0001 | B23: 3220 | C23: Adiantamento a Fornecedores | D23: 147010.2 | E23: 0 | F23: 0 | H23: 147010.2
A24: 1.1.03.03 | C24: OUTROS CREDITOS A RECEBER | D24: 126211.51 | E24: 0 | F24: 0 | H24: 126211.51
A25: 1.1.03.03.0001 | B25: 5789 | C25: Outros Creditos a Receber | D25: 126211.51 | E25: 0 | F25: 0 | H25: 126211.51
A26: 1.1.03.05 | C26: IMPOSTOS A RECUPERAR | D26: 7120.88 | E26: 18570.3 | F26: 18270.18 | H26: 7421
A27: 1.1.03.05.0003 | B27: 116 | C27: ICMS a Recuperar | D27: 0 | E27: 18570.3 | F27: 18270.18 | H27: 300.12
A28: 1.1.03.05.0008 | B28: 5274 | C28: ICMS Difal a Recuperar | D28: 7120.88 | E28: 0 | F28: 0 | H28: 7120.88
A29: 1.1.03.06 | C29: TRIBUTOS A COMPENSAR | D29: 64093.1 | E29: 0 | F29: 0 | H29: 64093.1
A30: 1.1.03.06.0003 | B30: 4502 | C30: Saldo Negativo IRPJ | D30: 13.87 | E30: 0 | F30: 0 | H30: 13.87
A31: 1.1.03.06.0004 | B31: 4510 | C31: CSLL a Compensar | D31: 34627.34 | E31: 0 | F31: 0 | H31: 34627.34
A32: 1.1.03.06.0007 | B32: 4545 | C32: IRRF Aplicação | D32: 16.21 | E32: 0 | F32: 0 | H32: 16.21
A33: 1.1.03.06.0009 | B33: 4561 | C33: IRPJ a Compensar | D33: 29435.68 | E33: 0 | F33: 0 | H33: 29435.68
A34: 1.1.06 | C34: ESTOQUES | D34: 953107.73 | E34: 26983.33 | F34: 162162.06 | H34: 817929
A35: 1.1.06.01 | C35: ESTOQUES PARA REVENDA | D35: 953107.73 | E35: 26983.33 | F35: 162162.06 | H35: 817929
A36: 1.1.06.01.0001 | B36: 175 | C36: Mercadorias para Revenda | D36: 953107.73 | E36: 26983.33 | F36: 162162.06 | H36: 817929
A37: 1.2 | C37: ATIVO NÃO CIRCULANTE | D37: 3147410.6 | E37: 0 | F37: 6083.86 | H37: 3141326.7
A38: 1.2.01 | C38: ATIVO REALIZÁVEL A LONGO PRAZO | D38: 3022149 | E38: 0 | F38: 0 | H38: 3022149
A39: 1.2.01.05 | C39: CRÉDITOS A SÓCIOS | D39: 3022149 | E39: 0 | F39: 0 | H39: 3022149
A40: 1.2.01.05.0001 | B40: 3336 | C40: Mutuo Sócios | D40: 1224589.3 | E40: 0 | F40: 0 | H40: 1224589.3
A41: 1.2.01.05.0002 | B41: 3344 | C41: Débitos de Sócios | D41: 1797559.7 | E41: 0 | F41: 0 | H41: 1797559.7
A42: 1.2.03 | C42: ATIVO IMOBILIZADO | D42: 69663.17 | E42: 0 | F42: 1767.19 | H42: 67895.98
A43: 1.2.03.01 | C43: IMOBILIZADO | D43: 139435.51 | E43: 0 | F43: 0 | H43: 139435.51
A44: 1.2.03.01.0001 | B44: 205 | C44: Computadores e Periféricos | D44: 132597.82 | E44: 0 | F44: 0 | H44: 132597.82
A45: 1.2.03.01.0002 | B45: 4588 | C45: Equipamentos de Comunicação | D45: 4888.69 | E45: 0 | F45: 0 | H45: 4888.69
A46: 1.2.03.01.0005 | B46: 248 | C46: Móveis e Utensílios | D46: 1949 | E46: 0 | F46: 0 | H46: 1949
A47: 1.2.03.02 | C47: (-) DEPRECIAÇÃO/AMORTIZAÇÃO ACUMULADA | D47: -69772.34 | E47: 0 | F47: 1767.19 | H47: -71539.53
A48: 1.2.03.02.0001 | B48: 280 | C48: (-) Computadores e Periféricos | D48: -66138.73 | E48: 0 | F48: 1666.29 | H48: -67805.02
A49: 1.2.03.02.0002 | B49: 299 | C49: (-) Equipamentos de Comunicação | D49: -3471.21 | E49: 0 | F49: 84.66 | H49: -3555.87
A50: 1.2.03.02.0006 | B50: 329 | C50: (-) Móveis e Utensílios | D50: -162.4 | E50: 0 | F50: 16.24 | H50: -178.64
A51: 1.2.04 | C51: INTANGÍVEL | D51: 55598.42 | E51: 0 | F51: 4316.67 | H51: 51281.75
A52: 1.2.04.01 | C52: INTANGÍVEL | D52: 109099 | E52: 0 | F52: 0 | H52: 109099
A53: 1.2.04.01.0001 | B53: 2615 | C53: Marcas e Patentes | D53: 5499 | E53: 0 | F53: 0 | H53: 5499
A54: 1.2.04.01.0002 | B54: 3948 | C54: Software | D54: 103600 | E54: 0 | F54: 0 | H54: 103600
A55: 1.2.04.02 | C55: AMORTIZAÇÃO ACUMULADA | D55: -53500.58 | E55: 0 | F55: 4316.67 | H55: -57817.25
A56: 1.2.04.02.0001 | B56: 3964 | C56: (-) Software | D56: -53500.58 | E56: 0 | F56: 4316.67 | H56: -57817.25
A57: 1.9 | C57: REMESSAS DE MERCADORIAS | D57: 0 | E57: 183724.5 | F57: 183724.5 | H57: 0
A58: 1.9.01 | C58: SIMPLES REMESSA | D58: 0 | E58: 183724.5 | F58: 183724.5 | H58: 0
A59: 1.9.01.00.0001 | B59: 5881 | C59: Simples Remessa | D59: 0 | E59: 63929.27 | F59: 63929.27 | H59: 0
A60: 1.9.01.00.0002 | B60: 5883 | C60: Transferencia entre Filiais | D60: 0 | E60: 24219 | F60: 24219 | H60: 0
A61: 1.9.01.00.0003 | B61: 5886 | C61: Remessa de Bonificação | D61: 0 | E61: 95576.23 | F61: 95576.23 | H61: 0
A62: 2 | C62: PASSIVO | D62: 5330654 | E62: 1784422.6 | F62: 1734481.4 | H62: 5280712.8
A63: 2.1 | C63: PASSIVO CIRCULANTE | D63: 3163022 | E63: 1597791.8 | F63: 1506878.2 | H63: 3072108.4
A64: 2.1.01 | C64: OBRIGAÇÕES DE CURTO PRAZO | D64: 3163022 | E64: 1597791.8 | F64: 1506878.2 | H64: 3072108.4
A65: 2.1.01.01 | C65: FORNECEDORES | D65: 1901555.7 | E65: 651639.39 | F65: 663057.07 | H65: 1912973.4
A66: 2.1.01.01.0001 | B66: 353 | C66: Fornecedores Nacionais | D66: 1901555.7 | E66: 651639.39 | F66: 663057.07 | H66: 1912973.4
A67: 2.1.01.02 | C67: EMPRÉSTIMOS/FINANCIAMENTOS BANCÁRIOS | D67: 0 | E67: 0 | F67: 218367.14 | H67: 218367.14
A68: 2.1.01.02.0001 | B68: 361 | C68: Banco Itaú | D68: 0 | E68: 0 | F68: 28351.71 | H68: 28351.71
A69: 2.1.01.02.0002 | B69: 362 | C69: Banco Bradesco | D69: 0 | E69: 0 | F69: 26575.43 | H69: 26575.43
A70: 2.1.01.02.0003 | B70: 5885 | C70: Banco Itaú Conta Garantida | D70: 0 | E70: 0 | F70: 163440 | H70: 163440
A71: 2.1.01.04 | C71: OBRIGAÇÕES TRABALHISTAS | D71: 26074.38 | E71: 58194.76 | F71: 73519.93 | H71: 41399.55
A72: 2.1.01.04.0004 | B72: 418 | C72: E-Consignado a Pagar | D72: 0 | E72: 1056.64 | F72: 1056.64 | H72: 0
A73: 2.1.01.04.0006 | B73: 434 | C73: Salários e Ordenados a Pagar | D73: 0 | E73: 50352.94 | F73: 50352.94 | H73: 0
A74: 2.1.01.04.0007 | B74: 4596 | C74: FGTS a Recolher | D74: 6785.18 | E74: 6785.18 | F74: 4495.99 | H74: 4495.99
A75: 2.1.01.04.0008 | B75: 4600 | C75: INSS a Recolher | D75: 19289.2 | E75: 0 | F75: 17614.36 | H75: 36903.56
A76: 2.1.01.05 | C76: CONTRIBUIÇÕES FISCAIS A RECOLHER | D76: 4994.61 | E76: 2843.05 | F76: 1543 | H76: 3694.56
A77: 2.1.01.05.0001 | B77: 4618 | C77: IRRF sobre Salários | D77: 2151.56 | E77: 0 | F77: 561.93 | H77: 2713.49
A78: 2.1.01.05.0002 | B78: 4626 | C78: COFINS a Recolher | D78: 2343.41 | E78: 2343.41 | F78: 806.07 | H78: 806.07
A79: 2.1.01.05.0007 | B79: 4677 | C79: PIS a Recolher | D79: 499.64 | E79: 499.64 | F79: 175 | H79: 175
A80: 2.1.01.06 | C80: PROVISÕES | D80: 411354.16 | E80: 190224.22 | F80: 215586.85 | H80: 436716.79
A81: 2.1.01.06.0001 | B81: 582 | C81: Provisão de 13º Salário | D81: 0 | E81: 0 | F81: 3848.18 | H81: 3848.18
A82: 2.1.01.06.0002 | B82: 590 | C82: Provisão de Férias | D82: 36554.57 | E82: 4559.21 | F82: 41546.57 | H82: 73541.93
A83: 2.1.01.06.0003 | B83: 3417 | C83: Provisão de Encargos sobre 13º Salário | D83: 0 | E83: 0 | F83: 1346.86 | H83: 1346.86
A84: 2.1.01.06.0004 | B84: 3425 | C84: Provisão de Encargos sobre Férias | D84: 12720.91 | E84: 0 | F84: 14541.3 | H84: 27262.21
A85: 2.1.01.06.0007 | B85: 5150 | C85: Provisão para Contingência Fiscal | D85: 34906.44 | E85: 0 | F85: 576.26 | H85: 35482.7
A86: 2.1.01.06.0008 | B86: 5240 | C86: Provisão de Despesas | D86: 327172.24 | E86: 185665.01 | F86: 153727.68 | H86: 295234.91
A87: 2.1.01.07 | C87: OBRIGAÇÕES TRIBUTÁRIAS | D87: 221806 | E87: 157805.9 | F87: 88655.4 | H87: 152655.5
A88: 2.1.01.07.0001 | B88: 604 | C88: ICMS a Recolher | D88: 68806.61 | E88: 32760.45 | F88: 60603.29 | H88: 96649.45
A89: 2.1.01.07.0003 | B89: 620 | C89: IRRF Retido a Recollher | D89: 1859.65 | E89: 1859.65 | F89: 365.73 | H89: 365.73
A90: 2.1.01.07.0007 | B90: 663 | C90: CSLL Retido a Recolher | D90: 3136.84 | E90: 3136.84 | F90: 0 | H90: 0
A91: 2.1.01.07.0009 | B91: 4650 | C91: ICMS Destino Difal a Recolher | D91: 136553.47 | E91: 103171.62 | F91: 12763.88 | H91: 46145.73
A92: 2.1.01.07.0015 | B92: 5880 | C92: CSRF a Recolher | D92: 11449.43 | E92: 16877.34 | F92: 14922.5 | H92: 9494.59
A93: 2.1.01.08 | C93: OUTRAS OBRIGAÇÕES | D93: 597237.13 | E93: 537084.5 | F93: 246148.83 | H93: 306301.46
A94: 2.1.01.08.0001 | B94: 3239 | C94: Cartão de Crédito a Pagar | D94: 0 | E94: 8982.02 | F94: 8982.02 | H94: 0
A95: 2.1.01.08.0004 | B95: 3468 | C95: Fretes e Armazenagem a Pagar | D95: 427552.51 | E95: 356856.16 | F95: 217379.06 | H95: 288075.41
A96: 2.1.01.08.0011 | B96: 5428 | C96: Reembolsos a Pagar - Ivanildo Pinheiro | D96: 44294.95 | E96: 44294.95 | F96: 18226.05 | H96: 18226.05
A97: 2.1.01.08.0012 | B97: 5436 | C97: Reembolso a Pagar - Carol Rojas | D97: 125389.67 | E97: 126951.37 | F97: 1561.7 | H97: 0
A98: 2.2 | C98: PASSIVO NÃO CIRCULANTE | D98: 3402830.8 | E98: 0 | F98: 40972.35 | H98: 3443803.1
A99: 2.2.01 | C99: OBRIGAÇÕES A LONGO PRAZO | D99: 3402830.8 | E99: 0 | F99: 40972.35 | H99: 3443803.1
A100: 2.2.01.04 | C100: OUTRAS OBRIGAÇÕES | D100: 3402830.8 | E100: 0 | F100: 40972.35 | H100: 3443803.1
...

Sheet 02.2026
A1: Conta contábil | B1: Código Red. | C1: Descrição da Conta | D1: Saldo anterior | E1: Débito | F1: Crédito | H1: Saldo Atual
A2: 1 | C2: ATIVO | D2: 4928069.7 | E2: 2269040 | F2: 2212147.2 | H2: 4984962.5
A3: 1.1 | C3: ATIVO CIRCULANTE | D3: 1786743 | E3: 2119253.7 | F3: 2056277 | H3: 1849719.7
A4: 1.1.01 | C4: DISPONÍVEL | D4: 6547.21 | E4: 1445920.8 | F4: 1446123.9 | H4: 6344.09
A5: 1.1.01.01 | C5: CAIXA | D5: 0 | E5: 85700 | F5: 85700 | H5: 0
A6: 1.1.01.01.0010 | B6: 5 | C6: Entre Contas | D6: 0 | E6: 85700 | F6: 85700 | H6: 0
A7: 1.1.01.02 | C7: BANCOS CONTA MOVIMENTO | D7: 6547.21 | E7: 1360220.8 | F7: 1360423.9 | H7: 6344.09
A8: 1.1.01.02.0001 | B8: 27 | C8: Banco Itaú | D8: 0 | E8: 1237885.7 | F8: 1237885.7 | H8: 0
A9: 1.1.01.02.0002 | B9: 576 | C9: Banco Pag Útil | D9: 1359.91 | E9: 46700 | F9: 47211.17 | H9: 848.74
A10: 1.1.01.02.0101 | B10: 5444 | C10: Mercado Pago - Banco Digital | D10: 5187.3 | E10: 308.05 | F10: 0 | H10: 5495.35
A11: 1.1.01.02.0102 | B11: 5860 | C11: Banco Bradesco | D11: 0 | E11: 75327 | F11: 75327 | H11: 0
A12: 1.1.02 | C12: CONTAS A RECEBER | D12: 614312.11 | E12: 526674.34 | F12: 366708.72 | H12: 774277.73
A13: 1.1.02.01 | C13: CLIENTES NACIONAIS | D13: 614312.11 | E13: 526674.34 | F13: 366708.72 | H13: 774277.73
A14: 1.1.02.01.0001 | B14: 43 | C14: Clientes Nacionais | D14: 399021.56 | E14: 526674.34 | F14: 366708.72 | H14: 558987.18
A15: 1.1.02.01.0002 | B15: 5347 | C15: Clientes B2B | D15: 215290.55 | E15: 0 | F15: 0 | H15: 215290.55
A16: 1.1.03 | C16: OUTROS CRÉDITOS | D16: 347954.71 | E16: 48831.97 | F16: 156526.52 | H16: 240260.16
A17: 1.1.03.01 | C17: CRÉDITOS DE FUNCIONÁRIOS | D17: 3218.9 | E17: 18863.81 | F17: 21169.83 | H17: 912.88
A18: 1.1.03.01.0002 | B18: 60 | C18: Adiantamento de Férias | D18: 3218.9 | E18: 0 | F18: 2306.02 | H18: 912.88
A19: 1.1.03.01.0003 | B19: 3263 | C19: Adiantamento de Salários | D19: 0 | E19: 18863.81 | F19: 18863.81 | H19: 0
A20: 1.1.03.02 | C20: ADIANTAMENTO A FORNECEDORES | D20: 147010.2 | E20: 0 | F20: 0 | H20: 147010.2
A21: 1.1.03.02.0001 | B21: 3220 | C21: Adiantamento a Fornecedores | D21: 147010.2 | E21: 0 | F21: 0 | H21: 147010.2
A22: 1.1.03.03 | C22: OUTROS CREDITOS A RECEBER | D22: 126211.51 | E22: 0 | F22: 105390.96 | H22: 20820.55
A23: 1.1.03.03.0001 | B23: 5789 | C23: Outros Creditos a Receber | D23: 126211.51 | E23: 0 | F23: 105390.96 | H23: 20820.55
A24: 1.1.03.05 | C24: IMPOSTOS A RECUPERAR | D24: 7421 | E24: 29968.16 | F24: 29965.73 | H24: 7423.43
A25: 1.1.03.05.0001 | B25: 94 | C25: COFINS a Recuperar | D25: 0 | E25: 1087.11 | F25: 1085.36 | H25: 1.75
A26: 1.1.03.05.0003 | B26: 116 | C26: ICMS a Recuperar | D26: 300.12 | E26: 28644.73 | F26: 28644.73 | H26: 300.12
A27: 1.1.03.05.0007 | B27: 159 | C27: PIS a Recuperar | D27: 0 | E27: 236.32 | F27: 235.64 | H27: 0.68
A28: 1.1.03.05.0008 | B28: 5274 | C28: ICMS Difal a Recuperar | D28: 7120.88 | E28: 0 | F28: 0 | H28: 7120.88
A29: 1.1.03.06 | C29: TRIBUTOS A COMPENSAR | D29: 64093.1 | E29: 0 | F29: 0 | H29: 64093.1
A30: 1.1.03.06.0003 | B30: 4502 | C30: Saldo Negativo IRPJ | D30: 13.87 | E30: 0 | F30: 0 | H30: 13.87
A31: 1.1.03.06.0004 | B31: 4510 | C31: CSLL a Compensar | D31: 34627.34 | E31: 0 | F31: 0 | H31: 34627.34
A32: 1.1.03.06.0007 | B32: 4545 | C32: IRRF Aplicação | D32: 16.21 | E32: 0 | F32: 0 | H32: 16.21
A33: 1.1.03.06.0009 | B33: 4561 | C33: IRPJ a Compensar | D33: 29435.68 | E33: 0 | F33: 0 | H33: 29435.68
A34: 1.1.06 | C34: ESTOQUES | D34: 817929 | E34: 97826.59 | F34: 86917.88 | H34: 828837.71
A35: 1.1.06.01 | C35: ESTOQUES PARA REVENDA | D35: 817929 | E35: 97826.59 | F35: 86917.88 | H35: 828837.71
A36: 1.1.06.01.0001 | B36: 175 | C36: Mercadorias para Revenda | D36: 817929 | E36: 97826.59 | F36: 86917.88 | H36: 828837.71
A37: 1.2 | C37: ATIVO NÃO CIRCULANTE | D37: 3141326.7 | E37: 0 | F37: 6083.86 | H37: 3135242.9
A38: 1.2.01 | C38: ATIVO REALIZÁVEL A LONGO PRAZO | D38: 3022149 | E38: 0 | F38: 0 | H38: 3022149
A39: 1.2.01.05 | C39: CRÉDITOS A SÓCIOS | D39: 3022149 | E39: 0 | F39: 0 | H39: 3022149
A40: 1.2.01.05.0001 | B40: 3336 | C40: Mutuo Sócios | D40: 1224589.3 | E40: 0 | F40: 0 | H40: 1224589.3
A41: 1.2.01.05.0002 | B41: 3344 | C41: Débitos de Sócios | D41: 1797559.7 | E41: 0 | F41: 0 | H41: 1797559.7
A42: 1.2.03 | C42: ATIVO IMOBILIZADO | D42: 67895.98 | E42: 0 | F42: 1767.19 | H42: 66128.79
A43: 1.2.03.01 | C43: IMOBILIZADO | D43: 139435.51 | E43: 0 | F43: 0 | H43: 139435.51
A44: 1.2.03.01.0001 | B44: 205 | C44: Computadores e Periféricos | D44: 132597.82 | E44: 0 | F44: 0 | H44: 132597.82
A45: 1.2.03.01.0002 | B45: 4588 | C45: Equipamentos de Comunicação | D45: 4888.69 | E45: 0 | F45: 0 | H45: 4888.69
A46: 1.2.03.01.0005 | B46: 248 | C46: Móveis e Utensílios | D46: 1949 | E46: 0 | F46: 0 | H46: 1949
A47: 1.2.03.02 | C47: (-) DEPRECIAÇÃO/AMORTIZAÇÃO ACUMULADA | D47: -71539.53 | E47: 0 | F47: 1767.19 | H47: -73306.72
A48: 1.2.03.02.0001 | B48: 280 | C48: (-) Computadores e Periféricos | D48: -67805.02 | E48: 0 | F48: 1666.29 | H48: -69471.31
A49: 1.2.03.02.0002 | B49: 299 | C49: (-) Equipamentos de Comunicação | D49: -3555.87 | E49: 0 | F49: 84.66 | H49: -3640.53
A50: 1.2.03.02.0006 | B50: 329 | C50: (-) Móveis e Utensílios | D50: -178.64 | E50: 0 | F50: 16.24 | H50: -194.88
A51: 1.2.04 | C51: INTANGÍVEL | D51: 51281.75 | E51: 0 | F51: 4316.67 | H51: 46965.08
A52: 1.2.04.01 | C52: INTANGÍVEL | D52: 109099 | E52: 0 | F52: 0 | H52: 109099
A53: 1.2.04.01.0001 | B53: 2615 | C53: Marcas e Patentes | D53: 5499 | E53: 0 | F53: 0 | H53: 5499
A54: 1.2.04.01.0002 | B54: 3948 | C54: Software | D54: 103600 | E54: 0 | F54: 0 | H54: 103600
A55: 1.2.04.02 | C55: AMORTIZAÇÃO ACUMULADA | D55: -57817.25 | E55: 0 | F55: 4316.67 | H55: -62133.92
A56: 1.2.04.02.0001 | B56: 3964 | C56: (-) Software | D56: -57817.25 | E56: 0 | F56: 4316.67 | H56: -62133.92
A57: 1.9 | C57: REMESSAS DE MERCADORIAS | D57: 0 | E57: 149786.33 | F57: 149786.33 | H57: 0
A58: 1.9.01 | C58: SIMPLES REMESSA | D58: 0 | E58: 149786.33 | F58: 149786.33 | H58: 0
A59: 1.9.01.00.0001 | B59: 5881 | C59: Simples Remessa | D59: 0 | E59: 86841 | F59: 86841 | H59: 0
A60: 1.9.01.00.0002 | B60: 5883 | C60: Transferencia entre Filiais | D60: 0 | E60: 7658 | F60: 7658 | H60: 0
A61: 1.9.01.00.0003 | B61: 5886 | C61: Remessa de Bonificação | D61: 0 | E61: 55287.33 | F61: 55287.33 | H61: 0
A62: 2 | C62: PASSIVO | D62: 5280712.8 | E62: 1755058.1 | F62: 2101016.9 | H62: 5626671.6
A63: 2.1 | C63: PASSIVO CIRCULANTE | D63: 3072108.4 | E63: 1604352.8 | F63: 1267779.9 | H63: 2735535.5
A64: 2.1.01 | C64: OBRIGAÇÕES DE CURTO PRAZO | D64: 3072108.4 | E64: 1604352.8 | F64: 1267779.9 | H64: 2735535.5
A65: 2.1.01.01 | C65: FORNECEDORES | D65: 1912973.4 | E65: 853113.86 | F65: 675380.26 | H65: 1735239.8
A66: 2.1.01.01.0001 | B66: 353 | C66: Fornecedores Nacionais | D66: 1912973.4 | E66: 853113.86 | F66: 675380.26 | H66: 1735239.8
A67: 2.1.01.02 | C67: EMPRÉSTIMOS/FINANCIAMENTOS BANCÁRIOS | D67: 218367.14 | E67: 65935.14 | F67: 87737.07 | H67: 240169.07
A68: 2.1.01.02.0001 | B68: 361 | C68: Banco Itaú | D68: 28351.71 | E68: 28351.71 | F68: 71109.01 | H68: 71109.01
A69: 2.1.01.02.0002 | B69: 362 | C69: Banco Bradesco | D69: 26575.43 | E69: 26575.43 | F69: 9060.06 | H69: 9060.06
A70: 2.1.01.02.0003 | B70: 5885 | C70: Banco Itaú Conta Garantida | D70: 163440 | E70: 11008 | F70: 7568 | H70: 160000
A71: 2.1.01.04 | C71: OBRIGAÇÕES TRABALHISTAS | D71: 41399.55 | E71: 136998.29 | F71: 164900.45 | H71: 69301.71
A72: 2.1.01.04.0004 | B72: 418 | C72: E-Consignado a Pagar | D72: 0 | E72: 2324.61 | F72: 2324.61 | H72: 0
A73: 2.1.01.04.0006 | B73: 434 | C73: Salários e Ordenados a Pagar | D73: 0 | E73: 77465.9 | F73: 77465.9 | H73: 0
A74: 2.1.01.04.0007 | B74: 4596 | C74: FGTS a Recolher | D74: 4495.99 | E74: 4918.6 | F74: 9156.63 | H74: 8734.02
A75: 2.1.01.04.0008 | B75: 4600 | C75: INSS a Recolher | D75: 36903.56 | E75: 51106.76 | F75: 45095.66 | H75: 30892.46
A76: 2.1.01.04.0009 | B76: 4812 | C76: Rescisões a Pagar | D76: 0 | E76: 1182.42 | F76: 30857.65 | H76: 29675.23
A77: 2.1.01.05 | C77: CONTRIBUIÇÕES FISCAIS A RECOLHER | D77: 3694.56 | E77: 5233.11 | F77: 2315.69 | H77: 777.14
A78: 2.1.01.05.0001 | B78: 4618 | C78: IRRF sobre Salários | D78: 2713.49 | E78: 3124.76 | F78: 994.69 | H78: 583.42
A79: 2.1.01.05.0002 | B79: 4626 | C79: COFINS a Recolher | D79: 806.07 | E79: 1732.26 | F79: 1085.36 | H79: 159.17
A80: 2.1.01.05.0007 | B80: 4677 | C80: PIS a Recolher | D80: 175 | E80: 376.09 | F80: 235.64 | H80: 34.55
A81: 2.1.01.06 | C81: PROVISÕES | D81: 436716.79 | E81: 156010.86 | F81: 122256.36 | H81: 402962.29
A82: 2.1.01.06.0001 | B82: 582 | C82: Provisão de 13º Salário | D82: 3848.18 | E82: 0 | F82: 4434.01 | H82: 8282.19
A83: 2.1.01.06.0002 | B83: 590 | C83: Provisão de Férias | D83: 73541.93 | E83: 2283.18 | F83: 6391.9 | H83: 77650.65
A84: 2.1.01.06.0003 | B84: 3417 | C84: Provisão de Encargos sobre 13º Salário | D84: 1346.86 | E84: 0 | F84: 1543.04 | H84: 2889.9
A85: 2.1.01.06.0004 | B85: 3425 | C85: Provisão de Encargos sobre Férias | D85: 27262.21 | E85: 0 | F85: 1671.55 | H85: 28933.76
A86: 2.1.01.06.0007 | B86: 5150 | C86: Provisão para Contingência Fiscal | D86: 35482.7 | E86: 0 | F86: 354.83 | H86: 35837.53
A87: 2.1.01.06.0008 | B87: 5240 | C87: Provisão de Despesas | D87: 295234.91 | E87: 153727.68 | F87: 107861.03 | H87: 249368.26
A88: 2.1.01.07 | C88: OBRIGAÇÕES TRIBUTÁRIAS | D88: 152655.5 | E88: 162485.17 | F88: 72085.72 | H88: 62256.05
A89: 2.1.01.07.0001 | B89: 604 | C89: ICMS a Recolher | D89: 96649.45 | E89: 125294.18 | F89: 66383.88 | H89: 37739.15
A90: 2.1.01.07.0003 | B90: 620 | C90: IRRF Retido a Recollher | D90: 365.73 | E90: 365.73 | F90: 1390.69 | H90: 1390.69
A91: 2.1.01.07.0009 | B91: 4650 | C91: ICMS Destino Difal a Recolher | D91: 46145.73 | E91: 27330.67 | F91: 0 | H91: 18815.06
A92: 2.1.01.07.0015 | B92: 5880 | C92: CSRF a Recolher | D92: 9494.59 | E92: 9494.59 | F92: 4311.15 | H92: 4311.15
A93: 2.1.01.08 | C93: OUTRAS OBRIGAÇÕES | D93: 306301.46 | E93: 224576.34 | F93: 143104.36 | H93: 224829.48
A94: 2.1.01.08.0004 | B94: 3468 | C94: Fretes e Armazenagem a Pagar | D94: 288075.41 | E94: 206172.78 | F94: 138545.43 | H94: 220448.06
A95: 2.1.01.08.0011 | B95: 5428 | C95: Reembolsos a Pagar - Ivanildo Pinheiro | D95: 18226.05 | E95: 18403.56 | F95: 4558.93 | H95: 4381.42
A96: 2.2 | C96: PASSIVO NÃO CIRCULANTE | D96: 3443803.1 | E96: 0 | F96: 682531.69 | H96: 4126334.8
A97: 2.2.01 | C97: OBRIGAÇÕES A LONGO PRAZO | D97: 3443803.1 | E97: 0 | F97: 682531.69 | H97: 4126334.8
A98: 2.2.01.04 | C98: OUTRAS OBRIGAÇÕES | D98: 3443803.1 | E98: 0 | F98: 682531.69 | H98: 4126334.8
A99: 2.2.01.04.0001 | B99: 3549 | C99: Débitos de Pessoas Ligadas a Longo Prazo | D99: 3443803.1 | E99: 0 | F99: 682531.69 | H99: 4126334.8
A100: 2.4 | C100: PATRIMÔNIO LÍQUIDO | D100: -1235198.8 | E100: 0 | F100: 0 | H100: -1235198.8
...

Sheet 03.2026
A1: Conta contábil | B1: Conta contábil | C1: Descrição da Conta | D1: Saldo anterior | E1: Débito | F1: Crédito | H1: Saldo Atual
A2: 1 | C2: ATIVO | D2: 4984962.5 | E2: 3771495.7 | F2: 3554120.9 | H2: 5202337.4
A3: 1.1 | C3: ATIVO CIRCULANTE | D3: 1849719.7 | E3: 2852940.9 | F3: 2629482.2 | H3: 2073178.4
A4: 1.1.01 | C4: DISPONÍVEL | D4: 6344.09 | E4: 1400595.6 | F4: 1404893 | H4: 2046.69
A5: 1.1.01.01 | C5: CAIXA | D5: 0 | E5: 108600 | F5: 108600 | H5: 0
A6: 1.1.01.01.0010 | B6: 5 | C6: Entre Contas | D6: 0 | E6: 108600 | F6: 108600 | H6: 0
A7: 1.1.01.02 | C7: BANCOS CONTA MOVIMENTO | D7: 6344.09 | E7: 1291995.6 | F7: 1296293 | H7: 2046.69
A8: 1.1.01.02.0001 | B8: 27 | C8: Banco Itaú | D8: 0 | E8: 1167251.9 | F8: 1167251.9 | H8: 0
A9: 1.1.01.02.0002 | B9: 576 | C9: Banco Pag Útil | D9: 848.74 | E9: 16200 | F9: 16962.5 | H9: 86.24
A10: 1.1.01.02.0101 | B10: 5444 | C10: Mercado Pago - Banco Digital | D10: 5495.35 | E10: 853.39 | F10: 5400 | H10: 948.74
A11: 1.1.01.02.0102 | B11: 5860 | C11: Banco Bradesco | D11: 0 | E11: 107690.35 | F11: 106678.64 | H11: 1011.71
A12: 1.1.02 | C12: CONTAS A RECEBER | D12: 774277.73 | E12: 884558.89 | F12: 951206 | H12: 707630.62
A13: 1.1.02.01 | C13: CLIENTES NACIONAIS | D13: 774277.73 | E13: 884558.89 | F13: 951206 | H13: 707630.62
A14: 1.1.02.01.0001 | B14: 43 | C14: Clientes Nacionais | D14: 558987.18 | E14: 884558.89 | F14: 951206 | H14: 492340.07
A15: 1.1.02.01.0002 | B15: 5347 | C15: Clientes B2B | D15: 215290.55 | E15: 0 | F15: 0 | H15: 215290.55
A16: 1.1.03 | C16: OUTROS CRÉDITOS | D16: 240260.16 | E16: 81198.76 | F16: 82070.68 | H16: 239388.24
A17: 1.1.03.01 | C17: CRÉDITOS DE FUNCIONÁRIOS | D17: 912.88 | E17: 16675.31 | F17: 17588.19 | H17: 0
A18: 1.1.03.01.0002 | B18: 60 | C18: Adiantamento de Férias | D18: 912.88 | E18: 0 | F18: 912.88 | H18: 0
A19: 1.1.03.01.0003 | B19: 3263 | C19: Adiantamento de Salários | D19: 0 | E19: 16675.31 | F19: 16675.31 | H19: 0
A20: 1.1.03.02 | C20: ADIANTAMENTO A FORNECEDORES | D20: 147010.2 | E20: 0 | F20: 0 | H20: 147010.2
A21: 1.1.03.02.0001 | B21: 3220 | C21: Adiantamento a Fornecedores | D21: 147010.2 | E21: 0 | F21: 0 | H21: 147010.2
A22: 1.1.03.03 | C22: OUTROS CREDITOS A RECEBER | D22: 20820.55 | E22: 0 | F22: 0 | H22: 20820.55
A23: 1.1.03.03.0001 | B23: 5789 | C23: Outros Creditos a Receber | D23: 20820.55 | E23: 0 | F23: 0 | H23: 20820.55
A24: 1.1.03.05 | C24: IMPOSTOS A RECUPERAR | D24: 7423.43 | E24: 64523.45 | F24: 64482.49 | H24: 7464.39
A25: 1.1.03.05.0001 | B25: 94 | C25: COFINS a Recuperar | D25: 1.75 | E25: 1521.73 | F25: 1523.48 | H25: 0
A26: 1.1.03.05.0003 | B26: 116 | C26: ICMS a Recuperar | D26: 300.12 | E26: 62671.65 | F26: 62628.26 | H26: 343.51
A27: 1.1.03.05.0007 | B27: 159 | C27: PIS a Recuperar | D27: 0.68 | E27: 330.07 | F27: 330.75 | H27: 0
A28: 1.1.03.05.0008 | B28: 5274 | C28: ICMS Difal a Recuperar | D28: 7120.88 | E28: 0 | F28: 0 | H28: 7120.88
A29: 1.1.03.06 | C29: TRIBUTOS A COMPENSAR | D29: 64093.1 | E29: 0 | F29: 0 | H29: 64093.1
A30: 1.1.03.06.0003 | B30: 4502 | C30: Saldo Negativo IRPJ | D30: 13.87 | E30: 0 | F30: 0 | H30: 13.87
A31: 1.1.03.06.0004 | B31: 4510 | C31: CSLL a Compensar | D31: 34627.34 | E31: 0 | F31: 0 | H31: 34627.34
A32: 1.1.03.06.0007 | B32: 4545 | C32: IRRF Aplicação | D32: 16.21 | E32: 0 | F32: 0 | H32: 16.21
A33: 1.1.03.06.0009 | B33: 4561 | C33: IRPJ a Compensar | D33: 29435.68 | E33: 0 | F33: 0 | H33: 29435.68
A34: 1.1.06 | C34: ESTOQUES | D34: 828837.71 | E34: 486587.57 | F34: 191312.45 | H34: 1124112.8
A35: 1.1.06.01 | C35: ESTOQUES PARA REVENDA | D35: 828837.71 | E35: 486587.57 | F35: 191312.45 | H35: 1124112.8
A36: 1.1.06.01.0001 | B36: 175 | C36: Mercadorias para Revenda | D36: 828837.71 | E36: 486587.57 | F36: 191312.45 | H36: 1124112.8 | I36: atualizado
A37: 1.2 | C37: ATIVO NÃO CIRCULANTE | D37: 3135242.9 | E37: 0 | F37: 6083.86 | H37: 3129159
A38: 1.2.01 | C38: ATIVO REALIZÁVEL A LONGO PRAZO | D38: 3022149 | E38: 0 | F38: 0 | H38: 3022149
A39: 1.2.01.05 | C39: CRÉDITOS A SÓCIOS | D39: 3022149 | E39: 0 | F39: 0 | H39: 3022149
A40: 1.2.01.05.0001 | B40: 3336 | C40: Mutuo Sócios | D40: 1224589.3 | E40: 0 | F40: 0 | H40: 1224589.3
A41: 1.2.01.05.0002 | B41: 3344 | C41: Débitos de Sócios | D41: 1797559.7 | E41: 0 | F41: 0 | H41: 1797559.7
A42: 1.2.03 | C42: ATIVO IMOBILIZADO | D42: 66128.79 | E42: 0 | F42: 1767.19 | H42: 64361.6
A43: 1.2.03.01 | C43: IMOBILIZADO | D43: 139435.51 | E43: 0 | F43: 0 | H43: 139435.51
A44: 1.2.03.01.0001 | B44: 205 | C44: Computadores e Periféricos | D44: 132597.82 | E44: 0 | F44: 0 | H44: 132597.82
A45: 1.2.03.01.0002 | B45: 4588 | C45: Equipamentos de Comunicação | D45: 4888.69 | E45: 0 | F45: 0 | H45: 4888.69
A46: 1.2.03.01.0005 | B46: 248 | C46: Móveis e Utensílios | D46: 1949 | E46: 0 | F46: 0 | H46: 1949
A47: 1.2.03.02 | C47: (-) DEPRECIAÇÃO/AMORTIZAÇÃO ACUMULADA | D47: -73306.72 | E47: 0 | F47: 1767.19 | H47: -75073.91
A48: 1.2.03.02.0001 | B48: 280 | C48: (-) Computadores e Periféricos | D48: -69471.31 | E48: 0 | F48: 1666.29 | H48: -71137.6
A49: 1.2.03.02.0002 | B49: 299 | C49: (-) Equipamentos de Comunicação | D49: -3640.53 | E49: 0 | F49: 84.66 | H49: -3725.19
A50: 1.2.03.02.0006 | B50: 329 | C50: (-) Móveis e Utensílios | D50: -194.88 | E50: 0 | F50: 16.24 | H50: -211.12
A51: 1.2.04 | C51: INTANGÍVEL | D51: 46965.08 | E51: 0 | F51: 4316.67 | H51: 42648.41
A52: 1.2.04.01 | C52: INTANGÍVEL | D52: 109099 | E52: 0 | F52: 0 | H52: 109099
A53: 1.2.04.01.0001 | B53: 2615 | C53: Marcas e Patentes | D53: 5499 | E53: 0 | F53: 0 | H53: 5499
A54: 1.2.04.01.0002 | B54: 3948 | C54: Software | D54: 103600 | E54: 0 | F54: 0 | H54: 103600
A55: 1.2.04.02 | C55: AMORTIZAÇÃO ACUMULADA | D55: -62133.92 | E55: 0 | F55: 4316.67 | H55: -66450.59
A56: 1.2.04.02.0001 | B56: 3964 | C56: (-) Software | D56: -62133.92 | E56: 0 | F56: 4316.67 | H56: -66450.59
A57: 1.9 | C57: REMESSAS DE MERCADORIAS | D57: 0 | E57: 918554.86 | F57: 918554.86 | H57: 0
A58: 1.9.01 | C58: SIMPLES REMESSA | D58: 0 | E58: 918554.86 | F58: 918554.86 | H58: 0
A59: 1.9.01.00.0001 | B59: 5881 | C59: Simples Remessa | D59: 0 | E59: 343687.99 | F59: 343687.99 | H59: 0
A60: 1.9.01.00.0002 | B60: 5883 | C60: Transferencia entre Filiais | D60: 0 | E60: 451663.89 | F60: 451663.89 | H60: 0
A61: 1.9.01.00.0003 | B61: 5886 | C61: Remessa de Bonificação | D61: 0 | E61: 123202.98 | F61: 123202.98 | H61: 0
A62: 2 | C62: PASSIVO | D62: 5626671.6 | E62: 2537267.5 | F62: 2809477.6 | H62: 5898881.7
A63: 2.1 | C63: PASSIVO CIRCULANTE | D63: 2735535.5 | E63: 1458712.7 | F63: 1622451.5 | H63: 2899274.4
A64: 2.1.01 | C64: OBRIGAÇÕES DE CURTO PRAZO | D64: 2735535.5 | E64: 1458712.7 | F64: 1622451.5 | H64: 2899274.4
A65: 2.1.01.01 | C65: FORNECEDORES | D65: 1735239.8 | E65: 632601.43 | F65: 990640.1 | H65: 2093278.5
A66: 2.1.01.01.0001 | B66: 353 | C66: Fornecedores Nacionais | D66: 1735239.8 | E66: 632601.43 | F66: 990640.1 | H66: 2093278.5 | I66: atualizado
A67: 2.1.01.02 | C67: EMPRÉSTIMOS/FINANCIAMENTOS BANCÁRIOS | D67: 240169.07 | E67: 90176.34 | F67: 90668.57 | H67: 240661.3
A68: 2.1.01.02.0001 | B68: 361 | C68: Banco Itaú | D68: 71109.01 | E68: 71109.01 | F68: 80661.3 | H68: 80661.3
A69: 2.1.01.02.0002 | B69: 362 | C69: Banco Bradesco | D69: 9060.06 | E69: 9060.06 | F69: 0 | H69: 0
A70: 2.1.01.02.0003 | B70: 5885 | C70: Banco Itaú Conta Garantida | D70: 160000 | E70: 10007.27 | F70: 10007.27 | H70: 160000
A71: 2.1.01.04 | C71: OBRIGAÇÕES TRABALHISTAS | D71: 69301.71 | E71: 111925.16 | F71: 70030.28 | H71: 27406.83
A72: 2.1.01.04.0004 | B72: 418 | C72: E-Consignado a Pagar | D72: 0 | E72: 2655.54 | F72: 2655.54 | H72: 0
A73: 2.1.01.04.0006 | B73: 434 | C73: Salários e Ordenados a Pagar | D73: 0 | E73: 40810.38 | F73: 40810.38 | H73: 0
A74: 2.1.01.04.0007 | B74: 4596 | C74: FGTS a Recolher | D74: 8734.02 | E74: 14229.61 | F74: 8699.2 | H74: 3203.61
A75: 2.1.01.04.0008 | B75: 4600 | C75: INSS a Recolher | D75: 30892.46 | E75: 23371.98 | F75: 16682.74 | H75: 24203.22
A76: 2.1.01.04.0009 | B76: 4812 | C76: Rescisões a Pagar | D76: 29675.23 | E76: 30857.65 | F76: 1182.42 | H76: 0
A77: 2.1.01.05 | C77: CONTRIBUIÇÕES FISCAIS A RECOLHER | D77: 777.14 | E77: 2437.65 | F77: 4401.54 | H77: 2741.03
A78: 2.1.01.05.0001 | B78: 4618 | C78: IRRF sobre Salários | D78: 583.42 | E78: 583.42 | F78: 1069.52 | H78: 1069.52
A79: 2.1.01.05.0002 | B79: 4626 | C79: COFINS a Recolher | D79: 159.17 | E79: 1523.48 | F79: 2737.65 | H79: 1373.34
A80: 2.1.01.05.0007 | B80: 4677 | C80: PIS a Recolher | D80: 34.55 | E80: 330.75 | F80: 594.37 | H80: 298.17
A81: 2.1.01.06 | C81: PROVISÕES | D81: 402962.29 | E81: 282968.75 | F81: 202671.87 | H81: 322665.41
A82: 2.1.01.06.0001 | B82: 582 | C82: Provisão de 13º Salário | D82: 8282.19 | E82: 0 | F82: 3398.86 | H82: 11681.05
A83: 2.1.01.06.0002 | B83: 590 | C83: Provisão de Férias | D83: 77650.65 | E83: 912.88 | F83: 6097.84 | H83: 82835.61
A84: 2.1.01.06.0003 | B84: 3417 | C84: Provisão de Encargos sobre 13º Salário | D84: 2889.9 | E84: 0 | F84: 1182.78 | H84: 4072.68
A85: 2.1.01.06.0004 | B85: 3425 | C85: Provisão de Encargos sobre Férias | D85: 28933.76 | E85: 0 | F85: 2122.04 | H85: 31055.8
A86: 2.1.01.06.0007 | B86: 5150 | C86: Provisão para Contingência Fiscal | D86: 35837.53 | E86: 0 | F86: 424.19 | H86: 36261.72
A87: 2.1.01.06.0008 | B87: 5240 | C87: Provisão de Despesas | D87: 249368.26 | E87: 282055.87 | F87: 189446.16 | H87: 156758.55
A88: 2.1.01.07 | C88: OBRIGAÇÕES TRIBUTÁRIAS | D88: 62256.05 | E88: 67645.93 | F88: 128644.33 | H88: 123254.45
A89: 2.1.01.07.0001 | B89: 604 | C89: ICMS a Recolher | D89: 37739.15 | E89: 60530.91 | F89: 128394.58 | H89: 105602.82
A90: 2.1.01.07.0003 | B90: 620 | C90: IRRF Retido a Recollher | D90: 1390.69 | E90: 1456.97 | F90: 132.56 | H90: 66.28
A91: 2.1.01.07.0009 | B91: 4650 | C91: ICMS Destino Difal a Recolher | D91: 18815.06 | E91: 5658.05 | F91: 0 | H91: 13157.01
A92: 2.1.01.07.0015 | B92: 5880 | C92: CSRF a Recolher | D92: 4311.15 | E92: 0 | F92: 117.19 | H92: 4428.34
A93: 2.1.01.08 | C93: OUTRAS OBRIGAÇÕES | D93: 224829.48 | E93: 270957.4 | F93: 135394.8 | H93: 89266.88
A94: 2.1.01.08.0004 | B94: 3468 | C94: Fretes e Armazenagem a Pagar | D94: 220448.06 | E94: 266575.98 | F94: 135394.8 | H94: 89266.88
A95: 2.1.01.08.0011 | B95: 5428 | C95: Reembolsos a Pagar - Ivanildo Pinheiro | D95: 4381.42 | E95: 4381.42 | F95: 0 | H95: 0
A96: 2.2 | C96: PASSIVO NÃO CIRCULANTE | D96: 4126334.8 | E96: 160000 | F96: 268471.27 | H96: 4234806.1
A97: 2.2.01 | C97: OBRIGAÇÕES A LONGO PRAZO | D97: 4126334.8 | E97: 160000 | F97: 268471.27 | H97: 4234806.1
A98: 2.2.01.04 | C98: OUTRAS OBRIGAÇÕES | D98: 4126334.8 | E98: 160000 | F98: 268471.27 | H98: 4234806.1
A99: 2.2.01.04.0001 | B99: 3549 | C99: Débitos de Pessoas Ligadas a Longo Prazo | D99: 4126334.8 | E99: 160000 | F99: 268471.27 | H99: 4234806.1
A100: 2.4 | C100: PATRIMÔNIO LÍQUIDO | D100: -1235198.8 | E100: 0 | F100: 0 | H100: -1235198.8
...

Sheet 04.2026
A1: Conta contábil | B1: Código Reduzido | C1: Descrição da Conta | D1: Saldo anterior | E1: Débito | F1: Crédito | H1: Saldo Atual
A2: 1 | C2: ATIVO | D2: 5202337.4 | E2: 1730488.8 | F2: 1718123.6 | H2: 5214702.5
A3: 1.1 | C3: ATIVO CIRCULANTE | D3: 2073178.4 | E3: 1730488.8 | F3: 1712039.8 | H3: 2091627.3
A4: 1.1.01 | C4: DISPONÍVEL | D4: 2046.69 | E4: 939671.15 | F4: 923363.77 | H4: 18354.07
A5: 1.1.01.01 | C5: CAIXA | D5: 0 | E5: 55000 | F5: 55000 | H5: 0
A6: 1.1.01.01.0010 | B6: 5 | C6: Entre Contas | D6: 0 | E6: 55000 | F6: 55000 | H6: 0
A7: 1.1.01.02 | C7: BANCOS CONTA MOVIMENTO | D7: 2046.69 | E7: 817509.01 | F7: 816270.4 | H7: 3285.3
A8: 1.1.01.02.0001 | B8: 27 | C8: Banco Itaú | D8: 0 | E8: 720738.15 | F8: 720738.15 | H8: 0
A9: 1.1.01.02.0002 | B9: 576 | C9: Banco Pag Útil | D9: 86.24 | E9: 55000 | F9: 53878.04 | H9: 1208.2
A10: 1.1.01.02.0101 | B10: 5444 | C10: Mercado Pago - Banco Digital | D10: 948.74 | E10: 1127.36 | F10: 0 | H10: 2076.1
A11: 1.1.01.02.0102 | B11: 5860 | C11: Banco Bradesco | D11: 1011.71 | E11: 40643.5 | F11: 41654.21 | H11: 1
A12: 1.1.01.03 | C12: APLICAÇÕES FINANCEIRAS | D12: 0 | E12: 67162.14 | F12: 52093.37 | H12: 15068.77
A13: 1.1.01.03.0001 | B13: 35 | C13: Aplicações Banco Itaú | D13: 0 | E13: 52093.37 | F13: 52093.37 | H13: 0 | J13: 0
A14: 1.1.01.03.0002 | B14: 5878 | C14: Aplicações Brando Bradesco | D14: 0 | E14: 15068.77 | F14: 0 | H14: 15068.77
A15: 1.1.02 | C15: CONTAS A RECEBER | D15: 707630.62 | E15: 617787.79 | F15: 655343.63 | H15: 670074.78
A16: 1.1.02.01 | C16: CLIENTES NACIONAIS | D16: 707630.62 | E16: 617787.79 | F16: 655343.63 | H16: 670074.78
A17: 1.1.02.01.0001 | B17: 43 | C17: Clientes Nacionais | D17: 492340.07 | E17: 617787.79 | F17: 614418.01 | H17: 495709.85
A18: 1.1.02.01.0002 | B18: 5347 | C18: Clientes B2B | D18: 215290.55 | E18: 0 | F18: 40925.62 | H18: 174364.93
A19: 1.1.03 | C19: OUTROS CRÉDITOS | D19: 239388.24 | E19: 37771.95 | F19: 35830.03 | H19: 241330.16
A20: 1.1.03.01 | C20: CRÉDITOS DE FUNCIONÁRIOS | D20: 0 | E20: 17071.93 | F20: 15130.01 | H20: 1941.92
A21: 1.1.03.01.0002 | B21: 60 | C21: Adiantamento de Férias | D21: 0 | E21: 1941.92 | F21: 0 | H21: 1941.92
A22: 1.1.03.01.0003 | B22: 3263 | C22: Adiantamento de Salários | D22: 0 | E22: 15130.01 | F22: 15130.01 | H22: 0
A23: 1.1.03.02 | C23: ADIANTAMENTO A FORNECEDORES | D23: 147010.2 | E23: 0 | F23: 0 | H23: 147010.2
A24: 1.1.03.02.0001 | B24: 3220 | C24: Adiantamento a Fornecedores | D24: 147010.2 | E24: 0 | F24: 0 | H24: 147010.2
A25: 1.1.03.03 | C25: OUTROS CREDITOS A RECEBER | D25: 20820.55 | E25: 0 | F25: 0 | H25: 20820.55
A26: 1.1.03.03.0001 | B26: 5789 | C26: Outros Creditos a Receber | D26: 20820.55 | E26: 0 | F26: 0 | H26: 20820.55
A27: 1.1.03.05 | C27: IMPOSTOS A RECUPERAR | D27: 7464.39 | E27: 20700.02 | F27: 20700.02 | H27: 7464.39
A28: 1.1.03.05.0001 | B28: 94 | C28: COFINS a Recuperar | D28: 0 | E28: 108.49 | F28: 108.49 | H28: 0
A29: 1.1.03.05.0003 | B29: 116 | C29: ICMS a Recuperar | D29: 343.51 | E29: 20567.98 | F29: 20567.98 | H29: 343.51
A30: 1.1.03.05.0007 | B30: 159 | C30: PIS a Recuperar | D30: 0 | E30: 23.55 | F30: 23.55 | H30: 0
A31: 1.1.03.05.0008 | B31: 5274 | C31: ICMS Difal a Recuperar | D31: 7120.88 | E31: 0 | F31: 0 | H31: 7120.88
A32: 1.1.03.06 | C32: TRIBUTOS A COMPENSAR | D32: 64093.1 | E32: 0 | F32: 0 | H32: 64093.1
A33: 1.1.03.06.0003 | B33: 4502 | C33: Saldo Negativo IRPJ | D33: 13.87 | E33: 0 | F33: 0 | H33: 13.87
A34: 1.1.03.06.0004 | B34: 4510 | C34: CSLL a Compensar | D34: 34627.34 | E34: 0 | F34: 0 | H34: 34627.34
A35: 1.1.03.06.0007 | B35: 4545 | C35: IRRF Aplicação | D35: 16.21 | E35: 0 | F35: 0 | H35: 16.21
A36: 1.1.03.06.0009 | B36: 4561 | C36: IRPJ a Compensar | D36: 29435.68 | E36: 0 | F36: 0 | H36: 29435.68
A37: 1.1.06 | C37: ESTOQUES | D37: 1124112.8 | E37: 135257.86 | F37: 97502.36 | H37: 1161868.3
A38: 1.1.06.01 | C38: ESTOQUES PARA REVENDA | D38: 1124112.8 | E38: 135257.86 | F38: 97502.36 | H38: 1161868.3
A39: 1.1.06.01.0001 | B39: 175 | C39: Mercadorias para Revenda | D39: 1124112.8 | E39: 135257.86 | F39: 97502.36 | H39: 1161868.3
A40: 1.2 | C40: ATIVO NÃO CIRCULANTE | D40: 3129159 | E40: 0 | F40: 6083.86 | H40: 3123075.1
A41: 1.2.01 | C41: ATIVO REALIZÁVEL A LONGO PRAZO | D41: 3022149 | E41: 0 | F41: 0 | H41: 3022149
A42: 1.2.01.05 | C42: CRÉDITOS A SÓCIOS | D42: 3022149 | E42: 0 | F42: 0 | H42: 3022149
A43: 1.2.01.05.0001 | B43: 3336 | C43: Mutuo Sócios | D43: 1224589.3 | E43: 0 | F43: 0 | H43: 1224589.3
A44: 1.2.01.05.0002 | B44: 3344 | C44: Débitos de Sócios | D44: 1797559.7 | E44: 0 | F44: 0 | H44: 1797559.7
A45: 1.2.03 | C45: ATIVO IMOBILIZADO | D45: 64361.6 | E45: 0 | F45: 1767.19 | H45: 62594.41
A46: 1.2.03.01 | C46: IMOBILIZADO | D46: 139435.51 | E46: 0 | F46: 0 | H46: 139435.51
A47: 1.2.03.01.0001 | B47: 205 | C47: Computadores e Periféricos | D47: 132597.82 | E47: 0 | F47: 0 | H47: 132597.82
A48: 1.2.03.01.0002 | B48: 4588 | C48: Equipamentos de Comunicação | D48: 4888.69 | E48: 0 | F48: 0 | H48: 4888.69
A49: 1.2.03.01.0005 | B49: 248 | C49: Móveis e Utensílios | D49: 1949 | E49: 0 | F49: 0 | H49: 1949
A50: 1.2.03.02 | C50: (-) DEPRECIAÇÃO/AMORTIZAÇÃO ACUMULADA | D50: -75073.91 | E50: 0 | F50: 1767.19 | H50: -76841.1
A51: 1.2.03.02.0001 | B51: 280 | C51: (-) Computadores e Periféricos | D51: -71137.6 | E51: 0 | F51: 1666.29 | H51: -72803.89
A52: 1.2.03.02.0002 | B52: 299 | C52: (-) Equipamentos de Comunicação | D52: -3725.19 | E52: 0 | F52: 84.66 | H52: -3809.85
A53: 1.2.03.02.0006 | B53: 329 | C53: (-) Móveis e Utensílios | D53: -211.12 | E53: 0 | F53: 16.24 | H53: -227.36
A54: 1.2.04 | C54: INTANGÍVEL | D54: 42648.41 | E54: 0 | F54: 4316.67 | H54: 38331.74
A55: 1.2.04.01 | C55: INTANGÍVEL | D55: 109099 | E55: 0 | F55: 0 | H55: 109099
A56: 1.2.04.01.0001 | B56: 2615 | C56: Marcas e Patentes | D56: 5499 | E56: 0 | F56: 0 | H56: 5499
A57: 1.2.04.01.0002 | B57: 3948 | C57: Software | D57: 103600 | E57: 0 | F57: 0 | H57: 103600
A58: 1.2.04.02 | C58: AMORTIZAÇÃO ACUMULADA | D58: -66450.59 | E58: 0 | F58: 4316.67 | H58: -70767.26
A59: 1.2.04.02.0001 | B59: 3964 | C59: (-) Software | D59: -66450.59 | E59: 0 | F59: 4316.67 | H59: -70767.26
A60: 2 | C60: PASSIVO | D60: 5898881.7 | E60: 1001112 | F60: 1363743.9 | H60: 6261513.6
A61: 2.1 | C61: PASSIVO CIRCULANTE | D61: 2899274.4 | E61: 1001112 | F61: 1281773.1 | H61: 3179935.4
A62: 2.1.01 | C62: OBRIGAÇÕES DE CURTO PRAZO | D62: 2899274.4 | E62: 1001112 | F62: 1281773.1 | H62: 3179935.4
A63: 2.1.01.01 | C63: FORNECEDORES | D63: 2093278.5 | E63: 370638.38 | F63: 703314.98 | H63: 2425955.1
A64: 2.1.01.01.0001 | B64: 353 | C64: Fornecedores Nacionais | D64: 2093278.5 | E64: 370638.38 | F64: 703314.98 | H64: 2425955.1
A65: 2.1.01.02 | C65: EMPRÉSTIMOS/FINANCIAMENTOS BANCÁRIOS | D65: 240661.3 | E65: 80661.3 | F65: 68754.68 | H65: 228754.68
A66: 2.1.01.02.0001 | B66: 361 | C66: Banco Itaú | D66: 80661.3 | E66: 80661.3 | F66: 68754.68 | H66: 68754.68
A67: 2.1.01.02.0003 | B67: 5885 | C67: Banco Itaú Conta Garantida | D67: 160000 | E67: 0 | F67: 0 | H67: 160000
A68: 2.1.01.04 | C68: OBRIGAÇÕES TRABALHISTAS | D68: 27406.83 | E68: 74623.05 | F68: 64442.28 | H68: 17226.06
A69: 2.1.01.04.0004 | B69: 418 | C69: E-Consignado a Pagar | D69: 0 | E69: 2601.95 | F69: 2601.95 | H69: 0
A70: 2.1.01.04.0006 | B70: 434 | C70: Salários e Ordenados a Pagar | D70: 0 | E70: 42654.71 | F70: 42654.71 | H70: 0
A71: 2.1.01.04.0007 | B71: 4596 | C71: FGTS a Recolher | D71: 3203.61 | E71: 5093.98 | F71: 4974.5 | H71: 3084.13
A72: 2.1.01.04.0008 | B72: 4600 | C72: INSS a Recolher | D72: 24203.22 | E72: 24203.22 | F72: 14141.93 | H72: 14141.93
A73: 2.1.01.04.0009 | B73: 4812 | C73: Rescisões a Pagar | D73: 0 | E73: 69.19 | F73: 69.19 | H73: 0
A74: 2.1.01.05 | C74: CONTRIBUIÇÕES FISCAIS A RECOLHER | D74: 2741.03 | E74: 1201.56 | F74: 25117.4 | H74: 26656.87
A75: 2.1.01.05.0001 | B75: 4618 | C75: IRRF sobre Salários | D75: 1069.52 | E75: 1069.52 | F75: 711.53 | H75: 711.53
A76: 2.1.01.05.0002 | B76: 4626 | C76: COFINS a Recolher | D76: 1373.34 | E76: 108.49 | F76: 20052.39 | H76: 21317.24
A77: 2.1.01.05.0007 | B77: 4677 | C77: PIS a Recolher | D77: 298.17 | E77: 23.55 | F77: 4353.48 | H77: 4628.1
A78: 2.1.01.06 | C78: PROVISÕES | D78: 322665.41 | E78: 188337.2 | F78: 136933.6 | H78: 271261.81
A79: 2.1.01.06.0001 | B79: 582 | C79: Provisão de 13º Salário | D79: 11681.05 | E79: 0 | F79: 3135.07 | H79: 14816.12
A80: 2.1.01.06.0002 | B80: 590 | C80: Provisão de Férias | D80: 82835.61 | E80: 0 | F80: 2499.91 | H80: 85335.52
A81: 2.1.01.06.0003 | B81: 3417 | C81: Provisão de Encargos sobre 13º Salário | D81: 4072.68 | E81: 0 | F81: 1090.98 | H81: 5163.66
A82: 2.1.01.06.0004 | B82: 3425 | C82: Provisão de Encargos sobre Férias | D82: 31055.8 | E82: 0 | F82: 194.19 | H82: 31249.99
A83: 2.1.01.06.0007 | B83: 5150 | C83: Provisão para Contingência Fiscal | D83: 36261.72 | E83: 0 | F83: 428.82 | H83: 36690.54
A84: 2.1.01.06.0008 | B84: 5240 | C84: Provisão de Despesas | D84: 156758.55 | E84: 188337.2 | F84: 129584.63 | H84: 98005.98
A85: 2.1.01.07 | C85: OBRIGAÇÕES TRIBUTÁRIAS | D85: 123254.45 | E85: 181155.99 | F85: 148327.03 | H85: 90425.49
A86: 2.1.01.07.0001 | B86: 604 | C86: ICMS a Recolher | D86: 105602.82 | E86: 122783.33 | F86: 80467.24 | H86: 63286.73
A87: 2.1.01.07.0003 | B87: 620 | C87: IRRF Retido a Recollher | D87: 66.28 | E87: 66.28 | F87: 99.28 | H87: 99.28
A88: 2.1.01.07.0009 | B88: 4650 | C88: ICMS Destino Difal a Recolher | D88: 13157.01 | E88: 53878.04 | F88: 67254.41 | H88: 26533.38
A89: 2.1.01.07.0015 | B89: 5880 | C89: CSRF a Recolher | D89: 4428.34 | E89: 4428.34 | F89: 506.1 | H89: 506.1
A90: 2.1.01.08 | C90: OUTRAS OBRIGAÇÕES | D90: 89266.88 | E90: 104494.54 | F90: 134883.08 | H90: 119655.42
A91: 2.1.01.08.0004 | B91: 3468 | C91: Fretes e Armazenagem a Pagar | D91: 89266.88 | E91: 89266.88 | F91: 119655.42 | H91: 119655.42
A92: 2.1.01.08.0010 | B92: 3514 | C92: Reembolsos a Pagar | D92: 0 | E92: 453.86 | F92: 453.86 | H92: 0
A93: 2.1.01.08.0011 | B93: 5428 | C93: Reembolsos a Pagar - Ivanildo Pinheiro | D93: 0 | E93: 14773.8 | F93: 14773.8 | H93: 0
A94: 2.2 | C94: PASSIVO NÃO CIRCULANTE | D94: 4234806.1 | E94: 0 | F94: 81970.89 | H94: 4316777
A95: 2.2.01 | C95: OBRIGAÇÕES A LONGO PRAZO | D95: 4234806.1 | E95: 0 | F95: 81970.89 | H95: 4316777
A96: 2.2.01.04 | C96: OUTRAS OBRIGAÇÕES | D96: 4234806.1 | E96: 0 | F96: 81970.89 | H96: 4316777
A97: 2.2.01.04.0001 | B97: 3549 | C97: Débitos de Pessoas Ligadas a Longo Prazo | D97: 4234806.1 | E97: 0 | F97: 81970.89 | H97: 4316777
A98: 2.4 | C98: PATRIMÔNIO LÍQUIDO | D98: -1235198.8 | E98: 0 | F98: 0 | H98: -1235198.8
A99: 2.4.01 | C99: CAPITAL REALIZADO | D99: 1128000 | E99: 0 | F99: 0 | H99: 1128000
A100: 2.4.01.01 | C100: CAPITAL SOCIAL | D100: 1128000 | E100: 0 | F100: 0 | H100: 1128000
...

Sheet ANÁLISE DE RESULTADO
A1: Conta Contábil | B1: C. Reduzido | C1: Descrição | D1: JANEIRO | E1: FEVEREIRO | F1: MARÇO | G1: ABRIL | K1: INDICADOR | L1: JANEIRO | M1: FEVEREIRO | N1: MARÇO | O1: ABRIL
A2: 3 | C2: RECEITAS | D2: =D3+D9+D16 -> 656359.67 | E2: =E3+E9+E16 -> 455561.03 | F2: =F3+F9+F16 -> 760260.76 | G2: =G3+G9+G16 -> 456584.58 | K2: RECEITA BRUTA | L2: =D3 -> 704049 | M2: =E3 -> 494905.82 | N2: =F3 -> 873714.52 | O2: =G3 -> 598893.85
A3: 3.1.01 | C3: RECEITAS BRUTAS | D3: =D4+D5+D7 -> 704049 | E3: =E4+E5+E7 -> 494905.82 | F3: =F4+F5+F7 -> 873714.52 | G3: =G4+G5+G7 -> 598893.85 | K3: (-) DEDUÇÕES | L3: =D5 -> -6163.13 | M3: =E5 -> -31768.52 | N3: =F5 -> -10496.15 | O3: =G5 -> -18893.94
A4: 3.1.01.01.0001 | B4: 922 | C4: Revendas de Mercadorias B2C | D4: =SUMIF('01.2026'!B:B,'ANÁLISE DE RESULTADO'!B4,'01.2026'!G:G) -> 651228.61 | E4: =SUMIF('02.2026'!B:B,'ANÁLISE DE RESULTADO'!B4,'02.2026'!G:G) -> 526674.34 | F4: =SUMIF('03.2026'!B:B,'ANÁLISE DE RESULTADO'!B4,'03.2026'!G:G) -> 884210.67 | G4: =SUMIF('04.2026'!B:B,'ANÁLISE DE RESULTADO'!B4,'04.2026'!G:G) -> 617787.79 | K4: (-) IMPOSTOS | L4: =D9 -> -47691.07 | M4: =E9 -> -39345.33 | N4: =F9 -> -113455.43 | O4: =G9 -> -142310.04
A5: 3.1.01.02 | C5: DEDUÇÕES DA RECEITA BRUTA | D5: =D6 -> -6163.13 | E5: =E6 -> -31768.52 | F5: =F6 -> -10496.15 | G5: =G6 -> -18893.94 | K5: "= RECEITA LÍQUIDA | L5: =SUM(L2:L4) -> 650194.8 | M5: =SUM(M2:M4) -> 423791.97 | N5: =SUM(N2:N4) -> 749762.94 | O5: =SUM(O2:O4) -> 437689.87
A6: 3.1.01.02.0004 | B6: 5363 | C6: (-) Devolução de Revenda | D6: =SUMIF('01.2026'!B:B,'ANÁLISE DE RESULTADO'!B6,'01.2026'!G:G) -> -6163.13 | E6: =SUMIF('02.2026'!B:B,'ANÁLISE DE RESULTADO'!B6,'02.2026'!G:G) -> -31768.52 | F6: =SUMIF('03.2026'!B:B,'ANÁLISE DE RESULTADO'!B6,'03.2026'!G:G) -> -10496.15 | G6: =SUMIF('04.2026'!B:B,'ANÁLISE DE RESULTADO'!B6,'04.2026'!G:G) -> -18893.94
A7: 3.1.01.03 | C7: RECEITA BRUTA REVENDA - B2B | D7: =D8 -> 58983.52 | E7: =E8 -> 0 | F7: =F8 -> 0 | G7: =G8 -> 0 | K7: (-) CMV | L7: =D19 -> -117500.55 | M7: =E19 -> -74422.81 | N7: =F19 -> -119524.39 | O7: =G19 -> -85461.46
A8: 3.1.01.03.0001 | B8: 5495 | C8: Revenda de mercadoria - B2B | D8: =SUMIF('01.2026'!B:B,'ANÁLISE DE RESULTADO'!B8,'01.2026'!G:G) -> 58983.52 | E8: =SUMIF('02.2026'!B:B,'ANÁLISE DE RESULTADO'!B8,'02.2026'!G:G) -> 0 | F8: =SUMIF('03.2026'!B:B,'ANÁLISE DE RESULTADO'!B8,'03.2026'!G:G) -> 0 | G8: =SUMIF('04.2026'!B:B,'ANÁLISE DE RESULTADO'!B8,'04.2026'!G:G) -> 0 | K8: = LUCRO BRUTO | L8: =L5+L7 -> 532694.25 | M8: =M5+M7 -> 349369.16 | N8: =N5+N7 -> 630238.55 | O8: =O5+O7 -> 352228.41
A9: 3.1.03 | C9: IMPOSTOS INCIDENTES | D9: =SUM(D10:D14) -> -47691.07 | E9: =SUM(E10:E14) -> -39345.33 | F9: =SUM(F10:F14) -> -113455.43 | G9: =SUM(G10:G14) -> -142310.04 | K9: "= MARGEM BRUTA % | L9: =L8/L5 -> 0.81928408 | M9: =M8/M5 -> 0.82438834 | N9: =N8/N5 -> 0.84058376 | O9: =O8/O5 -> 0.80474426
A10: 3.1.03.03.0001 | B10: 981 | C10: (-) COFINS sobre Revendas | D10: =SUMIF('01.2026'!B:B,'ANÁLISE DE RESULTADO'!B10,'01.2026'!G:G) -> -806.07 | E10: =SUMIF('02.2026'!B:B,'ANÁLISE DE RESULTADO'!B10,'02.2026'!G:G) -> -1085.36 | F10: =SUMIF('03.2026'!B:B,'ANÁLISE DE RESULTADO'!B10,'03.2026'!G:G) -> -2737.65 | G10: =SUMIF('04.2026'!B:B,'ANÁLISE DE RESULTADO'!B10,'04.2026'!G:G) -> -19917.76
A11: 3.1.03.03.0002 | B11: 4014 | C11: (-) PIS sobre Revendas | D11: =SUMIF('01.2026'!B:B,'ANÁLISE DE RESULTADO'!B11,'01.2026'!G:G) -> -175 | E11: =SUMIF('02.2026'!B:B,'ANÁLISE DE RESULTADO'!B11,'02.2026'!G:G) -> -235.64 | F11: =SUMIF('03.2026'!B:B,'ANÁLISE DE RESULTADO'!B11,'03.2026'!G:G) -> -594.37 | G11: =SUMIF('04.2026'!B:B,'ANÁLISE DE RESULTADO'!B11,'04.2026'!G:G) -> -4324.25 | K11: (-) PUBLICIDADE | L11: =D30 -> -275606.45 | M11: =E30 -> -263307.55 | N11: =F30 -> -251337.05 | O11: =G30 -> -292484.28
A12: 3.1.03.03.0003 | B12: 1007 | C12: (-) ICMS sobre Revendas | D12: =SUMIF('01.2026'!B:B,'ANÁLISE DE RESULTADO'!B12,'01.2026'!G:G) -> -57697.01 | E12: =SUMIF('02.2026'!B:B,'ANÁLISE DE RESULTADO'!B12,'02.2026'!G:G) -> -49411.16 | F12: =SUMIF('03.2026'!B:B,'ANÁLISE DE RESULTADO'!B12,'03.2026'!G:G) -> -126027.2 | G12: =SUMIF('04.2026'!B:B,'ANÁLISE DE RESULTADO'!B12,'04.2026'!G:G) -> -80254.67 | K12: (-) DESPESAS COM VENDAS | L12: =D33 -> -158230.31 | M12: =E33 -> -22960.64 | N12: =F33 -> -81358.96 | O12: =G33 -> -138776.03
A13: 3.1.03.03.0004 | B13: 4669 | C13: (-) ICMS Destino Difal s/ Vendas | D13: =SUMIF('01.2026'!B:B,'ANÁLISE DE RESULTADO'!B13,'01.2026'!G:G) -> 0 | E13: =SUMIF('02.2026'!B:B,'ANÁLISE DE RESULTADO'!B13,'02.2026'!G:G) -> 0 | F13: =SUMIF('03.2026'!B:B,'ANÁLISE DE RESULTADO'!B13,'03.2026'!G:G) -> 0 | G13: =SUMIF('04.2026'!B:B,'ANÁLISE DE RESULTADO'!B13,'04.2026'!G:G) -> -54840.9 | K13: "= MARGEM DE CONTRIBUIÇÃO | L13: =L8+L11+L12 -> 98857.49 | M13: =M8+M11+M12 -> 63100.97 | N13: =N8+N11+N12 -> 297542.54 | O13: =O8+O11+O12 -> -79031.9
A14: 3.1.03.03.0015 | B14: 5410 | C14: (-) ICMS Revenda Reg. Especial Cred. Pre | D14: =SUMIF('01.2026'!B:B,'ANÁLISE DE RESULTADO'!B14,'01.2026'!G:G) -> 10987.01 | E14: =SUMIF('02.2026'!B:B,'ANÁLISE DE RESULTADO'!B14,'02.2026'!G:G) -> 11386.83 | F14: =SUMIF('03.2026'!B:B,'ANÁLISE DE RESULTADO'!B14,'03.2026'!G:G) -> 15903.79 | G14: =SUMIF('04.2026'!B:B,'ANÁLISE DE RESULTADO'!B14,'04.2026'!G:G) -> 17027.54 | K14: "= MARGEM CONTRIBUIÇÃO % | L14: =L13/L5 -> 0.15204288 | M14: =M13/M5 -> 0.1488961 | N14: =N13/N5 -> 0.39684882 | O14: =O13/O5 -> -0.18056598
C15: RECEITA LÍQUIDA | D15: =D3+D5+D9 -> 650194.8 | E15: =E3+E5+E9 -> 423791.97 | F15: =F3+F5+F9 -> 749762.94 | G15: =G3+G5+G9 -> 437689.87
A16: 3.2 | C16: OUTRAS RECEITAS OPERACIONAIS | D16: =D17 -> 1.74 | E16: =E17 -> 0.54 | F16: =F17 -> 1.67 | G16: =G17 -> 0.77 | K16: (-) DESPESAS OPERACIONAIS | L16: =D29 -> -876623.77 | M16: =E29 -> -670007.4 | N16: =F29 -> -695571.64 | O16: =G29 -> -720020.31
A17: 3.2.01.01.0001 | B17: 3603 | C17: Rendimento de Aplicações Financeiras | D17: =SUMIF('01.2026'!B:B,'ANÁLISE DE RESULTADO'!B17,'01.2026'!G:G) -> 1.74 | E17: =SUMIF('02.2026'!B:B,'ANÁLISE DE RESULTADO'!B17,'02.2026'!G:G) -> 0.54 | F17: =SUMIF('03.2026'!B:B,'ANÁLISE DE RESULTADO'!B17,'03.2026'!G:G) -> 1.67 | G17: =SUMIF('04.2026'!B:B,'ANÁLISE DE RESULTADO'!B17,'04.2026'!G:G) -> 0.77 | K17: "= RESULTADO OPERACIONAL | L17: =D50 -> -343929.52 | M17: =E50 -> -320638.24 | N17: =F50 -> -65333.09 | O17: =G50 -> -367791.9
A18: 4 | C18: CUSTO E DESPESAS | D18: =D19+D25+D29 -> -1009002.7 | E18: =E19+E25+E29 -> -744627.06 | F18: =F19+F25+F29 -> -815096.03 | G18: =G19+G25+G29 -> -805481.77 | K18: "= MARGEM OPERACIONAL % | L18: =D51 -> -0.52896381 | M18: =E51 -> -0.75659348 | N18: =F51 -> -0.087138329 | O18: =G51 -> -0.84030252
A19: 4.2 | C19: CUSTO DE MERCADORIAS REVENDIDAS | D19: =SUM(D20:D24) -> -117500.55 | E19: =SUM(E20:E24) -> -74422.81 | F19: =SUM(F20:F24) -> -119524.39 | G19: =SUM(G20:G24) -> -85461.46
A20: 4.2.01.01.0001 | B20: 1120 | C20: (+) Estoque Inicial | D20: =SUMIF('01.2026'!B:B,'ANÁLISE DE RESULTADO'!B20,'01.2026'!G:G) -> 953107.73 | E20: =SUMIF('02.2026'!B:B,'ANÁLISE DE RESULTADO'!B20,'02.2026'!G:G) -> 0 | F20: =SUMIF('03.2026'!B:B,'ANÁLISE DE RESULTADO'!B20,'03.2026'!G:G) -> 0 | G20: =SUMIF('04.2026'!B:B,'ANÁLISE DE RESULTADO'!B20,'04.2026'!G:G) -> 0 | K20: (+) DEPRECIAÇÃO / AMORTIZAÇÃO | L20: =D70 -> -6083.86 | M20: =E70 -> -6083.86 | N20: =F70 -> -6083.86 | O20: =G70 -> -6083.86
A21: 4.2.01.01.0002 | B21: 1112 | C21: (+) Compra Mercadorias Brutas | D21: =SUMIF('01.2026'!B:B,'ANÁLISE DE RESULTADO'!B21,'01.2026'!G:G) -> 0 | E21: =SUMIF('02.2026'!B:B,'ANÁLISE DE RESULTADO'!B21,'02.2026'!G:G) -> -25573.5 | F21: =SUMIF('03.2026'!B:B,'ANÁLISE DE RESULTADO'!B21,'03.2026'!G:G) -> -9720 | G21: =SUMIF('04.2026'!B:B,'ANÁLISE DE RESULTADO'!B21,'04.2026'!G:G) -> -12000 | K21: "= EBITDA | L21: =L17-L20 -> -337845.66 | M21: =M17-M20 -> -314554.38 | N21: =N17-N20 -> -59249.23 | O21: =O17-O20 -> -361708.04
A22: 4.2.01.01.0009 | B22: 3034 | C22: (-) Devolução de Compras | D22: =SUMIF('01.2026'!B:B,'ANÁLISE DE RESULTADO'!B22,'01.2026'!G:G) -> 0 | E22: =SUMIF('02.2026'!B:B,'ANÁLISE DE RESULTADO'!B22,'02.2026'!G:G) -> 19240.6 | F22: =SUMIF('03.2026'!B:B,'ANÁLISE DE RESULTADO'!B22,'03.2026'!G:G) -> 0 | G22: =SUMIF('04.2026'!B:B,'ANÁLISE DE RESULTADO'!B22,'04.2026'!G:G) -> 1394.97 | K22: "= MARGEM EBITDA % | L22: =L21/L5 -> -0.51960683 | M22: =M21/M5 -> -0.74223771 | N22: =N21/N5 -> -0.079023951 | O22: =O21/O5 -> -0.82640259
A23: 4.2.01.01.0010 | B23: 1066 | C23: (-) Estoque Final | D23: =SUMIF('01.2026'!B:B,'ANÁLISE DE RESULTADO'!B23,'01.2026'!G:G) -> -1081516.5 | E23: =SUMIF('02.2026'!B:B,'ANÁLISE DE RESULTADO'!B23,'02.2026'!G:G) -> 0 | F23: =SUMIF('03.2026'!B:B,'ANÁLISE DE RESULTADO'!B23,'03.2026'!G:G) -> 0 | G23: =SUMIF('04.2026'!B:B,'ANÁLISE DE RESULTADO'!B23,'04.2026'!G:G) -> 0
A24: 4.2.01.01.0011 | B24: 4847 | C24: CMV | D24: =SUMIF('01.2026'!B:B,'ANÁLISE DE RESULTADO'!B24,'01.2026'!G:G) -> 10908.2 | E24: =SUMIF('02.2026'!B:B,'ANÁLISE DE RESULTADO'!B24,'02.2026'!G:G) -> -68089.91 | F24: =SUMIF('03.2026'!B:B,'ANÁLISE DE RESULTADO'!B24,'03.2026'!G:G) -> -109804.39 | G24: =SUMIF('04.2026'!B:B,'ANÁLISE DE RESULTADO'!B24,'04.2026'!G:G) -> -74856.43
A25: 4.2.01.02 | C25: CUSTO - B2B | D25: =D26 -> -14878.36 | E25: =E26 -> -196.85 | F25: =F26 -> 0 | G25: =G26 -> 0
A26: 4.2.01.02.0001 | B26: 5738 | C26: CMV - B2B | D26: =SUMIF('01.2026'!B:B,'ANÁLISE DE RESULTADO'!B26,'01.2026'!G:G) -> -14878.36 | E26: =SUMIF('02.2026'!B:B,'ANÁLISE DE RESULTADO'!B26,'02.2026'!G:G) -> -196.85 | F26: =SUMIF('03.2026'!B:B,'ANÁLISE DE RESULTADO'!B26,'03.2026'!G:G) -> 0 | G26: =SUMIF('04.2026'!B:B,'ANÁLISE DE RESULTADO'!B26,'04.2026'!G:G) -> 0
C27: LUCRO BRUTO | D27: =D15+D19 -> 532694.25 | E27: =E15+E19 -> 349369.16 | F27: =F15+F19 -> 630238.55 | G27: =G15+G19 -> 352228.41
C28: MARGEM OPERACIONAL BRUTA | D28: =D27/D15 -> 0.81928408 | E28: =E27/E15 -> 0.82438834 | F28: =F27/F15 -> 0.84058376 | G28: =G27/G15 -> 0.80474426
A29: 4.3 | C29: DESPESAS OPERACIONAIS | D29: =D30+D33+D39+D52+D77+D82+D70 -> -876623.77 | E29: =E30+E33+E39+E52+E77+E82+E70 -> -670007.4 | F29: =F30+F33+F39+F52+F77+F82+F70 -> -695571.64 | G29: =G30+G33+G39+G52+G77+G82+G70 -> -720020.31
A30: 4.3.01.01 | C30: DESPESAS COM PUBLICIDADE | D30: =SUM(D31:D32) -> -275606.45 | E30: =SUM(E31:E32) -> -263307.55 | F30: =SUM(F31:F32) -> -251337.05 | G30: =SUM(G31:G32) -> -292484.28
A31: 4.3.01.01.0010 | B31: 4057 | C31: Propaganda e Publicidade Online | D31: =SUMIF('01.2026'!B:B,'ANÁLISE DE RESULTADO'!B31,'01.2026'!G:G) -> -275606.45 | E31: =SUMIF('02.2026'!B:B,'ANÁLISE DE RESULTADO'!B31,'02.2026'!G:G) -> -199538.88 | F31: =SUMIF('03.2026'!B:B,'ANÁLISE DE RESULTADO'!B31,'03.2026'!G:G) -> -251337.05 | G31: =SUMIF('04.2026'!B:B,'ANÁLISE DE RESULTADO'!B31,'04.2026'!G:G) -> -292484.28
A32: 4.3.01.02.0010 | B32: 5665 | C32: Propaganda e Publicidade - B2B | D32: =SUMIF('01.2026'!B:B,'ANÁLISE DE RESULTADO'!B32,'01.2026'!G:G) -> 0 | E32: =SUMIF('02.2026'!B:B,'ANÁLISE DE RESULTADO'!B32,'02.2026'!G:G) -> -63768.67 | F32: =SUMIF('03.2026'!B:B,'ANÁLISE DE RESULTADO'!B32,'03.2026'!G:G) -> 0 | G32: =SUMIF('04.2026'!B:B,'ANÁLISE DE RESULTADO'!B32,'04.2026'!G:G) -> 0
A33: 4.3.01.03 | C33: DESPESAS COM VENDAS | D33: =SUM(D34:D36) -> -158230.31 | E33: =SUM(E34:E36) -> -22960.64 | F33: =SUM(F34:F36) -> -81358.96 | G33: =SUM(G34:G36) -> -138776.03
A34: 4.3.01.03.0001 | B34: 1090 | C34: Fretes e Carretos | D34: =SUMIF('01.2026'!B:B,'ANÁLISE DE RESULTADO'!B34,'01.2026'!G:G) -> -51658.84 | E34: =SUMIF('02.2026'!B:B,'ANÁLISE DE RESULTADO'!B34,'02.2026'!G:G) -> -22551.33 | F34: =SUMIF('03.2026'!B:B,'ANÁLISE DE RESULTADO'!B34,'03.2026'!G:G) -> -42848.64 | G34: =SUMIF('04.2026'!B:B,'ANÁLISE DE RESULTADO'!B34,'04.2026'!G:G) -> -60778.34
A35: 4.3.01.03.0002 | B35: 4049 | C35: Comissões sobre Vendas - PJ | D35: =SUMIF('01.2026'!B:B,'ANÁLISE DE RESULTADO'!B35,'01.2026'!G:G) -> -65490.38 | E35: =SUMIF('02.2026'!B:B,'ANÁLISE DE RESULTADO'!B35,'02.2026'!G:G) -> 13648.26 | F35: =SUMIF('03.2026'!B:B,'ANÁLISE DE RESULTADO'!B35,'03.2026'!G:G) -> -20883.31 | G35: =SUMIF('04.2026'!B:B,'ANÁLISE DE RESULTADO'!B35,'04.2026'!G:G) -> -9597.5
A36: 4.3.01.03.0004 | B36: 4855 | C36: Armazenagem | D36: =SUMIF('01.2026'!B:B,'ANÁLISE DE RESULTADO'!B36,'01.2026'!G:G) -> -41081.09 | E36: =SUMIF('02.2026'!B:B,'ANÁLISE DE RESULTADO'!B36,'02.2026'!G:G) -> -14057.57 | F36: =SUMIF('03.2026'!B:B,'ANÁLISE DE RESULTADO'!B36,'03.2026'!G:G) -> -17627.01 | G36: =SUMIF('04.2026'!B:B,'ANÁLISE DE RESULTADO'!B36,'04.2026'!G:G) -> -68400.19
C37: MARGEM DE CONTRIBUIÇÃO | D37: =(D15+D19+D30+D33) -> 98857.49 | E37: =(E15+E19+E30+E33) -> 63100.97 | F37: =(F15+F19+F30+F33) -> 297542.54 | G37: =(G15+G19+G30+G33) -> -79031.9
C38: MARGEM DE CONTRIBUIÇÃO (%) | D38: =D37/D15 -> 0.15204288 | E38: =E37/E15 -> 0.1488961 | F38: =F37/F15 -> 0.39684882 | G38: =G37/G15 -> -0.18056598
A39: 4.3.02.01 | C39: DESPESAS COM PESSOAL | D39: =SUM(D40:D49) -> -129748.95 | E39: =SUM(E40:E49) -> -115799.86 | F39: =SUM(F40:F49) -> -74183.77 | G39: =SUM(G40:G49) -> -50316.84
A40: 4.3.02.01.0002 | B40: 1465 | C40: Aviso Prévio | D40: =SUMIF('01.2026'!B:B,'ANÁLISE DE RESULTADO'!B40,'01.2026'!G:G) -> 0 | E40: =SUMIF('02.2026'!B:B,'ANÁLISE DE RESULTADO'!B40,'02.2026'!G:G) -> -34669.89 | F40: =SUMIF('03.2026'!B:B,'ANÁLISE DE RESULTADO'!B40,'03.2026'!G:G) -> -1182.42 | G40: =SUMIF('04.2026'!B:B,'ANÁLISE DE RESULTADO'!B40,'04.2026'!G:G) -> -1916.23
A41: 4.3.02.01.0003 | B41: 1473 | C41: Férias | D41: =SUMIF('01.2026'!B:B,'ANÁLISE DE RESULTADO'!B41,'01.2026'!G:G) -> -4406.88 | E41: =SUMIF('02.2026'!B:B,'ANÁLISE DE RESULTADO'!B41,'02.2026'!G:G) -> -2299.49 | F41: =SUMIF('03.2026'!B:B,'ANÁLISE DE RESULTADO'!B41,'03.2026'!G:G) -> 0 | G41: =SUMIF('04.2026'!B:B,'ANÁLISE DE RESULTADO'!B41,'04.2026'!G:G) -> -2107.25
A42: 4.3.02.01.0004 | B42: 1481 | C42: FGTS | D42: =SUMIF('01.2026'!B:B,'ANÁLISE DE RESULTADO'!B42,'01.2026'!G:G) -> -6982.89 | E42: =SUMIF('02.2026'!B:B,'ANÁLISE DE RESULTADO'!B42,'02.2026'!G:G) -> -5803.62 | F42: =SUMIF('03.2026'!B:B,'ANÁLISE DE RESULTADO'!B42,'03.2026'!G:G) -> -7287.64 | G42: =SUMIF('04.2026'!B:B,'ANÁLISE DE RESULTADO'!B42,'04.2026'!G:G) -> -3128.77
A43: 4.3.02.01.0005 | B43: 1490 | C43: INSS | D43: =SUMIF('01.2026'!B:B,'ANÁLISE DE RESULTADO'!B43,'01.2026'!G:G) -> -23392.71 | E43: =SUMIF('02.2026'!B:B,'ANÁLISE DE RESULTADO'!B43,'02.2026'!G:G) -> -15861.44 | F43: =SUMIF('03.2026'!B:B,'ANÁLISE DE RESULTADO'!B43,'03.2026'!G:G) -> -12366.34 | G43: =SUMIF('04.2026'!B:B,'ANÁLISE DE RESULTADO'!B43,'04.2026'!G:G) -> -10481.37
A44: 4.3.02.01.0006 | B44: 1503 | C44: Salários e Ordenados | D44: =SUMIF('01.2026'!B:B,'ANÁLISE DE RESULTADO'!B44,'01.2026'!G:G) -> -40541.53 | E44: =SUMIF('02.2026'!B:B,'ANÁLISE DE RESULTADO'!B44,'02.2026'!G:G) -> -38630.39 | F44: =SUMIF('03.2026'!B:B,'ANÁLISE DE RESULTADO'!B44,'03.2026'!G:G) -> -40051.13 | G44: =SUMIF('04.2026'!B:B,'ANÁLISE DE RESULTADO'!B44,'04.2026'!G:G) -> -27899.18
A45: 4.3.02.01.0010 | B45: 1546 | C45: Provisão de Férias | D45: =SUMIF('01.2026'!B:B,'ANÁLISE DE RESULTADO'!B45,'01.2026'!G:G) -> -39976.48 | E45: =SUMIF('02.2026'!B:B,'ANÁLISE DE RESULTADO'!B45,'02.2026'!G:G) -> -4803.36 | F45: =SUMIF('03.2026'!B:B,'ANÁLISE DE RESULTADO'!B45,'03.2026'!G:G) -> -6097.84 | G45: =SUMIF('04.2026'!B:B,'ANÁLISE DE RESULTADO'!B45,'04.2026'!G:G) -> -557.99
A46: 4.3.02.01.0011 | B46: 1554 | C46: Provisão de 13º Salário | D46: =SUMIF('01.2026'!B:B,'ANÁLISE DE RESULTADO'!B46,'01.2026'!G:G) -> -3855.89 | E46: =SUMIF('02.2026'!B:B,'ANÁLISE DE RESULTADO'!B46,'02.2026'!G:G) -> -4434.01 | F46: =SUMIF('03.2026'!B:B,'ANÁLISE DE RESULTADO'!B46,'03.2026'!G:G) -> -3398.86 | G46: =SUMIF('04.2026'!B:B,'ANÁLISE DE RESULTADO'!B46,'04.2026'!G:G) -> -3135.07
A47: 4.3.02.01.0013 | B47: 1570 | C47: Provisão Encargos Sobre 13º Salário | D47: =SUMIF('01.2026'!B:B,'ANÁLISE DE RESULTADO'!B47,'01.2026'!G:G) -> -1339.15 | E47: =SUMIF('02.2026'!B:B,'ANÁLISE DE RESULTADO'!B47,'02.2026'!G:G) -> -1543.04 | F47: =SUMIF('03.2026'!B:B,'ANÁLISE DE RESULTADO'!B47,'03.2026'!G:G) -> -1182.78 | G47: =SUMIF('04.2026'!B:B,'ANÁLISE DE RESULTADO'!B47,'04.2026'!G:G) -> -1090.98
A48: 4.3.02.01.0015 | B48: 1597 | C48: Vale Refeição | D48: =SUMIF('01.2026'!B:B,'ANÁLISE DE RESULTADO'!B48,'01.2026'!G:G) -> -1575 | E48: =SUMIF('02.2026'!B:B,'ANÁLISE DE RESULTADO'!B48,'02.2026'!G:G) -> -80 | F48: =SUMIF('03.2026'!B:B,'ANÁLISE DE RESULTADO'!B48,'03.2026'!G:G) -> 0 | G48: =SUMIF('04.2026'!B:B,'ANÁLISE DE RESULTADO'!B48,'04.2026'!G:G) -> 0
A49: 4.3.02.01.0017 | B49: 1619 | C49: Assistencia Médica | D49: =SUMIF('01.2026'!B:B,'ANÁLISE DE RESULTADO'!B49,'01.2026'!G:G) -> -7678.42 | E49: =SUMIF('02.2026'!B:B,'ANÁLISE DE RESULTADO'!B49,'02.2026'!G:G) -> -7674.62 | F49: =SUMIF('03.2026'!B:B,'ANÁLISE DE RESULTADO'!B49,'03.2026'!G:G) -> -2616.76 | G49: =SUMIF('04.2026'!B:B,'ANÁLISE DE RESULTADO'!B49,'04.2026'!G:G) -> 0
C50: RESULTADO OPERACIONAL | D50: =D27+D29 -> -343929.52 | E50: =E27+E29 -> -320638.24 | F50: =F27+F29 -> -65333.09 | G50: =G27+G29 -> -367791.9
C51: MARGEM OPERACIONAL LIQUIDA (%) | D51: =D50/D15 -> -0.52896381 | E51: =E50/E15 -> -0.75659348 | F51: =F50/F15 -> -0.087138329 | G51: =G50/G15 -> -0.84030252
A52: 4.3.03 | C52: DESPESAS ADMINISTRATIVAS | D52: =D53+D56+D63+D68 -> -147670.77 | E52: =E53+E56+E63+E68 -> -114659.44 | F52: =F53+F56+F63+F68 -> -135276.73 | G52: =G53+G56+G63+G68 -> -128741.4
A53: 4.3.03.01 | C53: DESPESAS DE OCUPAÇÃO | D53: =SUM(D54:D55) -> -1844.61 | E53: =SUM(E54:E55) -> -723.61 | F53: =SUM(F54:F55) -> -343.61 | G53: =SUM(G54:G55) -> -583.61
A54: 4.3.03.01.0001 | B54: 1864 | C54: Alugueis Pagos a PJ | D54: =SUMIF('01.2026'!B:B,'ANÁLISE DE RESULTADO'!B54,'01.2026'!G:G) -> -1700 | E54: =SUMIF('02.2026'!B:B,'ANÁLISE DE RESULTADO'!B54,'02.2026'!G:G) -> -579 | F54: =SUMIF('03.2026'!B:B,'ANÁLISE DE RESULTADO'!B54,'03.2026'!G:G) -> -199 | G54: =SUMIF('04.2026'!B:B,'ANÁLISE DE RESULTADO'!B54,'04.2026'!G:G) -> -199
A55: 4.3.03.01.0002 | B55: 1872 | C55: Telefone | D55: =SUMIF('01.2026'!B:B,'ANÁLISE DE RESULTADO'!B55,'01.2026'!G:G) -> -144.61 | E55: =SUMIF('02.2026'!B:B,'ANÁLISE DE RESULTADO'!B55,'02.2026'!G:G) -> -144.61 | F55: =SUMIF('03.2026'!B:B,'ANÁLISE DE RESULTADO'!B55,'03.2026'!G:G) -> -144.61 | G55: =SUMIF('04.2026'!B:B,'ANÁLISE DE RESULTADO'!B55,'04.2026'!G:G) -> -384.61
A56: 4.3.03.02 | C56: DESPESAS GERAIS E ADMINISTRATIVAS | D56: =SUM(D57:D62) -> -498.22 | E56: =SUM(E57:E62) -> -539.37 | F56: =SUM(F57:F62) -> -489.4 | G56: =SUM(G57:G62) -> -3629.69
A57: 4.3.03.02.0002 | B57: 4103 | C57: Combustíveis e Lubrificantes | D57: =SUMIF('01.2026'!B:B,'ANÁLISE DE RESULTADO'!B57,'01.2026'!G:G) -> 0 | E57: =SUMIF('02.2026'!B:B,'ANÁLISE DE RESULTADO'!B57,'02.2026'!G:G) -> -200 | F57: =SUMIF('03.2026'!B:B,'ANÁLISE DE RESULTADO'!B57,'03.2026'!G:G) -> 0 | G57: =SUMIF('04.2026'!B:B,'ANÁLISE DE RESULTADO'!B57,'04.2026'!G:G) -> 0
A58: 4.3.03.02.0009 | B58: 4170 | C58: Material de Escritório | D58: =SUMIF('01.2026'!B:B,'ANÁLISE DE RESULTADO'!B58,'01.2026'!G:G) -> 0 | E58: =SUMIF('02.2026'!B:B,'ANÁLISE DE RESULTADO'!B58,'02.2026'!G:G) -> 0 | F58: =SUMIF('03.2026'!B:B,'ANÁLISE DE RESULTADO'!B58,'03.2026'!G:G) -> -417 | G58: =SUMIF('04.2026'!B:B,'ANÁLISE DE RESULTADO'!B58,'04.2026'!G:G) -> -100
A59: 4.3.03.02.0010 | B59: 4189 | C59: Viagens e Estadias | D59: =SUMIF('01.2026'!B:B,'ANÁLISE DE RESULTADO'!B59,'01.2026'!G:G) -> 0 | E59: =SUMIF('02.2026'!B:B,'ANÁLISE DE RESULTADO'!B59,'02.2026'!G:G) -> 0 | F59: =SUMIF('03.2026'!B:B,'ANÁLISE DE RESULTADO'!B59,'03.2026'!G:G) -> 0 | G59: =SUMIF('04.2026'!B:B,'ANÁLISE DE RESULTADO'!B59,'04.2026'!G:G) -> 0
A60: 4.3.03.02.0012 | B60: 4200 | C60: Lanches e Refeições | D60: =SUMIF('01.2026'!B:B,'ANÁLISE DE RESULTADO'!B60,'01.2026'!G:G) -> -376 | E60: =SUMIF('02.2026'!B:B,'ANÁLISE DE RESULTADO'!B60,'02.2026'!G:G) -> 0 | F60: =SUMIF('03.2026'!B:B,'ANÁLISE DE RESULTADO'!B60,'03.2026'!G:G) -> 0 | G60: =SUMIF('04.2026'!B:B,'ANÁLISE DE RESULTADO'!B60,'04.2026'!G:G) -> 0
A61: 4.3.03.02.0015 | B61: 4235 | C61: Material de Uso e Consumo | D61: =SUMIF('01.2026'!B:B,'ANÁLISE DE RESULTADO'!B61,'01.2026'!G:G) -> -122.22 | E61: =SUMIF('02.2026'!B:B,'ANÁLISE DE RESULTADO'!B61,'02.2026'!G:G) -> 0 | F61: =SUMIF('03.2026'!B:B,'ANÁLISE DE RESULTADO'!B61,'03.2026'!G:G) -> 0 | G61: =SUMIF('04.2026'!B:B,'ANÁLISE DE RESULTADO'!B61,'04.2026'!G:G) -> -3436.85
A62: 4.3.03.02.0020 | B62: 4286 | C62: Correios | D62: =SUMIF('01.2026'!B:B,'ANÁLISE DE RESULTADO'!B62,'01.2026'!G:G) -> 0 | E62: =SUMIF('02.2026'!B:B,'ANÁLISE DE RESULTADO'!B62,'02.2026'!G:G) -> -339.37 | F62: =SUMIF('03.2026'!B:B,'ANÁLISE DE RESULTADO'!B62,'03.2026'!G:G) -> -72.4 | G62: =SUMIF('04.2026'!B:B,'ANÁLISE DE RESULTADO'!B62,'04.2026'!G:G) -> -92.84
A63: 4.3.03.03 | C63: DESP COM SERVICOS PROFISSIONAIS | D63: =SUM(D64:D67) -> -120147.16 | E63: =SUM(E64:E67) -> -104715.19 | F63: =SUM(F64:F67) -> -92374.69 | G63: =SUM(G64:G67) -> -102769.77
A64: 4.3.03.03.0002 | B64: 4316 | C64: Juridico | D64: =SUMIF('01.2026'!B:B,'ANÁLISE DE RESULTADO'!B64,'01.2026'!G:G) -> -2000 | E64: =SUMIF('02.2026'!B:B,'ANÁLISE DE RESULTADO'!B64,'02.2026'!G:G) -> -6867 | F64: =SUMIF('03.2026'!B:B,'ANÁLISE DE RESULTADO'!B64,'03.2026'!G:G) -> -6866 | G64: =SUMIF('04.2026'!B:B,'ANÁLISE DE RESULTADO'!B64,'04.2026'!G:G) -> -3066
A65: 4.3.03.03.0003 | B65: 4324 | C65: Contabilidade | D65: =SUMIF('01.2026'!B:B,'ANÁLISE DE RESULTADO'!B65,'01.2026'!G:G) -> -40280 | E65: =SUMIF('02.2026'!B:B,'ANÁLISE DE RESULTADO'!B65,'02.2026'!G:G) -> -40280 | F65: =SUMIF('03.2026'!B:B,'ANÁLISE DE RESULTADO'!B65,'03.2026'!G:G) -> -40280 | G65: =SUMIF('04.2026'!B:B,'ANÁLISE DE RESULTADO'!B65,'04.2026'!G:G) -> -40280
A66: 4.3.03.03.0004 | B66: 4332 | C66: Informática/Software | D66: =SUMIF('01.2026'!B:B,'ANÁLISE DE RESULTADO'!B66,'01.2026'!G:G) -> -69258.36 | E66: =SUMIF('02.2026'!B:B,'ANÁLISE DE RESULTADO'!B66,'02.2026'!G:G) -> -47311.39 | F66: =SUMIF('03.2026'!B:B,'ANÁLISE DE RESULTADO'!B66,'03.2026'!G:G) -> -40887.16 | G66: =SUMIF('04.2026'!B:B,'ANÁLISE DE RESULTADO'!B66,'04.2026'!G:G) -> -50674.44
A67: 4.3.03.03.0005 | B67: 4340 | C67: Outros Serviços Prestados | D67: =SUMIF('01.2026'!B:B,'ANÁLISE DE RESULTADO'!B67,'01.2026'!G:G) -> -8608.8 | E67: =SUMIF('02.2026'!B:B,'ANÁLISE DE RESULTADO'!B67,'02.2026'!G:G) -> -10256.8 | F67: =SUMIF('03.2026'!B:B,'ANÁLISE DE RESULTADO'!B67,'03.2026'!G:G) -> -4341.53 | G67: =SUMIF('04.2026'!B:B,'ANÁLISE DE RESULTADO'!B67,'04.2026'!G:G) -> -8749.33
A68: 4.3.03.04 | C68: DESPESAS COM DOAÇÃO E BONIFICAÇÃO | D68: =SUM(D69:D69) -> -25180.78 | E68: =SUM(E69:E69) -> -8681.27 | F68: =SUM(F69:F69) -> -42069.03 | G68: =SUM(G69:G69) -> -21758.33
A69: 4.3.03.04.0006 | B69: 4251 | C69: Bonificações | D69: =SUMIF('01.2026'!B:B,'ANÁLISE DE RESULTADO'!B69,'01.2026'!G:G) -> -25180.78 | E69: =SUMIF('02.2026'!B:B,'ANÁLISE DE RESULTADO'!B69,'02.2026'!G:G) -> -8681.27 | F69: =SUMIF('03.2026'!B:B,'ANÁLISE DE RESULTADO'!B69,'03.2026'!G:G) -> -42069.03 | G69: =SUMIF('04.2026'!B:B,'ANÁLISE DE RESULTADO'!B69,'04.2026'!G:G) -> -21758.33
A70: 4.3.04.01 | C70: DEPRECIAÇÕES | D70: =SUM(D71:D74) -> -6083.86 | E70: =SUM(E71:E74) -> -6083.86 | F70: =SUM(F71:F74) -> -6083.86 | G70: =SUM(G71:G74) -> -6083.86
A71: 4.3.04.01.0001 | B71: 1996 | C71: Depreciação de Computadores e Periférico | D71: =SUMIF('01.2026'!B:B,'ANÁLISE DE RESULTADO'!B71,'01.2026'!G:G) -> -1666.29 | E71: =SUMIF('02.2026'!B:B,'ANÁLISE DE RESULTADO'!B71,'02.2026'!G:G) -> -1666.29 | F71: =SUMIF('03.2026'!B:B,'ANÁLISE DE RESULTADO'!B71,'03.2026'!G:G) -> -1666.29 | G71: =SUMIF('04.2026'!B:B,'ANÁLISE DE RESULTADO'!B71,'04.2026'!G:G) -> -1666.29
A72: 4.3.04.01.0002 | B72: 2003 | C72: Depreciação de Equipamentos de Comunicaç | D72: =SUMIF('01.2026'!B:B,'ANÁLISE DE RESULTADO'!B72,'01.2026'!G:G) -> -84.66 | E72: =SUMIF('02.2026'!B:B,'ANÁLISE DE RESULTADO'!B72,'02.2026'!G:G) -> -84.66 | F72: =SUMIF('03.2026'!B:B,'ANÁLISE DE RESULTADO'!B72,'03.2026'!G:G) -> -84.66 | G72: =SUMIF('04.2026'!B:B,'ANÁLISE DE RESULTADO'!B72,'04.2026'!G:G) -> -84.66
A73: 4.3.04.01.0004 | B73: 5797 | C73: Amortização de Software | D73: =SUMIF('01.2026'!B:B,'ANÁLISE DE RESULTADO'!B73,'01.2026'!G:G) -> -4316.67 | E73: =SUMIF('02.2026'!B:B,'ANÁLISE DE RESULTADO'!B73,'02.2026'!G:G) -> -4316.67 | F73: =SUMIF('03.2026'!B:B,'ANÁLISE DE RESULTADO'!B73,'03.2026'!G:G) -> -4316.67 | G73: =SUMIF('04.2026'!B:B,'ANÁLISE DE RESULTADO'!B73,'04.2026'!G:G) -> -4316.67
A74: 4.3.04.01.0005 | B74: 5819 | C74: Depreciação de Móveis e Utensilios | D74: =SUMIF('01.2026'!B:B,'ANÁLISE DE RESULTADO'!B74,'01.2026'!G:G) -> -16.24 | E74: =SUMIF('02.2026'!B:B,'ANÁLISE DE RESULTADO'!B74,'02.2026'!G:G) -> -16.24 | F74: =SUMIF('03.2026'!B:B,'ANÁLISE DE RESULTADO'!B74,'03.2026'!G:G) -> -16.24 | G74: =SUMIF('04.2026'!B:B,'ANÁLISE DE RESULTADO'!B74,'04.2026'!G:G) -> -16.24
C75: EBITDA | D75: =D50-D70 -> -337845.66 | E75: =E50-E70 -> -314554.38 | F75: =F50-F70 -> -59249.23 | G75: =G50-G70 -> -361708.04
C76: MARGEM EBITDA (%) | D76: =D75/D15 -> -0.51960683 | E76: =E75/E15 -> -0.74223771 | F76: =F75/F15 -> -0.079023951 | G76: =G75/G15 -> -0.82640259
A77: 4.3.06 | C77: DESPESAS TRIBUTÁRIAS | D77: =D78 -> -9879.34 | E77: =E78 -> -22423.25 | F77: =F78 -> -13038.58 | G77: =G78 -> -12361.02
A78: 4.3.06.01 | C78: TRIBUTOS E CONTRIBUIÇÕES | D78: =SUM(D79:D81) -> -9879.34 | E78: =SUM(E79:E81) -> -22423.25 | F78: =SUM(F79:F81) -> -13038.58 | G78: =SUM(G79:G81) -> -12361.02
A79: 4.3.06.01.0005 | B79: 4448 | C79: Impostos e Taxas Diversas | D79: =SUMIF('01.2026'!B:B,'ANÁLISE DE RESULTADO'!B79,'01.2026'!G:G) -> -1561.7 | E79: =SUMIF('02.2026'!B:B,'ANÁLISE DE RESULTADO'!B79,'02.2026'!G:G) -> -437.98 | F79: =SUMIF('03.2026'!B:B,'ANÁLISE DE RESULTADO'!B79,'03.2026'!G:G) -> 0 | G79: =SUMIF('04.2026'!B:B,'ANÁLISE DE RESULTADO'!B79,'04.2026'!G:G) -> -2040
A80: 4.3.06.01.0007 | B80: 3859 | C80: IOF | D80: =SUMIF('01.2026'!B:B,'ANÁLISE DE RESULTADO'!B80,'01.2026'!G:G) -> -1161.18 | E80: =SUMIF('02.2026'!B:B,'ANÁLISE DE RESULTADO'!B80,'02.2026'!G:G) -> -2104.77 | F80: =SUMIF('03.2026'!B:B,'ANÁLISE DE RESULTADO'!B80,'03.2026'!G:G) -> -1734.13 | G80: =SUMIF('04.2026'!B:B,'ANÁLISE DE RESULTADO'!B80,'04.2026'!G:G) -> -1405.82
A81: 4.3.06.01.0009 | B81: 4863 | C81: ICMS Destino Difal sobre Brinde | D81: =SUMIF('01.2026'!B:B,'ANÁLISE DE RESULTADO'!B81,'01.2026'!G:G) -> -7156.46 | E81: =SUMIF('02.2026'!B:B,'ANÁLISE DE RESULTADO'!B81,'02.2026'!G:G) -> -19880.5 | F81: =SUMIF('03.2026'!B:B,'ANÁLISE DE RESULTADO'!B81,'03.2026'!G:G) -> -11304.45 | G81: =SUMIF('04.2026'!B:B,'ANÁLISE DE RESULTADO'!B81,'04.2026'!G:G) -> -8915.2
A82: 4.3.11 | C82: DESPESAS FINANCEIRAS | D82: =D83 -> -149404.09 | E82: =E83 -> -124772.8 | F82: =F83 -> -134292.69 | G82: =G83 -> -91256.88
A83: 4.3.11.01 | C83: DESPESAS FINANCEIRAS | D83: =SUM(D84:D87) -> -149404.09 | E83: =SUM(E84:E87) -> -124772.8 | F83: =SUM(F84:F87) -> -134292.69 | G83: =SUM(G84:G87) -> -91256.88
A84: 4.3.11.01.0001 | B84: 3816 | C84: Despesas Bancárias | D84: =SUMIF('01.2026'!B:B,'ANÁLISE DE RESULTADO'!B84,'01.2026'!G:G) -> -975.35 | E84: =SUMIF('02.2026'!B:B,'ANÁLISE DE RESULTADO'!B84,'02.2026'!G:G) -> -741.79 | F84: =SUMIF('03.2026'!B:B,'ANÁLISE DE RESULTADO'!B84,'03.2026'!G:G) -> -818.26 | G84: =SUMIF('04.2026'!B:B,'ANÁLISE DE RESULTADO'!B84,'04.2026'!G:G) -> -855.8
A85: 4.3.11.01.0002 | B85: 3824 | C85: Multa/Juros sobre Impostos Pagos em Atra | D85: =SUMIF('01.2026'!B:B,'ANÁLISE DE RESULTADO'!B85,'01.2026'!G:G) -> -5705.43 | E85: =SUMIF('02.2026'!B:B,'ANÁLISE DE RESULTADO'!B85,'02.2026'!G:G) -> -3607.35 | F85: =SUMIF('03.2026'!B:B,'ANÁLISE DE RESULTADO'!B85,'03.2026'!G:G) -> 0 | G85: =SUMIF('04.2026'!B:B,'ANÁLISE DE RESULTADO'!B85,'04.2026'!G:G) -> -3498.31
A86: 4.3.11.01.0003 | B86: 3832 | C86: Multa/Juros sobre Outras Contas Pagas | D86: =SUMIF('01.2026'!B:B,'ANÁLISE DE RESULTADO'!B86,'01.2026'!G:G) -> -5752.61 | E86: =SUMIF('02.2026'!B:B,'ANÁLISE DE RESULTADO'!B86,'02.2026'!G:G) -> -40142.35 | F86: =SUMIF('03.2026'!B:B,'ANÁLISE DE RESULTADO'!B86,'03.2026'!G:G) -> -12684.84 | G86: =SUMIF('04.2026'!B:B,'ANÁLISE DE RESULTADO'!B86,'04.2026'!G:G) -> -6856.38
A87: 4.3.11.01.0007 | B87: 5177 | C87: Encargos Financeiros - SELIC | D87: =SUMIF('01.2026'!B:B,'ANÁLISE DE RESULTADO'!B87,'01.2026'!G:G) -> -136970.7 | E87: =SUMIF('02.2026'!B:B,'ANÁLISE DE RESULTADO'!B87,'02.2026'!G:G) -> -80281.31 | F87: =SUMIF('03.2026'!B:B,'ANÁLISE DE RESULTADO'!B87,'03.2026'!G:G) -> -120789.59 | G87: =SUMIF('04.2026'!B:B,'ANÁLISE DE RESULTADO'!B87,'04.2026'!G:G) -> -80046.39
C89: RESULTADO LÍQUIDO DO PERÍODO | D89: =D2+D18 -> -352643.01 | E89: =E2+E18 -> -289066.03 | F89: =F2+F18 -> -54835.27 | G89: =G2+G18 -> -348897.19
