Workbook

Sheet Bisyou_DRE
A1: BISYOU — interactive channel DRE. Edit the yellow cells; everything below recalculates (open in Excel).
A3: ASSUMPTIONS (edit yellow) | C3: Conservative | D3: Run-rate
A4: Net revenue – annual (R$) | C4: 5500000 | D4: 7600000
A5: Gross margin % | C5: 0.8 | D5: 0.8
A6: Selling/logistics/card % | C6: 0.17 | D6: 0.17
A7: Marketing / CPA % | C7: 0.25 | D7: 0.25
A8: SG&A – annual (R$) | C8: 1250000 | D8: 1250000
A9: Royalty % | C9: 0.08 | D9: 0.08
A10: Tax gross-up % (net=gross*(1-tax)) | C10: 0.13 | D10: 0.13
A12: Gross revenue (R$) | C12: =C4/(1-C10) | D12: =D4/(1-D10)
A13: Monthly gross (R$) | C13: =C12/12 | D13: =D12/12
A14: Boniteca % (regressive lookup) | C14: =INDEX($G$31:$G$37,COUNT($F$31:$F$37)-COUNTIF($F$31:$F$37,">"&C13)+1) | D14: =INDEX($G$31:$G$37,COUNT($F$31:$F$37)-COUNTIF($F$31:$F$37,">"&D13)+1)
A16: DRE — ANNUAL RUN-RATE (R$) | C16: Conservative | D16: Run-rate
A17: Receita líquida | C17: =C4 | D17: =D4
A18: (–) CMV | C18: =-(1-C5)*C4 | D18: =-(1-D5)*D4
A19: =Margem bruta | C19: =C5*C4 | D19: =D5*D4
A20: (–) Despesas de venda | C20: =-C6*C4 | D20: =-D6*D4
A21: (–) Marketing / CPA | C21: =-C7*C4 | D21: =-D7*D4
A22: (–) SG&A | C22: =-C8 | D22: =-D8
A23: (–) Royalty | C23: =-C9*C4 | D23: =-D9*D4
A24: (–) Boniteca fee | C24: =-C14*C12 | D24: =-D14*D12
A25: =EBITDA (annual) | C25: =C19+C20+C21+C22+C23+C24 | D25: =D19+D20+D21+D22+D23+D24
A26: EBITDA margin % | C26: =C25/C4 | D26: =D25/D4
A27: =EBITDA — H2-2026 (Jul–Dec, ×0.5) | C27: =C25*0.5 | D27: =D25*0.5
A28: Boniteca uses GE's regressive table on MONTHLY gross (Bisyou's small scale → ~9%). Change Net revenue and the rate re-looks-up automatically.
F30: Boniteca band (monthly gross →) | G30: Fee %
F31: 500000 | G31: 0.1
F32: 750000 | G32: 0.09
F33: 1000000 | G33: 0.08
F34: 1250000 | G34: 0.075
F35: 1500000 | G35: 0.065
F36: 2000000 | G36: 0.06
F37: 10000000 | G37: 0.05

Sheet Group_Impact
A1: GROUP P&L IMPACT — GE 2026 (BP) + Bisyou H2-2026 (live from the Bisyou tab, Conservative col).
A3: Line | B3: GE 2026 (BP) | C3: Bisyou H2-2026 | D3: Pro-forma | E3: Δ %
A4: Receita líquida | B4: 16422117 | C4: ='Bisyou_DRE'!C17*0.5 | D4: =B4+C4 | E4: =C4/B4
A5: Margem bruta | B5: 11418596 | C5: ='Bisyou_DRE'!C19*0.5 | D5: =B5+C5 | E5: =C5/B5
A6: Margem de contribuição | B6: 6841991.6 | C6: =('Bisyou_DRE'!C19+'Bisyou_DRE'!C20+'Bisyou_DRE'!C21)*0.5 | D6: =B6+C6 | E6: =C6/B6
A7: EBITDA | B7: 3306290.3 | C7: ='Bisyou_DRE'!C25*0.5 | D7: =B7+C7 | E7: =C7/B7
A10: GE figures are the BP's 2026 group totals (static snapshot). Bisyou side is live from the Bisyou tab. NB: GE EBITDA is PRE-Boniteca (model convention); Bisyou EBITDA here is post-Boniteca+royalty.

Sheet Sensitivity
A1: EBITDA CONTRIBUTION (annual, R$) — Royalty % (rows) × Net revenue (cols). LIVE: references the Bisyou tab's GM/selling/mktg/SG&A/tax + band table.
A3: Royalty / Net rev | B3: 5000000 | C3: 5500000 | D3: 6000000 | E3: 6500000 | F3: 7000000 | G3: 7600000 | H3: 8000000
A4: 0.03 | B4: =B$3*'Bisyou_DRE'!$C$5-B$3*'Bisyou_DRE'!$C$6-B$3*'Bisyou_DRE'!$C$7-'Bisyou_DRE'!$C$8-$A4*B$3-INDEX('Bisyou_DRE'!$G$31:$G$37,COUNT('Bisyou_DRE'!$F$31:$F$37)-COUNTIF('Bisyou_DRE'!$F$31:$F$37,">"&((B$3/(1-'Bisyou_DRE'!$C$10))/12))+1)*(B$3/(1-'Bisyou_DRE'!$C$10)) | C4: =C$3*'Bisyou_DRE'!$C$5-C$3*'Bisyou_DRE'!$C$6-C$3*'Bisyou_DRE'!$C$7-'Bisyou_DRE'!$C$8-$A4*C$3-INDEX('Bisyou_DRE'!$G$31:$G$37,COUNT('Bisyou_DRE'!$F$31:$F$37)-COUNTIF('Bisyou_DRE'!$F$31:$F$37,">"&((C$3/(1-'Bisyou_DRE'!$C$10))/12))+1)*(C$3/(1-'Bisyou_DRE'!$C$10)) | D4: =D$3*'Bisyou_DRE'!$C$5-D$3*'Bisyou_DRE'!$C$6-D$3*'Bisyou_DRE'!$C$7-'Bisyou_DRE'!$C$8-$A4*D$3-INDEX('Bisyou_DRE'!$G$31:$G$37,COUNT('Bisyou_DRE'!$F$31:$F$37)-COUNTIF('Bisyou_DRE'!$F$31:$F$37,">"&((D$3/(1-'Bisyou_DRE'!$C$10))/12))+1)*(D$3/(1-'Bisyou_DRE'!$C$10)) | E4: =E$3*'Bisyou_DRE'!$C$5-E$3*'Bisyou_DRE'!$C$6-E$3*'Bisyou_DRE'!$C$7-'Bisyou_DRE'!$C$8-$A4*E$3-INDEX('Bisyou_DRE'!$G$31:$G$37,COUNT('Bisyou_DRE'!$F$31:$F$37)-COUNTIF('Bisyou_DRE'!$F$31:$F$37,">"&((E$3/(1-'Bisyou_DRE'!$C$10))/12))+1)*(E$3/(1-'Bisyou_DRE'!$C$10)) | F4: =F$3*'Bisyou_DRE'!$C$5-F$3*'Bisyou_DRE'!$C$6-F$3*'Bisyou_DRE'!$C$7-'Bisyou_DRE'!$C$8-$A4*F$3-INDEX('Bisyou_DRE'!$G$31:$G$37,COUNT('Bisyou_DRE'!$F$31:$F$37)-COUNTIF('Bisyou_DRE'!$F$31:$F$37,">"&((F$3/(1-'Bisyou_DRE'!$C$10))/12))+1)*(F$3/(1-'Bisyou_DRE'!$C$10)) | G4: =G$3*'Bisyou_DRE'!$C$5-G$3*'Bisyou_DRE'!$C$6-G$3*'Bisyou_DRE'!$C$7-'Bisyou_DRE'!$C$8-$A4*G$3-INDEX('Bisyou_DRE'!$G$31:$G$37,COUNT('Bisyou_DRE'!$F$31:$F$37)-COUNTIF('Bisyou_DRE'!$F$31:$F$37,">"&((G$3/(1-'Bisyou_DRE'!$C$10))/12))+1)*(G$3/(1-'Bisyou_DRE'!$C$10)) | H4: =H$3*'Bisyou_DRE'!$C$5-H$3*'Bisyou_DRE'!$C$6-H$3*'Bisyou_DRE'!$C$7-'Bisyou_DRE'!$C$8-$A4*H$3-INDEX('Bisyou_DRE'!$G$31:$G$37,COUNT('Bisyou_DRE'!$F$31:$F$37)-COUNTIF('Bisyou_DRE'!$F$31:$F$37,">"&((H$3/(1-'Bisyou_DRE'!$C$10))/12))+1)*(H$3/(1-'Bisyou_DRE'!$C$10))
A5: 0.04 | B5: =B$3*'Bisyou_DRE'!$C$5-B$3*'Bisyou_DRE'!$C$6-B$3*'Bisyou_DRE'!$C$7-'Bisyou_DRE'!$C$8-$A5*B$3-INDEX('Bisyou_DRE'!$G$31:$G$37,COUNT('Bisyou_DRE'!$F$31:$F$37)-COUNTIF('Bisyou_DRE'!$F$31:$F$37,">"&((B$3/(1-'Bisyou_DRE'!$C$10))/12))+1)*(B$3/(1-'Bisyou_DRE'!$C$10)) | C5: =C$3*'Bisyou_DRE'!$C$5-C$3*'Bisyou_DRE'!$C$6-C$3*'Bisyou_DRE'!$C$7-'Bisyou_DRE'!$C$8-$A5*C$3-INDEX('Bisyou_DRE'!$G$31:$G$37,COUNT('Bisyou_DRE'!$F$31:$F$37)-COUNTIF('Bisyou_DRE'!$F$31:$F$37,">"&((C$3/(1-'Bisyou_DRE'!$C$10))/12))+1)*(C$3/(1-'Bisyou_DRE'!$C$10)) | D5: =D$3*'Bisyou_DRE'!$C$5-D$3*'Bisyou_DRE'!$C$6-D$3*'Bisyou_DRE'!$C$7-'Bisyou_DRE'!$C$8-$A5*D$3-INDEX('Bisyou_DRE'!$G$31:$G$37,COUNT('Bisyou_DRE'!$F$31:$F$37)-COUNTIF('Bisyou_DRE'!$F$31:$F$37,">"&((D$3/(1-'Bisyou_DRE'!$C$10))/12))+1)*(D$3/(1-'Bisyou_DRE'!$C$10)) | E5: =E$3*'Bisyou_DRE'!$C$5-E$3*'Bisyou_DRE'!$C$6-E$3*'Bisyou_DRE'!$C$7-'Bisyou_DRE'!$C$8-$A5*E$3-INDEX('Bisyou_DRE'!$G$31:$G$37,COUNT('Bisyou_DRE'!$F$31:$F$37)-COUNTIF('Bisyou_DRE'!$F$31:$F$37,">"&((E$3/(1-'Bisyou_DRE'!$C$10))/12))+1)*(E$3/(1-'Bisyou_DRE'!$C$10)) | F5: =F$3*'Bisyou_DRE'!$C$5-F$3*'Bisyou_DRE'!$C$6-F$3*'Bisyou_DRE'!$C$7-'Bisyou_DRE'!$C$8-$A5*F$3-INDEX('Bisyou_DRE'!$G$31:$G$37,COUNT('Bisyou_DRE'!$F$31:$F$37)-COUNTIF('Bisyou_DRE'!$F$31:$F$37,">"&((F$3/(1-'Bisyou_DRE'!$C$10))/12))+1)*(F$3/(1-'Bisyou_DRE'!$C$10)) | G5: =G$3*'Bisyou_DRE'!$C$5-G$3*'Bisyou_DRE'!$C$6-G$3*'Bisyou_DRE'!$C$7-'Bisyou_DRE'!$C$8-$A5*G$3-INDEX('Bisyou_DRE'!$G$31:$G$37,COUNT('Bisyou_DRE'!$F$31:$F$37)-COUNTIF('Bisyou_DRE'!$F$31:$F$37,">"&((G$3/(1-'Bisyou_DRE'!$C$10))/12))+1)*(G$3/(1-'Bisyou_DRE'!$C$10)) | H5: =H$3*'Bisyou_DRE'!$C$5-H$3*'Bisyou_DRE'!$C$6-H$3*'Bisyou_DRE'!$C$7-'Bisyou_DRE'!$C$8-$A5*H$3-INDEX('Bisyou_DRE'!$G$31:$G$37,COUNT('Bisyou_DRE'!$F$31:$F$37)-COUNTIF('Bisyou_DRE'!$F$31:$F$37,">"&((H$3/(1-'Bisyou_DRE'!$C$10))/12))+1)*(H$3/(1-'Bisyou_DRE'!$C$10))
A6: 0.05 | B6: =B$3*'Bisyou_DRE'!$C$5-B$3*'Bisyou_DRE'!$C$6-B$3*'Bisyou_DRE'!$C$7-'Bisyou_DRE'!$C$8-$A6*B$3-INDEX('Bisyou_DRE'!$G$31:$G$37,COUNT('Bisyou_DRE'!$F$31:$F$37)-COUNTIF('Bisyou_DRE'!$F$31:$F$37,">"&((B$3/(1-'Bisyou_DRE'!$C$10))/12))+1)*(B$3/(1-'Bisyou_DRE'!$C$10)) | C6: =C$3*'Bisyou_DRE'!$C$5-C$3*'Bisyou_DRE'!$C$6-C$3*'Bisyou_DRE'!$C$7-'Bisyou_DRE'!$C$8-$A6*C$3-INDEX('Bisyou_DRE'!$G$31:$G$37,COUNT('Bisyou_DRE'!$F$31:$F$37)-COUNTIF('Bisyou_DRE'!$F$31:$F$37,">"&((C$3/(1-'Bisyou_DRE'!$C$10))/12))+1)*(C$3/(1-'Bisyou_DRE'!$C$10)) | D6: =D$3*'Bisyou_DRE'!$C$5-D$3*'Bisyou_DRE'!$C$6-D$3*'Bisyou_DRE'!$C$7-'Bisyou_DRE'!$C$8-$A6*D$3-INDEX('Bisyou_DRE'!$G$31:$G$37,COUNT('Bisyou_DRE'!$F$31:$F$37)-COUNTIF('Bisyou_DRE'!$F$31:$F$37,">"&((D$3/(1-'Bisyou_DRE'!$C$10))/12))+1)*(D$3/(1-'Bisyou_DRE'!$C$10)) | E6: =E$3*'Bisyou_DRE'!$C$5-E$3*'Bisyou_DRE'!$C$6-E$3*'Bisyou_DRE'!$C$7-'Bisyou_DRE'!$C$8-$A6*E$3-INDEX('Bisyou_DRE'!$G$31:$G$37,COUNT('Bisyou_DRE'!$F$31:$F$37)-COUNTIF('Bisyou_DRE'!$F$31:$F$37,">"&((E$3/(1-'Bisyou_DRE'!$C$10))/12))+1)*(E$3/(1-'Bisyou_DRE'!$C$10)) | F6: =F$3*'Bisyou_DRE'!$C$5-F$3*'Bisyou_DRE'!$C$6-F$3*'Bisyou_DRE'!$C$7-'Bisyou_DRE'!$C$8-$A6*F$3-INDEX('Bisyou_DRE'!$G$31:$G$37,COUNT('Bisyou_DRE'!$F$31:$F$37)-COUNTIF('Bisyou_DRE'!$F$31:$F$37,">"&((F$3/(1-'Bisyou_DRE'!$C$10))/12))+1)*(F$3/(1-'Bisyou_DRE'!$C$10)) | G6: =G$3*'Bisyou_DRE'!$C$5-G$3*'Bisyou_DRE'!$C$6-G$3*'Bisyou_DRE'!$C$7-'Bisyou_DRE'!$C$8-$A6*G$3-INDEX('Bisyou_DRE'!$G$31:$G$37,COUNT('Bisyou_DRE'!$F$31:$F$37)-COUNTIF('Bisyou_DRE'!$F$31:$F$37,">"&((G$3/(1-'Bisyou_DRE'!$C$10))/12))+1)*(G$3/(1-'Bisyou_DRE'!$C$10)) | H6: =H$3*'Bisyou_DRE'!$C$5-H$3*'Bisyou_DRE'!$C$6-H$3*'Bisyou_DRE'!$C$7-'Bisyou_DRE'!$C$8-$A6*H$3-INDEX('Bisyou_DRE'!$G$31:$G$37,COUNT('Bisyou_DRE'!$F$31:$F$37)-COUNTIF('Bisyou_DRE'!$F$31:$F$37,">"&((H$3/(1-'Bisyou_DRE'!$C$10))/12))+1)*(H$3/(1-'Bisyou_DRE'!$C$10))
A7: 0.06 | B7: =B$3*'Bisyou_DRE'!$C$5-B$3*'Bisyou_DRE'!$C$6-B$3*'Bisyou_DRE'!$C$7-'Bisyou_DRE'!$C$8-$A7*B$3-INDEX('Bisyou_DRE'!$G$31:$G$37,COUNT('Bisyou_DRE'!$F$31:$F$37)-COUNTIF('Bisyou_DRE'!$F$31:$F$37,">"&((B$3/(1-'Bisyou_DRE'!$C$10))/12))+1)*(B$3/(1-'Bisyou_DRE'!$C$10)) | C7: =C$3*'Bisyou_DRE'!$C$5-C$3*'Bisyou_DRE'!$C$6-C$3*'Bisyou_DRE'!$C$7-'Bisyou_DRE'!$C$8-$A7*C$3-INDEX('Bisyou_DRE'!$G$31:$G$37,COUNT('Bisyou_DRE'!$F$31:$F$37)-COUNTIF('Bisyou_DRE'!$F$31:$F$37,">"&((C$3/(1-'Bisyou_DRE'!$C$10))/12))+1)*(C$3/(1-'Bisyou_DRE'!$C$10)) | D7: =D$3*'Bisyou_DRE'!$C$5-D$3*'Bisyou_DRE'!$C$6-D$3*'Bisyou_DRE'!$C$7-'Bisyou_DRE'!$C$8-$A7*D$3-INDEX('Bisyou_DRE'!$G$31:$G$37,COUNT('Bisyou_DRE'!$F$31:$F$37)-COUNTIF('Bisyou_DRE'!$F$31:$F$37,">"&((D$3/(1-'Bisyou_DRE'!$C$10))/12))+1)*(D$3/(1-'Bisyou_DRE'!$C$10)) | E7: =E$3*'Bisyou_DRE'!$C$5-E$3*'Bisyou_DRE'!$C$6-E$3*'Bisyou_DRE'!$C$7-'Bisyou_DRE'!$C$8-$A7*E$3-INDEX('Bisyou_DRE'!$G$31:$G$37,COUNT('Bisyou_DRE'!$F$31:$F$37)-COUNTIF('Bisyou_DRE'!$F$31:$F$37,">"&((E$3/(1-'Bisyou_DRE'!$C$10))/12))+1)*(E$3/(1-'Bisyou_DRE'!$C$10)) | F7: =F$3*'Bisyou_DRE'!$C$5-F$3*'Bisyou_DRE'!$C$6-F$3*'Bisyou_DRE'!$C$7-'Bisyou_DRE'!$C$8-$A7*F$3-INDEX('Bisyou_DRE'!$G$31:$G$37,COUNT('Bisyou_DRE'!$F$31:$F$37)-COUNTIF('Bisyou_DRE'!$F$31:$F$37,">"&((F$3/(1-'Bisyou_DRE'!$C$10))/12))+1)*(F$3/(1-'Bisyou_DRE'!$C$10)) | G7: =G$3*'Bisyou_DRE'!$C$5-G$3*'Bisyou_DRE'!$C$6-G$3*'Bisyou_DRE'!$C$7-'Bisyou_DRE'!$C$8-$A7*G$3-INDEX('Bisyou_DRE'!$G$31:$G$37,COUNT('Bisyou_DRE'!$F$31:$F$37)-COUNTIF('Bisyou_DRE'!$F$31:$F$37,">"&((G$3/(1-'Bisyou_DRE'!$C$10))/12))+1)*(G$3/(1-'Bisyou_DRE'!$C$10)) | H7: =H$3*'Bisyou_DRE'!$C$5-H$3*'Bisyou_DRE'!$C$6-H$3*'Bisyou_DRE'!$C$7-'Bisyou_DRE'!$C$8-$A7*H$3-INDEX('Bisyou_DRE'!$G$31:$G$37,COUNT('Bisyou_DRE'!$F$31:$F$37)-COUNTIF('Bisyou_DRE'!$F$31:$F$37,">"&((H$3/(1-'Bisyou_DRE'!$C$10))/12))+1)*(H$3/(1-'Bisyou_DRE'!$C$10))
A8: 0.07 | B8: =B$3*'Bisyou_DRE'!$C$5-B$3*'Bisyou_DRE'!$C$6-B$3*'Bisyou_DRE'!$C$7-'Bisyou_DRE'!$C$8-$A8*B$3-INDEX('Bisyou_DRE'!$G$31:$G$37,COUNT('Bisyou_DRE'!$F$31:$F$37)-COUNTIF('Bisyou_DRE'!$F$31:$F$37,">"&((B$3/(1-'Bisyou_DRE'!$C$10))/12))+1)*(B$3/(1-'Bisyou_DRE'!$C$10)) | C8: =C$3*'Bisyou_DRE'!$C$5-C$3*'Bisyou_DRE'!$C$6-C$3*'Bisyou_DRE'!$C$7-'Bisyou_DRE'!$C$8-$A8*C$3-INDEX('Bisyou_DRE'!$G$31:$G$37,COUNT('Bisyou_DRE'!$F$31:$F$37)-COUNTIF('Bisyou_DRE'!$F$31:$F$37,">"&((C$3/(1-'Bisyou_DRE'!$C$10))/12))+1)*(C$3/(1-'Bisyou_DRE'!$C$10)) | D8: =D$3*'Bisyou_DRE'!$C$5-D$3*'Bisyou_DRE'!$C$6-D$3*'Bisyou_DRE'!$C$7-'Bisyou_DRE'!$C$8-$A8*D$3-INDEX('Bisyou_DRE'!$G$31:$G$37,COUNT('Bisyou_DRE'!$F$31:$F$37)-COUNTIF('Bisyou_DRE'!$F$31:$F$37,">"&((D$3/(1-'Bisyou_DRE'!$C$10))/12))+1)*(D$3/(1-'Bisyou_DRE'!$C$10)) | E8: =E$3*'Bisyou_DRE'!$C$5-E$3*'Bisyou_DRE'!$C$6-E$3*'Bisyou_DRE'!$C$7-'Bisyou_DRE'!$C$8-$A8*E$3-INDEX('Bisyou_DRE'!$G$31:$G$37,COUNT('Bisyou_DRE'!$F$31:$F$37)-COUNTIF('Bisyou_DRE'!$F$31:$F$37,">"&((E$3/(1-'Bisyou_DRE'!$C$10))/12))+1)*(E$3/(1-'Bisyou_DRE'!$C$10)) | F8: =F$3*'Bisyou_DRE'!$C$5-F$3*'Bisyou_DRE'!$C$6-F$3*'Bisyou_DRE'!$C$7-'Bisyou_DRE'!$C$8-$A8*F$3-INDEX('Bisyou_DRE'!$G$31:$G$37,COUNT('Bisyou_DRE'!$F$31:$F$37)-COUNTIF('Bisyou_DRE'!$F$31:$F$37,">"&((F$3/(1-'Bisyou_DRE'!$C$10))/12))+1)*(F$3/(1-'Bisyou_DRE'!$C$10)) | G8: =G$3*'Bisyou_DRE'!$C$5-G$3*'Bisyou_DRE'!$C$6-G$3*'Bisyou_DRE'!$C$7-'Bisyou_DRE'!$C$8-$A8*G$3-INDEX('Bisyou_DRE'!$G$31:$G$37,COUNT('Bisyou_DRE'!$F$31:$F$37)-COUNTIF('Bisyou_DRE'!$F$31:$F$37,">"&((G$3/(1-'Bisyou_DRE'!$C$10))/12))+1)*(G$3/(1-'Bisyou_DRE'!$C$10)) | H8: =H$3*'Bisyou_DRE'!$C$5-H$3*'Bisyou_DRE'!$C$6-H$3*'Bisyou_DRE'!$C$7-'Bisyou_DRE'!$C$8-$A8*H$3-INDEX('Bisyou_DRE'!$G$31:$G$37,COUNT('Bisyou_DRE'!$F$31:$F$37)-COUNTIF('Bisyou_DRE'!$F$31:$F$37,">"&((H$3/(1-'Bisyou_DRE'!$C$10))/12))+1)*(H$3/(1-'Bisyou_DRE'!$C$10))
A9: 0.08 | B9: =B$3*'Bisyou_DRE'!$C$5-B$3*'Bisyou_DRE'!$C$6-B$3*'Bisyou_DRE'!$C$7-'Bisyou_DRE'!$C$8-$A9*B$3-INDEX('Bisyou_DRE'!$G$31:$G$37,COUNT('Bisyou_DRE'!$F$31:$F$37)-COUNTIF('Bisyou_DRE'!$F$31:$F$37,">"&((B$3/(1-'Bisyou_DRE'!$C$10))/12))+1)*(B$3/(1-'Bisyou_DRE'!$C$10)) | C9: =C$3*'Bisyou_DRE'!$C$5-C$3*'Bisyou_DRE'!$C$6-C$3*'Bisyou_DRE'!$C$7-'Bisyou_DRE'!$C$8-$A9*C$3-INDEX('Bisyou_DRE'!$G$31:$G$37,COUNT('Bisyou_DRE'!$F$31:$F$37)-COUNTIF('Bisyou_DRE'!$F$31:$F$37,">"&((C$3/(1-'Bisyou_DRE'!$C$10))/12))+1)*(C$3/(1-'Bisyou_DRE'!$C$10)) | D9: =D$3*'Bisyou_DRE'!$C$5-D$3*'Bisyou_DRE'!$C$6-D$3*'Bisyou_DRE'!$C$7-'Bisyou_DRE'!$C$8-$A9*D$3-INDEX('Bisyou_DRE'!$G$31:$G$37,COUNT('Bisyou_DRE'!$F$31:$F$37)-COUNTIF('Bisyou_DRE'!$F$31:$F$37,">"&((D$3/(1-'Bisyou_DRE'!$C$10))/12))+1)*(D$3/(1-'Bisyou_DRE'!$C$10)) | E9: =E$3*'Bisyou_DRE'!$C$5-E$3*'Bisyou_DRE'!$C$6-E$3*'Bisyou_DRE'!$C$7-'Bisyou_DRE'!$C$8-$A9*E$3-INDEX('Bisyou_DRE'!$G$31:$G$37,COUNT('Bisyou_DRE'!$F$31:$F$37)-COUNTIF('Bisyou_DRE'!$F$31:$F$37,">"&((E$3/(1-'Bisyou_DRE'!$C$10))/12))+1)*(E$3/(1-'Bisyou_DRE'!$C$10)) | F9: =F$3*'Bisyou_DRE'!$C$5-F$3*'Bisyou_DRE'!$C$6-F$3*'Bisyou_DRE'!$C$7-'Bisyou_DRE'!$C$8-$A9*F$3-INDEX('Bisyou_DRE'!$G$31:$G$37,COUNT('Bisyou_DRE'!$F$31:$F$37)-COUNTIF('Bisyou_DRE'!$F$31:$F$37,">"&((F$3/(1-'Bisyou_DRE'!$C$10))/12))+1)*(F$3/(1-'Bisyou_DRE'!$C$10)) | G9: =G$3*'Bisyou_DRE'!$C$5-G$3*'Bisyou_DRE'!$C$6-G$3*'Bisyou_DRE'!$C$7-'Bisyou_DRE'!$C$8-$A9*G$3-INDEX('Bisyou_DRE'!$G$31:$G$37,COUNT('Bisyou_DRE'!$F$31:$F$37)-COUNTIF('Bisyou_DRE'!$F$31:$F$37,">"&((G$3/(1-'Bisyou_DRE'!$C$10))/12))+1)*(G$3/(1-'Bisyou_DRE'!$C$10)) | H9: =H$3*'Bisyou_DRE'!$C$5-H$3*'Bisyou_DRE'!$C$6-H$3*'Bisyou_DRE'!$C$7-'Bisyou_DRE'!$C$8-$A9*H$3-INDEX('Bisyou_DRE'!$G$31:$G$37,COUNT('Bisyou_DRE'!$F$31:$F$37)-COUNTIF('Bisyou_DRE'!$F$31:$F$37,">"&((H$3/(1-'Bisyou_DRE'!$C$10))/12))+1)*(H$3/(1-'Bisyou_DRE'!$C$10))
A12: Royalty ceiling (EBITDA=0) | B12: ='Bisyou_DRE'!$C$5-'Bisyou_DRE'!$C$6-'Bisyou_DRE'!$C$7-'Bisyou_DRE'!$C$8/B$3-INDEX('Bisyou_DRE'!$G$31:$G$37,COUNT('Bisyou_DRE'!$F$31:$F$37)-COUNTIF('Bisyou_DRE'!$F$31:$F$37,">"&((B$3/(1-'Bisyou_DRE'!$C$10))/12))+1)*(B$3/(1-'Bisyou_DRE'!$C$10))/B$3 | C12: ='Bisyou_DRE'!$C$5-'Bisyou_DRE'!$C$6-'Bisyou_DRE'!$C$7-'Bisyou_DRE'!$C$8/C$3-INDEX('Bisyou_DRE'!$G$31:$G$37,COUNT('Bisyou_DRE'!$F$31:$F$37)-COUNTIF('Bisyou_DRE'!$F$31:$F$37,">"&((C$3/(1-'Bisyou_DRE'!$C$10))/12))+1)*(C$3/(1-'Bisyou_DRE'!$C$10))/C$3 | D12: ='Bisyou_DRE'!$C$5-'Bisyou_DRE'!$C$6-'Bisyou_DRE'!$C$7-'Bisyou_DRE'!$C$8/D$3-INDEX('Bisyou_DRE'!$G$31:$G$37,COUNT('Bisyou_DRE'!$F$31:$F$37)-COUNTIF('Bisyou_DRE'!$F$31:$F$37,">"&((D$3/(1-'Bisyou_DRE'!$C$10))/12))+1)*(D$3/(1-'Bisyou_DRE'!$C$10))/D$3 | E12: ='Bisyou_DRE'!$C$5-'Bisyou_DRE'!$C$6-'Bisyou_DRE'!$C$7-'Bisyou_DRE'!$C$8/E$3-INDEX('Bisyou_DRE'!$G$31:$G$37,COUNT('Bisyou_DRE'!$F$31:$F$37)-COUNTIF('Bisyou_DRE'!$F$31:$F$37,">"&((E$3/(1-'Bisyou_DRE'!$C$10))/12))+1)*(E$3/(1-'Bisyou_DRE'!$C$10))/E$3 | F12: ='Bisyou_DRE'!$C$5-'Bisyou_DRE'!$C$6-'Bisyou_DRE'!$C$7-'Bisyou_DRE'!$C$8/F$3-INDEX('Bisyou_DRE'!$G$31:$G$37,COUNT('Bisyou_DRE'!$F$31:$F$37)-COUNTIF('Bisyou_DRE'!$F$31:$F$37,">"&((F$3/(1-'Bisyou_DRE'!$C$10))/12))+1)*(F$3/(1-'Bisyou_DRE'!$C$10))/F$3 | G12: ='Bisyou_DRE'!$C$5-'Bisyou_DRE'!$C$6-'Bisyou_DRE'!$C$7-'Bisyou_DRE'!$C$8/G$3-INDEX('Bisyou_DRE'!$G$31:$G$37,COUNT('Bisyou_DRE'!$F$31:$F$37)-COUNTIF('Bisyou_DRE'!$F$31:$F$37,">"&((G$3/(1-'Bisyou_DRE'!$C$10))/12))+1)*(G$3/(1-'Bisyou_DRE'!$C$10))/G$3 | H12: ='Bisyou_DRE'!$C$5-'Bisyou_DRE'!$C$6-'Bisyou_DRE'!$C$7-'Bisyou_DRE'!$C$8/H$3-INDEX('Bisyou_DRE'!$G$31:$G$37,COUNT('Bisyou_DRE'!$F$31:$F$37)-COUNTIF('Bisyou_DRE'!$F$31:$F$37,">"&((H$3/(1-'Bisyou_DRE'!$C$10))/12))+1)*(H$3/(1-'Bisyou_DRE'!$C$10))/H$3
A14: Green=accretive, red=dilutive (applied by Excel on open). Change marketing/SG&A on the Bisyou tab and the whole grid moves.
