Workbook
Name B2B_canais: #REF!
Name B2B_inicio: #REF!
Name B2B_início: #REF!
Name B2B_margem: #REF!
Name B2B_maturacao: #REF!
Name B2B_receitabruta: #REF!
Name B2B_sazonalidade: #REF!
Name B2B_sellout: #REF!
Name B2B_volume: #REF!
Name B2B_volumeprodutos: #REF!
Name B2B_volumeref: #REF!
Name Premissas_curvaabcajustada: #REF!
Name Premissas_produtos: #REF!

Sheet Grade
D1: 45261 | E1: 45292 | F1: 45323 | G1: 45352 | H1: 45383 | I1: 45413 | J1: 45444 | K1: 45474 | L1: 45505 | M1: 45536 | N1: 45566 | O1: 45597 | P1: 45627 | S1: 45292 | T1: 45323 | U1: 45352 | V1: 45383 | W1: 45413 | X1: 45444 | Y1: 45474 | Z1: 45505 | AA1: 45536 | AB1: 45566 | AC1: 45597 | AD1: 45627 | AH1: =EDATE(E1,-12) -> 44927 | AI1: =EDATE(F1,-12) -> 44958 | AJ1: =EDATE(G1,-12) -> 44986 | AK1: =EDATE(H1,-12) -> 45017 | AL1: =EDATE(I1,-12) -> 45047 | AM1: =EDATE(J1,-12) -> 45078 | AN1: =EDATE(K1,-12) -> 45108 | AO1: =EDATE(L1,-12) -> 45139 | ... AS1: =EDATE(P1,-12) -> 45261 | AW1: YTD | BA1: YTD | BG1: YTD
C2: 45627 | AW2: 45627 | BA2: =AW2 -> 45627 | BG2: =EDATE(AW2,-12) -> 45261
E3: Real | F3: Real | G3: Real | H3: Real | I3: Real | J3: Real | K3: Real | L3: Real | M3: Real | N3: Real | O3: Real | P3: Real | Q3: % | S3: Meta | T3: Meta | U3: Meta | V3: Meta | W3: Meta | X3: Meta | Y3: Meta | Z3: Meta | AA3: Meta | AB3: Meta | AC3: Meta | AD3: Meta | AE3: var R$ | AF3: var % | AH3: Ano-1 | AI3: Ano-1 | AJ3: Ano-1 | AK3: Ano-1 | AL3: Ano-1 | AM3: Ano-1 | AN3: Ano-1 | AO3: Ano-1 | AP3: Ano-1 | AQ3: Ano-1 | AR3: Ano-1 | AS3: Ano-1 | AT3: var R$ | AU3: var % | AW3: Real R$ | AX3: Real % | BA3: Meta R$ | BB3: Meta % | BC3: var R$ | BD3: var %/pp | BG3: Ano-1 R$ | BH3: Ano-1 % | BI3: var R$ | BJ3: var %/pp
A4: Receita | C4: Faturamento bruto | E4: =E5+E33+E34+E35 -> #REF! | F4: =F5+F33+F34+F35 -> #REF! | G4: =G5+G33+G34+G35 -> #REF! | H4: =H5+H33+H34+H35 -> #REF! | I4: =I5+I33+I34+I35 -> #REF! | J4: =J5+J33+J34+J35 -> #REF! | K4: =K5+K33+K34+K35 -> #REF! | L4: =L5+L33+L34+L35 -> #REF! | ... P4: =P5+P33+P34+P35 -> #REF! | S4: =S5+S33+S34+S35 -> #REF! | T4: =T5+T33+T34+T35 -> #REF! | U4: =U5+U33+U34+U35 -> #REF! | V4: =V5+V33+V34+V35 -> #REF! | W4: =W5+W33+W34+W35 -> #REF! | X4: =X5+X33+X34+X35 -> #REF! | Y4: =Y5+Y33+Y34+Y35 -> #REF! | Z4: =Z5+Z33+Z34+Z35 -> #REF! | ... AD4: =AD5+AD33+AD34+AD35 -> #REF! | AE4: =INDEX($E4:$P4,1,MATCH($C$2,$E$1:$P$1,0))-INDEX(S4:AD4,1,MATCH($C$2,S$1:AD$1,0)) -> #REF! | AF4: =IFERROR(INDEX($E4:$P4,1,MATCH($C$2,$E$1:$P$1,0))/INDEX($S4:$AD4,1,MATCH($C$2,S$1:AD$1,0))-1,0) -> 0 | AH4: =AH5+AH33+AH34+AH35 -> #REF! | AI4: =AI5+AI33+AI34+AI35 -> #REF! | AJ4: =AJ5+AJ33+AJ34+AJ35 -> #REF! | AK4: =AK5+AK33+AK34+AK35 -> #REF! | AL4: =AL5+AL33+AL34+AL35 -> #REF! | AM4: =AM5+AM33+AM34+AM35 -> #REF! | AN4: =AN5+AN33+AN34+AN35 -> #REF! | AO4: =AO5+AO33+AO34+AO35 -> #REF! | ... AS4: =AS5+AS33+AS34+AS35 -> #REF! | AT4: =INDEX($E4:$P4,1,MATCH($C$2,$E$1:$P$1,0))-INDEX(AH4:AS4,1,MATCH(EDATE($C$2,-12),AH$1:AS$1,0)) -> #REF! | AU4: =IFERROR(INDEX($E4:$P4,1,MATCH($C$2,$E$1:$P$1,0))/INDEX(AH4:AS4,1,MATCH(EDATE($C$2,-12),AH$1:AS$1,0))-1,0) -> 0 | AW4: =AW5+AW33+AW34+AW35 -> #REF! | BA4: =BA5+BA33+BA35 -> #REF! | BC4: =$AW4-BA4 -> #REF! | BD4: =IFERROR($AW4/BA4-1,"-") -> - | BG4: =SUMIF(AH$1:AS$1,"<="&BG$2,AH4:AS4) -> #REF! | BI4: =$AW4-BG4 -> #REF! | BJ4: =IFERROR($AW4/BG4-1,"-") -> -
A5: Receita | C5: Produtos | E5: =E6+E21+E15 -> #REF! | F5: =F6+F21+F15 -> #REF! | G5: =G6+G21+G15 -> #REF! | H5: =H6+H21+H15 -> #REF! | I5: =I6+I21+I15 -> #REF! | J5: =J6+J21+J15 -> #REF! | K5: =K6+K21+K15 -> #REF! | L5: =L6+L21+L15 -> #REF! | ... P5: =P6+P21+P15 -> #REF! | S5: =S6+S21 -> #REF! | T5: =T6+T21 -> #REF! | U5: =U6+U21 -> #REF! | V5: =V6+V21 -> #REF! | W5: =W6+W21 -> #REF! | X5: =X6+X21 -> #REF! | Y5: =Y6+Y21 -> #REF! | Z5: =Z6+Z21 -> #REF! | ... AD5: =AD6+AD21 -> #REF! | AE5: =INDEX($E5:$P5,1,MATCH($C$2,$E$1:$P$1,0))-INDEX(S5:AD5,1,MATCH($C$2,S$1:AD$1,0)) -> #REF! | AF5: =IFERROR(INDEX($E5:$P5,1,MATCH($C$2,$E$1:$P$1,0))/INDEX($S5:$AD5,1,MATCH($C$2,S$1:AD$1,0))-1,0) -> 0 | AH5: =AH6+AH21 -> #REF! | AI5: =AI6+AI21 -> #REF! | AJ5: =AJ6+AJ21 -> #REF! | AK5: =AK6+AK21 -> #REF! | AL5: =AL6+AL21 -> #REF! | AM5: =AM6+AM21 -> #REF! | AN5: =AN6+AN21 -> #REF! | AO5: =AO6+AO21 -> #REF! | ... AS5: =AS6+AS21 -> #REF! | AT5: =INDEX($E5:$P5,1,MATCH($C$2,$E$1:$P$1,0))-INDEX(AH5:AS5,1,MATCH(EDATE($C$2,-12),AH$1:AS$1,0)) -> #REF! | AU5: =IFERROR(INDEX($E5:$P5,1,MATCH($C$2,$E$1:$P$1,0))/INDEX(AH5:AS5,1,MATCH(EDATE($C$2,-12),AH$1:AS$1,0))-1,0) -> 0 | AW5: =AW6+AW21+AW15 -> #REF! | BA5: =BA6+BA21 -> #REF! | BC5: =$AW5-BA5 -> #REF! | BD5: =IFERROR($AW5/BA5-1,"-") -> - | BG5: =BG6+BG21 -> #REF! | BI5: =$AW5-BG5 -> #REF! | BJ5: =IFERROR($AW5/BG5-1,"-") -> -
A6: Receita | C6: Fórmulas | E6: =SUM(E7:E14) -> #REF! | F6: =SUM(F7:F14) -> #REF! | G6: =SUM(G7:G14) -> #REF! | H6: =SUM(H7:H14) -> #REF! | I6: =SUM(I7:I14) -> #REF! | J6: =SUM(J7:J14) -> #REF! | K6: =SUM(K7:K14) -> #REF! | L6: =SUM(L7:L14) -> #REF! | ... P6: =SUM(P7:P14) -> #REF! | S6: =SUM(S7:S14) -> #REF! | T6: =SUM(T7:T14) -> #REF! | U6: =SUM(U7:U14) -> #REF! | V6: =SUM(V7:V14) -> #REF! | W6: =SUM(W7:W14) -> #REF! | X6: =SUM(X7:X14) -> #REF! | Y6: =SUM(Y7:Y14) -> #REF! | Z6: =SUM(Z7:Z14) -> #REF! | ... AD6: =SUM(AD7:AD14) -> #REF! | AE6: =INDEX($E6:$P6,1,MATCH($C$2,$E$1:$P$1,0))-INDEX(S6:AD6,1,MATCH($C$2,S$1:AD$1,0)) -> #REF! | AF6: =IFERROR(INDEX($E6:$P6,1,MATCH($C$2,$E$1:$P$1,0))/INDEX($S6:$AD6,1,MATCH($C$2,S$1:AD$1,0))-1,0) -> 0 | AH6: =SUM(AH7:AH14) -> #REF! | AI6: =SUM(AI7:AI14) -> #REF! | AJ6: =SUM(AJ7:AJ14) -> #REF! | AK6: =SUM(AK7:AK14) -> #REF! | AL6: =SUM(AL7:AL14) -> #REF! | AM6: =SUM(AM7:AM14) -> #REF! | AN6: =SUM(AN7:AN14) -> #REF! | AO6: =SUM(AO7:AO14) -> #REF! | ... AS6: =SUM(AS7:AS14) -> #REF! | AT6: =INDEX($E6:$P6,1,MATCH($C$2,$E$1:$P$1,0))-INDEX(AH6:AS6,1,MATCH(EDATE($C$2,-12),AH$1:AS$1,0)) -> #REF! | AU6: =IFERROR(INDEX($E6:$P6,1,MATCH($C$2,$E$1:$P$1,0))/INDEX(AH6:AS6,1,MATCH(EDATE($C$2,-12),AH$1:AS$1,0))-1,0) -> 0 | AW6: =SUM(AW7:AW14) -> #REF! | BA6: =SUM(BA7:BA14) -> #REF! | BC6: =$AW6-BA6 -> #REF! | BD6: =IFERROR($AW6/BA6-1,"-") -> - | BG6: =SUM(BG7:BG14) -> #REF! | BI6: =$AW6-BG6 -> #REF! | BJ6: =IFERROR($AW6/BG6-1,"-") -> -
A7: Receita | C7: Shampoo 250ml | E7: {=INDEX(#REF!,MATCH($C7,#REF!,0),MATCH(E$1,#REF!,0))} -> #REF! | F7: {=INDEX(#REF!,MATCH($C7,#REF!,0),MATCH(F$1,#REF!,0))} -> #REF! | G7: {=INDEX(#REF!,MATCH($C7,#REF!,0),MATCH(G$1,#REF!,0))} -> #REF! | H7: {=INDEX(#REF!,MATCH($C7,#REF!,0),MATCH(H$1,#REF!,0))} -> #REF! | I7: {=INDEX(#REF!,MATCH($C7,#REF!,0),MATCH(I$1,#REF!,0))} -> #REF! | J7: {=INDEX(#REF!,MATCH($C7,#REF!,0),MATCH(J$1,#REF!,0))} -> #REF! | K7: {=INDEX(#REF!,MATCH($C7,#REF!,0),MATCH(K$1,#REF!,0))} -> #REF! | L7: {=INDEX(#REF!,MATCH($C7,#REF!,0),MATCH(L$1,#REF!,0))} -> #REF! | ... P7: {=INDEX(#REF!,MATCH($C7,#REF!,0),MATCH(P$1,#REF!,0))} -> #REF! | S7: {=INDEX(#REF!,MATCH($C7,#REF!,0),MATCH(S$1,#REF!,0))} -> #REF! | T7: {=INDEX(#REF!,MATCH($C7,#REF!,0),MATCH(T$1,#REF!,0))} -> #REF! | U7: {=INDEX(#REF!,MATCH($C7,#REF!,0),MATCH(U$1,#REF!,0))} -> #REF! | V7: {=INDEX(#REF!,MATCH($C7,#REF!,0),MATCH(V$1,#REF!,0))} -> #REF! | W7: {=INDEX(#REF!,MATCH($C7,#REF!,0),MATCH(W$1,#REF!,0))} -> #REF! | X7: {=INDEX(#REF!,MATCH($C7,#REF!,0),MATCH(X$1,#REF!,0))} -> #REF! | Y7: {=INDEX(#REF!,MATCH($C7,#REF!,0),MATCH(Y$1,#REF!,0))} -> #REF! | Z7: {=INDEX(#REF!,MATCH($C7,#REF!,0),MATCH(Z$1,#REF!,0))} -> #REF! | ... AD7: {=INDEX(#REF!,MATCH($C7,#REF!,0),MATCH(AD$1,#REF!,0))} -> #REF! | AE7: =INDEX($E7:$P7,1,MATCH($C$2,$E$1:$P$1,0))-INDEX(S7:AD7,1,MATCH($C$2,S$1:AD$1,0)) -> #REF! | AF7: =IFERROR(INDEX($E7:$P7,1,MATCH($C$2,$E$1:$P$1,0))/INDEX($S7:$AD7,1,MATCH($C$2,S$1:AD$1,0))-1,0) -> 0 | AH7: {=INDEX(#REF!,MATCH($C7,#REF!,0),MATCH(AH$1,#REF!,0))} -> #REF! | AI7: {=INDEX(#REF!,MATCH($C7,#REF!,0),MATCH(AI$1,#REF!,0))} -> #REF! | AJ7: {=INDEX(#REF!,MATCH($C7,#REF!,0),MATCH(AJ$1,#REF!,0))} -> #REF! | AK7: {=INDEX(#REF!,MATCH($C7,#REF!,0),MATCH(AK$1,#REF!,0))} -> #REF! | AL7: {=INDEX(#REF!,MATCH($C7,#REF!,0),MATCH(AL$1,#REF!,0))} -> #REF! | AM7: {=INDEX(#REF!,MATCH($C7,#REF!,0),MATCH(AM$1,#REF!,0))} -> #REF! | AN7: {=INDEX(#REF!,MATCH($C7,#REF!,0),MATCH(AN$1,#REF!,0))} -> #REF! | AO7: {=INDEX(#REF!,MATCH($C7,#REF!,0),MATCH(AO$1,#REF!,0))} -> #REF! | ... AS7: {=INDEX(#REF!,MATCH($C7,#REF!,0),MATCH(AS$1,#REF!,0))} -> #REF! | AT7: =INDEX($E7:$P7,1,MATCH($C$2,$E$1:$P$1,0))-INDEX(AH7:AS7,1,MATCH(EDATE($C$2,-12),AH$1:AS$1,0)) -> #REF! | AU7: =IFERROR(INDEX($E7:$P7,1,MATCH($C$2,$E$1:$P$1,0))/INDEX(AH7:AS7,1,MATCH(EDATE($C$2,-12),AH$1:AS$1,0))-1,0) -> 0 | AW7: =SUMIF(E$1:P$1,"<="&AW$2,E7:P7) -> #REF! | BA7: =SUMIF(S$1:AD$1,"<="&BA$2,S7:AD7) -> #REF! | BC7: =$AW7-BA7 -> #REF! | BD7: =IFERROR($AW7/BA7-1,"-") -> - | BG7: =SUMIF(AH$1:AS$1,"<="&BG$2,AH7:AS7) -> #REF! | BI7: =$AW7-BG7 -> #REF! | BJ7: =IFERROR($AW7/BG7-1,"-") -> -
A8: Receita | C8: Máscara 200ml | E8: {=INDEX(#REF!,MATCH($C8,#REF!,0),MATCH(E$1,#REF!,0))} -> #REF! | F8: {=INDEX(#REF!,MATCH($C8,#REF!,0),MATCH(F$1,#REF!,0))} -> #REF! | G8: {=INDEX(#REF!,MATCH($C8,#REF!,0),MATCH(G$1,#REF!,0))} -> #REF! | H8: {=INDEX(#REF!,MATCH($C8,#REF!,0),MATCH(H$1,#REF!,0))} -> #REF! | I8: {=INDEX(#REF!,MATCH($C8,#REF!,0),MATCH(I$1,#REF!,0))} -> #REF! | J8: {=INDEX(#REF!,MATCH($C8,#REF!,0),MATCH(J$1,#REF!,0))} -> #REF! | K8: {=INDEX(#REF!,MATCH($C8,#REF!,0),MATCH(K$1,#REF!,0))} -> #REF! | L8: {=INDEX(#REF!,MATCH($C8,#REF!,0),MATCH(L$1,#REF!,0))} -> #REF! | ... P8: {=INDEX(#REF!,MATCH($C8,#REF!,0),MATCH(P$1,#REF!,0))} -> #REF! | S8: {=INDEX(#REF!,MATCH($C8,#REF!,0),MATCH(S$1,#REF!,0))} -> #REF! | T8: {=INDEX(#REF!,MATCH($C8,#REF!,0),MATCH(T$1,#REF!,0))} -> #REF! | U8: {=INDEX(#REF!,MATCH($C8,#REF!,0),MATCH(U$1,#REF!,0))} -> #REF! | V8: {=INDEX(#REF!,MATCH($C8,#REF!,0),MATCH(V$1,#REF!,0))} -> #REF! | W8: {=INDEX(#REF!,MATCH($C8,#REF!,0),MATCH(W$1,#REF!,0))} -> #REF! | X8: {=INDEX(#REF!,MATCH($C8,#REF!,0),MATCH(X$1,#REF!,0))} -> #REF! | Y8: {=INDEX(#REF!,MATCH($C8,#REF!,0),MATCH(Y$1,#REF!,0))} -> #REF! | Z8: {=INDEX(#REF!,MATCH($C8,#REF!,0),MATCH(Z$1,#REF!,0))} -> #REF! | ... AD8: {=INDEX(#REF!,MATCH($C8,#REF!,0),MATCH(AD$1,#REF!,0))} -> #REF! | AE8: =INDEX($E8:$P8,1,MATCH($C$2,$E$1:$P$1,0))-INDEX(S8:AD8,1,MATCH($C$2,S$1:AD$1,0)) -> #REF! | AF8: =IFERROR(INDEX($E8:$P8,1,MATCH($C$2,$E$1:$P$1,0))/INDEX($S8:$AD8,1,MATCH($C$2,S$1:AD$1,0))-1,0) -> 0 | AH8: {=INDEX(#REF!,MATCH($C8,#REF!,0),MATCH(AH$1,#REF!,0))} -> #REF! | AI8: {=INDEX(#REF!,MATCH($C8,#REF!,0),MATCH(AI$1,#REF!,0))} -> #REF! | AJ8: {=INDEX(#REF!,MATCH($C8,#REF!,0),MATCH(AJ$1,#REF!,0))} -> #REF! | AK8: {=INDEX(#REF!,MATCH($C8,#REF!,0),MATCH(AK$1,#REF!,0))} -> #REF! | AL8: {=INDEX(#REF!,MATCH($C8,#REF!,0),MATCH(AL$1,#REF!,0))} -> #REF! | AM8: {=INDEX(#REF!,MATCH($C8,#REF!,0),MATCH(AM$1,#REF!,0))} -> #REF! | AN8: {=INDEX(#REF!,MATCH($C8,#REF!,0),MATCH(AN$1,#REF!,0))} -> #REF! | AO8: {=INDEX(#REF!,MATCH($C8,#REF!,0),MATCH(AO$1,#REF!,0))} -> #REF! | ... AS8: {=INDEX(#REF!,MATCH($C8,#REF!,0),MATCH(AS$1,#REF!,0))} -> #REF! | AT8: =INDEX($E8:$P8,1,MATCH($C$2,$E$1:$P$1,0))-INDEX(AH8:AS8,1,MATCH(EDATE($C$2,-12),AH$1:AS$1,0)) -> #REF! | AU8: =IFERROR(INDEX($E8:$P8,1,MATCH($C$2,$E$1:$P$1,0))/INDEX(AH8:AS8,1,MATCH(EDATE($C$2,-12),AH$1:AS$1,0))-1,0) -> 0 | AW8: =SUMIF(E$1:P$1,"<="&AW$2,E8:P8) -> #REF! | BA8: =SUMIF(S$1:AD$1,"<="&BA$2,S8:AD8) -> #REF! | BC8: =$AW8-BA8 -> #REF! | BD8: =IFERROR($AW8/BA8-1,"-") -> - | BG8: =SUMIF(AH$1:AS$1,"<="&BG$2,AH8:AS8) -> #REF! | BI8: =$AW8-BG8 -> #REF! | BJ8: =IFERROR($AW8/BG8-1,"-") -> -
A9: Receita | C9: Leave-in 150ml | E9: {=INDEX(#REF!,MATCH($C9,#REF!,0),MATCH(E$1,#REF!,0))} -> #REF! | F9: {=INDEX(#REF!,MATCH($C9,#REF!,0),MATCH(F$1,#REF!,0))} -> #REF! | G9: {=INDEX(#REF!,MATCH($C9,#REF!,0),MATCH(G$1,#REF!,0))} -> #REF! | H9: {=INDEX(#REF!,MATCH($C9,#REF!,0),MATCH(H$1,#REF!,0))} -> #REF! | I9: {=INDEX(#REF!,MATCH($C9,#REF!,0),MATCH(I$1,#REF!,0))} -> #REF! | J9: {=INDEX(#REF!,MATCH($C9,#REF!,0),MATCH(J$1,#REF!,0))} -> #REF! | K9: {=INDEX(#REF!,MATCH($C9,#REF!,0),MATCH(K$1,#REF!,0))} -> #REF! | L9: {=INDEX(#REF!,MATCH($C9,#REF!,0),MATCH(L$1,#REF!,0))} -> #REF! | ... P9: {=INDEX(#REF!,MATCH($C9,#REF!,0),MATCH(P$1,#REF!,0))} -> #REF! | S9: {=INDEX(#REF!,MATCH($C9,#REF!,0),MATCH(S$1,#REF!,0))} -> #REF! | T9: {=INDEX(#REF!,MATCH($C9,#REF!,0),MATCH(T$1,#REF!,0))} -> #REF! | U9: {=INDEX(#REF!,MATCH($C9,#REF!,0),MATCH(U$1,#REF!,0))} -> #REF! | V9: {=INDEX(#REF!,MATCH($C9,#REF!,0),MATCH(V$1,#REF!,0))} -> #REF! | W9: {=INDEX(#REF!,MATCH($C9,#REF!,0),MATCH(W$1,#REF!,0))} -> #REF! | X9: {=INDEX(#REF!,MATCH($C9,#REF!,0),MATCH(X$1,#REF!,0))} -> #REF! | Y9: {=INDEX(#REF!,MATCH($C9,#REF!,0),MATCH(Y$1,#REF!,0))} -> #REF! | Z9: {=INDEX(#REF!,MATCH($C9,#REF!,0),MATCH(Z$1,#REF!,0))} -> #REF! | ... AD9: {=INDEX(#REF!,MATCH($C9,#REF!,0),MATCH(AD$1,#REF!,0))} -> #REF! | AE9: =INDEX($E9:$P9,1,MATCH($C$2,$E$1:$P$1,0))-INDEX(S9:AD9,1,MATCH($C$2,S$1:AD$1,0)) -> #REF! | AF9: =IFERROR(INDEX($E9:$P9,1,MATCH($C$2,$E$1:$P$1,0))/INDEX($S9:$AD9,1,MATCH($C$2,S$1:AD$1,0))-1,0) -> 0 | AH9: {=INDEX(#REF!,MATCH($C9,#REF!,0),MATCH(AH$1,#REF!,0))} -> #REF! | AI9: {=INDEX(#REF!,MATCH($C9,#REF!,0),MATCH(AI$1,#REF!,0))} -> #REF! | AJ9: {=INDEX(#REF!,MATCH($C9,#REF!,0),MATCH(AJ$1,#REF!,0))} -> #REF! | AK9: {=INDEX(#REF!,MATCH($C9,#REF!,0),MATCH(AK$1,#REF!,0))} -> #REF! | AL9: {=INDEX(#REF!,MATCH($C9,#REF!,0),MATCH(AL$1,#REF!,0))} -> #REF! | AM9: {=INDEX(#REF!,MATCH($C9,#REF!,0),MATCH(AM$1,#REF!,0))} -> #REF! | AN9: {=INDEX(#REF!,MATCH($C9,#REF!,0),MATCH(AN$1,#REF!,0))} -> #REF! | AO9: {=INDEX(#REF!,MATCH($C9,#REF!,0),MATCH(AO$1,#REF!,0))} -> #REF! | ... AS9: {=INDEX(#REF!,MATCH($C9,#REF!,0),MATCH(AS$1,#REF!,0))} -> #REF! | AT9: =INDEX($E9:$P9,1,MATCH($C$2,$E$1:$P$1,0))-INDEX(AH9:AS9,1,MATCH(EDATE($C$2,-12),AH$1:AS$1,0)) -> #REF! | AU9: =IFERROR(INDEX($E9:$P9,1,MATCH($C$2,$E$1:$P$1,0))/INDEX(AH9:AS9,1,MATCH(EDATE($C$2,-12),AH$1:AS$1,0))-1,0) -> 0 | AW9: =SUMIF(E$1:P$1,"<="&AW$2,E9:P9) -> #REF! | BA9: =SUMIF(S$1:AD$1,"<="&BA$2,S9:AD9) -> #REF! | BC9: =$AW9-BA9 -> #REF! | BD9: =IFERROR($AW9/BA9-1,"-") -> - | BG9: =SUMIF(AH$1:AS$1,"<="&BG$2,AH9:AS9) -> #REF! | BI9: =$AW9-BG9 -> #REF! | BJ9: =IFERROR($AW9/BG9-1,"-") -> -
A10: Receita | C10: Booster antioxidante | E10: {=INDEX(#REF!,MATCH($C10,#REF!,0),MATCH(E$1,#REF!,0))} -> #REF! | F10: {=INDEX(#REF!,MATCH($C10,#REF!,0),MATCH(F$1,#REF!,0))} -> #REF! | G10: {=INDEX(#REF!,MATCH($C10,#REF!,0),MATCH(G$1,#REF!,0))} -> #REF! | H10: {=INDEX(#REF!,MATCH($C10,#REF!,0),MATCH(H$1,#REF!,0))} -> #REF! | I10: {=INDEX(#REF!,MATCH($C10,#REF!,0),MATCH(I$1,#REF!,0))} -> #REF! | J10: {=INDEX(#REF!,MATCH($C10,#REF!,0),MATCH(J$1,#REF!,0))} -> #REF! | K10: {=INDEX(#REF!,MATCH($C10,#REF!,0),MATCH(K$1,#REF!,0))} -> #REF! | L10: {=INDEX(#REF!,MATCH($C10,#REF!,0),MATCH(L$1,#REF!,0))} -> #REF! | ... P10: {=INDEX(#REF!,MATCH($C10,#REF!,0),MATCH(P$1,#REF!,0))} -> #REF! | S10: {=INDEX(#REF!,MATCH($C10,#REF!,0),MATCH(S$1,#REF!,0))} -> #REF! | T10: {=INDEX(#REF!,MATCH($C10,#REF!,0),MATCH(T$1,#REF!,0))} -> #REF! | U10: {=INDEX(#REF!,MATCH($C10,#REF!,0),MATCH(U$1,#REF!,0))} -> #REF! | V10: {=INDEX(#REF!,MATCH($C10,#REF!,0),MATCH(V$1,#REF!,0))} -> #REF! | W10: {=INDEX(#REF!,MATCH($C10,#REF!,0),MATCH(W$1,#REF!,0))} -> #REF! | X10: {=INDEX(#REF!,MATCH($C10,#REF!,0),MATCH(X$1,#REF!,0))} -> #REF! | Y10: {=INDEX(#REF!,MATCH($C10,#REF!,0),MATCH(Y$1,#REF!,0))} -> #REF! | Z10: {=INDEX(#REF!,MATCH($C10,#REF!,0),MATCH(Z$1,#REF!,0))} -> #REF! | ... AD10: {=INDEX(#REF!,MATCH($C10,#REF!,0),MATCH(AD$1,#REF!,0))} -> #REF! | AE10: =INDEX($E10:$P10,1,MATCH($C$2,$E$1:$P$1,0))-INDEX(S10:AD10,1,MATCH($C$2,S$1:AD$1,0)) -> #REF! | AF10: =IFERROR(INDEX($E10:$P10,1,MATCH($C$2,$E$1:$P$1,0))/INDEX($S10:$AD10,1,MATCH($C$2,S$1:AD$1,0))-1,0) -> 0 | AH10: {=INDEX(#REF!,MATCH($C10,#REF!,0),MATCH(AH$1,#REF!,0))} -> #REF! | AI10: {=INDEX(#REF!,MATCH($C10,#REF!,0),MATCH(AI$1,#REF!,0))} -> #REF! | AJ10: {=INDEX(#REF!,MATCH($C10,#REF!,0),MATCH(AJ$1,#REF!,0))} -> #REF! | AK10: {=INDEX(#REF!,MATCH($C10,#REF!,0),MATCH(AK$1,#REF!,0))} -> #REF! | AL10: {=INDEX(#REF!,MATCH($C10,#REF!,0),MATCH(AL$1,#REF!,0))} -> #REF! | AM10: {=INDEX(#REF!,MATCH($C10,#REF!,0),MATCH(AM$1,#REF!,0))} -> #REF! | AN10: {=INDEX(#REF!,MATCH($C10,#REF!,0),MATCH(AN$1,#REF!,0))} -> #REF! | AO10: {=INDEX(#REF!,MATCH($C10,#REF!,0),MATCH(AO$1,#REF!,0))} -> #REF! | ... AS10: {=INDEX(#REF!,MATCH($C10,#REF!,0),MATCH(AS$1,#REF!,0))} -> #REF! | AT10: =INDEX($E10:$P10,1,MATCH($C$2,$E$1:$P$1,0))-INDEX(AH10:AS10,1,MATCH(EDATE($C$2,-12),AH$1:AS$1,0)) -> #REF! | AU10: =IFERROR(INDEX($E10:$P10,1,MATCH($C$2,$E$1:$P$1,0))/INDEX(AH10:AS10,1,MATCH(EDATE($C$2,-12),AH$1:AS$1,0))-1,0) -> 0 | AW10: =SUMIF(E$1:P$1,"<="&AW$2,E10:P10) -> #REF! | BA10: =SUMIF(S$1:AD$1,"<="&BA$2,S10:AD10) -> #REF! | BC10: =$AW10-BA10 -> #REF! | BD10: =IFERROR($AW10/BA10-1,"-") -> - | BG10: =SUMIF(AH$1:AS$1,"<="&BG$2,AH10:AS10) -> #REF! | BI10: =$AW10-BG10 -> #REF! | BJ10: =IFERROR($AW10/BG10-1,"-") -> -
A11: Receita | C11: Booster definição | E11: {=INDEX(#REF!,MATCH($C11,#REF!,0),MATCH(E$1,#REF!,0))} -> #REF! | F11: {=INDEX(#REF!,MATCH($C11,#REF!,0),MATCH(F$1,#REF!,0))} -> #REF! | G11: {=INDEX(#REF!,MATCH($C11,#REF!,0),MATCH(G$1,#REF!,0))} -> #REF! | H11: {=INDEX(#REF!,MATCH($C11,#REF!,0),MATCH(H$1,#REF!,0))} -> #REF! | I11: {=INDEX(#REF!,MATCH($C11,#REF!,0),MATCH(I$1,#REF!,0))} -> #REF! | J11: {=INDEX(#REF!,MATCH($C11,#REF!,0),MATCH(J$1,#REF!,0))} -> #REF! | K11: {=INDEX(#REF!,MATCH($C11,#REF!,0),MATCH(K$1,#REF!,0))} -> #REF! | L11: {=INDEX(#REF!,MATCH($C11,#REF!,0),MATCH(L$1,#REF!,0))} -> #REF! | ... P11: {=INDEX(#REF!,MATCH($C11,#REF!,0),MATCH(P$1,#REF!,0))} -> #REF! | S11: {=INDEX(#REF!,MATCH($C11,#REF!,0),MATCH(S$1,#REF!,0))} -> #REF! | T11: {=INDEX(#REF!,MATCH($C11,#REF!,0),MATCH(T$1,#REF!,0))} -> #REF! | U11: {=INDEX(#REF!,MATCH($C11,#REF!,0),MATCH(U$1,#REF!,0))} -> #REF! | V11: {=INDEX(#REF!,MATCH($C11,#REF!,0),MATCH(V$1,#REF!,0))} -> #REF! | W11: {=INDEX(#REF!,MATCH($C11,#REF!,0),MATCH(W$1,#REF!,0))} -> #REF! | X11: {=INDEX(#REF!,MATCH($C11,#REF!,0),MATCH(X$1,#REF!,0))} -> #REF! | Y11: {=INDEX(#REF!,MATCH($C11,#REF!,0),MATCH(Y$1,#REF!,0))} -> #REF! | Z11: {=INDEX(#REF!,MATCH($C11,#REF!,0),MATCH(Z$1,#REF!,0))} -> #REF! | ... AD11: {=INDEX(#REF!,MATCH($C11,#REF!,0),MATCH(AD$1,#REF!,0))} -> #REF! | AE11: =INDEX($E11:$P11,1,MATCH($C$2,$E$1:$P$1,0))-INDEX(S11:AD11,1,MATCH($C$2,S$1:AD$1,0)) -> #REF! | AF11: =IFERROR(INDEX($E11:$P11,1,MATCH($C$2,$E$1:$P$1,0))/INDEX($S11:$AD11,1,MATCH($C$2,S$1:AD$1,0))-1,0) -> 0 | AH11: {=INDEX(#REF!,MATCH($C11,#REF!,0),MATCH(AH$1,#REF!,0))} -> #REF! | AI11: {=INDEX(#REF!,MATCH($C11,#REF!,0),MATCH(AI$1,#REF!,0))} -> #REF! | AJ11: {=INDEX(#REF!,MATCH($C11,#REF!,0),MATCH(AJ$1,#REF!,0))} -> #REF! | AK11: {=INDEX(#REF!,MATCH($C11,#REF!,0),MATCH(AK$1,#REF!,0))} -> #REF! | AL11: {=INDEX(#REF!,MATCH($C11,#REF!,0),MATCH(AL$1,#REF!,0))} -> #REF! | AM11: {=INDEX(#REF!,MATCH($C11,#REF!,0),MATCH(AM$1,#REF!,0))} -> #REF! | AN11: {=INDEX(#REF!,MATCH($C11,#REF!,0),MATCH(AN$1,#REF!,0))} -> #REF! | AO11: {=INDEX(#REF!,MATCH($C11,#REF!,0),MATCH(AO$1,#REF!,0))} -> #REF! | ... AS11: {=INDEX(#REF!,MATCH($C11,#REF!,0),MATCH(AS$1,#REF!,0))} -> #REF! | AT11: =INDEX($E11:$P11,1,MATCH($C$2,$E$1:$P$1,0))-INDEX(AH11:AS11,1,MATCH(EDATE($C$2,-12),AH$1:AS$1,0)) -> #REF! | AU11: =IFERROR(INDEX($E11:$P11,1,MATCH($C$2,$E$1:$P$1,0))/INDEX(AH11:AS11,1,MATCH(EDATE($C$2,-12),AH$1:AS$1,0))-1,0) -> 0 | AW11: =SUMIF(E$1:P$1,"<="&AW$2,E11:P11) -> #REF! | BA11: =SUMIF(S$1:AD$1,"<="&BA$2,S11:AD11) -> #REF! | BC11: =$AW11-BA11 -> #REF! | BD11: =IFERROR($AW11/BA11-1,"-") -> - | BG11: =SUMIF(AH$1:AS$1,"<="&BG$2,AH11:AS11) -> #REF! | BI11: =$AW11-BG11 -> #REF! | BJ11: =IFERROR($AW11/BG11-1,"-") -> -
A12: Receita | C12: Booster hidratante | E12: {=INDEX(#REF!,MATCH($C12,#REF!,0),MATCH(E$1,#REF!,0))} -> #REF! | F12: {=INDEX(#REF!,MATCH($C12,#REF!,0),MATCH(F$1,#REF!,0))} -> #REF! | G12: {=INDEX(#REF!,MATCH($C12,#REF!,0),MATCH(G$1,#REF!,0))} -> #REF! | H12: {=INDEX(#REF!,MATCH($C12,#REF!,0),MATCH(H$1,#REF!,0))} -> #REF! | I12: {=INDEX(#REF!,MATCH($C12,#REF!,0),MATCH(I$1,#REF!,0))} -> #REF! | J12: {=INDEX(#REF!,MATCH($C12,#REF!,0),MATCH(J$1,#REF!,0))} -> #REF! | K12: {=INDEX(#REF!,MATCH($C12,#REF!,0),MATCH(K$1,#REF!,0))} -> #REF! | L12: {=INDEX(#REF!,MATCH($C12,#REF!,0),MATCH(L$1,#REF!,0))} -> #REF! | ... P12: {=INDEX(#REF!,MATCH($C12,#REF!,0),MATCH(P$1,#REF!,0))} -> #REF! | S12: {=INDEX(#REF!,MATCH($C12,#REF!,0),MATCH(S$1,#REF!,0))} -> #REF! | T12: {=INDEX(#REF!,MATCH($C12,#REF!,0),MATCH(T$1,#REF!,0))} -> #REF! | U12: {=INDEX(#REF!,MATCH($C12,#REF!,0),MATCH(U$1,#REF!,0))} -> #REF! | V12: {=INDEX(#REF!,MATCH($C12,#REF!,0),MATCH(V$1,#REF!,0))} -> #REF! | W12: {=INDEX(#REF!,MATCH($C12,#REF!,0),MATCH(W$1,#REF!,0))} -> #REF! | X12: {=INDEX(#REF!,MATCH($C12,#REF!,0),MATCH(X$1,#REF!,0))} -> #REF! | Y12: {=INDEX(#REF!,MATCH($C12,#REF!,0),MATCH(Y$1,#REF!,0))} -> #REF! | Z12: {=INDEX(#REF!,MATCH($C12,#REF!,0),MATCH(Z$1,#REF!,0))} -> #REF! | ... AD12: {=INDEX(#REF!,MATCH($C12,#REF!,0),MATCH(AD$1,#REF!,0))} -> #REF! | AE12: =INDEX($E12:$P12,1,MATCH($C$2,$E$1:$P$1,0))-INDEX(S12:AD12,1,MATCH($C$2,S$1:AD$1,0)) -> #REF! | AF12: =IFERROR(INDEX($E12:$P12,1,MATCH($C$2,$E$1:$P$1,0))/INDEX($S12:$AD12,1,MATCH($C$2,S$1:AD$1,0))-1,0) -> 0 | AH12: {=INDEX(#REF!,MATCH($C12,#REF!,0),MATCH(AH$1,#REF!,0))} -> #REF! | AI12: {=INDEX(#REF!,MATCH($C12,#REF!,0),MATCH(AI$1,#REF!,0))} -> #REF! | AJ12: {=INDEX(#REF!,MATCH($C12,#REF!,0),MATCH(AJ$1,#REF!,0))} -> #REF! | AK12: {=INDEX(#REF!,MATCH($C12,#REF!,0),MATCH(AK$1,#REF!,0))} -> #REF! | AL12: {=INDEX(#REF!,MATCH($C12,#REF!,0),MATCH(AL$1,#REF!,0))} -> #REF! | AM12: {=INDEX(#REF!,MATCH($C12,#REF!,0),MATCH(AM$1,#REF!,0))} -> #REF! | AN12: {=INDEX(#REF!,MATCH($C12,#REF!,0),MATCH(AN$1,#REF!,0))} -> #REF! | AO12: {=INDEX(#REF!,MATCH($C12,#REF!,0),MATCH(AO$1,#REF!,0))} -> #REF! | ... AS12: {=INDEX(#REF!,MATCH($C12,#REF!,0),MATCH(AS$1,#REF!,0))} -> #REF! | AT12: =INDEX($E12:$P12,1,MATCH($C$2,$E$1:$P$1,0))-INDEX(AH12:AS12,1,MATCH(EDATE($C$2,-12),AH$1:AS$1,0)) -> #REF! | AU12: =IFERROR(INDEX($E12:$P12,1,MATCH($C$2,$E$1:$P$1,0))/INDEX(AH12:AS12,1,MATCH(EDATE($C$2,-12),AH$1:AS$1,0))-1,0) -> 0 | AW12: =SUMIF(E$1:P$1,"<="&AW$2,E12:P12) -> #REF! | BA12: =SUMIF(S$1:AD$1,"<="&BA$2,S12:AD12) -> #REF! | BC12: =$AW12-BA12 -> #REF! | BD12: =IFERROR($AW12/BA12-1,"-") -> - | BG12: =SUMIF(AH$1:AS$1,"<="&BG$2,AH12:AS12) -> #REF! | BI12: =$AW12-BG12 -> #REF! | BJ12: =IFERROR($AW12/BG12-1,"-") -> -
A13: Receita | C13: Booster fortificante | E13: {=INDEX(#REF!,MATCH($C13,#REF!,0),MATCH(E$1,#REF!,0))} -> #REF! | F13: {=INDEX(#REF!,MATCH($C13,#REF!,0),MATCH(F$1,#REF!,0))} -> #REF! | G13: {=INDEX(#REF!,MATCH($C13,#REF!,0),MATCH(G$1,#REF!,0))} -> #REF! | H13: {=INDEX(#REF!,MATCH($C13,#REF!,0),MATCH(H$1,#REF!,0))} -> #REF! | I13: {=INDEX(#REF!,MATCH($C13,#REF!,0),MATCH(I$1,#REF!,0))} -> #REF! | J13: {=INDEX(#REF!,MATCH($C13,#REF!,0),MATCH(J$1,#REF!,0))} -> #REF! | K13: {=INDEX(#REF!,MATCH($C13,#REF!,0),MATCH(K$1,#REF!,0))} -> #REF! | L13: {=INDEX(#REF!,MATCH($C13,#REF!,0),MATCH(L$1,#REF!,0))} -> #REF! | ... P13: {=INDEX(#REF!,MATCH($C13,#REF!,0),MATCH(P$1,#REF!,0))} -> #REF! | S13: {=INDEX(#REF!,MATCH($C13,#REF!,0),MATCH(S$1,#REF!,0))} -> #REF! | T13: {=INDEX(#REF!,MATCH($C13,#REF!,0),MATCH(T$1,#REF!,0))} -> #REF! | U13: {=INDEX(#REF!,MATCH($C13,#REF!,0),MATCH(U$1,#REF!,0))} -> #REF! | V13: {=INDEX(#REF!,MATCH($C13,#REF!,0),MATCH(V$1,#REF!,0))} -> #REF! | W13: {=INDEX(#REF!,MATCH($C13,#REF!,0),MATCH(W$1,#REF!,0))} -> #REF! | X13: {=INDEX(#REF!,MATCH($C13,#REF!,0),MATCH(X$1,#REF!,0))} -> #REF! | Y13: {=INDEX(#REF!,MATCH($C13,#REF!,0),MATCH(Y$1,#REF!,0))} -> #REF! | Z13: {=INDEX(#REF!,MATCH($C13,#REF!,0),MATCH(Z$1,#REF!,0))} -> #REF! | ... AD13: {=INDEX(#REF!,MATCH($C13,#REF!,0),MATCH(AD$1,#REF!,0))} -> #REF! | AE13: =INDEX($E13:$P13,1,MATCH($C$2,$E$1:$P$1,0))-INDEX(S13:AD13,1,MATCH($C$2,S$1:AD$1,0)) -> #REF! | AF13: =IFERROR(INDEX($E13:$P13,1,MATCH($C$2,$E$1:$P$1,0))/INDEX($S13:$AD13,1,MATCH($C$2,S$1:AD$1,0))-1,0) -> 0 | AH13: {=INDEX(#REF!,MATCH($C13,#REF!,0),MATCH(AH$1,#REF!,0))} -> #REF! | AI13: {=INDEX(#REF!,MATCH($C13,#REF!,0),MATCH(AI$1,#REF!,0))} -> #REF! | AJ13: {=INDEX(#REF!,MATCH($C13,#REF!,0),MATCH(AJ$1,#REF!,0))} -> #REF! | AK13: {=INDEX(#REF!,MATCH($C13,#REF!,0),MATCH(AK$1,#REF!,0))} -> #REF! | AL13: {=INDEX(#REF!,MATCH($C13,#REF!,0),MATCH(AL$1,#REF!,0))} -> #REF! | AM13: {=INDEX(#REF!,MATCH($C13,#REF!,0),MATCH(AM$1,#REF!,0))} -> #REF! | AN13: {=INDEX(#REF!,MATCH($C13,#REF!,0),MATCH(AN$1,#REF!,0))} -> #REF! | AO13: {=INDEX(#REF!,MATCH($C13,#REF!,0),MATCH(AO$1,#REF!,0))} -> #REF! | ... AS13: {=INDEX(#REF!,MATCH($C13,#REF!,0),MATCH(AS$1,#REF!,0))} -> #REF! | AT13: =INDEX($E13:$P13,1,MATCH($C$2,$E$1:$P$1,0))-INDEX(AH13:AS13,1,MATCH(EDATE($C$2,-12),AH$1:AS$1,0)) -> #REF! | AU13: =IFERROR(INDEX($E13:$P13,1,MATCH($C$2,$E$1:$P$1,0))/INDEX(AH13:AS13,1,MATCH(EDATE($C$2,-12),AH$1:AS$1,0))-1,0) -> 0 | AW13: =SUMIF(E$1:P$1,"<="&AW$2,E13:P13) -> #REF! | BA13: =SUMIF(S$1:AD$1,"<="&BA$2,S13:AD13) -> #REF! | BC13: =$AW13-BA13 -> #REF! | BD13: =IFERROR($AW13/BA13-1,"-") -> - | BG13: =SUMIF(AH$1:AS$1,"<="&BG$2,AH13:AS13) -> #REF! | BI13: =$AW13-BG13 -> #REF! | BJ13: =IFERROR($AW13/BG13-1,"-") -> -
A14: Receita | C14: Shampoo a seco 150ml | E14: {=INDEX(#REF!,MATCH($C14,#REF!,0),MATCH(E$1,#REF!,0))} -> #REF! | F14: {=INDEX(#REF!,MATCH($C14,#REF!,0),MATCH(F$1,#REF!,0))} -> #REF! | G14: {=INDEX(#REF!,MATCH($C14,#REF!,0),MATCH(G$1,#REF!,0))} -> #REF! | H14: {=INDEX(#REF!,MATCH($C14,#REF!,0),MATCH(H$1,#REF!,0))} -> #REF! | I14: {=INDEX(#REF!,MATCH($C14,#REF!,0),MATCH(I$1,#REF!,0))} -> #REF! | J14: {=INDEX(#REF!,MATCH($C14,#REF!,0),MATCH(J$1,#REF!,0))} -> #REF! | K14: {=INDEX(#REF!,MATCH($C14,#REF!,0),MATCH(K$1,#REF!,0))} -> #REF! | L14: {=INDEX(#REF!,MATCH($C14,#REF!,0),MATCH(L$1,#REF!,0))} -> #REF! | ... P14: {=INDEX(#REF!,MATCH($C14,#REF!,0),MATCH(P$1,#REF!,0))} -> #REF! | S14: {=INDEX(#REF!,MATCH($C14,#REF!,0),MATCH(S$1,#REF!,0))} -> #REF! | T14: {=INDEX(#REF!,MATCH($C14,#REF!,0),MATCH(T$1,#REF!,0))} -> #REF! | U14: {=INDEX(#REF!,MATCH($C14,#REF!,0),MATCH(U$1,#REF!,0))} -> #REF! | V14: {=INDEX(#REF!,MATCH($C14,#REF!,0),MATCH(V$1,#REF!,0))} -> #REF! | W14: {=INDEX(#REF!,MATCH($C14,#REF!,0),MATCH(W$1,#REF!,0))} -> #REF! | X14: {=INDEX(#REF!,MATCH($C14,#REF!,0),MATCH(X$1,#REF!,0))} -> #REF! | Y14: {=INDEX(#REF!,MATCH($C14,#REF!,0),MATCH(Y$1,#REF!,0))} -> #REF! | Z14: {=INDEX(#REF!,MATCH($C14,#REF!,0),MATCH(Z$1,#REF!,0))} -> #REF! | ... AD14: {=INDEX(#REF!,MATCH($C14,#REF!,0),MATCH(AD$1,#REF!,0))} -> #REF! | AE14: =INDEX($E14:$P14,1,MATCH($C$2,$E$1:$P$1,0))-INDEX(S14:AD14,1,MATCH($C$2,S$1:AD$1,0)) -> #REF! | AF14: =IFERROR(INDEX($E14:$P14,1,MATCH($C$2,$E$1:$P$1,0))/INDEX($S14:$AD14,1,MATCH($C$2,S$1:AD$1,0))-1,0) -> 0 | AH14: {=INDEX(#REF!,MATCH($C14,#REF!,0),MATCH(AH$1,#REF!,0))} -> #REF! | AI14: {=INDEX(#REF!,MATCH($C14,#REF!,0),MATCH(AI$1,#REF!,0))} -> #REF! | AJ14: {=INDEX(#REF!,MATCH($C14,#REF!,0),MATCH(AJ$1,#REF!,0))} -> #REF! | AK14: {=INDEX(#REF!,MATCH($C14,#REF!,0),MATCH(AK$1,#REF!,0))} -> #REF! | AL14: {=INDEX(#REF!,MATCH($C14,#REF!,0),MATCH(AL$1,#REF!,0))} -> #REF! | AM14: {=INDEX(#REF!,MATCH($C14,#REF!,0),MATCH(AM$1,#REF!,0))} -> #REF! | AN14: {=INDEX(#REF!,MATCH($C14,#REF!,0),MATCH(AN$1,#REF!,0))} -> #REF! | AO14: {=INDEX(#REF!,MATCH($C14,#REF!,0),MATCH(AO$1,#REF!,0))} -> #REF! | ... AS14: {=INDEX(#REF!,MATCH($C14,#REF!,0),MATCH(AS$1,#REF!,0))} -> #REF! | AT14: =INDEX($E14:$P14,1,MATCH($C$2,$E$1:$P$1,0))-INDEX(AH14:AS14,1,MATCH(EDATE($C$2,-12),AH$1:AS$1,0)) -> #REF! | AU14: =IFERROR(INDEX($E14:$P14,1,MATCH($C$2,$E$1:$P$1,0))/INDEX(AH14:AS14,1,MATCH(EDATE($C$2,-12),AH$1:AS$1,0))-1,0) -> 0 | AW14: =SUMIF(E$1:P$1,"<="&AW$2,E14:P14) -> #REF! | BA14: =SUMIF(S$1:AD$1,"<="&BA$2,S14:AD14) -> #REF! | BC14: =$AW14-BA14 -> #REF! | BD14: =IFERROR($AW14/BA14-1,"-") -> - | BG14: =SUMIF(AH$1:AS$1,"<="&BG$2,AH14:AS14) -> #REF! | BI14: =$AW14-BG14 -> #REF! | BJ14: =IFERROR($AW14/BG14-1,"-") -> -
A15: Receita | C15: Lançamentos | E15: =SUM(E16:E20) -> #REF! | F15: =SUM(F16:F20) -> #REF! | G15: =SUM(G16:G20) -> #REF! | H15: =SUM(H16:H20) -> #REF! | I15: =SUM(I16:I20) -> #REF! | J15: =SUM(J16:J20) -> #REF! | K15: =SUM(K16:K20) -> #REF! | L15: =SUM(L16:L20) -> #REF! | ... P15: =SUM(P16:P20) -> #REF! | S15: =SUM(S16:S20) -> #REF! | T15: =SUM(T16:T20) -> #REF! | U15: =SUM(U16:U20) -> #REF! | V15: =SUM(V16:V20) -> #REF! | W15: =SUM(W16:W20) -> #REF! | X15: =SUM(X16:X20) -> #REF! | Y15: =SUM(Y16:Y20) -> #REF! | Z15: =SUM(Z16:Z20) -> #REF! | ... AD15: =SUM(AD16:AD20) -> #REF! | AE15: =INDEX($E15:$P15,1,MATCH($C$2,$E$1:$P$1,0))-INDEX(S15:AD15,1,MATCH($C$2,S$1:AD$1,0)) -> #REF! | AF15: =IFERROR(INDEX($E15:$P15,1,MATCH($C$2,$E$1:$P$1,0))/INDEX($S15:$AD15,1,MATCH($C$2,S$1:AD$1,0))-1,0) -> 0 | AH15: =SUM(AH16:AH20) -> #REF! | AI15: =SUM(AI16:AI20) -> #REF! | AJ15: =SUM(AJ16:AJ20) -> #REF! | AK15: =SUM(AK16:AK20) -> #REF! | AL15: =SUM(AL16:AL20) -> #REF! | AM15: =SUM(AM16:AM20) -> #REF! | AN15: =SUM(AN16:AN20) -> #REF! | AO15: =SUM(AO16:AO20) -> #REF! | ... AS15: =SUM(AS16:AS20) -> #REF! | AT15: =INDEX($E15:$P15,1,MATCH($C$2,$E$1:$P$1,0))-INDEX(AH15:AS15,1,MATCH(EDATE($C$2,-12),AH$1:AS$1,0)) -> #REF! | AU15: =IFERROR(INDEX($E15:$P15,1,MATCH($C$2,$E$1:$P$1,0))/INDEX(AH15:AS15,1,MATCH(EDATE($C$2,-12),AH$1:AS$1,0))-1,0) -> 0 | AW15: =SUM(AW16:AW20) -> #REF! | BA15: =SUM(BA16:BA20) -> #REF! | BC15: =$AW15-BA15 -> #REF! | BD15: =IFERROR($AW15/BA15-1,"-") -> - | BG15: =SUM(BG16:BG20) -> #REF! | BI15: =$AW15-BG15 -> #REF! | BJ15: =IFERROR($AW15/BG15-1,"-") -> -
A16: Receita | B16: 1 | C16: {=INDEX(#REF!,MATCH($C$15&$B16,#REF!,0),MATCH(C$15,#REF!,0))} -> #REF! | E16: {=INDEX(#REF!,MATCH($C16,#REF!,0),MATCH(E$1,#REF!,0))} -> #REF! | F16: {=INDEX(#REF!,MATCH($C16,#REF!,0),MATCH(F$1,#REF!,0))} -> #REF! | G16: {=INDEX(#REF!,MATCH($C16,#REF!,0),MATCH(G$1,#REF!,0))} -> #REF! | H16: {=INDEX(#REF!,MATCH($C16,#REF!,0),MATCH(H$1,#REF!,0))} -> #REF! | I16: {=INDEX(#REF!,MATCH($C16,#REF!,0),MATCH(I$1,#REF!,0))} -> #REF! | J16: {=INDEX(#REF!,MATCH($C16,#REF!,0),MATCH(J$1,#REF!,0))} -> #REF! | K16: {=INDEX(#REF!,MATCH($C16,#REF!,0),MATCH(K$1,#REF!,0))} -> #REF! | L16: {=INDEX(#REF!,MATCH($C16,#REF!,0),MATCH(L$1,#REF!,0))} -> #REF! | ... P16: {=INDEX(#REF!,MATCH($C16,#REF!,0),MATCH(P$1,#REF!,0))} -> #REF! | S16: {=INDEX(#REF!,MATCH($C16,#REF!,0),MATCH(S$1,#REF!,0))} -> #REF! | T16: {=INDEX(#REF!,MATCH($C16,#REF!,0),MATCH(T$1,#REF!,0))} -> #REF! | U16: {=INDEX(#REF!,MATCH($C16,#REF!,0),MATCH(U$1,#REF!,0))} -> #REF! | V16: {=INDEX(#REF!,MATCH($C16,#REF!,0),MATCH(V$1,#REF!,0))} -> #REF! | W16: {=INDEX(#REF!,MATCH($C16,#REF!,0),MATCH(W$1,#REF!,0))} -> #REF! | X16: {=INDEX(#REF!,MATCH($C16,#REF!,0),MATCH(X$1,#REF!,0))} -> #REF! | Y16: {=INDEX(#REF!,MATCH($C16,#REF!,0),MATCH(Y$1,#REF!,0))} -> #REF! | Z16: {=INDEX(#REF!,MATCH($C16,#REF!,0),MATCH(Z$1,#REF!,0))} -> #REF! | ... AD16: {=INDEX(#REF!,MATCH($C16,#REF!,0),MATCH(AD$1,#REF!,0))} -> #REF! | AE16: =INDEX($E16:$P16,1,MATCH($C$2,$E$1:$P$1,0))-INDEX(S16:AD16,1,MATCH($C$2,S$1:AD$1,0)) -> #REF! | AF16: =IFERROR(INDEX($E16:$P16,1,MATCH($C$2,$E$1:$P$1,0))/INDEX($S16:$AD16,1,MATCH($C$2,S$1:AD$1,0))-1,0) -> 0 | AH16: {=INDEX(#REF!,MATCH($C16,#REF!,0),MATCH(AH$1,#REF!,0))} -> #REF! | AI16: {=INDEX(#REF!,MATCH($C16,#REF!,0),MATCH(AI$1,#REF!,0))} -> #REF! | AJ16: {=INDEX(#REF!,MATCH($C16,#REF!,0),MATCH(AJ$1,#REF!,0))} -> #REF! | AK16: {=INDEX(#REF!,MATCH($C16,#REF!,0),MATCH(AK$1,#REF!,0))} -> #REF! | AL16: {=INDEX(#REF!,MATCH($C16,#REF!,0),MATCH(AL$1,#REF!,0))} -> #REF! | AM16: {=INDEX(#REF!,MATCH($C16,#REF!,0),MATCH(AM$1,#REF!,0))} -> #REF! | AN16: {=INDEX(#REF!,MATCH($C16,#REF!,0),MATCH(AN$1,#REF!,0))} -> #REF! | AO16: {=INDEX(#REF!,MATCH($C16,#REF!,0),MATCH(AO$1,#REF!,0))} -> #REF! | ... AS16: {=INDEX(#REF!,MATCH($C16,#REF!,0),MATCH(AS$1,#REF!,0))} -> #REF! | AT16: =INDEX($E16:$P16,1,MATCH($C$2,$E$1:$P$1,0))-INDEX(AH16:AS16,1,MATCH(EDATE($C$2,-12),AH$1:AS$1,0)) -> #REF! | AU16: =IFERROR(INDEX($E16:$P16,1,MATCH($C$2,$E$1:$P$1,0))/INDEX(AH16:AS16,1,MATCH(EDATE($C$2,-12),AH$1:AS$1,0))-1,0) -> 0 | AW16: =SUMIF(E$1:P$1,"<="&AW$2,E16:P16) -> #REF! | BA16: =SUMIF(S$1:AD$1,"<="&BA$2,S16:AD16) -> #REF! | BC16: =$AW16-BA16 -> #REF! | BD16: =IFERROR($AW16/BA16-1,"-") -> - | BG16: =SUMIF(AH$1:AS$1,"<="&BG$2,AH16:AS16) -> #REF! | BI16: =$AW16-BG16 -> #REF! | BJ16: =IFERROR($AW16/BG16-1,"-") -> - | BK16: 1
A17: Receita | B17: 2 | C17: {=INDEX(#REF!,MATCH($C$15&$B17,#REF!,0),MATCH(C$15,#REF!,0))} -> #REF! | E17: {=INDEX(#REF!,MATCH($C17,#REF!,0),MATCH(E$1,#REF!,0))} -> #REF! | F17: {=INDEX(#REF!,MATCH($C17,#REF!,0),MATCH(F$1,#REF!,0))} -> #REF! | G17: {=INDEX(#REF!,MATCH($C17,#REF!,0),MATCH(G$1,#REF!,0))} -> #REF! | H17: {=INDEX(#REF!,MATCH($C17,#REF!,0),MATCH(H$1,#REF!,0))} -> #REF! | I17: {=INDEX(#REF!,MATCH($C17,#REF!,0),MATCH(I$1,#REF!,0))} -> #REF! | J17: {=INDEX(#REF!,MATCH($C17,#REF!,0),MATCH(J$1,#REF!,0))} -> #REF! | K17: {=INDEX(#REF!,MATCH($C17,#REF!,0),MATCH(K$1,#REF!,0))} -> #REF! | L17: {=INDEX(#REF!,MATCH($C17,#REF!,0),MATCH(L$1,#REF!,0))} -> #REF! | ... P17: {=INDEX(#REF!,MATCH($C17,#REF!,0),MATCH(P$1,#REF!,0))} -> #REF! | S17: {=INDEX(#REF!,MATCH($C17,#REF!,0),MATCH(S$1,#REF!,0))} -> #REF! | T17: {=INDEX(#REF!,MATCH($C17,#REF!,0),MATCH(T$1,#REF!,0))} -> #REF! | U17: {=INDEX(#REF!,MATCH($C17,#REF!,0),MATCH(U$1,#REF!,0))} -> #REF! | V17: {=INDEX(#REF!,MATCH($C17,#REF!,0),MATCH(V$1,#REF!,0))} -> #REF! | W17: {=INDEX(#REF!,MATCH($C17,#REF!,0),MATCH(W$1,#REF!,0))} -> #REF! | X17: {=INDEX(#REF!,MATCH($C17,#REF!,0),MATCH(X$1,#REF!,0))} -> #REF! | Y17: {=INDEX(#REF!,MATCH($C17,#REF!,0),MATCH(Y$1,#REF!,0))} -> #REF! | Z17: {=INDEX(#REF!,MATCH($C17,#REF!,0),MATCH(Z$1,#REF!,0))} -> #REF! | ... AD17: {=INDEX(#REF!,MATCH($C17,#REF!,0),MATCH(AD$1,#REF!,0))} -> #REF! | AE17: =INDEX($E17:$P17,1,MATCH($C$2,$E$1:$P$1,0))-INDEX(S17:AD17,1,MATCH($C$2,S$1:AD$1,0)) -> #REF! | AF17: =IFERROR(INDEX($E17:$P17,1,MATCH($C$2,$E$1:$P$1,0))/INDEX($S17:$AD17,1,MATCH($C$2,S$1:AD$1,0))-1,0) -> 0 | AH17: {=INDEX(#REF!,MATCH($C17,#REF!,0),MATCH(AH$1,#REF!,0))} -> #REF! | AI17: {=INDEX(#REF!,MATCH($C17,#REF!,0),MATCH(AI$1,#REF!,0))} -> #REF! | AJ17: {=INDEX(#REF!,MATCH($C17,#REF!,0),MATCH(AJ$1,#REF!,0))} -> #REF! | AK17: {=INDEX(#REF!,MATCH($C17,#REF!,0),MATCH(AK$1,#REF!,0))} -> #REF! | AL17: {=INDEX(#REF!,MATCH($C17,#REF!,0),MATCH(AL$1,#REF!,0))} -> #REF! | AM17: {=INDEX(#REF!,MATCH($C17,#REF!,0),MATCH(AM$1,#REF!,0))} -> #REF! | AN17: {=INDEX(#REF!,MATCH($C17,#REF!,0),MATCH(AN$1,#REF!,0))} -> #REF! | AO17: {=INDEX(#REF!,MATCH($C17,#REF!,0),MATCH(AO$1,#REF!,0))} -> #REF! | ... AS17: {=INDEX(#REF!,MATCH($C17,#REF!,0),MATCH(AS$1,#REF!,0))} -> #REF! | AT17: =INDEX($E17:$P17,1,MATCH($C$2,$E$1:$P$1,0))-INDEX(AH17:AS17,1,MATCH(EDATE($C$2,-12),AH$1:AS$1,0)) -> #REF! | AU17: =IFERROR(INDEX($E17:$P17,1,MATCH($C$2,$E$1:$P$1,0))/INDEX(AH17:AS17,1,MATCH(EDATE($C$2,-12),AH$1:AS$1,0))-1,0) -> 0 | AW17: =SUMIF(E$1:P$1,"<="&AW$2,E17:P17) -> #REF! | BA17: =SUMIF(S$1:AD$1,"<="&BA$2,S17:AD17) -> #REF! | BC17: =$AW17-BA17 -> #REF! | BD17: =IFERROR($AW17/BA17-1,"-") -> - | BG17: =SUMIF(AH$1:AS$1,"<="&BG$2,AH17:AS17) -> #REF! | BI17: =$AW17-BG17 -> #REF! | BJ17: =IFERROR($AW17/BG17-1,"-") -> - | BK17: 2
A18: Receita | B18: 3 | C18: {=INDEX(#REF!,MATCH($C$15&$B18,#REF!,0),MATCH(C$15,#REF!,0))} -> #REF! | E18: {=INDEX(#REF!,MATCH($C18,#REF!,0),MATCH(E$1,#REF!,0))} -> #REF! | F18: {=INDEX(#REF!,MATCH($C18,#REF!,0),MATCH(F$1,#REF!,0))} -> #REF! | G18: {=INDEX(#REF!,MATCH($C18,#REF!,0),MATCH(G$1,#REF!,0))} -> #REF! | H18: {=INDEX(#REF!,MATCH($C18,#REF!,0),MATCH(H$1,#REF!,0))} -> #REF! | I18: {=INDEX(#REF!,MATCH($C18,#REF!,0),MATCH(I$1,#REF!,0))} -> #REF! | J18: {=INDEX(#REF!,MATCH($C18,#REF!,0),MATCH(J$1,#REF!,0))} -> #REF! | K18: {=INDEX(#REF!,MATCH($C18,#REF!,0),MATCH(K$1,#REF!,0))} -> #REF! | L18: {=INDEX(#REF!,MATCH($C18,#REF!,0),MATCH(L$1,#REF!,0))} -> #REF! | ... P18: {=INDEX(#REF!,MATCH($C18,#REF!,0),MATCH(P$1,#REF!,0))} -> #REF! | S18: {=INDEX(#REF!,MATCH($C18,#REF!,0),MATCH(S$1,#REF!,0))} -> #REF! | T18: {=INDEX(#REF!,MATCH($C18,#REF!,0),MATCH(T$1,#REF!,0))} -> #REF! | U18: {=INDEX(#REF!,MATCH($C18,#REF!,0),MATCH(U$1,#REF!,0))} -> #REF! | V18: {=INDEX(#REF!,MATCH($C18,#REF!,0),MATCH(V$1,#REF!,0))} -> #REF! | W18: {=INDEX(#REF!,MATCH($C18,#REF!,0),MATCH(W$1,#REF!,0))} -> #REF! | X18: {=INDEX(#REF!,MATCH($C18,#REF!,0),MATCH(X$1,#REF!,0))} -> #REF! | Y18: {=INDEX(#REF!,MATCH($C18,#REF!,0),MATCH(Y$1,#REF!,0))} -> #REF! | Z18: {=INDEX(#REF!,MATCH($C18,#REF!,0),MATCH(Z$1,#REF!,0))} -> #REF! | ... AD18: {=INDEX(#REF!,MATCH($C18,#REF!,0),MATCH(AD$1,#REF!,0))} -> #REF! | AE18: =INDEX($E18:$P18,1,MATCH($C$2,$E$1:$P$1,0))-INDEX(S18:AD18,1,MATCH($C$2,S$1:AD$1,0)) -> #REF! | AF18: =IFERROR(INDEX($E18:$P18,1,MATCH($C$2,$E$1:$P$1,0))/INDEX($S18:$AD18,1,MATCH($C$2,S$1:AD$1,0))-1,0) -> 0 | AH18: {=INDEX(#REF!,MATCH($C18,#REF!,0),MATCH(AH$1,#REF!,0))} -> #REF! | AI18: {=INDEX(#REF!,MATCH($C18,#REF!,0),MATCH(AI$1,#REF!,0))} -> #REF! | AJ18: {=INDEX(#REF!,MATCH($C18,#REF!,0),MATCH(AJ$1,#REF!,0))} -> #REF! | AK18: {=INDEX(#REF!,MATCH($C18,#REF!,0),MATCH(AK$1,#REF!,0))} -> #REF! | AL18: {=INDEX(#REF!,MATCH($C18,#REF!,0),MATCH(AL$1,#REF!,0))} -> #REF! | AM18: {=INDEX(#REF!,MATCH($C18,#REF!,0),MATCH(AM$1,#REF!,0))} -> #REF! | AN18: {=INDEX(#REF!,MATCH($C18,#REF!,0),MATCH(AN$1,#REF!,0))} -> #REF! | AO18: {=INDEX(#REF!,MATCH($C18,#REF!,0),MATCH(AO$1,#REF!,0))} -> #REF! | ... AS18: {=INDEX(#REF!,MATCH($C18,#REF!,0),MATCH(AS$1,#REF!,0))} -> #REF! | AT18: =INDEX($E18:$P18,1,MATCH($C$2,$E$1:$P$1,0))-INDEX(AH18:AS18,1,MATCH(EDATE($C$2,-12),AH$1:AS$1,0)) -> #REF! | AU18: =IFERROR(INDEX($E18:$P18,1,MATCH($C$2,$E$1:$P$1,0))/INDEX(AH18:AS18,1,MATCH(EDATE($C$2,-12),AH$1:AS$1,0))-1,0) -> 0 | AW18: =SUMIF(E$1:P$1,"<="&AW$2,E18:P18) -> #REF! | BA18: =SUMIF(S$1:AD$1,"<="&BA$2,S18:AD18) -> #REF! | BC18: =$AW18-BA18 -> #REF! | BD18: =IFERROR($AW18/BA18-1,"-") -> - | BG18: =SUMIF(AH$1:AS$1,"<="&BG$2,AH18:AS18) -> #REF! | BI18: =$AW18-BG18 -> #REF! | BJ18: =IFERROR($AW18/BG18-1,"-") -> - | BK18: 3
A19: Receita | B19: 2 | C19: Primer cachos definidos 250ml | E19: {=INDEX(#REF!,MATCH($C19,#REF!,0),MATCH(E$1,#REF!,0))} -> #REF! | F19: {=INDEX(#REF!,MATCH($C19,#REF!,0),MATCH(F$1,#REF!,0))} -> #REF! | G19: {=INDEX(#REF!,MATCH($C19,#REF!,0),MATCH(G$1,#REF!,0))} -> #REF! | H19: {=INDEX(#REF!,MATCH($C19,#REF!,0),MATCH(H$1,#REF!,0))} -> #REF! | I19: {=INDEX(#REF!,MATCH($C19,#REF!,0),MATCH(I$1,#REF!,0))} -> #REF! | J19: {=INDEX(#REF!,MATCH($C19,#REF!,0),MATCH(J$1,#REF!,0))} -> #REF! | K19: {=INDEX(#REF!,MATCH($C19,#REF!,0),MATCH(K$1,#REF!,0))} -> #REF! | L19: {=INDEX(#REF!,MATCH($C19,#REF!,0),MATCH(L$1,#REF!,0))} -> #REF! | ... P19: {=INDEX(#REF!,MATCH($C19,#REF!,0),MATCH(P$1,#REF!,0))} -> #REF! | S19: {=INDEX(#REF!,MATCH($C19,#REF!,0),MATCH(S$1,#REF!,0))} -> #REF! | T19: {=INDEX(#REF!,MATCH($C19,#REF!,0),MATCH(T$1,#REF!,0))} -> #REF! | U19: {=INDEX(#REF!,MATCH($C19,#REF!,0),MATCH(U$1,#REF!,0))} -> #REF! | V19: {=INDEX(#REF!,MATCH($C19,#REF!,0),MATCH(V$1,#REF!,0))} -> #REF! | W19: {=INDEX(#REF!,MATCH($C19,#REF!,0),MATCH(W$1,#REF!,0))} -> #REF! | X19: {=INDEX(#REF!,MATCH($C19,#REF!,0),MATCH(X$1,#REF!,0))} -> #REF! | Y19: {=INDEX(#REF!,MATCH($C19,#REF!,0),MATCH(Y$1,#REF!,0))} -> #REF! | Z19: {=INDEX(#REF!,MATCH($C19,#REF!,0),MATCH(Z$1,#REF!,0))} -> #REF! | ... AD19: {=INDEX(#REF!,MATCH($C19,#REF!,0),MATCH(AD$1,#REF!,0))} -> #REF! | AE19: =INDEX($E19:$P19,1,MATCH($C$2,$E$1:$P$1,0))-INDEX(S19:AD19,1,MATCH($C$2,S$1:AD$1,0)) -> #REF! | AF19: =IFERROR(INDEX($E19:$P19,1,MATCH($C$2,$E$1:$P$1,0))/INDEX($S19:$AD19,1,MATCH($C$2,S$1:AD$1,0))-1,0) -> 0 | AH19: {=INDEX(#REF!,MATCH($C19,#REF!,0),MATCH(AH$1,#REF!,0))} -> #REF! | AI19: {=INDEX(#REF!,MATCH($C19,#REF!,0),MATCH(AI$1,#REF!,0))} -> #REF! | AJ19: {=INDEX(#REF!,MATCH($C19,#REF!,0),MATCH(AJ$1,#REF!,0))} -> #REF! | AK19: {=INDEX(#REF!,MATCH($C19,#REF!,0),MATCH(AK$1,#REF!,0))} -> #REF! | AL19: {=INDEX(#REF!,MATCH($C19,#REF!,0),MATCH(AL$1,#REF!,0))} -> #REF! | AM19: {=INDEX(#REF!,MATCH($C19,#REF!,0),MATCH(AM$1,#REF!,0))} -> #REF! | AN19: {=INDEX(#REF!,MATCH($C19,#REF!,0),MATCH(AN$1,#REF!,0))} -> #REF! | AO19: {=INDEX(#REF!,MATCH($C19,#REF!,0),MATCH(AO$1,#REF!,0))} -> #REF! | ... AS19: {=INDEX(#REF!,MATCH($C19,#REF!,0),MATCH(AS$1,#REF!,0))} -> #REF! | AT19: =INDEX($E19:$P19,1,MATCH($C$2,$E$1:$P$1,0))-INDEX(AH19:AS19,1,MATCH(EDATE($C$2,-12),AH$1:AS$1,0)) -> #REF! | AU19: =IFERROR(INDEX($E19:$P19,1,MATCH($C$2,$E$1:$P$1,0))/INDEX(AH19:AS19,1,MATCH(EDATE($C$2,-12),AH$1:AS$1,0))-1,0) -> 0 | AW19: =SUMIF(E$1:P$1,"<="&AW$2,E19:P19) -> #REF! | BA19: =SUMIF(S$1:AD$1,"<="&BA$2,S19:AD19) -> #REF! | BC19: =$AW19-BA19 -> #REF! | BD19: =IFERROR($AW19/BA19-1,"-") -> - | BG19: =SUMIF(AH$1:AS$1,"<="&BG$2,AH19:AS19) -> #REF! | BI19: =$AW19-BG19 -> #REF! | BJ19: =IFERROR($AW19/BG19-1,"-") -> - | BK19: 2
A20: Receita | B20: 3 | C20: Primer liso intacto 150ml | E20: {=INDEX(#REF!,MATCH($C20,#REF!,0),MATCH(E$1,#REF!,0))} -> #REF! | F20: {=INDEX(#REF!,MATCH($C20,#REF!,0),MATCH(F$1,#REF!,0))} -> #REF! | G20: {=INDEX(#REF!,MATCH($C20,#REF!,0),MATCH(G$1,#REF!,0))} -> #REF! | H20: {=INDEX(#REF!,MATCH($C20,#REF!,0),MATCH(H$1,#REF!,0))} -> #REF! | I20: {=INDEX(#REF!,MATCH($C20,#REF!,0),MATCH(I$1,#REF!,0))} -> #REF! | J20: {=INDEX(#REF!,MATCH($C20,#REF!,0),MATCH(J$1,#REF!,0))} -> #REF! | K20: {=INDEX(#REF!,MATCH($C20,#REF!,0),MATCH(K$1,#REF!,0))} -> #REF! | L20: {=INDEX(#REF!,MATCH($C20,#REF!,0),MATCH(L$1,#REF!,0))} -> #REF! | ... P20: {=INDEX(#REF!,MATCH($C20,#REF!,0),MATCH(P$1,#REF!,0))} -> #REF! | S20: {=INDEX(#REF!,MATCH($C20,#REF!,0),MATCH(S$1,#REF!,0))} -> #REF! | T20: {=INDEX(#REF!,MATCH($C20,#REF!,0),MATCH(T$1,#REF!,0))} -> #REF! | U20: {=INDEX(#REF!,MATCH($C20,#REF!,0),MATCH(U$1,#REF!,0))} -> #REF! | V20: {=INDEX(#REF!,MATCH($C20,#REF!,0),MATCH(V$1,#REF!,0))} -> #REF! | W20: {=INDEX(#REF!,MATCH($C20,#REF!,0),MATCH(W$1,#REF!,0))} -> #REF! | X20: {=INDEX(#REF!,MATCH($C20,#REF!,0),MATCH(X$1,#REF!,0))} -> #REF! | Y20: {=INDEX(#REF!,MATCH($C20,#REF!,0),MATCH(Y$1,#REF!,0))} -> #REF! | Z20: {=INDEX(#REF!,MATCH($C20,#REF!,0),MATCH(Z$1,#REF!,0))} -> #REF! | ... AD20: {=INDEX(#REF!,MATCH($C20,#REF!,0),MATCH(AD$1,#REF!,0))} -> #REF! | AE20: =INDEX($E20:$P20,1,MATCH($C$2,$E$1:$P$1,0))-INDEX(S20:AD20,1,MATCH($C$2,S$1:AD$1,0)) -> #REF! | AF20: =IFERROR(INDEX($E20:$P20,1,MATCH($C$2,$E$1:$P$1,0))/INDEX($S20:$AD20,1,MATCH($C$2,S$1:AD$1,0))-1,0) -> 0 | AH20: {=INDEX(#REF!,MATCH($C20,#REF!,0),MATCH(AH$1,#REF!,0))} -> #REF! | AI20: {=INDEX(#REF!,MATCH($C20,#REF!,0),MATCH(AI$1,#REF!,0))} -> #REF! | AJ20: {=INDEX(#REF!,MATCH($C20,#REF!,0),MATCH(AJ$1,#REF!,0))} -> #REF! | AK20: {=INDEX(#REF!,MATCH($C20,#REF!,0),MATCH(AK$1,#REF!,0))} -> #REF! | AL20: {=INDEX(#REF!,MATCH($C20,#REF!,0),MATCH(AL$1,#REF!,0))} -> #REF! | AM20: {=INDEX(#REF!,MATCH($C20,#REF!,0),MATCH(AM$1,#REF!,0))} -> #REF! | AN20: {=INDEX(#REF!,MATCH($C20,#REF!,0),MATCH(AN$1,#REF!,0))} -> #REF! | AO20: {=INDEX(#REF!,MATCH($C20,#REF!,0),MATCH(AO$1,#REF!,0))} -> #REF! | ... AS20: {=INDEX(#REF!,MATCH($C20,#REF!,0),MATCH(AS$1,#REF!,0))} -> #REF! | AT20: =INDEX($E20:$P20,1,MATCH($C$2,$E$1:$P$1,0))-INDEX(AH20:AS20,1,MATCH(EDATE($C$2,-12),AH$1:AS$1,0)) -> #REF! | AU20: =IFERROR(INDEX($E20:$P20,1,MATCH($C$2,$E$1:$P$1,0))/INDEX(AH20:AS20,1,MATCH(EDATE($C$2,-12),AH$1:AS$1,0))-1,0) -> 0 | AW20: =SUMIF(E$1:P$1,"<="&AW$2,E20:P20) -> #REF! | BA20: =SUMIF(S$1:AD$1,"<="&BA$2,S20:AD20) -> #REF! | BC20: =$AW20-BA20 -> #REF! | BD20: =IFERROR($AW20/BA20-1,"-") -> - | BG20: =SUMIF(AH$1:AS$1,"<="&BG$2,AH20:AS20) -> #REF! | BI20: =$AW20-BG20 -> #REF! | BJ20: =IFERROR($AW20/BG20-1,"-") -> - | BK20: 3
A21: Receita | C21: Acessórios | E21: =SUM(E22:E32) -> #REF! | F21: =SUM(F22:F32) -> #REF! | G21: =SUM(G22:G32) -> #REF! | H21: =SUM(H22:H32) -> #REF! | I21: =SUM(I22:I32) -> #REF! | J21: =SUM(J22:J32) -> #REF! | K21: =SUM(K22:K32) -> #REF! | L21: =SUM(L22:L32) -> #REF! | ... P21: =SUM(P22:P32) -> #REF! | S21: =SUM(S22:S32) -> #REF! | T21: =SUM(T22:T32) -> #REF! | U21: =SUM(U22:U32) -> #REF! | V21: =SUM(V22:V32) -> #REF! | W21: =SUM(W22:W32) -> #REF! | X21: =SUM(X22:X32) -> #REF! | Y21: =SUM(Y22:Y32) -> #REF! | Z21: =SUM(Z22:Z32) -> #REF! | ... AD21: =SUM(AD22:AD32) -> #REF! | AE21: =INDEX($E21:$P21,1,MATCH($C$2,$E$1:$P$1,0))-INDEX(S21:AD21,1,MATCH($C$2,S$1:AD$1,0)) -> #REF! | AF21: =IFERROR(INDEX($E21:$P21,1,MATCH($C$2,$E$1:$P$1,0))/INDEX($S21:$AD21,1,MATCH($C$2,S$1:AD$1,0))-1,0) -> 0 | AH21: =SUM(AH22:AH32) -> #REF! | AI21: =SUM(AI22:AI32) -> #REF! | AJ21: =SUM(AJ22:AJ32) -> #REF! | AK21: =SUM(AK22:AK32) -> #REF! | AL21: =SUM(AL22:AL32) -> #REF! | AM21: =SUM(AM22:AM32) -> #REF! | AN21: =SUM(AN22:AN32) -> #REF! | AO21: =SUM(AO22:AO32) -> #REF! | ... AS21: =SUM(AS22:AS32) -> #REF! | AT21: =INDEX($E21:$P21,1,MATCH($C$2,$E$1:$P$1,0))-INDEX(AH21:AS21,1,MATCH(EDATE($C$2,-12),AH$1:AS$1,0)) -> #REF! | AU21: =IFERROR(INDEX($E21:$P21,1,MATCH($C$2,$E$1:$P$1,0))/INDEX(AH21:AS21,1,MATCH(EDATE($C$2,-12),AH$1:AS$1,0))-1,0) -> 0 | AW21: =SUM(AW22:AW32) -> #REF! | BA21: =SUM(BA22:BA32) -> #REF! | BC21: =$AW21-BA21 -> #REF! | BD21: =IFERROR($AW21/BA21-1,"-") -> - | BG21: =SUM(BG22:BG32) -> #REF! | BI21: =$AW21-BG21 -> #REF! | BJ21: =IFERROR($AW21/BG21-1,"-") -> -
A22: Receita | C22: Cubeta pequena | E22: {=INDEX(#REF!,MATCH($C22,#REF!,0),MATCH(E$1,#REF!,0))} -> #REF! | F22: {=INDEX(#REF!,MATCH($C22,#REF!,0),MATCH(F$1,#REF!,0))} -> #REF! | G22: {=INDEX(#REF!,MATCH($C22,#REF!,0),MATCH(G$1,#REF!,0))} -> #REF! | H22: {=INDEX(#REF!,MATCH($C22,#REF!,0),MATCH(H$1,#REF!,0))} -> #REF! | I22: {=INDEX(#REF!,MATCH($C22,#REF!,0),MATCH(I$1,#REF!,0))} -> #REF! | J22: {=INDEX(#REF!,MATCH($C22,#REF!,0),MATCH(J$1,#REF!,0))} -> #REF! | K22: {=INDEX(#REF!,MATCH($C22,#REF!,0),MATCH(K$1,#REF!,0))} -> #REF! | L22: {=INDEX(#REF!,MATCH($C22,#REF!,0),MATCH(L$1,#REF!,0))} -> #REF! | ... P22: {=INDEX(#REF!,MATCH($C22,#REF!,0),MATCH(P$1,#REF!,0))} -> #REF! | S22: {=INDEX(#REF!,MATCH($C22,#REF!,0),MATCH(S$1,#REF!,0))} -> #REF! | T22: {=INDEX(#REF!,MATCH($C22,#REF!,0),MATCH(T$1,#REF!,0))} -> #REF! | U22: {=INDEX(#REF!,MATCH($C22,#REF!,0),MATCH(U$1,#REF!,0))} -> #REF! | V22: {=INDEX(#REF!,MATCH($C22,#REF!,0),MATCH(V$1,#REF!,0))} -> #REF! | W22: {=INDEX(#REF!,MATCH($C22,#REF!,0),MATCH(W$1,#REF!,0))} -> #REF! | X22: {=INDEX(#REF!,MATCH($C22,#REF!,0),MATCH(X$1,#REF!,0))} -> #REF! | Y22: {=INDEX(#REF!,MATCH($C22,#REF!,0),MATCH(Y$1,#REF!,0))} -> #REF! | Z22: {=INDEX(#REF!,MATCH($C22,#REF!,0),MATCH(Z$1,#REF!,0))} -> #REF! | ... AD22: {=INDEX(#REF!,MATCH($C22,#REF!,0),MATCH(AD$1,#REF!,0))} -> #REF! | AE22: =INDEX($E22:$P22,1,MATCH($C$2,$E$1:$P$1,0))-INDEX(S22:AD22,1,MATCH($C$2,S$1:AD$1,0)) -> #REF! | AF22: =IFERROR(INDEX($E22:$P22,1,MATCH($C$2,$E$1:$P$1,0))/INDEX($S22:$AD22,1,MATCH($C$2,S$1:AD$1,0))-1,0) -> 0 | AH22: {=INDEX(#REF!,MATCH($C22,#REF!,0),MATCH(AH$1,#REF!,0))} -> #REF! | AI22: {=INDEX(#REF!,MATCH($C22,#REF!,0),MATCH(AI$1,#REF!,0))} -> #REF! | AJ22: {=INDEX(#REF!,MATCH($C22,#REF!,0),MATCH(AJ$1,#REF!,0))} -> #REF! | AK22: {=INDEX(#REF!,MATCH($C22,#REF!,0),MATCH(AK$1,#REF!,0))} -> #REF! | AL22: {=INDEX(#REF!,MATCH($C22,#REF!,0),MATCH(AL$1,#REF!,0))} -> #REF! | AM22: {=INDEX(#REF!,MATCH($C22,#REF!,0),MATCH(AM$1,#REF!,0))} -> #REF! | AN22: {=INDEX(#REF!,MATCH($C22,#REF!,0),MATCH(AN$1,#REF!,0))} -> #REF! | AO22: {=INDEX(#REF!,MATCH($C22,#REF!,0),MATCH(AO$1,#REF!,0))} -> #REF! | ... AS22: {=INDEX(#REF!,MATCH($C22,#REF!,0),MATCH(AS$1,#REF!,0))} -> #REF! | AT22: =INDEX($E22:$P22,1,MATCH($C$2,$E$1:$P$1,0))-INDEX(AH22:AS22,1,MATCH(EDATE($C$2,-12),AH$1:AS$1,0)) -> #REF! | AU22: =IFERROR(INDEX($E22:$P22,1,MATCH($C$2,$E$1:$P$1,0))/INDEX(AH22:AS22,1,MATCH(EDATE($C$2,-12),AH$1:AS$1,0))-1,0) -> 0 | AW22: =SUMIF(E$1:P$1,"<="&AW$2,E22:P22) -> #REF! | BA22: =SUMIF(S$1:AD$1,"<="&BA$2,S22:AD22) -> #REF! | BC22: =$AW22-BA22 -> #REF! | BD22: =IFERROR($AW22/BA22-1,"-") -> - | BG22: =SUMIF(AH$1:AS$1,"<="&BG$2,AH22:AS22) -> #REF! | BI22: =$AW22-BG22 -> #REF! | BJ22: =IFERROR($AW22/BG22-1,"-") -> -
A23: Receita | C23: Espátula | E23: {=INDEX(#REF!,MATCH($C23,#REF!,0),MATCH(E$1,#REF!,0))} -> #REF! | F23: {=INDEX(#REF!,MATCH($C23,#REF!,0),MATCH(F$1,#REF!,0))} -> #REF! | G23: {=INDEX(#REF!,MATCH($C23,#REF!,0),MATCH(G$1,#REF!,0))} -> #REF! | H23: {=INDEX(#REF!,MATCH($C23,#REF!,0),MATCH(H$1,#REF!,0))} -> #REF! | I23: {=INDEX(#REF!,MATCH($C23,#REF!,0),MATCH(I$1,#REF!,0))} -> #REF! | J23: {=INDEX(#REF!,MATCH($C23,#REF!,0),MATCH(J$1,#REF!,0))} -> #REF! | K23: {=INDEX(#REF!,MATCH($C23,#REF!,0),MATCH(K$1,#REF!,0))} -> #REF! | L23: {=INDEX(#REF!,MATCH($C23,#REF!,0),MATCH(L$1,#REF!,0))} -> #REF! | ... P23: {=INDEX(#REF!,MATCH($C23,#REF!,0),MATCH(P$1,#REF!,0))} -> #REF! | S23: {=INDEX(#REF!,MATCH($C23,#REF!,0),MATCH(S$1,#REF!,0))} -> #REF! | T23: {=INDEX(#REF!,MATCH($C23,#REF!,0),MATCH(T$1,#REF!,0))} -> #REF! | U23: {=INDEX(#REF!,MATCH($C23,#REF!,0),MATCH(U$1,#REF!,0))} -> #REF! | V23: {=INDEX(#REF!,MATCH($C23,#REF!,0),MATCH(V$1,#REF!,0))} -> #REF! | W23: {=INDEX(#REF!,MATCH($C23,#REF!,0),MATCH(W$1,#REF!,0))} -> #REF! | X23: {=INDEX(#REF!,MATCH($C23,#REF!,0),MATCH(X$1,#REF!,0))} -> #REF! | Y23: {=INDEX(#REF!,MATCH($C23,#REF!,0),MATCH(Y$1,#REF!,0))} -> #REF! | Z23: {=INDEX(#REF!,MATCH($C23,#REF!,0),MATCH(Z$1,#REF!,0))} -> #REF! | ... AD23: {=INDEX(#REF!,MATCH($C23,#REF!,0),MATCH(AD$1,#REF!,0))} -> #REF! | AE23: =INDEX($E23:$P23,1,MATCH($C$2,$E$1:$P$1,0))-INDEX(S23:AD23,1,MATCH($C$2,S$1:AD$1,0)) -> #REF! | AF23: =IFERROR(INDEX($E23:$P23,1,MATCH($C$2,$E$1:$P$1,0))/INDEX($S23:$AD23,1,MATCH($C$2,S$1:AD$1,0))-1,0) -> 0 | AH23: {=INDEX(#REF!,MATCH($C23,#REF!,0),MATCH(AH$1,#REF!,0))} -> #REF! | AI23: {=INDEX(#REF!,MATCH($C23,#REF!,0),MATCH(AI$1,#REF!,0))} -> #REF! | AJ23: {=INDEX(#REF!,MATCH($C23,#REF!,0),MATCH(AJ$1,#REF!,0))} -> #REF! | AK23: {=INDEX(#REF!,MATCH($C23,#REF!,0),MATCH(AK$1,#REF!,0))} -> #REF! | AL23: {=INDEX(#REF!,MATCH($C23,#REF!,0),MATCH(AL$1,#REF!,0))} -> #REF! | AM23: {=INDEX(#REF!,MATCH($C23,#REF!,0),MATCH(AM$1,#REF!,0))} -> #REF! | AN23: {=INDEX(#REF!,MATCH($C23,#REF!,0),MATCH(AN$1,#REF!,0))} -> #REF! | AO23: {=INDEX(#REF!,MATCH($C23,#REF!,0),MATCH(AO$1,#REF!,0))} -> #REF! | ... AS23: {=INDEX(#REF!,MATCH($C23,#REF!,0),MATCH(AS$1,#REF!,0))} -> #REF! | AT23: =INDEX($E23:$P23,1,MATCH($C$2,$E$1:$P$1,0))-INDEX(AH23:AS23,1,MATCH(EDATE($C$2,-12),AH$1:AS$1,0)) -> #REF! | AU23: =IFERROR(INDEX($E23:$P23,1,MATCH($C$2,$E$1:$P$1,0))/INDEX(AH23:AS23,1,MATCH(EDATE($C$2,-12),AH$1:AS$1,0))-1,0) -> 0 | AW23: =SUMIF(E$1:P$1,"<="&AW$2,E23:P23) -> #REF! | BA23: =SUMIF(S$1:AD$1,"<="&BA$2,S23:AD23) -> #REF! | BC23: =$AW23-BA23 -> #REF! | BD23: =IFERROR($AW23/BA23-1,"-") -> - | BG23: =SUMIF(AH$1:AS$1,"<="&BG$2,AH23:AS23) -> #REF! | BI23: =$AW23-BG23 -> #REF! | BJ23: =IFERROR($AW23/BG23-1,"-") -> -
A24: Receita | C24: Escova oval | E24: {=INDEX(#REF!,MATCH($C24,#REF!,0),MATCH(E$1,#REF!,0))} -> #REF! | F24: {=INDEX(#REF!,MATCH($C24,#REF!,0),MATCH(F$1,#REF!,0))} -> #REF! | G24: {=INDEX(#REF!,MATCH($C24,#REF!,0),MATCH(G$1,#REF!,0))} -> #REF! | H24: {=INDEX(#REF!,MATCH($C24,#REF!,0),MATCH(H$1,#REF!,0))} -> #REF! | I24: {=INDEX(#REF!,MATCH($C24,#REF!,0),MATCH(I$1,#REF!,0))} -> #REF! | J24: {=INDEX(#REF!,MATCH($C24,#REF!,0),MATCH(J$1,#REF!,0))} -> #REF! | K24: {=INDEX(#REF!,MATCH($C24,#REF!,0),MATCH(K$1,#REF!,0))} -> #REF! | L24: {=INDEX(#REF!,MATCH($C24,#REF!,0),MATCH(L$1,#REF!,0))} -> #REF! | ... P24: {=INDEX(#REF!,MATCH($C24,#REF!,0),MATCH(P$1,#REF!,0))} -> #REF! | S24: {=INDEX(#REF!,MATCH($C24,#REF!,0),MATCH(S$1,#REF!,0))} -> #REF! | T24: {=INDEX(#REF!,MATCH($C24,#REF!,0),MATCH(T$1,#REF!,0))} -> #REF! | U24: {=INDEX(#REF!,MATCH($C24,#REF!,0),MATCH(U$1,#REF!,0))} -> #REF! | V24: {=INDEX(#REF!,MATCH($C24,#REF!,0),MATCH(V$1,#REF!,0))} -> #REF! | W24: {=INDEX(#REF!,MATCH($C24,#REF!,0),MATCH(W$1,#REF!,0))} -> #REF! | X24: {=INDEX(#REF!,MATCH($C24,#REF!,0),MATCH(X$1,#REF!,0))} -> #REF! | Y24: {=INDEX(#REF!,MATCH($C24,#REF!,0),MATCH(Y$1,#REF!,0))} -> #REF! | Z24: {=INDEX(#REF!,MATCH($C24,#REF!,0),MATCH(Z$1,#REF!,0))} -> #REF! | ... AD24: {=INDEX(#REF!,MATCH($C24,#REF!,0),MATCH(AD$1,#REF!,0))} -> #REF! | AE24: =INDEX($E24:$P24,1,MATCH($C$2,$E$1:$P$1,0))-INDEX(S24:AD24,1,MATCH($C$2,S$1:AD$1,0)) -> #REF! | AF24: =IFERROR(INDEX($E24:$P24,1,MATCH($C$2,$E$1:$P$1,0))/INDEX($S24:$AD24,1,MATCH($C$2,S$1:AD$1,0))-1,0) -> 0 | AH24: {=INDEX(#REF!,MATCH($C24,#REF!,0),MATCH(AH$1,#REF!,0))} -> #REF! | AI24: {=INDEX(#REF!,MATCH($C24,#REF!,0),MATCH(AI$1,#REF!,0))} -> #REF! | AJ24: {=INDEX(#REF!,MATCH($C24,#REF!,0),MATCH(AJ$1,#REF!,0))} -> #REF! | AK24: {=INDEX(#REF!,MATCH($C24,#REF!,0),MATCH(AK$1,#REF!,0))} -> #REF! | AL24: {=INDEX(#REF!,MATCH($C24,#REF!,0),MATCH(AL$1,#REF!,0))} -> #REF! | AM24: {=INDEX(#REF!,MATCH($C24,#REF!,0),MATCH(AM$1,#REF!,0))} -> #REF! | AN24: {=INDEX(#REF!,MATCH($C24,#REF!,0),MATCH(AN$1,#REF!,0))} -> #REF! | AO24: {=INDEX(#REF!,MATCH($C24,#REF!,0),MATCH(AO$1,#REF!,0))} -> #REF! | ... AS24: {=INDEX(#REF!,MATCH($C24,#REF!,0),MATCH(AS$1,#REF!,0))} -> #REF! | AT24: =INDEX($E24:$P24,1,MATCH($C$2,$E$1:$P$1,0))-INDEX(AH24:AS24,1,MATCH(EDATE($C$2,-12),AH$1:AS$1,0)) -> #REF! | AU24: =IFERROR(INDEX($E24:$P24,1,MATCH($C$2,$E$1:$P$1,0))/INDEX(AH24:AS24,1,MATCH(EDATE($C$2,-12),AH$1:AS$1,0))-1,0) -> 0 | AW24: =SUMIF(E$1:P$1,"<="&AW$2,E24:P24) -> #REF! | BA24: =SUMIF(S$1:AD$1,"<="&BA$2,S24:AD24) -> #REF! | BC24: =$AW24-BA24 -> #REF! | BD24: =IFERROR($AW24/BA24-1,"-") -> - | BG24: =SUMIF(AH$1:AS$1,"<="&BG$2,AH24:AS24) -> #REF! | BI24: =$AW24-BG24 -> #REF! | BJ24: =IFERROR($AW24/BG24-1,"-") -> -
A25: Receita | C25: Escova polvo | E25: {=INDEX(#REF!,MATCH($C25,#REF!,0),MATCH(E$1,#REF!,0))} -> #REF! | F25: {=INDEX(#REF!,MATCH($C25,#REF!,0),MATCH(F$1,#REF!,0))} -> #REF! | G25: {=INDEX(#REF!,MATCH($C25,#REF!,0),MATCH(G$1,#REF!,0))} -> #REF! | H25: {=INDEX(#REF!,MATCH($C25,#REF!,0),MATCH(H$1,#REF!,0))} -> #REF! | I25: {=INDEX(#REF!,MATCH($C25,#REF!,0),MATCH(I$1,#REF!,0))} -> #REF! | J25: {=INDEX(#REF!,MATCH($C25,#REF!,0),MATCH(J$1,#REF!,0))} -> #REF! | K25: {=INDEX(#REF!,MATCH($C25,#REF!,0),MATCH(K$1,#REF!,0))} -> #REF! | L25: {=INDEX(#REF!,MATCH($C25,#REF!,0),MATCH(L$1,#REF!,0))} -> #REF! | ... P25: {=INDEX(#REF!,MATCH($C25,#REF!,0),MATCH(P$1,#REF!,0))} -> #REF! | S25: {=INDEX(#REF!,MATCH($C25,#REF!,0),MATCH(S$1,#REF!,0))} -> #REF! | T25: {=INDEX(#REF!,MATCH($C25,#REF!,0),MATCH(T$1,#REF!,0))} -> #REF! | U25: {=INDEX(#REF!,MATCH($C25,#REF!,0),MATCH(U$1,#REF!,0))} -> #REF! | V25: {=INDEX(#REF!,MATCH($C25,#REF!,0),MATCH(V$1,#REF!,0))} -> #REF! | W25: {=INDEX(#REF!,MATCH($C25,#REF!,0),MATCH(W$1,#REF!,0))} -> #REF! | X25: {=INDEX(#REF!,MATCH($C25,#REF!,0),MATCH(X$1,#REF!,0))} -> #REF! | Y25: {=INDEX(#REF!,MATCH($C25,#REF!,0),MATCH(Y$1,#REF!,0))} -> #REF! | Z25: {=INDEX(#REF!,MATCH($C25,#REF!,0),MATCH(Z$1,#REF!,0))} -> #REF! | ... AD25: {=INDEX(#REF!,MATCH($C25,#REF!,0),MATCH(AD$1,#REF!,0))} -> #REF! | AE25: =INDEX($E25:$P25,1,MATCH($C$2,$E$1:$P$1,0))-INDEX(S25:AD25,1,MATCH($C$2,S$1:AD$1,0)) -> #REF! | AF25: =IFERROR(INDEX($E25:$P25,1,MATCH($C$2,$E$1:$P$1,0))/INDEX($S25:$AD25,1,MATCH($C$2,S$1:AD$1,0))-1,0) -> 0 | AH25: {=INDEX(#REF!,MATCH($C25,#REF!,0),MATCH(AH$1,#REF!,0))} -> #REF! | AI25: {=INDEX(#REF!,MATCH($C25,#REF!,0),MATCH(AI$1,#REF!,0))} -> #REF! | AJ25: {=INDEX(#REF!,MATCH($C25,#REF!,0),MATCH(AJ$1,#REF!,0))} -> #REF! | AK25: {=INDEX(#REF!,MATCH($C25,#REF!,0),MATCH(AK$1,#REF!,0))} -> #REF! | AL25: {=INDEX(#REF!,MATCH($C25,#REF!,0),MATCH(AL$1,#REF!,0))} -> #REF! | AM25: {=INDEX(#REF!,MATCH($C25,#REF!,0),MATCH(AM$1,#REF!,0))} -> #REF! | AN25: {=INDEX(#REF!,MATCH($C25,#REF!,0),MATCH(AN$1,#REF!,0))} -> #REF! | AO25: {=INDEX(#REF!,MATCH($C25,#REF!,0),MATCH(AO$1,#REF!,0))} -> #REF! | ... AS25: {=INDEX(#REF!,MATCH($C25,#REF!,0),MATCH(AS$1,#REF!,0))} -> #REF! | AT25: =INDEX($E25:$P25,1,MATCH($C$2,$E$1:$P$1,0))-INDEX(AH25:AS25,1,MATCH(EDATE($C$2,-12),AH$1:AS$1,0)) -> #REF! | AU25: =IFERROR(INDEX($E25:$P25,1,MATCH($C$2,$E$1:$P$1,0))/INDEX(AH25:AS25,1,MATCH(EDATE($C$2,-12),AH$1:AS$1,0))-1,0) -> 0 | AW25: =SUMIF(E$1:P$1,"<="&AW$2,E25:P25) -> #REF! | BA25: =SUMIF(S$1:AD$1,"<="&BA$2,S25:AD25) -> #REF! | BC25: =$AW25-BA25 -> #REF! | BD25: =IFERROR($AW25/BA25-1,"-") -> - | BG25: =SUMIF(AH$1:AS$1,"<="&BG$2,AH25:AS25) -> #REF! | BI25: =$AW25-BG25 -> #REF! | BJ25: =IFERROR($AW25/BG25-1,"-") -> -
A26: Receita | C26: Necessaire GE Beauty | E26: {=INDEX(#REF!,MATCH($C26,#REF!,0),MATCH(E$1,#REF!,0))} -> #REF! | F26: {=INDEX(#REF!,MATCH($C26,#REF!,0),MATCH(F$1,#REF!,0))} -> #REF! | G26: {=INDEX(#REF!,MATCH($C26,#REF!,0),MATCH(G$1,#REF!,0))} -> #REF! | H26: {=INDEX(#REF!,MATCH($C26,#REF!,0),MATCH(H$1,#REF!,0))} -> #REF! | I26: {=INDEX(#REF!,MATCH($C26,#REF!,0),MATCH(I$1,#REF!,0))} -> #REF! | J26: {=INDEX(#REF!,MATCH($C26,#REF!,0),MATCH(J$1,#REF!,0))} -> #REF! | K26: {=INDEX(#REF!,MATCH($C26,#REF!,0),MATCH(K$1,#REF!,0))} -> #REF! | L26: {=INDEX(#REF!,MATCH($C26,#REF!,0),MATCH(L$1,#REF!,0))} -> #REF! | ... P26: {=INDEX(#REF!,MATCH($C26,#REF!,0),MATCH(P$1,#REF!,0))} -> #REF! | S26: {=INDEX(#REF!,MATCH($C26,#REF!,0),MATCH(S$1,#REF!,0))} -> #REF! | T26: {=INDEX(#REF!,MATCH($C26,#REF!,0),MATCH(T$1,#REF!,0))} -> #REF! | U26: {=INDEX(#REF!,MATCH($C26,#REF!,0),MATCH(U$1,#REF!,0))} -> #REF! | V26: {=INDEX(#REF!,MATCH($C26,#REF!,0),MATCH(V$1,#REF!,0))} -> #REF! | W26: {=INDEX(#REF!,MATCH($C26,#REF!,0),MATCH(W$1,#REF!,0))} -> #REF! | X26: {=INDEX(#REF!,MATCH($C26,#REF!,0),MATCH(X$1,#REF!,0))} -> #REF! | Y26: {=INDEX(#REF!,MATCH($C26,#REF!,0),MATCH(Y$1,#REF!,0))} -> #REF! | Z26: {=INDEX(#REF!,MATCH($C26,#REF!,0),MATCH(Z$1,#REF!,0))} -> #REF! | ... AD26: {=INDEX(#REF!,MATCH($C26,#REF!,0),MATCH(AD$1,#REF!,0))} -> #REF! | AE26: =INDEX($E26:$P26,1,MATCH($C$2,$E$1:$P$1,0))-INDEX(S26:AD26,1,MATCH($C$2,S$1:AD$1,0)) -> #REF! | AF26: =IFERROR(INDEX($E26:$P26,1,MATCH($C$2,$E$1:$P$1,0))/INDEX($S26:$AD26,1,MATCH($C$2,S$1:AD$1,0))-1,0) -> 0 | AH26: {=INDEX(#REF!,MATCH($C26,#REF!,0),MATCH(AH$1,#REF!,0))} -> #REF! | AI26: {=INDEX(#REF!,MATCH($C26,#REF!,0),MATCH(AI$1,#REF!,0))} -> #REF! | AJ26: {=INDEX(#REF!,MATCH($C26,#REF!,0),MATCH(AJ$1,#REF!,0))} -> #REF! | AK26: {=INDEX(#REF!,MATCH($C26,#REF!,0),MATCH(AK$1,#REF!,0))} -> #REF! | AL26: {=INDEX(#REF!,MATCH($C26,#REF!,0),MATCH(AL$1,#REF!,0))} -> #REF! | AM26: {=INDEX(#REF!,MATCH($C26,#REF!,0),MATCH(AM$1,#REF!,0))} -> #REF! | AN26: {=INDEX(#REF!,MATCH($C26,#REF!,0),MATCH(AN$1,#REF!,0))} -> #REF! | AO26: {=INDEX(#REF!,MATCH($C26,#REF!,0),MATCH(AO$1,#REF!,0))} -> #REF! | ... AS26: {=INDEX(#REF!,MATCH($C26,#REF!,0),MATCH(AS$1,#REF!,0))} -> #REF! | AT26: =INDEX($E26:$P26,1,MATCH($C$2,$E$1:$P$1,0))-INDEX(AH26:AS26,1,MATCH(EDATE($C$2,-12),AH$1:AS$1,0)) -> #REF! | AU26: =IFERROR(INDEX($E26:$P26,1,MATCH($C$2,$E$1:$P$1,0))/INDEX(AH26:AS26,1,MATCH(EDATE($C$2,-12),AH$1:AS$1,0))-1,0) -> 0 | AW26: =SUMIF(E$1:P$1,"<="&AW$2,E26:P26) -> #REF! | BA26: =SUMIF(S$1:AD$1,"<="&BA$2,S26:AD26) -> #REF! | BC26: =$AW26-BA26 -> #REF! | BD26: =IFERROR($AW26/BA26-1,"-") -> - | BG26: =SUMIF(AH$1:AS$1,"<="&BG$2,AH26:AS26) -> #REF! | BI26: =$AW26-BG26 -> #REF! | BJ26: =IFERROR($AW26/BG26-1,"-") -> -
A27: Receita | C27: Necessaire GE Beauty 2024 | E27: {=INDEX(#REF!,MATCH($C27,#REF!,0),MATCH(E$1,#REF!,0))} -> #REF! | F27: {=INDEX(#REF!,MATCH($C27,#REF!,0),MATCH(F$1,#REF!,0))} -> #REF! | G27: {=INDEX(#REF!,MATCH($C27,#REF!,0),MATCH(G$1,#REF!,0))} -> #REF! | H27: {=INDEX(#REF!,MATCH($C27,#REF!,0),MATCH(H$1,#REF!,0))} -> #REF! | I27: {=INDEX(#REF!,MATCH($C27,#REF!,0),MATCH(I$1,#REF!,0))} -> #REF! | J27: {=INDEX(#REF!,MATCH($C27,#REF!,0),MATCH(J$1,#REF!,0))} -> #REF! | K27: {=INDEX(#REF!,MATCH($C27,#REF!,0),MATCH(K$1,#REF!,0))} -> #REF! | L27: {=INDEX(#REF!,MATCH($C27,#REF!,0),MATCH(L$1,#REF!,0))} -> #REF! | ... P27: {=INDEX(#REF!,MATCH($C27,#REF!,0),MATCH(P$1,#REF!,0))} -> #REF! | S27: {=INDEX(#REF!,MATCH($C27,#REF!,0),MATCH(S$1,#REF!,0))} -> #REF! | T27: {=INDEX(#REF!,MATCH($C27,#REF!,0),MATCH(T$1,#REF!,0))} -> #REF! | U27: {=INDEX(#REF!,MATCH($C27,#REF!,0),MATCH(U$1,#REF!,0))} -> #REF! | V27: {=INDEX(#REF!,MATCH($C27,#REF!,0),MATCH(V$1,#REF!,0))} -> #REF! | W27: {=INDEX(#REF!,MATCH($C27,#REF!,0),MATCH(W$1,#REF!,0))} -> #REF! | X27: {=INDEX(#REF!,MATCH($C27,#REF!,0),MATCH(X$1,#REF!,0))} -> #REF! | Y27: {=INDEX(#REF!,MATCH($C27,#REF!,0),MATCH(Y$1,#REF!,0))} -> #REF! | Z27: {=INDEX(#REF!,MATCH($C27,#REF!,0),MATCH(Z$1,#REF!,0))} -> #REF! | ... AD27: {=INDEX(#REF!,MATCH($C27,#REF!,0),MATCH(AD$1,#REF!,0))} -> #REF! | AE27: =INDEX($E27:$P27,1,MATCH($C$2,$E$1:$P$1,0))-INDEX(S27:AD27,1,MATCH($C$2,S$1:AD$1,0)) -> #REF! | AF27: =IFERROR(INDEX($E27:$P27,1,MATCH($C$2,$E$1:$P$1,0))/INDEX($S27:$AD27,1,MATCH($C$2,S$1:AD$1,0))-1,0) -> 0 | AH27: {=INDEX(#REF!,MATCH($C27,#REF!,0),MATCH(AH$1,#REF!,0))} -> #REF! | AI27: {=INDEX(#REF!,MATCH($C27,#REF!,0),MATCH(AI$1,#REF!,0))} -> #REF! | AJ27: {=INDEX(#REF!,MATCH($C27,#REF!,0),MATCH(AJ$1,#REF!,0))} -> #REF! | AK27: {=INDEX(#REF!,MATCH($C27,#REF!,0),MATCH(AK$1,#REF!,0))} -> #REF! | AL27: {=INDEX(#REF!,MATCH($C27,#REF!,0),MATCH(AL$1,#REF!,0))} -> #REF! | AM27: {=INDEX(#REF!,MATCH($C27,#REF!,0),MATCH(AM$1,#REF!,0))} -> #REF! | AN27: {=INDEX(#REF!,MATCH($C27,#REF!,0),MATCH(AN$1,#REF!,0))} -> #REF! | AO27: {=INDEX(#REF!,MATCH($C27,#REF!,0),MATCH(AO$1,#REF!,0))} -> #REF! | ... AS27: {=INDEX(#REF!,MATCH($C27,#REF!,0),MATCH(AS$1,#REF!,0))} -> #REF! | AT27: =INDEX($E27:$P27,1,MATCH($C$2,$E$1:$P$1,0))-INDEX(AH27:AS27,1,MATCH(EDATE($C$2,-12),AH$1:AS$1,0)) -> #REF! | AU27: =IFERROR(INDEX($E27:$P27,1,MATCH($C$2,$E$1:$P$1,0))/INDEX(AH27:AS27,1,MATCH(EDATE($C$2,-12),AH$1:AS$1,0))-1,0) -> 0 | AW27: =SUMIF(E$1:P$1,"<="&AW$2,E27:P27) -> #REF! | BA27: =SUMIF(S$1:AD$1,"<="&BA$2,S27:AD27) -> #REF! | BC27: =$AW27-BA27 -> #REF! | BD27: =IFERROR($AW27/BA27-1,"-") -> - | BG27: =SUMIF(AH$1:AS$1,"<="&BG$2,AH27:AS27) -> #REF! | BI27: =$AW27-BG27 -> #REF! | BJ27: =IFERROR($AW27/BG27-1,"-") -> -
A28: Receita | C28: Necessaire Clutch G Vermelha | E28: {=INDEX(#REF!,MATCH($C28,#REF!,0),MATCH(E$1,#REF!,0))} -> #REF! | F28: {=INDEX(#REF!,MATCH($C28,#REF!,0),MATCH(F$1,#REF!,0))} -> #REF! | G28: {=INDEX(#REF!,MATCH($C28,#REF!,0),MATCH(G$1,#REF!,0))} -> #REF! | H28: {=INDEX(#REF!,MATCH($C28,#REF!,0),MATCH(H$1,#REF!,0))} -> #REF! | I28: {=INDEX(#REF!,MATCH($C28,#REF!,0),MATCH(I$1,#REF!,0))} -> #REF! | J28: {=INDEX(#REF!,MATCH($C28,#REF!,0),MATCH(J$1,#REF!,0))} -> #REF! | K28: {=INDEX(#REF!,MATCH($C28,#REF!,0),MATCH(K$1,#REF!,0))} -> #REF! | L28: {=INDEX(#REF!,MATCH($C28,#REF!,0),MATCH(L$1,#REF!,0))} -> #REF! | ... P28: {=INDEX(#REF!,MATCH($C28,#REF!,0),MATCH(P$1,#REF!,0))} -> #REF! | S28: {=INDEX(#REF!,MATCH($C28,#REF!,0),MATCH(S$1,#REF!,0))} -> #REF! | T28: {=INDEX(#REF!,MATCH($C28,#REF!,0),MATCH(T$1,#REF!,0))} -> #REF! | U28: {=INDEX(#REF!,MATCH($C28,#REF!,0),MATCH(U$1,#REF!,0))} -> #REF! | V28: {=INDEX(#REF!,MATCH($C28,#REF!,0),MATCH(V$1,#REF!,0))} -> #REF! | W28: {=INDEX(#REF!,MATCH($C28,#REF!,0),MATCH(W$1,#REF!,0))} -> #REF! | X28: {=INDEX(#REF!,MATCH($C28,#REF!,0),MATCH(X$1,#REF!,0))} -> #REF! | Y28: {=INDEX(#REF!,MATCH($C28,#REF!,0),MATCH(Y$1,#REF!,0))} -> #REF! | Z28: {=INDEX(#REF!,MATCH($C28,#REF!,0),MATCH(Z$1,#REF!,0))} -> #REF! | ... AD28: {=INDEX(#REF!,MATCH($C28,#REF!,0),MATCH(AD$1,#REF!,0))} -> #REF! | AE28: =INDEX($E28:$P28,1,MATCH($C$2,$E$1:$P$1,0))-INDEX(S28:AD28,1,MATCH($C$2,S$1:AD$1,0)) -> #REF! | AF28: =IFERROR(INDEX($E28:$P28,1,MATCH($C$2,$E$1:$P$1,0))/INDEX($S28:$AD28,1,MATCH($C$2,S$1:AD$1,0))-1,0) -> 0 | AH28: {=INDEX(#REF!,MATCH($C28,#REF!,0),MATCH(AH$1,#REF!,0))} -> #REF! | AI28: {=INDEX(#REF!,MATCH($C28,#REF!,0),MATCH(AI$1,#REF!,0))} -> #REF! | AJ28: {=INDEX(#REF!,MATCH($C28,#REF!,0),MATCH(AJ$1,#REF!,0))} -> #REF! | AK28: {=INDEX(#REF!,MATCH($C28,#REF!,0),MATCH(AK$1,#REF!,0))} -> #REF! | AL28: {=INDEX(#REF!,MATCH($C28,#REF!,0),MATCH(AL$1,#REF!,0))} -> #REF! | AM28: {=INDEX(#REF!,MATCH($C28,#REF!,0),MATCH(AM$1,#REF!,0))} -> #REF! | AN28: {=INDEX(#REF!,MATCH($C28,#REF!,0),MATCH(AN$1,#REF!,0))} -> #REF! | AO28: {=INDEX(#REF!,MATCH($C28,#REF!,0),MATCH(AO$1,#REF!,0))} -> #REF! | ... AS28: {=INDEX(#REF!,MATCH($C28,#REF!,0),MATCH(AS$1,#REF!,0))} -> #REF! | AT28: =INDEX($E28:$P28,1,MATCH($C$2,$E$1:$P$1,0))-INDEX(AH28:AS28,1,MATCH(EDATE($C$2,-12),AH$1:AS$1,0)) -> #REF! | AU28: =IFERROR(INDEX($E28:$P28,1,MATCH($C$2,$E$1:$P$1,0))/INDEX(AH28:AS28,1,MATCH(EDATE($C$2,-12),AH$1:AS$1,0))-1,0) -> 0 | AW28: =SUMIF(E$1:P$1,"<="&AW$2,E28:P28) -> #REF! | BA28: =SUMIF(S$1:AD$1,"<="&BA$2,S28:AD28) -> #REF! | BC28: =$AW28-BA28 -> #REF! | BD28: =IFERROR($AW28/BA28-1,"-") -> - | BG28: =SUMIF(AH$1:AS$1,"<="&BG$2,AH28:AS28) -> #REF! | BI28: =$AW28-BG28 -> #REF! | BJ28: =IFERROR($AW28/BG28-1,"-") -> -
A29: Receita | C29: Necessaire Clutch G Bordô | E29: {=INDEX(#REF!,MATCH($C29,#REF!,0),MATCH(E$1,#REF!,0))} -> #REF! | F29: {=INDEX(#REF!,MATCH($C29,#REF!,0),MATCH(F$1,#REF!,0))} -> #REF! | G29: {=INDEX(#REF!,MATCH($C29,#REF!,0),MATCH(G$1,#REF!,0))} -> #REF! | H29: {=INDEX(#REF!,MATCH($C29,#REF!,0),MATCH(H$1,#REF!,0))} -> #REF! | I29: {=INDEX(#REF!,MATCH($C29,#REF!,0),MATCH(I$1,#REF!,0))} -> #REF! | J29: {=INDEX(#REF!,MATCH($C29,#REF!,0),MATCH(J$1,#REF!,0))} -> #REF! | K29: {=INDEX(#REF!,MATCH($C29,#REF!,0),MATCH(K$1,#REF!,0))} -> #REF! | L29: {=INDEX(#REF!,MATCH($C29,#REF!,0),MATCH(L$1,#REF!,0))} -> #REF! | ... P29: {=INDEX(#REF!,MATCH($C29,#REF!,0),MATCH(P$1,#REF!,0))} -> #REF! | S29: {=INDEX(#REF!,MATCH($C29,#REF!,0),MATCH(S$1,#REF!,0))} -> #REF! | T29: {=INDEX(#REF!,MATCH($C29,#REF!,0),MATCH(T$1,#REF!,0))} -> #REF! | U29: {=INDEX(#REF!,MATCH($C29,#REF!,0),MATCH(U$1,#REF!,0))} -> #REF! | V29: {=INDEX(#REF!,MATCH($C29,#REF!,0),MATCH(V$1,#REF!,0))} -> #REF! | W29: {=INDEX(#REF!,MATCH($C29,#REF!,0),MATCH(W$1,#REF!,0))} -> #REF! | X29: {=INDEX(#REF!,MATCH($C29,#REF!,0),MATCH(X$1,#REF!,0))} -> #REF! | Y29: {=INDEX(#REF!,MATCH($C29,#REF!,0),MATCH(Y$1,#REF!,0))} -> #REF! | Z29: {=INDEX(#REF!,MATCH($C29,#REF!,0),MATCH(Z$1,#REF!,0))} -> #REF! | ... AD29: {=INDEX(#REF!,MATCH($C29,#REF!,0),MATCH(AD$1,#REF!,0))} -> #REF! | AE29: =INDEX($E29:$P29,1,MATCH($C$2,$E$1:$P$1,0))-INDEX(S29:AD29,1,MATCH($C$2,S$1:AD$1,0)) -> #REF! | AF29: =IFERROR(INDEX($E29:$P29,1,MATCH($C$2,$E$1:$P$1,0))/INDEX($S29:$AD29,1,MATCH($C$2,S$1:AD$1,0))-1,0) -> 0 | AH29: {=INDEX(#REF!,MATCH($C29,#REF!,0),MATCH(AH$1,#REF!,0))} -> #REF! | AI29: {=INDEX(#REF!,MATCH($C29,#REF!,0),MATCH(AI$1,#REF!,0))} -> #REF! | AJ29: {=INDEX(#REF!,MATCH($C29,#REF!,0),MATCH(AJ$1,#REF!,0))} -> #REF! | AK29: {=INDEX(#REF!,MATCH($C29,#REF!,0),MATCH(AK$1,#REF!,0))} -> #REF! | AL29: {=INDEX(#REF!,MATCH($C29,#REF!,0),MATCH(AL$1,#REF!,0))} -> #REF! | AM29: {=INDEX(#REF!,MATCH($C29,#REF!,0),MATCH(AM$1,#REF!,0))} -> #REF! | AN29: {=INDEX(#REF!,MATCH($C29,#REF!,0),MATCH(AN$1,#REF!,0))} -> #REF! | AO29: {=INDEX(#REF!,MATCH($C29,#REF!,0),MATCH(AO$1,#REF!,0))} -> #REF! | ... AS29: {=INDEX(#REF!,MATCH($C29,#REF!,0),MATCH(AS$1,#REF!,0))} -> #REF! | AT29: =INDEX($E29:$P29,1,MATCH($C$2,$E$1:$P$1,0))-INDEX(AH29:AS29,1,MATCH(EDATE($C$2,-12),AH$1:AS$1,0)) -> #REF! | AU29: =IFERROR(INDEX($E29:$P29,1,MATCH($C$2,$E$1:$P$1,0))/INDEX(AH29:AS29,1,MATCH(EDATE($C$2,-12),AH$1:AS$1,0))-1,0) -> 0 | AW29: =SUMIF(E$1:P$1,"<="&AW$2,E29:P29) -> #REF! | BA29: =SUMIF(S$1:AD$1,"<="&BA$2,S29:AD29) -> #REF! | BC29: =$AW29-BA29 -> #REF! | BD29: =IFERROR($AW29/BA29-1,"-") -> - | BG29: =SUMIF(AH$1:AS$1,"<="&BG$2,AH29:AS29) -> #REF! | BI29: =$AW29-BG29 -> #REF! | BJ29: =IFERROR($AW29/BG29-1,"-") -> -
A30: Receita | C30: Caixa de presente | E30: {=INDEX(#REF!,MATCH($C30,#REF!,0),MATCH(E$1,#REF!,0))} -> #REF! | F30: {=INDEX(#REF!,MATCH($C30,#REF!,0),MATCH(F$1,#REF!,0))} -> #REF! | G30: {=INDEX(#REF!,MATCH($C30,#REF!,0),MATCH(G$1,#REF!,0))} -> #REF! | H30: {=INDEX(#REF!,MATCH($C30,#REF!,0),MATCH(H$1,#REF!,0))} -> #REF! | I30: {=INDEX(#REF!,MATCH($C30,#REF!,0),MATCH(I$1,#REF!,0))} -> #REF! | J30: {=INDEX(#REF!,MATCH($C30,#REF!,0),MATCH(J$1,#REF!,0))} -> #REF! | K30: {=INDEX(#REF!,MATCH($C30,#REF!,0),MATCH(K$1,#REF!,0))} -> #REF! | L30: {=INDEX(#REF!,MATCH($C30,#REF!,0),MATCH(L$1,#REF!,0))} -> #REF! | ... P30: {=INDEX(#REF!,MATCH($C30,#REF!,0),MATCH(P$1,#REF!,0))} -> #REF! | S30: {=INDEX(#REF!,MATCH($C30,#REF!,0),MATCH(S$1,#REF!,0))} -> #REF! | T30: {=INDEX(#REF!,MATCH($C30,#REF!,0),MATCH(T$1,#REF!,0))} -> #REF! | U30: {=INDEX(#REF!,MATCH($C30,#REF!,0),MATCH(U$1,#REF!,0))} -> #REF! | V30: {=INDEX(#REF!,MATCH($C30,#REF!,0),MATCH(V$1,#REF!,0))} -> #REF! | W30: {=INDEX(#REF!,MATCH($C30,#REF!,0),MATCH(W$1,#REF!,0))} -> #REF! | X30: {=INDEX(#REF!,MATCH($C30,#REF!,0),MATCH(X$1,#REF!,0))} -> #REF! | Y30: {=INDEX(#REF!,MATCH($C30,#REF!,0),MATCH(Y$1,#REF!,0))} -> #REF! | Z30: {=INDEX(#REF!,MATCH($C30,#REF!,0),MATCH(Z$1,#REF!,0))} -> #REF! | ... AD30: {=INDEX(#REF!,MATCH($C30,#REF!,0),MATCH(AD$1,#REF!,0))} -> #REF! | AE30: =INDEX($E30:$P30,1,MATCH($C$2,$E$1:$P$1,0))-INDEX(S30:AD30,1,MATCH($C$2,S$1:AD$1,0)) -> #REF! | AF30: =IFERROR(INDEX($E30:$P30,1,MATCH($C$2,$E$1:$P$1,0))/INDEX($S30:$AD30,1,MATCH($C$2,S$1:AD$1,0))-1,0) -> 0 | AH30: {=INDEX(#REF!,MATCH($C30,#REF!,0),MATCH(AH$1,#REF!,0))} -> #REF! | AI30: {=INDEX(#REF!,MATCH($C30,#REF!,0),MATCH(AI$1,#REF!,0))} -> #REF! | AJ30: {=INDEX(#REF!,MATCH($C30,#REF!,0),MATCH(AJ$1,#REF!,0))} -> #REF! | AK30: {=INDEX(#REF!,MATCH($C30,#REF!,0),MATCH(AK$1,#REF!,0))} -> #REF! | AL30: {=INDEX(#REF!,MATCH($C30,#REF!,0),MATCH(AL$1,#REF!,0))} -> #REF! | AM30: {=INDEX(#REF!,MATCH($C30,#REF!,0),MATCH(AM$1,#REF!,0))} -> #REF! | AN30: {=INDEX(#REF!,MATCH($C30,#REF!,0),MATCH(AN$1,#REF!,0))} -> #REF! | AO30: {=INDEX(#REF!,MATCH($C30,#REF!,0),MATCH(AO$1,#REF!,0))} -> #REF! | ... AS30: {=INDEX(#REF!,MATCH($C30,#REF!,0),MATCH(AS$1,#REF!,0))} -> #REF! | AT30: =INDEX($E30:$P30,1,MATCH($C$2,$E$1:$P$1,0))-INDEX(AH30:AS30,1,MATCH(EDATE($C$2,-12),AH$1:AS$1,0)) -> #REF! | AU30: =IFERROR(INDEX($E30:$P30,1,MATCH($C$2,$E$1:$P$1,0))/INDEX(AH30:AS30,1,MATCH(EDATE($C$2,-12),AH$1:AS$1,0))-1,0) -> 0 | AW30: =SUMIF(E$1:P$1,"<="&AW$2,E30:P30) -> #REF! | BA30: =SUMIF(S$1:AD$1,"<="&BA$2,S30:AD30) -> #REF! | BC30: =$AW30-BA30 -> #REF! | BD30: =IFERROR($AW30/BA30-1,"-") -> - | BG30: =SUMIF(AH$1:AS$1,"<="&BG$2,AH30:AS30) -> #REF! | BI30: =$AW30-BG30 -> #REF! | BJ30: =IFERROR($AW30/BG30-1,"-") -> -
A31: Receita | C31: Vela Haji + GE Beauty | E31: {=INDEX(#REF!,MATCH($C31,#REF!,0),MATCH(E$1,#REF!,0))} -> #REF! | F31: {=INDEX(#REF!,MATCH($C31,#REF!,0),MATCH(F$1,#REF!,0))} -> #REF! | G31: {=INDEX(#REF!,MATCH($C31,#REF!,0),MATCH(G$1,#REF!,0))} -> #REF! | H31: {=INDEX(#REF!,MATCH($C31,#REF!,0),MATCH(H$1,#REF!,0))} -> #REF! | I31: {=INDEX(#REF!,MATCH($C31,#REF!,0),MATCH(I$1,#REF!,0))} -> #REF! | J31: {=INDEX(#REF!,MATCH($C31,#REF!,0),MATCH(J$1,#REF!,0))} -> #REF! | K31: {=INDEX(#REF!,MATCH($C31,#REF!,0),MATCH(K$1,#REF!,0))} -> #REF! | L31: {=INDEX(#REF!,MATCH($C31,#REF!,0),MATCH(L$1,#REF!,0))} -> #REF! | ... P31: {=INDEX(#REF!,MATCH($C31,#REF!,0),MATCH(P$1,#REF!,0))} -> #REF! | S31: {=INDEX(#REF!,MATCH($C31,#REF!,0),MATCH(S$1,#REF!,0))} -> #REF! | T31: {=INDEX(#REF!,MATCH($C31,#REF!,0),MATCH(T$1,#REF!,0))} -> #REF! | U31: {=INDEX(#REF!,MATCH($C31,#REF!,0),MATCH(U$1,#REF!,0))} -> #REF! | V31: {=INDEX(#REF!,MATCH($C31,#REF!,0),MATCH(V$1,#REF!,0))} -> #REF! | W31: {=INDEX(#REF!,MATCH($C31,#REF!,0),MATCH(W$1,#REF!,0))} -> #REF! | X31: {=INDEX(#REF!,MATCH($C31,#REF!,0),MATCH(X$1,#REF!,0))} -> #REF! | Y31: {=INDEX(#REF!,MATCH($C31,#REF!,0),MATCH(Y$1,#REF!,0))} -> #REF! | Z31: {=INDEX(#REF!,MATCH($C31,#REF!,0),MATCH(Z$1,#REF!,0))} -> #REF! | ... AD31: {=INDEX(#REF!,MATCH($C31,#REF!,0),MATCH(AD$1,#REF!,0))} -> #REF! | AE31: =INDEX($E31:$P31,1,MATCH($C$2,$E$1:$P$1,0))-INDEX(S31:AD31,1,MATCH($C$2,S$1:AD$1,0)) -> #REF! | AF31: =IFERROR(INDEX($E31:$P31,1,MATCH($C$2,$E$1:$P$1,0))/INDEX($S31:$AD31,1,MATCH($C$2,S$1:AD$1,0))-1,0) -> 0 | AH31: {=INDEX(#REF!,MATCH($C31,#REF!,0),MATCH(AH$1,#REF!,0))} -> #REF! | AI31: {=INDEX(#REF!,MATCH($C31,#REF!,0),MATCH(AI$1,#REF!,0))} -> #REF! | AJ31: {=INDEX(#REF!,MATCH($C31,#REF!,0),MATCH(AJ$1,#REF!,0))} -> #REF! | AK31: {=INDEX(#REF!,MATCH($C31,#REF!,0),MATCH(AK$1,#REF!,0))} -> #REF! | AL31: {=INDEX(#REF!,MATCH($C31,#REF!,0),MATCH(AL$1,#REF!,0))} -> #REF! | AM31: {=INDEX(#REF!,MATCH($C31,#REF!,0),MATCH(AM$1,#REF!,0))} -> #REF! | AN31: {=INDEX(#REF!,MATCH($C31,#REF!,0),MATCH(AN$1,#REF!,0))} -> #REF! | AO31: {=INDEX(#REF!,MATCH($C31,#REF!,0),MATCH(AO$1,#REF!,0))} -> #REF! | ... AS31: {=INDEX(#REF!,MATCH($C31,#REF!,0),MATCH(AS$1,#REF!,0))} -> #REF! | AT31: =INDEX($E31:$P31,1,MATCH($C$2,$E$1:$P$1,0))-INDEX(AH31:AS31,1,MATCH(EDATE($C$2,-12),AH$1:AS$1,0)) -> #REF! | AU31: =IFERROR(INDEX($E31:$P31,1,MATCH($C$2,$E$1:$P$1,0))/INDEX(AH31:AS31,1,MATCH(EDATE($C$2,-12),AH$1:AS$1,0))-1,0) -> 0 | AW31: =SUMIF(E$1:P$1,"<="&AW$2,E31:P31) -> #REF! | BA31: =SUMIF(S$1:AD$1,"<="&BA$2,S31:AD31) -> #REF! | BC31: =$AW31-BA31 -> #REF! | BD31: =IFERROR($AW31/BA31-1,"-") -> - | BG31: =SUMIF(AH$1:AS$1,"<="&BG$2,AH31:AS31) -> #REF! | BI31: =$AW31-BG31 -> #REF! | BJ31: =IFERROR($AW31/BG31-1,"-") -> -
A32: Receita | C32: Outros | E32: {=INDEX(#REF!,MATCH($C32,#REF!,0),MATCH(E$1,#REF!,0))} -> #REF! | F32: {=INDEX(#REF!,MATCH($C32,#REF!,0),MATCH(F$1,#REF!,0))} -> #REF! | G32: {=INDEX(#REF!,MATCH($C32,#REF!,0),MATCH(G$1,#REF!,0))} -> #REF! | H32: {=INDEX(#REF!,MATCH($C32,#REF!,0),MATCH(H$1,#REF!,0))} -> #REF! | I32: {=INDEX(#REF!,MATCH($C32,#REF!,0),MATCH(I$1,#REF!,0))} -> #REF! | J32: {=INDEX(#REF!,MATCH($C32,#REF!,0),MATCH(J$1,#REF!,0))} -> #REF! | K32: {=INDEX(#REF!,MATCH($C32,#REF!,0),MATCH(K$1,#REF!,0))} -> #REF! | L32: {=INDEX(#REF!,MATCH($C32,#REF!,0),MATCH(L$1,#REF!,0))} -> #REF! | ... P32: {=INDEX(#REF!,MATCH($C32,#REF!,0),MATCH(P$1,#REF!,0))} -> #REF! | S32: {=INDEX(#REF!,MATCH($C32,#REF!,0),MATCH(S$1,#REF!,0))} -> #REF! | T32: {=INDEX(#REF!,MATCH($C32,#REF!,0),MATCH(T$1,#REF!,0))} -> #REF! | U32: {=INDEX(#REF!,MATCH($C32,#REF!,0),MATCH(U$1,#REF!,0))} -> #REF! | V32: {=INDEX(#REF!,MATCH($C32,#REF!,0),MATCH(V$1,#REF!,0))} -> #REF! | W32: {=INDEX(#REF!,MATCH($C32,#REF!,0),MATCH(W$1,#REF!,0))} -> #REF! | X32: {=INDEX(#REF!,MATCH($C32,#REF!,0),MATCH(X$1,#REF!,0))} -> #REF! | Y32: {=INDEX(#REF!,MATCH($C32,#REF!,0),MATCH(Y$1,#REF!,0))} -> #REF! | Z32: {=INDEX(#REF!,MATCH($C32,#REF!,0),MATCH(Z$1,#REF!,0))} -> #REF! | ... AD32: {=INDEX(#REF!,MATCH($C32,#REF!,0),MATCH(AD$1,#REF!,0))} -> #REF! | AE32: =INDEX($E32:$P32,1,MATCH($C$2,$E$1:$P$1,0))-INDEX(S32:AD32,1,MATCH($C$2,S$1:AD$1,0)) -> #REF! | AF32: =IFERROR(INDEX($E32:$P32,1,MATCH($C$2,$E$1:$P$1,0))/INDEX($S32:$AD32,1,MATCH($C$2,S$1:AD$1,0))-1,0) -> 0 | AH32: {=INDEX(#REF!,MATCH($C32,#REF!,0),MATCH(AH$1,#REF!,0))} -> #REF! | AI32: {=INDEX(#REF!,MATCH($C32,#REF!,0),MATCH(AI$1,#REF!,0))} -> #REF! | AJ32: {=INDEX(#REF!,MATCH($C32,#REF!,0),MATCH(AJ$1,#REF!,0))} -> #REF! | AK32: {=INDEX(#REF!,MATCH($C32,#REF!,0),MATCH(AK$1,#REF!,0))} -> #REF! | AL32: {=INDEX(#REF!,MATCH($C32,#REF!,0),MATCH(AL$1,#REF!,0))} -> #REF! | AM32: {=INDEX(#REF!,MATCH($C32,#REF!,0),MATCH(AM$1,#REF!,0))} -> #REF! | AN32: {=INDEX(#REF!,MATCH($C32,#REF!,0),MATCH(AN$1,#REF!,0))} -> #REF! | AO32: {=INDEX(#REF!,MATCH($C32,#REF!,0),MATCH(AO$1,#REF!,0))} -> #REF! | ... AS32: {=INDEX(#REF!,MATCH($C32,#REF!,0),MATCH(AS$1,#REF!,0))} -> #REF! | AT32: =INDEX($E32:$P32,1,MATCH($C$2,$E$1:$P$1,0))-INDEX(AH32:AS32,1,MATCH(EDATE($C$2,-12),AH$1:AS$1,0)) -> #REF! | AU32: =IFERROR(INDEX($E32:$P32,1,MATCH($C$2,$E$1:$P$1,0))/INDEX(AH32:AS32,1,MATCH(EDATE($C$2,-12),AH$1:AS$1,0))-1,0) -> 0 | AW32: =SUMIF(E$1:P$1,"<="&AW$2,E32:P32) -> #REF! | BA32: =SUMIF(S$1:AD$1,"<="&BA$2,S32:AD32) -> #REF! | BC32: =$AW32-BA32 -> #REF! | BD32: =IFERROR($AW32/BA32-1,"-") -> - | BG32: =SUMIF(AH$1:AS$1,"<="&BG$2,AH32:AS32) -> #REF! | BI32: =$AW32-BG32 -> #REF! | BJ32: =IFERROR($AW32/BG32-1,"-") -> -
A33: Receita | C33: Frete + Seguro | E33: {=INDEX(#REF!,MATCH($C33,#REF!,0),MATCH(E$1,#REF!,0))} -> #REF! | F33: {=INDEX(#REF!,MATCH($C33,#REF!,0),MATCH(F$1,#REF!,0))} -> #REF! | G33: {=INDEX(#REF!,MATCH($C33,#REF!,0),MATCH(G$1,#REF!,0))} -> #REF! | H33: {=INDEX(#REF!,MATCH($C33,#REF!,0),MATCH(H$1,#REF!,0))} -> #REF! | I33: {=INDEX(#REF!,MATCH($C33,#REF!,0),MATCH(I$1,#REF!,0))} -> #REF! | J33: {=INDEX(#REF!,MATCH($C33,#REF!,0),MATCH(J$1,#REF!,0))} -> #REF! | K33: {=INDEX(#REF!,MATCH($C33,#REF!,0),MATCH(K$1,#REF!,0))} -> #REF! | L33: {=INDEX(#REF!,MATCH($C33,#REF!,0),MATCH(L$1,#REF!,0))} -> #REF! | ... P33: {=INDEX(#REF!,MATCH($C33,#REF!,0),MATCH(P$1,#REF!,0))} -> #REF! | S33: {=INDEX(#REF!,MATCH($C33,#REF!,0),MATCH(S$1,#REF!,0))} -> #REF! | T33: {=INDEX(#REF!,MATCH($C33,#REF!,0),MATCH(T$1,#REF!,0))} -> #REF! | U33: {=INDEX(#REF!,MATCH($C33,#REF!,0),MATCH(U$1,#REF!,0))} -> #REF! | V33: {=INDEX(#REF!,MATCH($C33,#REF!,0),MATCH(V$1,#REF!,0))} -> #REF! | W33: {=INDEX(#REF!,MATCH($C33,#REF!,0),MATCH(W$1,#REF!,0))} -> #REF! | X33: {=INDEX(#REF!,MATCH($C33,#REF!,0),MATCH(X$1,#REF!,0))} -> #REF! | Y33: {=INDEX(#REF!,MATCH($C33,#REF!,0),MATCH(Y$1,#REF!,0))} -> #REF! | Z33: {=INDEX(#REF!,MATCH($C33,#REF!,0),MATCH(Z$1,#REF!,0))} -> #REF! | ... AD33: {=INDEX(#REF!,MATCH($C33,#REF!,0),MATCH(AD$1,#REF!,0))} -> #REF! | AE33: =INDEX($E33:$P33,1,MATCH($C$2,$E$1:$P$1,0))-INDEX(S33:AD33,1,MATCH($C$2,S$1:AD$1,0)) -> #REF! | AF33: =IFERROR(INDEX($E33:$P33,1,MATCH($C$2,$E$1:$P$1,0))/INDEX($S33:$AD33,1,MATCH($C$2,S$1:AD$1,0))-1,0) -> 0 | AH33: {=INDEX(#REF!,MATCH($C33,#REF!,0),MATCH(AH$1,#REF!,0))} -> #REF! | AI33: {=INDEX(#REF!,MATCH($C33,#REF!,0),MATCH(AI$1,#REF!,0))} -> #REF! | AJ33: {=INDEX(#REF!,MATCH($C33,#REF!,0),MATCH(AJ$1,#REF!,0))} -> #REF! | AK33: {=INDEX(#REF!,MATCH($C33,#REF!,0),MATCH(AK$1,#REF!,0))} -> #REF! | AL33: {=INDEX(#REF!,MATCH($C33,#REF!,0),MATCH(AL$1,#REF!,0))} -> #REF! | AM33: {=INDEX(#REF!,MATCH($C33,#REF!,0),MATCH(AM$1,#REF!,0))} -> #REF! | AN33: {=INDEX(#REF!,MATCH($C33,#REF!,0),MATCH(AN$1,#REF!,0))} -> #REF! | AO33: {=INDEX(#REF!,MATCH($C33,#REF!,0),MATCH(AO$1,#REF!,0))} -> #REF! | ... AS33: {=INDEX(#REF!,MATCH($C33,#REF!,0),MATCH(AS$1,#REF!,0))} -> #REF! | AT33: =INDEX($E33:$P33,1,MATCH($C$2,$E$1:$P$1,0))-INDEX(AH33:AS33,1,MATCH(EDATE($C$2,-12),AH$1:AS$1,0)) -> #REF! | AU33: =IFERROR(INDEX($E33:$P33,1,MATCH($C$2,$E$1:$P$1,0))/INDEX(AH33:AS33,1,MATCH(EDATE($C$2,-12),AH$1:AS$1,0))-1,0) -> 0 | AW33: =SUMIF(E$1:P$1,"<="&AW$2,E33:P33) -> #REF! | BA33: =SUMIF(S$1:AD$1,"<="&BA$2,S33:AD33) -> #REF! | BC33: =$AW33-BA33 -> #REF! | BD33: =IFERROR($AW33/BA33-1,"-") -> - | BG33: =SUMIF(AH$1:AS$1,"<="&BG$2,AH33:AS33) -> #REF! | BI33: =$AW33-BG33 -> #REF! | BJ33: =IFERROR($AW33/BG33-1,"-") -> -
A34: Receita | C34: ICMS ST | E34: {=INDEX(#REF!,MATCH($C34,#REF!,0),MATCH(E$1,#REF!,0))} -> #REF! | F34: {=INDEX(#REF!,MATCH($C34,#REF!,0),MATCH(F$1,#REF!,0))} -> #REF! | G34: {=INDEX(#REF!,MATCH($C34,#REF!,0),MATCH(G$1,#REF!,0))} -> #REF! | H34: {=INDEX(#REF!,MATCH($C34,#REF!,0),MATCH(H$1,#REF!,0))} -> #REF! | I34: {=INDEX(#REF!,MATCH($C34,#REF!,0),MATCH(I$1,#REF!,0))} -> #REF! | J34: {=INDEX(#REF!,MATCH($C34,#REF!,0),MATCH(J$1,#REF!,0))} -> #REF! | K34: {=INDEX(#REF!,MATCH($C34,#REF!,0),MATCH(K$1,#REF!,0))} -> #REF! | L34: {=INDEX(#REF!,MATCH($C34,#REF!,0),MATCH(L$1,#REF!,0))} -> #REF! | ... P34: {=INDEX(#REF!,MATCH($C34,#REF!,0),MATCH(P$1,#REF!,0))} -> #REF! | S34: {=INDEX(#REF!,MATCH($C34,#REF!,0),MATCH(S$1,#REF!,0))} -> #REF! | T34: {=INDEX(#REF!,MATCH($C34,#REF!,0),MATCH(T$1,#REF!,0))} -> #REF! | U34: {=INDEX(#REF!,MATCH($C34,#REF!,0),MATCH(U$1,#REF!,0))} -> #REF! | V34: {=INDEX(#REF!,MATCH($C34,#REF!,0),MATCH(V$1,#REF!,0))} -> #REF! | W34: {=INDEX(#REF!,MATCH($C34,#REF!,0),MATCH(W$1,#REF!,0))} -> #REF! | X34: {=INDEX(#REF!,MATCH($C34,#REF!,0),MATCH(X$1,#REF!,0))} -> #REF! | Y34: {=INDEX(#REF!,MATCH($C34,#REF!,0),MATCH(Y$1,#REF!,0))} -> #REF! | Z34: {=INDEX(#REF!,MATCH($C34,#REF!,0),MATCH(Z$1,#REF!,0))} -> #REF! | ... AD34: {=INDEX(#REF!,MATCH($C34,#REF!,0),MATCH(AD$1,#REF!,0))} -> #REF! | AE34: =INDEX($E34:$P34,1,MATCH($C$2,$E$1:$P$1,0))-INDEX(S34:AD34,1,MATCH($C$2,S$1:AD$1,0)) -> #REF! | AF34: =IFERROR(INDEX($E34:$P34,1,MATCH($C$2,$E$1:$P$1,0))/INDEX($S34:$AD34,1,MATCH($C$2,S$1:AD$1,0))-1,0) -> 0 | AH34: {=INDEX(#REF!,MATCH($C34,#REF!,0),MATCH(AH$1,#REF!,0))} -> #REF! | AI34: {=INDEX(#REF!,MATCH($C34,#REF!,0),MATCH(AI$1,#REF!,0))} -> #REF! | AJ34: {=INDEX(#REF!,MATCH($C34,#REF!,0),MATCH(AJ$1,#REF!,0))} -> #REF! | AK34: {=INDEX(#REF!,MATCH($C34,#REF!,0),MATCH(AK$1,#REF!,0))} -> #REF! | AL34: {=INDEX(#REF!,MATCH($C34,#REF!,0),MATCH(AL$1,#REF!,0))} -> #REF! | AM34: {=INDEX(#REF!,MATCH($C34,#REF!,0),MATCH(AM$1,#REF!,0))} -> #REF! | AN34: {=INDEX(#REF!,MATCH($C34,#REF!,0),MATCH(AN$1,#REF!,0))} -> #REF! | AO34: {=INDEX(#REF!,MATCH($C34,#REF!,0),MATCH(AO$1,#REF!,0))} -> #REF! | ... AS34: {=INDEX(#REF!,MATCH($C34,#REF!,0),MATCH(AS$1,#REF!,0))} -> #REF! | AT34: =INDEX($E34:$P34,1,MATCH($C$2,$E$1:$P$1,0))-INDEX(AH34:AS34,1,MATCH(EDATE($C$2,-12),AH$1:AS$1,0)) -> #REF! | AU34: =IFERROR(INDEX($E34:$P34,1,MATCH($C$2,$E$1:$P$1,0))/INDEX(AH34:AS34,1,MATCH(EDATE($C$2,-12),AH$1:AS$1,0))-1,0) -> 0 | AW34: =SUMIF(E$1:P$1,"<="&AW$2,E34:P34) -> #REF! | BA34: =SUMIF(S$1:AD$1,"<="&BA$2,S34:AD34) -> #REF! | BC34: =$AW34-BA34 -> #REF! | BD34: =IFERROR($AW34/BA34-1,"-") -> - | BG34: =SUMIF(AH$1:AS$1,"<="&BG$2,AH34:AS34) -> #REF! | BI34: =$AW34-BG34 -> #REF! | BJ34: =IFERROR($AW34/BG34-1,"-") -> -
A35: Receita | C35: Collabs | E35: =SUM(E36) -> #REF! | F35: =SUM(F36) -> #REF! | G35: =SUM(G36) -> #REF! | H35: =SUM(H36) -> #REF! | I35: =SUM(I36) -> #REF! | J35: =SUM(J36) -> #REF! | K35: =SUM(K36) -> #REF! | L35: =SUM(L36) -> #REF! | ... P35: =SUM(P36) -> #REF! | S35: =SUM(S36) -> #REF! | T35: =SUM(T36) -> #REF! | U35: =SUM(U36) -> #REF! | V35: =SUM(V36) -> #REF! | W35: =SUM(W36) -> #REF! | X35: =SUM(X36) -> #REF! | Y35: =SUM(Y36) -> #REF! | Z35: =SUM(Z36) -> #REF! | ... AD35: =SUM(AD36) -> #REF! | AE35: =INDEX($E35:$P35,1,MATCH($C$2,$E$1:$P$1,0))-INDEX(S35:AD35,1,MATCH($C$2,S$1:AD$1,0)) -> #REF! | AF35: =IFERROR(INDEX($E35:$P35,1,MATCH($C$2,$E$1:$P$1,0))/INDEX($S35:$AD35,1,MATCH($C$2,S$1:AD$1,0))-1,0) -> 0 | AH35: =SUM(AH36) -> #REF! | AI35: =SUM(AI36) -> #REF! | AJ35: =SUM(AJ36) -> #REF! | AK35: =SUM(AK36) -> #REF! | AL35: =SUM(AL36) -> #REF! | AM35: =SUM(AM36) -> #REF! | AN35: =SUM(AN36) -> #REF! | AO35: =SUM(AO36) -> #REF! | ... AS35: =SUM(AS36) -> #REF! | AT35: =INDEX($E35:$P35,1,MATCH($C$2,$E$1:$P$1,0))-INDEX(AH35:AS35,1,MATCH(EDATE($C$2,-12),AH$1:AS$1,0)) -> #REF! | AU35: =IFERROR(INDEX($E35:$P35,1,MATCH($C$2,$E$1:$P$1,0))/INDEX(AH35:AS35,1,MATCH(EDATE($C$2,-12),AH$1:AS$1,0))-1,0) -> 0 | AW35: =SUM(AW36) -> #REF! | BA35: =SUM(BA36) -> #REF! | BC35: =$AW35-BA35 -> #REF! | BD35: =IFERROR($AW35/BA35-1,"-") -> - | BG35: =SUM(BG36) -> #REF! | BI35: =$AW35-BG35 -> #REF! | BJ35: =IFERROR($AW35/BG35-1,"-") -> -
A36: Receita | C36: Zerezes | E36: {=INDEX(#REF!,MATCH($C36,#REF!,0),MATCH(E$1,#REF!,0))} -> #REF! | F36: {=INDEX(#REF!,MATCH($C36,#REF!,0),MATCH(F$1,#REF!,0))} -> #REF! | G36: {=INDEX(#REF!,MATCH($C36,#REF!,0),MATCH(G$1,#REF!,0))} -> #REF! | H36: {=INDEX(#REF!,MATCH($C36,#REF!,0),MATCH(H$1,#REF!,0))} -> #REF! | I36: {=INDEX(#REF!,MATCH($C36,#REF!,0),MATCH(I$1,#REF!,0))} -> #REF! | J36: {=INDEX(#REF!,MATCH($C36,#REF!,0),MATCH(J$1,#REF!,0))} -> #REF! | K36: {=INDEX(#REF!,MATCH($C36,#REF!,0),MATCH(K$1,#REF!,0))} -> #REF! | L36: {=INDEX(#REF!,MATCH($C36,#REF!,0),MATCH(L$1,#REF!,0))} -> #REF! | ... P36: {=INDEX(#REF!,MATCH($C36,#REF!,0),MATCH(P$1,#REF!,0))} -> #REF! | S36: {=INDEX(#REF!,MATCH($C36,#REF!,0),MATCH(S$1,#REF!,0))} -> #REF! | T36: {=INDEX(#REF!,MATCH($C36,#REF!,0),MATCH(T$1,#REF!,0))} -> #REF! | U36: {=INDEX(#REF!,MATCH($C36,#REF!,0),MATCH(U$1,#REF!,0))} -> #REF! | V36: {=INDEX(#REF!,MATCH($C36,#REF!,0),MATCH(V$1,#REF!,0))} -> #REF! | W36: {=INDEX(#REF!,MATCH($C36,#REF!,0),MATCH(W$1,#REF!,0))} -> #REF! | X36: {=INDEX(#REF!,MATCH($C36,#REF!,0),MATCH(X$1,#REF!,0))} -> #REF! | Y36: {=INDEX(#REF!,MATCH($C36,#REF!,0),MATCH(Y$1,#REF!,0))} -> #REF! | Z36: {=INDEX(#REF!,MATCH($C36,#REF!,0),MATCH(Z$1,#REF!,0))} -> #REF! | ... AD36: {=INDEX(#REF!,MATCH($C36,#REF!,0),MATCH(AD$1,#REF!,0))} -> #REF! | AE36: =INDEX($E36:$P36,1,MATCH($C$2,$E$1:$P$1,0))-INDEX(S36:AD36,1,MATCH($C$2,S$1:AD$1,0)) -> #REF! | AF36: =IFERROR(INDEX($E36:$P36,1,MATCH($C$2,$E$1:$P$1,0))/INDEX($S36:$AD36,1,MATCH($C$2,S$1:AD$1,0))-1,0) -> 0 | AH36: {=INDEX(#REF!,MATCH($C36,#REF!,0),MATCH(AH$1,#REF!,0))} -> #REF! | AI36: {=INDEX(#REF!,MATCH($C36,#REF!,0),MATCH(AI$1,#REF!,0))} -> #REF! | AJ36: {=INDEX(#REF!,MATCH($C36,#REF!,0),MATCH(AJ$1,#REF!,0))} -> #REF! | AK36: {=INDEX(#REF!,MATCH($C36,#REF!,0),MATCH(AK$1,#REF!,0))} -> #REF! | AL36: {=INDEX(#REF!,MATCH($C36,#REF!,0),MATCH(AL$1,#REF!,0))} -> #REF! | AM36: {=INDEX(#REF!,MATCH($C36,#REF!,0),MATCH(AM$1,#REF!,0))} -> #REF! | AN36: {=INDEX(#REF!,MATCH($C36,#REF!,0),MATCH(AN$1,#REF!,0))} -> #REF! | AO36: {=INDEX(#REF!,MATCH($C36,#REF!,0),MATCH(AO$1,#REF!,0))} -> #REF! | ... AS36: {=INDEX(#REF!,MATCH($C36,#REF!,0),MATCH(AS$1,#REF!,0))} -> #REF! | AT36: =INDEX($E36:$P36,1,MATCH($C$2,$E$1:$P$1,0))-INDEX(AH36:AS36,1,MATCH(EDATE($C$2,-12),AH$1:AS$1,0)) -> #REF! | AU36: =IFERROR(INDEX($E36:$P36,1,MATCH($C$2,$E$1:$P$1,0))/INDEX(AH36:AS36,1,MATCH(EDATE($C$2,-12),AH$1:AS$1,0))-1,0) -> 0 | AW36: =SUMIF(E$1:P$1,"<="&AW$2,E36:P36) -> #REF! | BA36: =SUMIF(S$1:AD$1,"<="&BA$2,S36:AD36) -> #REF! | BC36: =$AW36-BA36 -> #REF! | BD36: =IFERROR($AW36/BA36-1,"-") -> - | BG36: =SUMIF(AH$1:AS$1,"<="&BG$2,AH36:AS36) -> #REF! | BI36: =$AW36-BG36 -> #REF! | BJ36: =IFERROR($AW36/BG36-1,"-") -> -
A37: Receita | C37: Desconto | E37: {=INDEX(#REF!,MATCH($C37,#REF!,0),MATCH(E$1,#REF!,0))} -> #REF! | F37: {=INDEX(#REF!,MATCH($C37,#REF!,0),MATCH(F$1,#REF!,0))} -> #REF! | G37: {=INDEX(#REF!,MATCH($C37,#REF!,0),MATCH(G$1,#REF!,0))} -> #REF! | H37: {=INDEX(#REF!,MATCH($C37,#REF!,0),MATCH(H$1,#REF!,0))} -> #REF! | I37: {=INDEX(#REF!,MATCH($C37,#REF!,0),MATCH(I$1,#REF!,0))} -> #REF! | J37: {=INDEX(#REF!,MATCH($C37,#REF!,0),MATCH(J$1,#REF!,0))} -> #REF! | K37: {=INDEX(#REF!,MATCH($C37,#REF!,0),MATCH(K$1,#REF!,0))} -> #REF! | L37: {=INDEX(#REF!,MATCH($C37,#REF!,0),MATCH(L$1,#REF!,0))} -> #REF! | ... P37: {=INDEX(#REF!,MATCH($C37,#REF!,0),MATCH(P$1,#REF!,0))} -> #REF! | S37: {=INDEX(#REF!,MATCH($C37,#REF!,0),MATCH(S$1,#REF!,0))} -> #REF! | T37: {=INDEX(#REF!,MATCH($C37,#REF!,0),MATCH(T$1,#REF!,0))} -> #REF! | U37: {=INDEX(#REF!,MATCH($C37,#REF!,0),MATCH(U$1,#REF!,0))} -> #REF! | V37: {=INDEX(#REF!,MATCH($C37,#REF!,0),MATCH(V$1,#REF!,0))} -> #REF! | W37: {=INDEX(#REF!,MATCH($C37,#REF!,0),MATCH(W$1,#REF!,0))} -> #REF! | X37: {=INDEX(#REF!,MATCH($C37,#REF!,0),MATCH(X$1,#REF!,0))} -> #REF! | Y37: {=INDEX(#REF!,MATCH($C37,#REF!,0),MATCH(Y$1,#REF!,0))} -> #REF! | Z37: {=INDEX(#REF!,MATCH($C37,#REF!,0),MATCH(Z$1,#REF!,0))} -> #REF! | ... AD37: {=INDEX(#REF!,MATCH($C37,#REF!,0),MATCH(AD$1,#REF!,0))} -> #REF! | AE37: =INDEX($E37:$P37,1,MATCH($C$2,$E$1:$P$1,0))-INDEX(S37:AD37,1,MATCH($C$2,S$1:AD$1,0)) -> #REF! | AF37: =IFERROR(INDEX($E37:$P37,1,MATCH($C$2,$E$1:$P$1,0))/INDEX($S37:$AD37,1,MATCH($C$2,S$1:AD$1,0))-1,0) -> 0 | AH37: {=INDEX(#REF!,MATCH($C37,#REF!,0),MATCH(AH$1,#REF!,0))} -> #REF! | AI37: {=INDEX(#REF!,MATCH($C37,#REF!,0),MATCH(AI$1,#REF!,0))} -> #REF! | AJ37: {=INDEX(#REF!,MATCH($C37,#REF!,0),MATCH(AJ$1,#REF!,0))} -> #REF! | AK37: {=INDEX(#REF!,MATCH($C37,#REF!,0),MATCH(AK$1,#REF!,0))} -> #REF! | AL37: {=INDEX(#REF!,MATCH($C37,#REF!,0),MATCH(AL$1,#REF!,0))} -> #REF! | AM37: {=INDEX(#REF!,MATCH($C37,#REF!,0),MATCH(AM$1,#REF!,0))} -> #REF! | AN37: {=INDEX(#REF!,MATCH($C37,#REF!,0),MATCH(AN$1,#REF!,0))} -> #REF! | AO37: {=INDEX(#REF!,MATCH($C37,#REF!,0),MATCH(AO$1,#REF!,0))} -> #REF! | ... AS37: {=INDEX(#REF!,MATCH($C37,#REF!,0),MATCH(AS$1,#REF!,0))} -> #REF! | AT37: =INDEX($E37:$P37,1,MATCH($C$2,$E$1:$P$1,0))-INDEX(AH37:AS37,1,MATCH(EDATE($C$2,-12),AH$1:AS$1,0)) -> #REF! | AU37: =IFERROR(INDEX($E37:$P37,1,MATCH($C$2,$E$1:$P$1,0))/INDEX(AH37:AS37,1,MATCH(EDATE($C$2,-12),AH$1:AS$1,0))-1,0) -> 0 | AW37: =SUMIF(E$1:P$1,"<="&AW$2,E37:P37) -> #REF! | BA37: =SUMIF(S$1:AD$1,"<="&BA$2,S37:AD37) -> #REF! | BC37: =$AW37-BA37 -> #REF! | BD37: =IFERROR($AW37/BA37-1,"-") -> - | BG37: =SUMIF(AH$1:AS$1,"<="&BG$2,AH37:AS37) -> #REF! | BI37: =$AW37-BG37 -> #REF! | BJ37: =IFERROR($AW37/BG37-1,"-") -> -
A38: Receita | C38: Receita bruta | E38: =E4+E37 -> #REF! | F38: =F4+F37 -> #REF! | G38: =G4+G37 -> #REF! | H38: =H4+H37 -> #REF! | I38: =I4+I37 -> #REF! | J38: =J4+J37 -> #REF! | K38: =K4+K37 -> #REF! | L38: =L4+L37 -> #REF! | ... P38: =P4+P37 -> #REF! | Q38: =IFERROR(INDEX($E38:$P38,1,MATCH($C$2,$E$1:$P$1,0))/INDEX($E$38:$P$38,1,MATCH($C$2,$E$1:$P$1,0)),0) -> 0 | S38: =S4+S37 -> #REF! | T38: =T4+T37 -> #REF! | U38: =U4+U37 -> #REF! | V38: =V4+V37 -> #REF! | W38: =W4+W37 -> #REF! | X38: =X4+X37 -> #REF! | Y38: =Y4+Y37 -> #REF! | Z38: =Z4+Z37 -> #REF! | ... AD38: =AD4+AD37 -> #REF! | AE38: =INDEX($E38:$P38,1,MATCH($C$2,$E$1:$P$1,0))-INDEX(S38:AD38,1,MATCH($C$2,S$1:AD$1,0)) -> #REF! | AF38: =IFERROR(1*--(INDEX($S38:$AD38,1,MATCH($C$2,S$1:AD$1,0))<0)+INDEX($E38:$P38,1,MATCH($C$2,$E$1:$P$1,0))/INDEX($S38:$AD38,1,MATCH($C$2,S$1:AD$1,0))-1*--(INDEX($S38:$AD38,1,MATCH($C$2,S$1:AD$1,0))>=0),0) -> 0 | AH38: 276643.04 | AI38: 359281.46 | AJ38: 744847.97 | AK38: 422735.33 | AL38: 519926.69 | AM38: 491964.54 | AN38: 637072.6 | AO38: 562042.29 | AP38: 516675.95 | AQ38: 519972.19 | AR38: 1025370.4 | AS38: 445579.27 | AT38: =INDEX($E38:$P38,1,MATCH($C$2,$E$1:$P$1,0))-INDEX(AH38:AS38,1,MATCH(EDATE($C$2,-12),AH$1:AS$1,0)) -> #REF! | AU38: =IFERROR(INDEX($E38:$P38,1,MATCH($C$2,$E$1:$P$1,0))/INDEX(AH38:AS38,1,MATCH(EDATE($C$2,-12),AH$1:AS$1,0))-1,0) -> 0 | AW38: =AW4+AW37 -> #REF! | AX38: =AW38/AW$38 -> #REF! | BA38: =BA4+BA37 -> #REF! | BB38: =BA38/BA$38 -> #REF! | BC38: =$AW38-BA38 -> #REF! | BD38: =IFERROR($AW38/BA38-1,"-") -> - | BG38: =SUMIF(AH$1:AS$1,"<="&BG$2,AH38:AS38) -> 6522111.7 | BH38: =BG38/BG$38 -> 1 | BI38: =$AW38-BG38 -> #REF! | BJ38: =IFERROR($AW38/BG38-1,"-") -> -
A39: Despesa | C39: Impostos sobre receita | E39: =SUM(E40:E42) -> #REF! | F39: =SUM(F40:F42) -> #REF! | G39: =SUM(G40:G42) -> #REF! | H39: =SUM(H40:H42) -> #REF! | I39: =SUM(I40:I42) -> #REF! | J39: =SUM(J40:J42) -> #REF! | K39: =SUM(K40:K42) -> #REF! | L39: =SUM(L40:L42) -> #REF! | ... P39: =SUM(P40:P42) -> #REF! | Q39: =IFERROR(INDEX($E39:$P39,1,MATCH($C$2,$E$1:$P$1,0))/INDEX($E$38:$P$38,1,MATCH($C$2,$E$1:$P$1,0)),0) -> 0 | S39: =SUM(S40:S42) -> #REF! | T39: =SUM(T40:T42) -> #REF! | U39: =SUM(U40:U42) -> #REF! | V39: =SUM(V40:V42) -> #REF! | W39: =SUM(W40:W42) -> #REF! | X39: =SUM(X40:X42) -> #REF! | Y39: =SUM(Y40:Y42) -> #REF! | Z39: =SUM(Z40:Z42) -> #REF! | ... AD39: =SUM(AD40:AD42) -> #REF! | AE39: =INDEX($E39:$P39,1,MATCH($C$2,$E$1:$P$1,0))-INDEX(S39:AD39,1,MATCH($C$2,S$1:AD$1,0)) -> #REF! | AF39: =IFERROR(1*--(INDEX($S39:$AD39,1,MATCH($C$2,S$1:AD$1,0))<0)+INDEX($E39:$P39,1,MATCH($C$2,$E$1:$P$1,0))/INDEX($S39:$AD39,1,MATCH($C$2,S$1:AD$1,0))-1*--(INDEX($S39:$AD39,1,MATCH($C$2,S$1:AD$1,0))>=0),0) -> 0 | AH39: =SUM(AH40:AH42) -> #REF! | AI39: =SUM(AI40:AI42) -> #REF! | AJ39: =SUM(AJ40:AJ42) -> #REF! | AK39: =SUM(AK40:AK42) -> #REF! | AL39: =SUM(AL40:AL42) -> #REF! | AM39: =SUM(AM40:AM42) -> #REF! | AN39: =SUM(AN40:AN42) -> #REF! | AO39: =SUM(AO40:AO42) -> #REF! | ... AS39: =SUM(AS40:AS42) -> #REF! | AT39: =INDEX($E39:$P39,1,MATCH($C$2,$E$1:$P$1,0))-INDEX(AH39:AS39,1,MATCH(EDATE($C$2,-12),AH$1:AS$1,0)) -> #REF! | AU39: =IFERROR(INDEX($E39:$P39,1,MATCH($C$2,$E$1:$P$1,0))/INDEX(AH39:AS39,1,MATCH(EDATE($C$2,-12),AH$1:AS$1,0))-1,0) -> 0 | AW39: =SUM(AW40:AW42) -> #REF! | AX39: =AW39/AW$38 -> #REF! | BA39: =SUM(BA40:BA42) -> #REF! | BB39: =BA39/BA$38 -> #REF! | BC39: =$AW39-BA39 -> #REF! | BD39: =($AX39-BB39)*100 -> #REF! | BG39: =SUM(BG40:BG42) -> #REF! | BH39: =BG39/BG$38 -> #REF! | BI39: =$AW39-BG39 -> #REF! | BJ39: =($AX39-BH39)*100 -> #REF!
A40: Despesa | C40: ICMS | E40: {=INDEX(#REF!,MATCH($C40,#REF!,0),MATCH(E$1,#REF!,0))} -> #REF! | F40: {=INDEX(#REF!,MATCH($C40,#REF!,0),MATCH(F$1,#REF!,0))} -> #REF! | G40: {=INDEX(#REF!,MATCH($C40,#REF!,0),MATCH(G$1,#REF!,0))} -> #REF! | H40: {=INDEX(#REF!,MATCH($C40,#REF!,0),MATCH(H$1,#REF!,0))} -> #REF! | I40: {=INDEX(#REF!,MATCH($C40,#REF!,0),MATCH(I$1,#REF!,0))} -> #REF! | J40: {=INDEX(#REF!,MATCH($C40,#REF!,0),MATCH(J$1,#REF!,0))} -> #REF! | K40: {=INDEX(#REF!,MATCH($C40,#REF!,0),MATCH(K$1,#REF!,0))} -> #REF! | L40: {=INDEX(#REF!,MATCH($C40,#REF!,0),MATCH(L$1,#REF!,0))} -> #REF! | ... P40: {=INDEX(#REF!,MATCH($C40,#REF!,0),MATCH(P$1,#REF!,0))} -> #REF! | Q40: =IFERROR(INDEX($E40:$P40,1,MATCH($C$2,$E$1:$P$1,0))/INDEX($E$38:$P$38,1,MATCH($C$2,$E$1:$P$1,0)),0) -> 0 | S40: {=INDEX(#REF!,MATCH($C40,#REF!,0),MATCH(S$1,#REF!,0))} -> #REF! | T40: {=INDEX(#REF!,MATCH($C40,#REF!,0),MATCH(T$1,#REF!,0))} -> #REF! | U40: {=INDEX(#REF!,MATCH($C40,#REF!,0),MATCH(U$1,#REF!,0))} -> #REF! | V40: {=INDEX(#REF!,MATCH($C40,#REF!,0),MATCH(V$1,#REF!,0))} -> #REF! | W40: {=INDEX(#REF!,MATCH($C40,#REF!,0),MATCH(W$1,#REF!,0))} -> #REF! | X40: {=INDEX(#REF!,MATCH($C40,#REF!,0),MATCH(X$1,#REF!,0))} -> #REF! | Y40: {=INDEX(#REF!,MATCH($C40,#REF!,0),MATCH(Y$1,#REF!,0))} -> #REF! | Z40: {=INDEX(#REF!,MATCH($C40,#REF!,0),MATCH(Z$1,#REF!,0))} -> #REF! | ... AD40: {=INDEX(#REF!,MATCH($C40,#REF!,0),MATCH(AD$1,#REF!,0))} -> #REF! | AE40: =INDEX($E40:$P40,1,MATCH($C$2,$E$1:$P$1,0))-INDEX(S40:AD40,1,MATCH($C$2,S$1:AD$1,0)) -> #REF! | AF40: =IFERROR(INDEX($E40:$P40,1,MATCH($C$2,$E$1:$P$1,0))/INDEX($S40:$AD40,1,MATCH($C$2,S$1:AD$1,0))-1,0) -> 0 | AH40: {=INDEX(#REF!,MATCH($C40,#REF!,0),MATCH(AH$1,#REF!,0))} -> #REF! | AI40: {=INDEX(#REF!,MATCH($C40,#REF!,0),MATCH(AI$1,#REF!,0))} -> #REF! | AJ40: {=INDEX(#REF!,MATCH($C40,#REF!,0),MATCH(AJ$1,#REF!,0))} -> #REF! | AK40: {=INDEX(#REF!,MATCH($C40,#REF!,0),MATCH(AK$1,#REF!,0))} -> #REF! | AL40: {=INDEX(#REF!,MATCH($C40,#REF!,0),MATCH(AL$1,#REF!,0))} -> #REF! | AM40: {=INDEX(#REF!,MATCH($C40,#REF!,0),MATCH(AM$1,#REF!,0))} -> #REF! | AN40: {=INDEX(#REF!,MATCH($C40,#REF!,0),MATCH(AN$1,#REF!,0))} -> #REF! | AO40: {=INDEX(#REF!,MATCH($C40,#REF!,0),MATCH(AO$1,#REF!,0))} -> #REF! | ... AS40: {=INDEX(#REF!,MATCH($C40,#REF!,0),MATCH(AS$1,#REF!,0))} -> #REF! | AT40: =INDEX($E40:$P40,1,MATCH($C$2,$E$1:$P$1,0))-INDEX(AH40:AS40,1,MATCH(EDATE($C$2,-12),AH$1:AS$1,0)) -> #REF! | AU40: =IFERROR(INDEX($E40:$P40,1,MATCH($C$2,$E$1:$P$1,0))/INDEX(AH40:AS40,1,MATCH(EDATE($C$2,-12),AH$1:AS$1,0))-1,0) -> 0 | AW40: =SUMIF(E$1:P$1,"<="&AW$2,E40:P40) -> #REF! | AX40: =AW40/AW$38 -> #REF! | BA40: =SUMIF(S$1:AD$1,"<="&BA$2,S40:AD40) -> #REF! | BB40: =BA40/BA$38 -> #REF! | BC40: =$AW40-BA40 -> #REF! | BD40: =($AX40-BB40)*100 -> #REF! | BG40: =SUMIF(AH$1:AS$1,"<="&BG$2,AH40:AS40) -> #REF! | BH40: =BG40/BG$38 -> #REF! | BI40: =$AW40-BG40 -> #REF! | BJ40: =($AX40-BH40)*100 -> #REF!
A41: Despesa | C41: PIS/COFINS | E41: {=INDEX(#REF!,MATCH($C41,#REF!,0),MATCH(E$1,#REF!,0))} -> #REF! | F41: {=INDEX(#REF!,MATCH($C41,#REF!,0),MATCH(F$1,#REF!,0))} -> #REF! | G41: {=INDEX(#REF!,MATCH($C41,#REF!,0),MATCH(G$1,#REF!,0))} -> #REF! | H41: {=INDEX(#REF!,MATCH($C41,#REF!,0),MATCH(H$1,#REF!,0))} -> #REF! | I41: {=INDEX(#REF!,MATCH($C41,#REF!,0),MATCH(I$1,#REF!,0))} -> #REF! | J41: {=INDEX(#REF!,MATCH($C41,#REF!,0),MATCH(J$1,#REF!,0))} -> #REF! | K41: {=INDEX(#REF!,MATCH($C41,#REF!,0),MATCH(K$1,#REF!,0))} -> #REF! | L41: {=INDEX(#REF!,MATCH($C41,#REF!,0),MATCH(L$1,#REF!,0))} -> #REF! | ... P41: {=INDEX(#REF!,MATCH($C41,#REF!,0),MATCH(P$1,#REF!,0))} -> #REF! | Q41: =IFERROR(INDEX($E41:$P41,1,MATCH($C$2,$E$1:$P$1,0))/INDEX($E$38:$P$38,1,MATCH($C$2,$E$1:$P$1,0)),0) -> 0 | S41: {=INDEX(#REF!,MATCH($C41,#REF!,0),MATCH(S$1,#REF!,0))} -> #REF! | T41: {=INDEX(#REF!,MATCH($C41,#REF!,0),MATCH(T$1,#REF!,0))} -> #REF! | U41: {=INDEX(#REF!,MATCH($C41,#REF!,0),MATCH(U$1,#REF!,0))} -> #REF! | V41: {=INDEX(#REF!,MATCH($C41,#REF!,0),MATCH(V$1,#REF!,0))} -> #REF! | W41: {=INDEX(#REF!,MATCH($C41,#REF!,0),MATCH(W$1,#REF!,0))} -> #REF! | X41: {=INDEX(#REF!,MATCH($C41,#REF!,0),MATCH(X$1,#REF!,0))} -> #REF! | Y41: {=INDEX(#REF!,MATCH($C41,#REF!,0),MATCH(Y$1,#REF!,0))} -> #REF! | Z41: {=INDEX(#REF!,MATCH($C41,#REF!,0),MATCH(Z$1,#REF!,0))} -> #REF! | ... AD41: {=INDEX(#REF!,MATCH($C41,#REF!,0),MATCH(AD$1,#REF!,0))} -> #REF! | AE41: =INDEX($E41:$P41,1,MATCH($C$2,$E$1:$P$1,0))-INDEX(S41:AD41,1,MATCH($C$2,S$1:AD$1,0)) -> #REF! | AF41: =IFERROR(INDEX($E41:$P41,1,MATCH($C$2,$E$1:$P$1,0))/INDEX($S41:$AD41,1,MATCH($C$2,S$1:AD$1,0))-1,0) -> 0 | AH41: {=INDEX(#REF!,MATCH($C41,#REF!,0),MATCH(AH$1,#REF!,0))} -> #REF! | AI41: {=INDEX(#REF!,MATCH($C41,#REF!,0),MATCH(AI$1,#REF!,0))} -> #REF! | AJ41: {=INDEX(#REF!,MATCH($C41,#REF!,0),MATCH(AJ$1,#REF!,0))} -> #REF! | AK41: {=INDEX(#REF!,MATCH($C41,#REF!,0),MATCH(AK$1,#REF!,0))} -> #REF! | AL41: {=INDEX(#REF!,MATCH($C41,#REF!,0),MATCH(AL$1,#REF!,0))} -> #REF! | AM41: {=INDEX(#REF!,MATCH($C41,#REF!,0),MATCH(AM$1,#REF!,0))} -> #REF! | AN41: {=INDEX(#REF!,MATCH($C41,#REF!,0),MATCH(AN$1,#REF!,0))} -> #REF! | AO41: {=INDEX(#REF!,MATCH($C41,#REF!,0),MATCH(AO$1,#REF!,0))} -> #REF! | ... AS41: {=INDEX(#REF!,MATCH($C41,#REF!,0),MATCH(AS$1,#REF!,0))} -> #REF! | AT41: =INDEX($E41:$P41,1,MATCH($C$2,$E$1:$P$1,0))-INDEX(AH41:AS41,1,MATCH(EDATE($C$2,-12),AH$1:AS$1,0)) -> #REF! | AU41: =IFERROR(INDEX($E41:$P41,1,MATCH($C$2,$E$1:$P$1,0))/INDEX(AH41:AS41,1,MATCH(EDATE($C$2,-12),AH$1:AS$1,0))-1,0) -> 0 | AW41: =SUMIF(E$1:P$1,"<="&AW$2,E41:P41) -> #REF! | AX41: =AW41/AW$38 -> #REF! | BA41: =SUMIF(S$1:AD$1,"<="&BA$2,S41:AD41) -> #REF! | BB41: =BA41/BA$38 -> #REF! | BC41: =$AW41-BA41 -> #REF! | BD41: =($AX41-BB41)*100 -> #REF! | BG41: =SUMIF(AH$1:AS$1,"<="&BG$2,AH41:AS41) -> #REF! | BH41: =BG41/BG$38 -> #REF! | BI41: =$AW41-BG41 -> #REF! | BJ41: =($AX41-BH41)*100 -> #REF!
A42: Despesa | C42: DIFAL + FCP | E42: {=INDEX(#REF!,MATCH($C42,#REF!,0),MATCH(E$1,#REF!,0))} -> #REF! | F42: {=INDEX(#REF!,MATCH($C42,#REF!,0),MATCH(F$1,#REF!,0))} -> #REF! | G42: {=INDEX(#REF!,MATCH($C42,#REF!,0),MATCH(G$1,#REF!,0))} -> #REF! | H42: {=INDEX(#REF!,MATCH($C42,#REF!,0),MATCH(H$1,#REF!,0))} -> #REF! | I42: {=INDEX(#REF!,MATCH($C42,#REF!,0),MATCH(I$1,#REF!,0))} -> #REF! | J42: {=INDEX(#REF!,MATCH($C42,#REF!,0),MATCH(J$1,#REF!,0))} -> #REF! | K42: {=INDEX(#REF!,MATCH($C42,#REF!,0),MATCH(K$1,#REF!,0))} -> #REF! | L42: {=INDEX(#REF!,MATCH($C42,#REF!,0),MATCH(L$1,#REF!,0))} -> #REF! | ... P42: {=INDEX(#REF!,MATCH($C42,#REF!,0),MATCH(P$1,#REF!,0))} -> #REF! | Q42: =IFERROR(INDEX($E42:$P42,1,MATCH($C$2,$E$1:$P$1,0))/INDEX($E$38:$P$38,1,MATCH($C$2,$E$1:$P$1,0)),0) -> 0 | S42: {=INDEX(#REF!,MATCH($C42,#REF!,0),MATCH(S$1,#REF!,0))} -> #REF! | T42: {=INDEX(#REF!,MATCH($C42,#REF!,0),MATCH(T$1,#REF!,0))} -> #REF! | U42: {=INDEX(#REF!,MATCH($C42,#REF!,0),MATCH(U$1,#REF!,0))} -> #REF! | V42: {=INDEX(#REF!,MATCH($C42,#REF!,0),MATCH(V$1,#REF!,0))} -> #REF! | W42: {=INDEX(#REF!,MATCH($C42,#REF!,0),MATCH(W$1,#REF!,0))} -> #REF! | X42: {=INDEX(#REF!,MATCH($C42,#REF!,0),MATCH(X$1,#REF!,0))} -> #REF! | Y42: {=INDEX(#REF!,MATCH($C42,#REF!,0),MATCH(Y$1,#REF!,0))} -> #REF! | Z42: {=INDEX(#REF!,MATCH($C42,#REF!,0),MATCH(Z$1,#REF!,0))} -> #REF! | ... AD42: {=INDEX(#REF!,MATCH($C42,#REF!,0),MATCH(AD$1,#REF!,0))} -> #REF! | AE42: =INDEX($E42:$P42,1,MATCH($C$2,$E$1:$P$1,0))-INDEX(S42:AD42,1,MATCH($C$2,S$1:AD$1,0)) -> #REF! | AF42: =IFERROR(INDEX($E42:$P42,1,MATCH($C$2,$E$1:$P$1,0))/INDEX($S42:$AD42,1,MATCH($C$2,S$1:AD$1,0))-1,0) -> 0 | AH42: {=INDEX(#REF!,MATCH($C42,#REF!,0),MATCH(AH$1,#REF!,0))} -> #REF! | AI42: {=INDEX(#REF!,MATCH($C42,#REF!,0),MATCH(AI$1,#REF!,0))} -> #REF! | AJ42: {=INDEX(#REF!,MATCH($C42,#REF!,0),MATCH(AJ$1,#REF!,0))} -> #REF! | AK42: {=INDEX(#REF!,MATCH($C42,#REF!,0),MATCH(AK$1,#REF!,0))} -> #REF! | AL42: {=INDEX(#REF!,MATCH($C42,#REF!,0),MATCH(AL$1,#REF!,0))} -> #REF! | AM42: {=INDEX(#REF!,MATCH($C42,#REF!,0),MATCH(AM$1,#REF!,0))} -> #REF! | AN42: {=INDEX(#REF!,MATCH($C42,#REF!,0),MATCH(AN$1,#REF!,0))} -> #REF! | AO42: {=INDEX(#REF!,MATCH($C42,#REF!,0),MATCH(AO$1,#REF!,0))} -> #REF! | ... AS42: {=INDEX(#REF!,MATCH($C42,#REF!,0),MATCH(AS$1,#REF!,0))} -> #REF! | AT42: =INDEX($E42:$P42,1,MATCH($C$2,$E$1:$P$1,0))-INDEX(AH42:AS42,1,MATCH(EDATE($C$2,-12),AH$1:AS$1,0)) -> #REF! | AU42: =IFERROR(INDEX($E42:$P42,1,MATCH($C$2,$E$1:$P$1,0))/INDEX(AH42:AS42,1,MATCH(EDATE($C$2,-12),AH$1:AS$1,0))-1,0) -> 0 | AW42: =SUMIF(E$1:P$1,"<="&AW$2,E42:P42) -> #REF! | AX42: =AW42/AW$38 -> #REF! | BA42: =SUMIF(S$1:AD$1,"<="&BA$2,S42:AD42) -> #REF! | BB42: =BA42/BA$38 -> #REF! | BC42: =$AW42-BA42 -> #REF! | BD42: =($AX42-BB42)*100 -> #REF! | BG42: =SUMIF(AH$1:AS$1,"<="&BG$2,AH42:AS42) -> #REF! | BH42: =BG42/BG$38 -> #REF! | BI42: =$AW42-BG42 -> #REF! | BJ42: =($AX42-BH42)*100 -> #REF!
A43: Despesa | C43: Receita líquida | E43: =E38+E39 -> #REF! | F43: =F38+F39 -> #REF! | G43: =G38+G39 -> #REF! | H43: =H38+H39 -> #REF! | I43: =I38+I39 -> #REF! | J43: =J38+J39 -> #REF! | K43: =K38+K39 -> #REF! | L43: =L38+L39 -> #REF! | ... P43: =P38+P39 -> #REF! | Q43: =IFERROR(INDEX($E43:$P43,1,MATCH($C$2,$E$1:$P$1,0))/INDEX($E$38:$P$38,1,MATCH($C$2,$E$1:$P$1,0)),0) -> 0 | S43: =S38+S39 -> #REF! | T43: =T38+T39 -> #REF! | U43: =U38+U39 -> #REF! | V43: =V38+V39 -> #REF! | W43: =W38+W39 -> #REF! | X43: =X38+X39 -> #REF! | Y43: =Y38+Y39 -> #REF! | Z43: =Z38+Z39 -> #REF! | ... AD43: =AD38+AD39 -> #REF! | AE43: =INDEX($E43:$P43,1,MATCH($C$2,$E$1:$P$1,0))-INDEX(S43:AD43,1,MATCH($C$2,S$1:AD$1,0)) -> #REF! | AF43: =IFERROR(1*--(INDEX($S43:$AD43,1,MATCH($C$2,S$1:AD$1,0))<0)+INDEX($E43:$P43,1,MATCH($C$2,$E$1:$P$1,0))/INDEX($S43:$AD43,1,MATCH($C$2,S$1:AD$1,0))-1*--(INDEX($S43:$AD43,1,MATCH($C$2,S$1:AD$1,0))>=0),0) -> 0 | AH43: =AH38+AH39 -> #REF! | AI43: =AI38+AI39 -> #REF! | AJ43: =AJ38+AJ39 -> #REF! | AK43: =AK38+AK39 -> #REF! | AL43: =AL38+AL39 -> #REF! | AM43: =AM38+AM39 -> #REF! | AN43: =AN38+AN39 -> #REF! | AO43: =AO38+AO39 -> #REF! | ... AS43: =AS38+AS39 -> #REF! | AT43: =INDEX($E43:$P43,1,MATCH($C$2,$E$1:$P$1,0))-INDEX(AH43:AS43,1,MATCH(EDATE($C$2,-12),AH$1:AS$1,0)) -> #REF! | AU43: =IFERROR(INDEX($E43:$P43,1,MATCH($C$2,$E$1:$P$1,0))/INDEX(AH43:AS43,1,MATCH(EDATE($C$2,-12),AH$1:AS$1,0))-1,0) -> 0 | AW43: =AW38+AW39 -> #REF! | AX43: =AW43/AW$38 -> #REF! | BA43: =BA38+BA39 -> #REF! | BB43: =BA43/BA$38 -> #REF! | BC43: =$AW43-BA43 -> #REF! | BD43: =($AX43-BB43)*100 -> #REF! | BG43: =BG38+BG39 -> #REF! | BH43: =BG43/BG$38 -> #REF! | BI43: =$AW43-BG43 -> #REF! | BJ43: =($AX43-BH43)*100 -> #REF!
A44: Despesa | C44: CMV | E44: =SUM(E45:E48) -> #REF! | F44: =SUM(F45:F48) -> #REF! | G44: =SUM(G45:G48) -> #REF! | H44: =SUM(H45:H48) -> #REF! | I44: =SUM(I45:I48) -> #REF! | J44: =SUM(J45:J48) -> #REF! | K44: =SUM(K45:K48) -> #REF! | L44: =SUM(L45:L48) -> #REF! | ... P44: =SUM(P45:P48) -> #REF! | Q44: =IFERROR(INDEX($E44:$P44,1,MATCH($C$2,$E$1:$P$1,0))/INDEX($E$38:$P$38,1,MATCH($C$2,$E$1:$P$1,0)),0) -> 0 | S44: =SUM(S45:S48) -> #REF! | T44: =SUM(T45:T48) -> #REF! | U44: =SUM(U45:U48) -> #REF! | V44: =SUM(V45:V48) -> #REF! | W44: =SUM(W45:W48) -> #REF! | X44: =SUM(X45:X48) -> #REF! | Y44: =SUM(Y45:Y48) -> #REF! | Z44: =SUM(Z45:Z48) -> #REF! | ... AD44: =SUM(AD45:AD48) -> #REF! | AE44: =INDEX($E44:$P44,1,MATCH($C$2,$E$1:$P$1,0))-INDEX(S44:AD44,1,MATCH($C$2,S$1:AD$1,0)) -> #REF! | AF44: =IFERROR(1*--(INDEX($S44:$AD44,1,MATCH($C$2,S$1:AD$1,0))<0)+INDEX($E44:$P44,1,MATCH($C$2,$E$1:$P$1,0))/INDEX($S44:$AD44,1,MATCH($C$2,S$1:AD$1,0))-1*--(INDEX($S44:$AD44,1,MATCH($C$2,S$1:AD$1,0))>=0),0) -> 0 | AH44: =SUM(AH45:AH48) -> #REF! | AI44: =SUM(AI45:AI48) -> #REF! | AJ44: =SUM(AJ45:AJ48) -> #REF! | AK44: =SUM(AK45:AK48) -> #REF! | AL44: =SUM(AL45:AL48) -> #REF! | AM44: =SUM(AM45:AM48) -> #REF! | AN44: =SUM(AN45:AN48) -> #REF! | AO44: =SUM(AO45:AO48) -> #REF! | ... AS44: =SUM(AS45:AS48) -> #REF! | AT44: =INDEX($E44:$P44,1,MATCH($C$2,$E$1:$P$1,0))-INDEX(AH44:AS44,1,MATCH(EDATE($C$2,-12),AH$1:AS$1,0)) -> #REF! | AU44: =IFERROR(INDEX($E44:$P44,1,MATCH($C$2,$E$1:$P$1,0))/INDEX(AH44:AS44,1,MATCH(EDATE($C$2,-12),AH$1:AS$1,0))-1,0) -> 0 | AW44: =SUM(AW45:AW48) -> #REF! | AX44: =AW44/AW$38 -> #REF! | BA44: =SUM(BA45:BA48) -> #REF! | BB44: =BA44/BA$38 -> #REF! | BC44: =$AW44-BA44 -> #REF! | BD44: =($AX44-BB44)*100 -> #REF! | BG44: =SUM(BG45:BG48) -> #REF! | BH44: =BG44/BG$38 -> #REF! | BI44: =$AW44-BG44 -> #REF! | BJ44: =($AX44-BH44)*100 -> #REF!
A45: Despesa | C45: Produto | E45: {=INDEX(#REF!,MATCH($C45,#REF!,0),MATCH(E$1,#REF!,0))} -> #REF! | F45: {=INDEX(#REF!,MATCH($C45,#REF!,0),MATCH(F$1,#REF!,0))} -> #REF! | G45: {=INDEX(#REF!,MATCH($C45,#REF!,0),MATCH(G$1,#REF!,0))} -> #REF! | H45: {=INDEX(#REF!,MATCH($C45,#REF!,0),MATCH(H$1,#REF!,0))} -> #REF! | I45: {=INDEX(#REF!,MATCH($C45,#REF!,0),MATCH(I$1,#REF!,0))} -> #REF! | J45: {=INDEX(#REF!,MATCH($C45,#REF!,0),MATCH(J$1,#REF!,0))} -> #REF! | K45: {=INDEX(#REF!,MATCH($C45,#REF!,0),MATCH(K$1,#REF!,0))} -> #REF! | L45: {=INDEX(#REF!,MATCH($C45,#REF!,0),MATCH(L$1,#REF!,0))} -> #REF! | ... P45: {=INDEX(#REF!,MATCH($C45,#REF!,0),MATCH(P$1,#REF!,0))} -> #REF! | Q45: =IFERROR(INDEX($E45:$P45,1,MATCH($C$2,$E$1:$P$1,0))/INDEX($E$38:$P$38,1,MATCH($C$2,$E$1:$P$1,0)),0) -> 0 | S45: {=INDEX(#REF!,MATCH($C45,#REF!,0),MATCH(S$1,#REF!,0))} -> #REF! | T45: {=INDEX(#REF!,MATCH($C45,#REF!,0),MATCH(T$1,#REF!,0))} -> #REF! | U45: {=INDEX(#REF!,MATCH($C45,#REF!,0),MATCH(U$1,#REF!,0))} -> #REF! | V45: {=INDEX(#REF!,MATCH($C45,#REF!,0),MATCH(V$1,#REF!,0))} -> #REF! | W45: {=INDEX(#REF!,MATCH($C45,#REF!,0),MATCH(W$1,#REF!,0))} -> #REF! | X45: {=INDEX(#REF!,MATCH($C45,#REF!,0),MATCH(X$1,#REF!,0))} -> #REF! | Y45: {=INDEX(#REF!,MATCH($C45,#REF!,0),MATCH(Y$1,#REF!,0))} -> #REF! | Z45: {=INDEX(#REF!,MATCH($C45,#REF!,0),MATCH(Z$1,#REF!,0))} -> #REF! | ... AD45: {=INDEX(#REF!,MATCH($C45,#REF!,0),MATCH(AD$1,#REF!,0))} -> #REF! | AE45: =INDEX($E45:$P45,1,MATCH($C$2,$E$1:$P$1,0))-INDEX(S45:AD45,1,MATCH($C$2,S$1:AD$1,0)) -> #REF! | AF45: =IFERROR(INDEX($E45:$P45,1,MATCH($C$2,$E$1:$P$1,0))/INDEX($S45:$AD45,1,MATCH($C$2,S$1:AD$1,0))-1,0) -> 0 | AH45: {=INDEX(#REF!,MATCH($C45,#REF!,0),MATCH(AH$1,#REF!,0))} -> #REF! | AI45: {=INDEX(#REF!,MATCH($C45,#REF!,0),MATCH(AI$1,#REF!,0))} -> #REF! | AJ45: {=INDEX(#REF!,MATCH($C45,#REF!,0),MATCH(AJ$1,#REF!,0))} -> #REF! | AK45: {=INDEX(#REF!,MATCH($C45,#REF!,0),MATCH(AK$1,#REF!,0))} -> #REF! | AL45: {=INDEX(#REF!,MATCH($C45,#REF!,0),MATCH(AL$1,#REF!,0))} -> #REF! | AM45: {=INDEX(#REF!,MATCH($C45,#REF!,0),MATCH(AM$1,#REF!,0))} -> #REF! | AN45: {=INDEX(#REF!,MATCH($C45,#REF!,0),MATCH(AN$1,#REF!,0))} -> #REF! | AO45: {=INDEX(#REF!,MATCH($C45,#REF!,0),MATCH(AO$1,#REF!,0))} -> #REF! | ... AS45: {=INDEX(#REF!,MATCH($C45,#REF!,0),MATCH(AS$1,#REF!,0))} -> #REF! | AT45: =INDEX($E45:$P45,1,MATCH($C$2,$E$1:$P$1,0))-INDEX(AH45:AS45,1,MATCH(EDATE($C$2,-12),AH$1:AS$1,0)) -> #REF! | AU45: =IFERROR(INDEX($E45:$P45,1,MATCH($C$2,$E$1:$P$1,0))/INDEX(AH45:AS45,1,MATCH(EDATE($C$2,-12),AH$1:AS$1,0))-1,0) -> 0 | AW45: =SUMIF(E$1:P$1,"<="&AW$2,E45:P45) -> #REF! | AX45: =AW45/AW$38 -> #REF! | BA45: =SUMIF(S$1:AD$1,"<="&BA$2,S45:AD45) -> #REF! | BB45: =BA45/BA$38 -> #REF! | BC45: =$AW45-BA45 -> #REF! | BD45: =($AX45-BB45)*100 -> #REF! | BG45: =SUMIF(AH$1:AS$1,"<="&BG$2,AH45:AS45) -> #REF! | BH45: =BG45/BG$38 -> #REF! | BI45: =$AW45-BG45 -> #REF! | BJ45: =($AX45-BH45)*100 -> #REF!
A46: Despesa | C46: Boniteca | E46: {=INDEX(#REF!,MATCH($C46,#REF!,0),MATCH(E$1,#REF!,0))} -> #REF! | F46: {=INDEX(#REF!,MATCH($C46,#REF!,0),MATCH(F$1,#REF!,0))} -> #REF! | G46: {=INDEX(#REF!,MATCH($C46,#REF!,0),MATCH(G$1,#REF!,0))} -> #REF! | H46: {=INDEX(#REF!,MATCH($C46,#REF!,0),MATCH(H$1,#REF!,0))} -> #REF! | I46: {=INDEX(#REF!,MATCH($C46,#REF!,0),MATCH(I$1,#REF!,0))} -> #REF! | J46: {=INDEX(#REF!,MATCH($C46,#REF!,0),MATCH(J$1,#REF!,0))} -> #REF! | K46: {=INDEX(#REF!,MATCH($C46,#REF!,0),MATCH(K$1,#REF!,0))} -> #REF! | L46: {=INDEX(#REF!,MATCH($C46,#REF!,0),MATCH(L$1,#REF!,0))} -> #REF! | ... P46: {=INDEX(#REF!,MATCH($C46,#REF!,0),MATCH(P$1,#REF!,0))} -> #REF! | Q46: =IFERROR(INDEX($E46:$P46,1,MATCH($C$2,$E$1:$P$1,0))/INDEX($E$38:$P$38,1,MATCH($C$2,$E$1:$P$1,0)),0) -> 0 | S46: {=INDEX(#REF!,MATCH($C46,#REF!,0),MATCH(S$1,#REF!,0))} -> #REF! | T46: {=INDEX(#REF!,MATCH($C46,#REF!,0),MATCH(T$1,#REF!,0))} -> #REF! | U46: {=INDEX(#REF!,MATCH($C46,#REF!,0),MATCH(U$1,#REF!,0))} -> #REF! | V46: {=INDEX(#REF!,MATCH($C46,#REF!,0),MATCH(V$1,#REF!,0))} -> #REF! | W46: {=INDEX(#REF!,MATCH($C46,#REF!,0),MATCH(W$1,#REF!,0))} -> #REF! | X46: {=INDEX(#REF!,MATCH($C46,#REF!,0),MATCH(X$1,#REF!,0))} -> #REF! | Y46: {=INDEX(#REF!,MATCH($C46,#REF!,0),MATCH(Y$1,#REF!,0))} -> #REF! | Z46: {=INDEX(#REF!,MATCH($C46,#REF!,0),MATCH(Z$1,#REF!,0))} -> #REF! | ... AD46: {=INDEX(#REF!,MATCH($C46,#REF!,0),MATCH(AD$1,#REF!,0))} -> #REF! | AE46: =INDEX($E46:$P46,1,MATCH($C$2,$E$1:$P$1,0))-INDEX(S46:AD46,1,MATCH($C$2,S$1:AD$1,0)) -> #REF! | AF46: =IFERROR(INDEX($E46:$P46,1,MATCH($C$2,$E$1:$P$1,0))/INDEX($S46:$AD46,1,MATCH($C$2,S$1:AD$1,0))-1,0) -> 0 | AH46: {=INDEX(#REF!,MATCH($C46,#REF!,0),MATCH(AH$1,#REF!,0))} -> #REF! | AI46: {=INDEX(#REF!,MATCH($C46,#REF!,0),MATCH(AI$1,#REF!,0))} -> #REF! | AJ46: {=INDEX(#REF!,MATCH($C46,#REF!,0),MATCH(AJ$1,#REF!,0))} -> #REF! | AK46: {=INDEX(#REF!,MATCH($C46,#REF!,0),MATCH(AK$1,#REF!,0))} -> #REF! | AL46: {=INDEX(#REF!,MATCH($C46,#REF!,0),MATCH(AL$1,#REF!,0))} -> #REF! | AM46: {=INDEX(#REF!,MATCH($C46,#REF!,0),MATCH(AM$1,#REF!,0))} -> #REF! | AN46: {=INDEX(#REF!,MATCH($C46,#REF!,0),MATCH(AN$1,#REF!,0))} -> #REF! | AO46: {=INDEX(#REF!,MATCH($C46,#REF!,0),MATCH(AO$1,#REF!,0))} -> #REF! | ... AS46: {=INDEX(#REF!,MATCH($C46,#REF!,0),MATCH(AS$1,#REF!,0))} -> #REF! | AT46: =INDEX($E46:$P46,1,MATCH($C$2,$E$1:$P$1,0))-INDEX(AH46:AS46,1,MATCH(EDATE($C$2,-12),AH$1:AS$1,0)) -> #REF! | AU46: =IFERROR(INDEX($E46:$P46,1,MATCH($C$2,$E$1:$P$1,0))/INDEX(AH46:AS46,1,MATCH(EDATE($C$2,-12),AH$1:AS$1,0))-1,0) -> 0 | AW46: =SUMIF(E$1:P$1,"<="&AW$2,E46:P46) -> #REF! | AX46: =AW46/AW$38 -> #REF! | BA46: =SUMIF(S$1:AD$1,"<="&BA$2,S46:AD46) -> #REF! | BB46: =BA46/BA$38 -> #REF! | BC46: =$AW46-BA46 -> #REF! | BD46: =($AX46-BB46)*100 -> #REF! | BG46: =SUMIF(AH$1:AS$1,"<="&BG$2,AH46:AS46) -> #REF! | BH46: =BG46/BG$38 -> #REF! | BI46: =$AW46-BG46 -> #REF! | BJ46: =($AX46-BH46)*100 -> #REF!
A47: Despesa | C47: Frete sobre Compras | E47: {=INDEX(#REF!,MATCH($C47,#REF!,0),MATCH(E$1,#REF!,0))} -> #REF! | F47: {=INDEX(#REF!,MATCH($C47,#REF!,0),MATCH(F$1,#REF!,0))} -> #REF! | G47: {=INDEX(#REF!,MATCH($C47,#REF!,0),MATCH(G$1,#REF!,0))} -> #REF! | H47: {=INDEX(#REF!,MATCH($C47,#REF!,0),MATCH(H$1,#REF!,0))} -> #REF! | I47: {=INDEX(#REF!,MATCH($C47,#REF!,0),MATCH(I$1,#REF!,0))} -> #REF! | J47: {=INDEX(#REF!,MATCH($C47,#REF!,0),MATCH(J$1,#REF!,0))} -> #REF! | K47: {=INDEX(#REF!,MATCH($C47,#REF!,0),MATCH(K$1,#REF!,0))} -> #REF! | L47: {=INDEX(#REF!,MATCH($C47,#REF!,0),MATCH(L$1,#REF!,0))} -> #REF! | ... P47: {=INDEX(#REF!,MATCH($C47,#REF!,0),MATCH(P$1,#REF!,0))} -> #REF! | Q47: =IFERROR(INDEX($E47:$P47,1,MATCH($C$2,$E$1:$P$1,0))/INDEX($E$38:$P$38,1,MATCH($C$2,$E$1:$P$1,0)),0) -> 0 | S47: {=INDEX(#REF!,MATCH($C47,#REF!,0),MATCH(S$1,#REF!,0))} -> #REF! | T47: {=INDEX(#REF!,MATCH($C47,#REF!,0),MATCH(T$1,#REF!,0))} -> #REF! | U47: {=INDEX(#REF!,MATCH($C47,#REF!,0),MATCH(U$1,#REF!,0))} -> #REF! | V47: {=INDEX(#REF!,MATCH($C47,#REF!,0),MATCH(V$1,#REF!,0))} -> #REF! | W47: {=INDEX(#REF!,MATCH($C47,#REF!,0),MATCH(W$1,#REF!,0))} -> #REF! | X47: {=INDEX(#REF!,MATCH($C47,#REF!,0),MATCH(X$1,#REF!,0))} -> #REF! | Y47: {=INDEX(#REF!,MATCH($C47,#REF!,0),MATCH(Y$1,#REF!,0))} -> #REF! | Z47: {=INDEX(#REF!,MATCH($C47,#REF!,0),MATCH(Z$1,#REF!,0))} -> #REF! | ... AD47: {=INDEX(#REF!,MATCH($C47,#REF!,0),MATCH(AD$1,#REF!,0))} -> #REF! | AE47: =INDEX($E47:$P47,1,MATCH($C$2,$E$1:$P$1,0))-INDEX(S47:AD47,1,MATCH($C$2,S$1:AD$1,0)) -> #REF! | AF47: =IFERROR(INDEX($E47:$P47,1,MATCH($C$2,$E$1:$P$1,0))/INDEX($S47:$AD47,1,MATCH($C$2,S$1:AD$1,0))-1,0) -> 0 | AH47: {=INDEX(#REF!,MATCH($C47,#REF!,0),MATCH(AH$1,#REF!,0))} -> #REF! | AI47: {=INDEX(#REF!,MATCH($C47,#REF!,0),MATCH(AI$1,#REF!,0))} -> #REF! | AJ47: {=INDEX(#REF!,MATCH($C47,#REF!,0),MATCH(AJ$1,#REF!,0))} -> #REF! | AK47: {=INDEX(#REF!,MATCH($C47,#REF!,0),MATCH(AK$1,#REF!,0))} -> #REF! | AL47: {=INDEX(#REF!,MATCH($C47,#REF!,0),MATCH(AL$1,#REF!,0))} -> #REF! | AM47: {=INDEX(#REF!,MATCH($C47,#REF!,0),MATCH(AM$1,#REF!,0))} -> #REF! | AN47: {=INDEX(#REF!,MATCH($C47,#REF!,0),MATCH(AN$1,#REF!,0))} -> #REF! | AO47: {=INDEX(#REF!,MATCH($C47,#REF!,0),MATCH(AO$1,#REF!,0))} -> #REF! | ... AS47: {=INDEX(#REF!,MATCH($C47,#REF!,0),MATCH(AS$1,#REF!,0))} -> #REF! | AT47: =INDEX($E47:$P47,1,MATCH($C$2,$E$1:$P$1,0))-INDEX(AH47:AS47,1,MATCH(EDATE($C$2,-12),AH$1:AS$1,0)) -> #REF! | AU47: =IFERROR(INDEX($E47:$P47,1,MATCH($C$2,$E$1:$P$1,0))/INDEX(AH47:AS47,1,MATCH(EDATE($C$2,-12),AH$1:AS$1,0))-1,0) -> 0 | AW47: =SUMIF(E$1:P$1,"<="&AW$2,E47:P47) -> #REF! | AX47: =AW47/AW$38 -> #REF! | BA47: =SUMIF(S$1:AD$1,"<="&BA$2,S47:AD47) -> #REF! | BB47: =BA47/BA$38 -> #REF! | BC47: =$AW47-BA47 -> #REF! | BD47: =($AX47-BB47)*100 -> #REF! | BG47: =SUMIF(AH$1:AS$1,"<="&BG$2,AH47:AS47) -> #REF! | BH47: =BG47/BG$38 -> #REF! | BI47: =$AW47-BG47 -> #REF! | BJ47: =($AX47-BH47)*100 -> #REF!
A48: Despesa | C48: Embalagem | E48: {=INDEX(#REF!,MATCH($C48,#REF!,0),MATCH(E$1,#REF!,0))} -> #REF! | F48: {=INDEX(#REF!,MATCH($C48,#REF!,0),MATCH(F$1,#REF!,0))} -> #REF! | G48: {=INDEX(#REF!,MATCH($C48,#REF!,0),MATCH(G$1,#REF!,0))} -> #REF! | H48: {=INDEX(#REF!,MATCH($C48,#REF!,0),MATCH(H$1,#REF!,0))} -> #REF! | I48: {=INDEX(#REF!,MATCH($C48,#REF!,0),MATCH(I$1,#REF!,0))} -> #REF! | J48: {=INDEX(#REF!,MATCH($C48,#REF!,0),MATCH(J$1,#REF!,0))} -> #REF! | K48: {=INDEX(#REF!,MATCH($C48,#REF!,0),MATCH(K$1,#REF!,0))} -> #REF! | L48: {=INDEX(#REF!,MATCH($C48,#REF!,0),MATCH(L$1,#REF!,0))} -> #REF! | ... P48: {=INDEX(#REF!,MATCH($C48,#REF!,0),MATCH(P$1,#REF!,0))} -> #REF! | Q48: =IFERROR(INDEX($E48:$P48,1,MATCH($C$2,$E$1:$P$1,0))/INDEX($E$38:$P$38,1,MATCH($C$2,$E$1:$P$1,0)),0) -> 0 | S48: {=INDEX(#REF!,MATCH($C48,#REF!,0),MATCH(S$1,#REF!,0))} -> #REF! | T48: {=INDEX(#REF!,MATCH($C48,#REF!,0),MATCH(T$1,#REF!,0))} -> #REF! | U48: {=INDEX(#REF!,MATCH($C48,#REF!,0),MATCH(U$1,#REF!,0))} -> #REF! | V48: {=INDEX(#REF!,MATCH($C48,#REF!,0),MATCH(V$1,#REF!,0))} -> #REF! | W48: {=INDEX(#REF!,MATCH($C48,#REF!,0),MATCH(W$1,#REF!,0))} -> #REF! | X48: {=INDEX(#REF!,MATCH($C48,#REF!,0),MATCH(X$1,#REF!,0))} -> #REF! | Y48: {=INDEX(#REF!,MATCH($C48,#REF!,0),MATCH(Y$1,#REF!,0))} -> #REF! | Z48: {=INDEX(#REF!,MATCH($C48,#REF!,0),MATCH(Z$1,#REF!,0))} -> #REF! | ... AD48: {=INDEX(#REF!,MATCH($C48,#REF!,0),MATCH(AD$1,#REF!,0))} -> #REF! | AE48: =INDEX($E48:$P48,1,MATCH($C$2,$E$1:$P$1,0))-INDEX(S48:AD48,1,MATCH($C$2,S$1:AD$1,0)) -> #REF! | AF48: =IFERROR(INDEX($E48:$P48,1,MATCH($C$2,$E$1:$P$1,0))/INDEX($S48:$AD48,1,MATCH($C$2,S$1:AD$1,0))-1,0) -> 0 | AH48: {=INDEX(#REF!,MATCH($C48,#REF!,0),MATCH(AH$1,#REF!,0))} -> #REF! | AI48: {=INDEX(#REF!,MATCH($C48,#REF!,0),MATCH(AI$1,#REF!,0))} -> #REF! | AJ48: {=INDEX(#REF!,MATCH($C48,#REF!,0),MATCH(AJ$1,#REF!,0))} -> #REF! | AK48: {=INDEX(#REF!,MATCH($C48,#REF!,0),MATCH(AK$1,#REF!,0))} -> #REF! | AL48: {=INDEX(#REF!,MATCH($C48,#REF!,0),MATCH(AL$1,#REF!,0))} -> #REF! | AM48: {=INDEX(#REF!,MATCH($C48,#REF!,0),MATCH(AM$1,#REF!,0))} -> #REF! | AN48: {=INDEX(#REF!,MATCH($C48,#REF!,0),MATCH(AN$1,#REF!,0))} -> #REF! | AO48: {=INDEX(#REF!,MATCH($C48,#REF!,0),MATCH(AO$1,#REF!,0))} -> #REF! | ... AS48: {=INDEX(#REF!,MATCH($C48,#REF!,0),MATCH(AS$1,#REF!,0))} -> #REF! | AT48: =INDEX($E48:$P48,1,MATCH($C$2,$E$1:$P$1,0))-INDEX(AH48:AS48,1,MATCH(EDATE($C$2,-12),AH$1:AS$1,0)) -> #REF! | AU48: =IFERROR(INDEX($E48:$P48,1,MATCH($C$2,$E$1:$P$1,0))/INDEX(AH48:AS48,1,MATCH(EDATE($C$2,-12),AH$1:AS$1,0))-1,0) -> 0 | AW48: =SUMIF(E$1:P$1,"<="&AW$2,E48:P48) -> #REF! | AX48: =AW48/AW$38 -> #REF! | BA48: =SUMIF(S$1:AD$1,"<="&BA$2,S48:AD48) -> #REF! | BB48: =BA48/BA$38 -> #REF! | BC48: =$AW48-BA48 -> #REF! | BD48: =($AX48-BB48)*100 -> #REF! | BG48: =SUMIF(AH$1:AS$1,"<="&BG$2,AH48:AS48) -> #REF! | BH48: =BG48/BG$38 -> #REF! | BI48: =$AW48-BG48 -> #REF! | BJ48: =($AX48-BH48)*100 -> #REF!
A49: Despesa | C49: Margem bruta | E49: =E43+E44 -> #REF! | F49: =F43+F44 -> #REF! | G49: =G43+G44 -> #REF! | H49: =H43+H44 -> #REF! | I49: =I43+I44 -> #REF! | J49: =J43+J44 -> #REF! | K49: =K43+K44 -> #REF! | L49: =L43+L44 -> #REF! | ... P49: =P43+P44 -> #REF! | Q49: =IFERROR(INDEX($E49:$P49,1,MATCH($C$2,$E$1:$P$1,0))/INDEX($E$38:$P$38,1,MATCH($C$2,$E$1:$P$1,0)),0) -> 0 | S49: =S43+S44 -> #REF! | T49: =T43+T44 -> #REF! | U49: =U43+U44 -> #REF! | V49: =V43+V44 -> #REF! | W49: =W43+W44 -> #REF! | X49: =X43+X44 -> #REF! | Y49: =Y43+Y44 -> #REF! | Z49: =Z43+Z44 -> #REF! | ... AD49: =AD43+AD44 -> #REF! | AE49: =INDEX($E49:$P49,1,MATCH($C$2,$E$1:$P$1,0))-INDEX(S49:AD49,1,MATCH($C$2,S$1:AD$1,0)) -> #REF! | AF49: =IFERROR(1*--(INDEX($S49:$AD49,1,MATCH($C$2,S$1:AD$1,0))<0)+INDEX($E49:$P49,1,MATCH($C$2,$E$1:$P$1,0))/INDEX($S49:$AD49,1,MATCH($C$2,S$1:AD$1,0))-1*--(INDEX($S49:$AD49,1,MATCH($C$2,S$1:AD$1,0))>=0),0) -> 0 | AH49: =AH43+AH44 -> #REF! | AI49: =AI43+AI44 -> #REF! | AJ49: =AJ43+AJ44 -> #REF! | AK49: =AK43+AK44 -> #REF! | AL49: =AL43+AL44 -> #REF! | AM49: =AM43+AM44 -> #REF! | AN49: =AN43+AN44 -> #REF! | AO49: =AO43+AO44 -> #REF! | ... AS49: =AS43+AS44 -> #REF! | AT49: =INDEX($E49:$P49,1,MATCH($C$2,$E$1:$P$1,0))-INDEX(AH49:AS49,1,MATCH(EDATE($C$2,-12),AH$1:AS$1,0)) -> #REF! | AU49: =IFERROR(INDEX($E49:$P49,1,MATCH($C$2,$E$1:$P$1,0))/INDEX(AH49:AS49,1,MATCH(EDATE($C$2,-12),AH$1:AS$1,0))-1,0) -> 0 | AW49: =AW43+AW44 -> #REF! | AX49: =AW49/AW$38 -> #REF! | BA49: =BA43+BA44 -> #REF! | BB49: =BA49/BA$38 -> #REF! | BC49: =$AW49-BA49 -> #REF! | BD49: =($AX49-BB49)*100 -> #REF! | BG49: =BG43+BG44 -> #REF! | BH49: =BG49/BG$38 -> #REF! | BI49: =$AW49-BG49 -> #REF! | BJ49: =($AX49-BH49)*100 -> #REF!
A50: Despesa | C50: Despesas variáveis | E50: =E51+E59+E82 -> #REF! | F50: =F51+F59+F82 -> #REF! | G50: =G51+G59+G82 -> #REF! | H50: =H51+H59+H82 -> #REF! | I50: =I51+I59+I82 -> #REF! | J50: =J51+J59+J82 -> #REF! | K50: =K51+K59+K82 -> #REF! | L50: =L51+L59+L82 -> #REF! | ... P50: =P51+P59+P82 -> #REF! | Q50: =IFERROR(INDEX($E50:$P50,1,MATCH($C$2,$E$1:$P$1,0))/INDEX($E$38:$P$38,1,MATCH($C$2,$E$1:$P$1,0)),0) -> 0 | S50: =S51+S59+S82 -> #REF! | T50: =T51+T59+T82 -> #REF! | U50: =U51+U59+U82 -> #REF! | V50: =V51+V59+V82 -> #REF! | W50: =W51+W59+W82 -> #REF! | X50: =X51+X59+X82 -> #REF! | Y50: =Y51+Y59+Y82 -> #REF! | Z50: =Z51+Z59+Z82 -> #REF! | ... AD50: =AD51+AD59+AD82 -> #REF! | AE50: =INDEX($E50:$P50,1,MATCH($C$2,$E$1:$P$1,0))-INDEX(S50:AD50,1,MATCH($C$2,S$1:AD$1,0)) -> #REF! | AF50: =IFERROR(1*--(INDEX($S50:$AD50,1,MATCH($C$2,S$1:AD$1,0))<0)+INDEX($E50:$P50,1,MATCH($C$2,$E$1:$P$1,0))/INDEX($S50:$AD50,1,MATCH($C$2,S$1:AD$1,0))-1*--(INDEX($S50:$AD50,1,MATCH($C$2,S$1:AD$1,0))>=0),0) -> 0 | AH50: =AH51+AH59+AH82 -> #REF! | AI50: =AI51+AI59+AI82 -> #REF! | AJ50: =AJ51+AJ59+AJ82 -> #REF! | AK50: =AK51+AK59+AK82 -> #REF! | AL50: =AL51+AL59+AL82 -> #REF! | AM50: =AM51+AM59+AM82 -> #REF! | AN50: =AN51+AN59+AN82 -> #REF! | AO50: =AO51+AO59+AO82 -> #REF! | ... AS50: =AS51+AS59+AS82 -> #REF! | AT50: =INDEX($E50:$P50,1,MATCH($C$2,$E$1:$P$1,0))-INDEX(AH50:AS50,1,MATCH(EDATE($C$2,-12),AH$1:AS$1,0)) -> #REF! | AU50: =IFERROR(INDEX($E50:$P50,1,MATCH($C$2,$E$1:$P$1,0))/INDEX(AH50:AS50,1,MATCH(EDATE($C$2,-12),AH$1:AS$1,0))-1,0) -> 0 | AW50: =AW51+AW59+AW82 -> #REF! | AX50: =AW50/AW$38 -> #REF! | BA50: =BA51+BA59+BA82 -> #REF! | BB50: =BA50/BA$38 -> #REF! | BC50: =$AW50-BA50 -> #REF! | BD50: =($AX50-BB50)*100 -> #REF! | BG50: =BG51+BG59+BG82 -> #REF! | BH50: =BG50/BG$38 -> #REF! | BI50: =$AW50-BG50 -> #REF! | BJ50: =($AX50-BH50)*100 -> #REF!
A51: Despesa | C51: Despesas de venda | E51: =SUM(E52:E56) -> #REF! | F51: =SUM(F52:F56) -> #REF! | G51: =SUM(G52:G56) -> #REF! | H51: =SUM(H52:H56) -> #REF! | I51: =SUM(I52:I56) -> #REF! | J51: =SUM(J52:J56) -> #REF! | K51: =SUM(K52:K56) -> #REF! | L51: =SUM(L52:L56) -> #REF! | ... P51: =SUM(P52:P56) -> #REF! | Q51: =IFERROR(INDEX($E51:$P51,1,MATCH($C$2,$E$1:$P$1,0))/INDEX($E$38:$P$38,1,MATCH($C$2,$E$1:$P$1,0)),0) -> 0 | S51: =SUM(S52:S56) -> #REF! | T51: =SUM(T52:T56) -> #REF! | U51: =SUM(U52:U56) -> #REF! | V51: =SUM(V52:V56) -> #REF! | W51: =SUM(W52:W56) -> #REF! | X51: =SUM(X52:X56) -> #REF! | Y51: =SUM(Y52:Y56) -> #REF! | Z51: =SUM(Z52:Z56) -> #REF! | ... AD51: =SUM(AD52:AD56) -> #REF! | AE51: =INDEX($E51:$P51,1,MATCH($C$2,$E$1:$P$1,0))-INDEX(S51:AD51,1,MATCH($C$2,S$1:AD$1,0)) -> #REF! | AF51: =IFERROR(1*--(INDEX($S51:$AD51,1,MATCH($C$2,S$1:AD$1,0))<0)+INDEX($E51:$P51,1,MATCH($C$2,$E$1:$P$1,0))/INDEX($S51:$AD51,1,MATCH($C$2,S$1:AD$1,0))-1*--(INDEX($S51:$AD51,1,MATCH($C$2,S$1:AD$1,0))>=0),0) -> 0 | AH51: =SUM(AH52:AH56) -> #REF! | AI51: =SUM(AI52:AI56) -> #REF! | AJ51: =SUM(AJ52:AJ56) -> #REF! | AK51: =SUM(AK52:AK56) -> #REF! | AL51: =SUM(AL52:AL56) -> #REF! | AM51: =SUM(AM52:AM56) -> #REF! | AN51: =SUM(AN52:AN56) -> #REF! | AO51: =SUM(AO52:AO56) -> #REF! | ... AS51: =SUM(AS52:AS56) -> #REF! | AT51: =INDEX($E51:$P51,1,MATCH($C$2,$E$1:$P$1,0))-INDEX(AH51:AS51,1,MATCH(EDATE($C$2,-12),AH$1:AS$1,0)) -> #REF! | AU51: =IFERROR(INDEX($E51:$P51,1,MATCH($C$2,$E$1:$P$1,0))/INDEX(AH51:AS51,1,MATCH(EDATE($C$2,-12),AH$1:AS$1,0))-1,0) -> 0 | AW51: =SUM(AW52:AW56) -> #REF! | AX51: =AW51/AW$38 -> #REF! | BA51: =SUM(BA52:BA56) -> #REF! | BB51: =BA51/BA$38 -> #REF! | BC51: =$AW51-BA51 -> #REF! | BD51: =($AX51-BB51)*100 -> #REF! | BG51: =SUM(BG52:BG56) -> #REF! | BH51: =BG51/BG$38 -> #REF! | BI51: =$AW51-BG51 -> #REF! | BJ51: =($AX51-BH51)*100 -> #REF!
A52: Despesa | C52: Armazenagem | E52: {=INDEX(#REF!,MATCH($C52,#REF!,0),MATCH(E$1,#REF!,0))} -> #REF! | F52: {=INDEX(#REF!,MATCH($C52,#REF!,0),MATCH(F$1,#REF!,0))} -> #REF! | G52: {=INDEX(#REF!,MATCH($C52,#REF!,0),MATCH(G$1,#REF!,0))} -> #REF! | H52: {=INDEX(#REF!,MATCH($C52,#REF!,0),MATCH(H$1,#REF!,0))} -> #REF! | I52: {=INDEX(#REF!,MATCH($C52,#REF!,0),MATCH(I$1,#REF!,0))} -> #REF! | J52: {=INDEX(#REF!,MATCH($C52,#REF!,0),MATCH(J$1,#REF!,0))} -> #REF! | K52: {=INDEX(#REF!,MATCH($C52,#REF!,0),MATCH(K$1,#REF!,0))} -> #REF! | L52: {=INDEX(#REF!,MATCH($C52,#REF!,0),MATCH(L$1,#REF!,0))} -> #REF! | ... P52: {=INDEX(#REF!,MATCH($C52,#REF!,0),MATCH(P$1,#REF!,0))} -> #REF! | Q52: =IFERROR(INDEX($E52:$P52,1,MATCH($C$2,$E$1:$P$1,0))/INDEX($E$38:$P$38,1,MATCH($C$2,$E$1:$P$1,0)),0) -> 0 | S52: {=INDEX(#REF!,MATCH($C52,#REF!,0),MATCH(S$1,#REF!,0))} -> #REF! | T52: {=INDEX(#REF!,MATCH($C52,#REF!,0),MATCH(T$1,#REF!,0))} -> #REF! | U52: {=INDEX(#REF!,MATCH($C52,#REF!,0),MATCH(U$1,#REF!,0))} -> #REF! | V52: {=INDEX(#REF!,MATCH($C52,#REF!,0),MATCH(V$1,#REF!,0))} -> #REF! | W52: {=INDEX(#REF!,MATCH($C52,#REF!,0),MATCH(W$1,#REF!,0))} -> #REF! | X52: {=INDEX(#REF!,MATCH($C52,#REF!,0),MATCH(X$1,#REF!,0))} -> #REF! | Y52: {=INDEX(#REF!,MATCH($C52,#REF!,0),MATCH(Y$1,#REF!,0))} -> #REF! | Z52: {=INDEX(#REF!,MATCH($C52,#REF!,0),MATCH(Z$1,#REF!,0))} -> #REF! | ... AD52: {=INDEX(#REF!,MATCH($C52,#REF!,0),MATCH(AD$1,#REF!,0))} -> #REF! | AE52: =INDEX($E52:$P52,1,MATCH($C$2,$E$1:$P$1,0))-INDEX(S52:AD52,1,MATCH($C$2,S$1:AD$1,0)) -> #REF! | AF52: =IFERROR(INDEX($E52:$P52,1,MATCH($C$2,$E$1:$P$1,0))/INDEX($S52:$AD52,1,MATCH($C$2,S$1:AD$1,0))-1,0) -> 0 | AH52: {=INDEX(#REF!,MATCH($C52,#REF!,0),MATCH(AH$1,#REF!,0))} -> #REF! | AI52: {=INDEX(#REF!,MATCH($C52,#REF!,0),MATCH(AI$1,#REF!,0))} -> #REF! | AJ52: {=INDEX(#REF!,MATCH($C52,#REF!,0),MATCH(AJ$1,#REF!,0))} -> #REF! | AK52: {=INDEX(#REF!,MATCH($C52,#REF!,0),MATCH(AK$1,#REF!,0))} -> #REF! | AL52: {=INDEX(#REF!,MATCH($C52,#REF!,0),MATCH(AL$1,#REF!,0))} -> #REF! | AM52: {=INDEX(#REF!,MATCH($C52,#REF!,0),MATCH(AM$1,#REF!,0))} -> #REF! | AN52: {=INDEX(#REF!,MATCH($C52,#REF!,0),MATCH(AN$1,#REF!,0))} -> #REF! | AO52: {=INDEX(#REF!,MATCH($C52,#REF!,0),MATCH(AO$1,#REF!,0))} -> #REF! | ... AS52: {=INDEX(#REF!,MATCH($C52,#REF!,0),MATCH(AS$1,#REF!,0))} -> #REF! | AT52: =INDEX($E52:$P52,1,MATCH($C$2,$E$1:$P$1,0))-INDEX(AH52:AS52,1,MATCH(EDATE($C$2,-12),AH$1:AS$1,0)) -> #REF! | AU52: =IFERROR(INDEX($E52:$P52,1,MATCH($C$2,$E$1:$P$1,0))/INDEX(AH52:AS52,1,MATCH(EDATE($C$2,-12),AH$1:AS$1,0))-1,0) -> 0 | AW52: =SUMIF(E$1:P$1,"<="&AW$2,E52:P52) -> #REF! | AX52: =AW52/AW$38 -> #REF! | BA52: =SUMIF(S$1:AD$1,"<="&BA$2,S52:AD52) -> #REF! | BB52: =BA52/BA$38 -> #REF! | BC52: =$AW52-BA52 -> #REF! | BD52: =($AX52-BB52)*100 -> #REF! | BG52: =SUMIF(AH$1:AS$1,"<="&BG$2,AH52:AS52) -> #REF! | BH52: =BG52/BG$38 -> #REF! | BI52: =$AW52-BG52 -> #REF! | BJ52: =($AX52-BH52)*100 -> #REF!
A53: Despesa | C53: Frete sobre Vendas | E53: {=INDEX(#REF!,MATCH($C53,#REF!,0),MATCH(E$1,#REF!,0))} -> #REF! | F53: {=INDEX(#REF!,MATCH($C53,#REF!,0),MATCH(F$1,#REF!,0))} -> #REF! | G53: {=INDEX(#REF!,MATCH($C53,#REF!,0),MATCH(G$1,#REF!,0))} -> #REF! | H53: {=INDEX(#REF!,MATCH($C53,#REF!,0),MATCH(H$1,#REF!,0))} -> #REF! | I53: {=INDEX(#REF!,MATCH($C53,#REF!,0),MATCH(I$1,#REF!,0))} -> #REF! | J53: {=INDEX(#REF!,MATCH($C53,#REF!,0),MATCH(J$1,#REF!,0))} -> #REF! | K53: {=INDEX(#REF!,MATCH($C53,#REF!,0),MATCH(K$1,#REF!,0))} -> #REF! | L53: {=INDEX(#REF!,MATCH($C53,#REF!,0),MATCH(L$1,#REF!,0))} -> #REF! | ... P53: {=INDEX(#REF!,MATCH($C53,#REF!,0),MATCH(P$1,#REF!,0))} -> #REF! | Q53: =IFERROR(INDEX($E53:$P53,1,MATCH($C$2,$E$1:$P$1,0))/INDEX($E$38:$P$38,1,MATCH($C$2,$E$1:$P$1,0)),0) -> 0 | S53: {=INDEX(#REF!,MATCH($C53,#REF!,0),MATCH(S$1,#REF!,0))} -> #REF! | T53: {=INDEX(#REF!,MATCH($C53,#REF!,0),MATCH(T$1,#REF!,0))} -> #REF! | U53: {=INDEX(#REF!,MATCH($C53,#REF!,0),MATCH(U$1,#REF!,0))} -> #REF! | V53: {=INDEX(#REF!,MATCH($C53,#REF!,0),MATCH(V$1,#REF!,0))} -> #REF! | W53: {=INDEX(#REF!,MATCH($C53,#REF!,0),MATCH(W$1,#REF!,0))} -> #REF! | X53: {=INDEX(#REF!,MATCH($C53,#REF!,0),MATCH(X$1,#REF!,0))} -> #REF! | Y53: {=INDEX(#REF!,MATCH($C53,#REF!,0),MATCH(Y$1,#REF!,0))} -> #REF! | Z53: {=INDEX(#REF!,MATCH($C53,#REF!,0),MATCH(Z$1,#REF!,0))} -> #REF! | ... AD53: {=INDEX(#REF!,MATCH($C53,#REF!,0),MATCH(AD$1,#REF!,0))} -> #REF! | AE53: =INDEX($E53:$P53,1,MATCH($C$2,$E$1:$P$1,0))-INDEX(S53:AD53,1,MATCH($C$2,S$1:AD$1,0)) -> #REF! | AF53: =IFERROR(INDEX($E53:$P53,1,MATCH($C$2,$E$1:$P$1,0))/INDEX($S53:$AD53,1,MATCH($C$2,S$1:AD$1,0))-1,0) -> 0 | AH53: {=INDEX(#REF!,MATCH($C53,#REF!,0),MATCH(AH$1,#REF!,0))} -> #REF! | AI53: {=INDEX(#REF!,MATCH($C53,#REF!,0),MATCH(AI$1,#REF!,0))} -> #REF! | AJ53: {=INDEX(#REF!,MATCH($C53,#REF!,0),MATCH(AJ$1,#REF!,0))} -> #REF! | AK53: {=INDEX(#REF!,MATCH($C53,#REF!,0),MATCH(AK$1,#REF!,0))} -> #REF! | AL53: {=INDEX(#REF!,MATCH($C53,#REF!,0),MATCH(AL$1,#REF!,0))} -> #REF! | AM53: {=INDEX(#REF!,MATCH($C53,#REF!,0),MATCH(AM$1,#REF!,0))} -> #REF! | AN53: {=INDEX(#REF!,MATCH($C53,#REF!,0),MATCH(AN$1,#REF!,0))} -> #REF! | AO53: {=INDEX(#REF!,MATCH($C53,#REF!,0),MATCH(AO$1,#REF!,0))} -> #REF! | ... AS53: {=INDEX(#REF!,MATCH($C53,#REF!,0),MATCH(AS$1,#REF!,0))} -> #REF! | AT53: =INDEX($E53:$P53,1,MATCH($C$2,$E$1:$P$1,0))-INDEX(AH53:AS53,1,MATCH(EDATE($C$2,-12),AH$1:AS$1,0)) -> #REF! | AU53: =IFERROR(INDEX($E53:$P53,1,MATCH($C$2,$E$1:$P$1,0))/INDEX(AH53:AS53,1,MATCH(EDATE($C$2,-12),AH$1:AS$1,0))-1,0) -> 0 | AW53: =SUMIF(E$1:P$1,"<="&AW$2,E53:P53) -> #REF! | AX53: =AW53/AW$38 -> #REF! | BA53: =SUMIF(S$1:AD$1,"<="&BA$2,S53:AD53) -> #REF! | BB53: =BA53/BA$38 -> #REF! | BC53: =$AW53-BA53 -> #REF! | BD53: =($AX53-BB53)*100 -> #REF! | BG53: =SUMIF(AH$1:AS$1,"<="&BG$2,AH53:AS53) -> #REF! | BH53: =BG53/BG$38 -> #REF! | BI53: =$AW53-BG53 -> #REF! | BJ53: =($AX53-BH53)*100 -> #REF!
A54: Despesa | C54: Custo de Ocupação | E54: {=INDEX(#REF!,MATCH($C54,#REF!,0),MATCH(E$1,#REF!,0))} -> #REF! | F54: {=INDEX(#REF!,MATCH($C54,#REF!,0),MATCH(F$1,#REF!,0))} -> #REF! | G54: {=INDEX(#REF!,MATCH($C54,#REF!,0),MATCH(G$1,#REF!,0))} -> #REF! | H54: {=INDEX(#REF!,MATCH($C54,#REF!,0),MATCH(H$1,#REF!,0))} -> #REF! | I54: {=INDEX(#REF!,MATCH($C54,#REF!,0),MATCH(I$1,#REF!,0))} -> #REF! | J54: {=INDEX(#REF!,MATCH($C54,#REF!,0),MATCH(J$1,#REF!,0))} -> #REF! | K54: {=INDEX(#REF!,MATCH($C54,#REF!,0),MATCH(K$1,#REF!,0))} -> #REF! | L54: {=INDEX(#REF!,MATCH($C54,#REF!,0),MATCH(L$1,#REF!,0))} -> #REF! | ... P54: {=INDEX(#REF!,MATCH($C54,#REF!,0),MATCH(P$1,#REF!,0))} -> #REF! | Q54: =IFERROR(INDEX($E54:$P54,1,MATCH($C$2,$E$1:$P$1,0))/INDEX($E$38:$P$38,1,MATCH($C$2,$E$1:$P$1,0)),0) -> 0 | S54: {=INDEX(#REF!,MATCH($C54,#REF!,0),MATCH(S$1,#REF!,0))} -> #REF! | T54: {=INDEX(#REF!,MATCH($C54,#REF!,0),MATCH(T$1,#REF!,0))} -> #REF! | U54: {=INDEX(#REF!,MATCH($C54,#REF!,0),MATCH(U$1,#REF!,0))} -> #REF! | V54: {=INDEX(#REF!,MATCH($C54,#REF!,0),MATCH(V$1,#REF!,0))} -> #REF! | W54: {=INDEX(#REF!,MATCH($C54,#REF!,0),MATCH(W$1,#REF!,0))} -> #REF! | X54: {=INDEX(#REF!,MATCH($C54,#REF!,0),MATCH(X$1,#REF!,0))} -> #REF! | Y54: {=INDEX(#REF!,MATCH($C54,#REF!,0),MATCH(Y$1,#REF!,0))} -> #REF! | Z54: {=INDEX(#REF!,MATCH($C54,#REF!,0),MATCH(Z$1,#REF!,0))} -> #REF! | ... AD54: {=INDEX(#REF!,MATCH($C54,#REF!,0),MATCH(AD$1,#REF!,0))} -> #REF! | AE54: =INDEX($E54:$P54,1,MATCH($C$2,$E$1:$P$1,0))-INDEX(S54:AD54,1,MATCH($C$2,S$1:AD$1,0)) -> #REF! | AF54: =IFERROR(INDEX($E54:$P54,1,MATCH($C$2,$E$1:$P$1,0))/INDEX($S54:$AD54,1,MATCH($C$2,S$1:AD$1,0))-1,0) -> 0 | AH54: {=INDEX(#REF!,MATCH($C54,#REF!,0),MATCH(AH$1,#REF!,0))} -> #REF! | AI54: {=INDEX(#REF!,MATCH($C54,#REF!,0),MATCH(AI$1,#REF!,0))} -> #REF! | AJ54: {=INDEX(#REF!,MATCH($C54,#REF!,0),MATCH(AJ$1,#REF!,0))} -> #REF! | AK54: {=INDEX(#REF!,MATCH($C54,#REF!,0),MATCH(AK$1,#REF!,0))} -> #REF! | AL54: {=INDEX(#REF!,MATCH($C54,#REF!,0),MATCH(AL$1,#REF!,0))} -> #REF! | AM54: {=INDEX(#REF!,MATCH($C54,#REF!,0),MATCH(AM$1,#REF!,0))} -> #REF! | AN54: {=INDEX(#REF!,MATCH($C54,#REF!,0),MATCH(AN$1,#REF!,0))} -> #REF! | AO54: {=INDEX(#REF!,MATCH($C54,#REF!,0),MATCH(AO$1,#REF!,0))} -> #REF! | ... AS54: {=INDEX(#REF!,MATCH($C54,#REF!,0),MATCH(AS$1,#REF!,0))} -> #REF! | AT54: =INDEX($E54:$P54,1,MATCH($C$2,$E$1:$P$1,0))-INDEX(AH54:AS54,1,MATCH(EDATE($C$2,-12),AH$1:AS$1,0)) -> #REF! | AU54: =IFERROR(INDEX($E54:$P54,1,MATCH($C$2,$E$1:$P$1,0))/INDEX(AH54:AS54,1,MATCH(EDATE($C$2,-12),AH$1:AS$1,0))-1,0) -> 0 | AW54: =SUMIF(E$1:P$1,"<="&AW$2,E54:P54) -> #REF! | AX54: =AW54/AW$38 -> #REF! | BA54: =SUMIF(S$1:AD$1,"<="&BA$2,S54:AD54) -> #REF! | BB54: =BA54/BA$38 -> #REF! | BC54: =$AW54-BA54 -> #REF! | BD54: =($AX54-BB54)*100 -> #REF! | BG54: =SUMIF(AH$1:AS$1,"<="&BG$2,AH54:AS54) -> #REF! | BH54: =BG54/BG$38 -> #REF! | BI54: =$AW54-BG54 -> #REF! | BJ54: =($AX54-BH54)*100 -> #REF!
A55: Despesa | C55: Outras despesas lojas | E55: {=INDEX(#REF!,MATCH($C55,#REF!,0),MATCH(E$1,#REF!,0))} -> #REF! | F55: {=INDEX(#REF!,MATCH($C55,#REF!,0),MATCH(F$1,#REF!,0))} -> #REF! | G55: {=INDEX(#REF!,MATCH($C55,#REF!,0),MATCH(G$1,#REF!,0))} -> #REF! | H55: {=INDEX(#REF!,MATCH($C55,#REF!,0),MATCH(H$1,#REF!,0))} -> #REF! | I55: {=INDEX(#REF!,MATCH($C55,#REF!,0),MATCH(I$1,#REF!,0))} -> #REF! | J55: {=INDEX(#REF!,MATCH($C55,#REF!,0),MATCH(J$1,#REF!,0))} -> #REF! | K55: {=INDEX(#REF!,MATCH($C55,#REF!,0),MATCH(K$1,#REF!,0))} -> #REF! | L55: {=INDEX(#REF!,MATCH($C55,#REF!,0),MATCH(L$1,#REF!,0))} -> #REF! | ... P55: {=INDEX(#REF!,MATCH($C55,#REF!,0),MATCH(P$1,#REF!,0))} -> #REF! | Q55: =IFERROR(INDEX($E55:$P55,1,MATCH($C$2,$E$1:$P$1,0))/INDEX($E$38:$P$38,1,MATCH($C$2,$E$1:$P$1,0)),0) -> 0 | S55: {=INDEX(#REF!,MATCH($C55,#REF!,0),MATCH(S$1,#REF!,0))} -> #REF! | T55: {=INDEX(#REF!,MATCH($C55,#REF!,0),MATCH(T$1,#REF!,0))} -> #REF! | U55: {=INDEX(#REF!,MATCH($C55,#REF!,0),MATCH(U$1,#REF!,0))} -> #REF! | V55: {=INDEX(#REF!,MATCH($C55,#REF!,0),MATCH(V$1,#REF!,0))} -> #REF! | W55: {=INDEX(#REF!,MATCH($C55,#REF!,0),MATCH(W$1,#REF!,0))} -> #REF! | X55: {=INDEX(#REF!,MATCH($C55,#REF!,0),MATCH(X$1,#REF!,0))} -> #REF! | Y55: {=INDEX(#REF!,MATCH($C55,#REF!,0),MATCH(Y$1,#REF!,0))} -> #REF! | Z55: {=INDEX(#REF!,MATCH($C55,#REF!,0),MATCH(Z$1,#REF!,0))} -> #REF! | ... AD55: {=INDEX(#REF!,MATCH($C55,#REF!,0),MATCH(AD$1,#REF!,0))} -> #REF! | AE55: =INDEX($E55:$P55,1,MATCH($C$2,$E$1:$P$1,0))-INDEX(S55:AD55,1,MATCH($C$2,S$1:AD$1,0)) -> #REF! | AF55: =IFERROR(INDEX($E55:$P55,1,MATCH($C$2,$E$1:$P$1,0))/INDEX($S55:$AD55,1,MATCH($C$2,S$1:AD$1,0))-1,0) -> 0 | AH55: {=INDEX(#REF!,MATCH($C55,#REF!,0),MATCH(AH$1,#REF!,0))} -> #REF! | AI55: {=INDEX(#REF!,MATCH($C55,#REF!,0),MATCH(AI$1,#REF!,0))} -> #REF! | AJ55: {=INDEX(#REF!,MATCH($C55,#REF!,0),MATCH(AJ$1,#REF!,0))} -> #REF! | AK55: {=INDEX(#REF!,MATCH($C55,#REF!,0),MATCH(AK$1,#REF!,0))} -> #REF! | AL55: {=INDEX(#REF!,MATCH($C55,#REF!,0),MATCH(AL$1,#REF!,0))} -> #REF! | AM55: {=INDEX(#REF!,MATCH($C55,#REF!,0),MATCH(AM$1,#REF!,0))} -> #REF! | AN55: {=INDEX(#REF!,MATCH($C55,#REF!,0),MATCH(AN$1,#REF!,0))} -> #REF! | AO55: {=INDEX(#REF!,MATCH($C55,#REF!,0),MATCH(AO$1,#REF!,0))} -> #REF! | ... AS55: {=INDEX(#REF!,MATCH($C55,#REF!,0),MATCH(AS$1,#REF!,0))} -> #REF! | AT55: =INDEX($E55:$P55,1,MATCH($C$2,$E$1:$P$1,0))-INDEX(AH55:AS55,1,MATCH(EDATE($C$2,-12),AH$1:AS$1,0)) -> #REF! | AU55: =IFERROR(INDEX($E55:$P55,1,MATCH($C$2,$E$1:$P$1,0))/INDEX(AH55:AS55,1,MATCH(EDATE($C$2,-12),AH$1:AS$1,0))-1,0) -> 0 | AW55: =SUMIF(E$1:P$1,"<="&AW$2,E55:P55) -> #REF! | AX55: =AW55/AW$38 -> #REF! | BA55: =SUMIF(S$1:AD$1,"<="&BA$2,S55:AD55) -> #REF! | BB55: =BA55/BA$38 -> #REF! | BC55: =$AW55-BA55 -> #REF! | BD55: =($AX55-BB55)*100 -> #REF! | BG55: =SUMIF(AH$1:AS$1,"<="&BG$2,AH55:AS55) -> #REF! | BH55: =BG55/BG$38 -> #REF! | BI55: =$AW55-BG55 -> #REF! | BJ55: =($AX55-BH55)*100 -> #REF!
A56: Despesa | C56: Taxas comerciais | E56: =SUM(E57:E58) -> #REF! | F56: =SUM(F57:F58) -> #REF! | G56: =SUM(G57:G58) -> #REF! | H56: =SUM(H57:H58) -> #REF! | I56: =SUM(I57:I58) -> #REF! | J56: =SUM(J57:J58) -> #REF! | K56: =SUM(K57:K58) -> #REF! | L56: =SUM(L57:L58) -> #REF! | ... P56: =SUM(P57:P58) -> #REF! | Q56: =IFERROR(INDEX($E56:$P56,1,MATCH($C$2,$E$1:$P$1,0))/INDEX($E$38:$P$38,1,MATCH($C$2,$E$1:$P$1,0)),0) -> 0 | S56: =SUM(S57:S58) -> #REF! | T56: =SUM(T57:T58) -> #REF! | U56: =SUM(U57:U58) -> #REF! | V56: =SUM(V57:V58) -> #REF! | W56: =SUM(W57:W58) -> #REF! | X56: =SUM(X57:X58) -> #REF! | Y56: =SUM(Y57:Y58) -> #REF! | Z56: =SUM(Z57:Z58) -> #REF! | ... AD56: =SUM(AD57:AD58) -> #REF! | AE56: =INDEX($E56:$P56,1,MATCH($C$2,$E$1:$P$1,0))-INDEX(S56:AD56,1,MATCH($C$2,S$1:AD$1,0)) -> #REF! | AF56: =IFERROR(INDEX($E56:$P56,1,MATCH($C$2,$E$1:$P$1,0))/INDEX($S56:$AD56,1,MATCH($C$2,S$1:AD$1,0))-1,0) -> 0 | AH56: =SUM(AH57:AH58) -> #REF! | AI56: =SUM(AI57:AI58) -> #REF! | AJ56: =SUM(AJ57:AJ58) -> #REF! | AK56: =SUM(AK57:AK58) -> #REF! | AL56: =SUM(AL57:AL58) -> #REF! | AM56: =SUM(AM57:AM58) -> #REF! | AN56: =SUM(AN57:AN58) -> #REF! | AO56: =SUM(AO57:AO58) -> #REF! | ... AS56: =SUM(AS57:AS58) -> #REF! | AT56: =INDEX($E56:$P56,1,MATCH($C$2,$E$1:$P$1,0))-INDEX(AH56:AS56,1,MATCH(EDATE($C$2,-12),AH$1:AS$1,0)) -> #REF! | AU56: =IFERROR(INDEX($E56:$P56,1,MATCH($C$2,$E$1:$P$1,0))/INDEX(AH56:AS56,1,MATCH(EDATE($C$2,-12),AH$1:AS$1,0))-1,0) -> 0 | AW56: =SUM(AW57:AW58) -> #REF! | AX56: =AW56/AW$38 -> #REF! | BA56: =SUM(BA57:BA58) -> #REF! | BB56: =BA56/BA$38 -> #REF! | BC56: =$AW56-BA56 -> #REF! | BD56: =($AX56-BB56)*100 -> #REF! | BG56: =SUM(BG57:BG58) -> #REF! | BH56: =BG56/BG$38 -> #REF! | BI56: =$AW56-BG56 -> #REF! | BJ56: =($AX56-BH56)*100 -> #REF!
A57: Despesa | C57: Taxa adquirência | E57: {=INDEX(#REF!,MATCH($C57,#REF!,0),MATCH(E$1,#REF!,0))} -> #REF! | F57: {=INDEX(#REF!,MATCH($C57,#REF!,0),MATCH(F$1,#REF!,0))} -> #REF! | G57: {=INDEX(#REF!,MATCH($C57,#REF!,0),MATCH(G$1,#REF!,0))} -> #REF! | H57: {=INDEX(#REF!,MATCH($C57,#REF!,0),MATCH(H$1,#REF!,0))} -> #REF! | I57: {=INDEX(#REF!,MATCH($C57,#REF!,0),MATCH(I$1,#REF!,0))} -> #REF! | J57: {=INDEX(#REF!,MATCH($C57,#REF!,0),MATCH(J$1,#REF!,0))} -> #REF! | K57: {=INDEX(#REF!,MATCH($C57,#REF!,0),MATCH(K$1,#REF!,0))} -> #REF! | L57: {=INDEX(#REF!,MATCH($C57,#REF!,0),MATCH(L$1,#REF!,0))} -> #REF! | ... P57: {=INDEX(#REF!,MATCH($C57,#REF!,0),MATCH(P$1,#REF!,0))} -> #REF! | Q57: =IFERROR(INDEX($E57:$P57,1,MATCH($C$2,$E$1:$P$1,0))/INDEX($E$38:$P$38,1,MATCH($C$2,$E$1:$P$1,0)),0) -> 0 | S57: {=INDEX(#REF!,MATCH($C57,#REF!,0),MATCH(S$1,#REF!,0))} -> #REF! | T57: {=INDEX(#REF!,MATCH($C57,#REF!,0),MATCH(T$1,#REF!,0))} -> #REF! | U57: {=INDEX(#REF!,MATCH($C57,#REF!,0),MATCH(U$1,#REF!,0))} -> #REF! | V57: {=INDEX(#REF!,MATCH($C57,#REF!,0),MATCH(V$1,#REF!,0))} -> #REF! | W57: {=INDEX(#REF!,MATCH($C57,#REF!,0),MATCH(W$1,#REF!,0))} -> #REF! | X57: {=INDEX(#REF!,MATCH($C57,#REF!,0),MATCH(X$1,#REF!,0))} -> #REF! | Y57: {=INDEX(#REF!,MATCH($C57,#REF!,0),MATCH(Y$1,#REF!,0))} -> #REF! | Z57: {=INDEX(#REF!,MATCH($C57,#REF!,0),MATCH(Z$1,#REF!,0))} -> #REF! | ... AD57: {=INDEX(#REF!,MATCH($C57,#REF!,0),MATCH(AD$1,#REF!,0))} -> #REF! | AE57: =INDEX($E57:$P57,1,MATCH($C$2,$E$1:$P$1,0))-INDEX(S57:AD57,1,MATCH($C$2,S$1:AD$1,0)) -> #REF! | AF57: =IFERROR(INDEX($E57:$P57,1,MATCH($C$2,$E$1:$P$1,0))/INDEX($S57:$AD57,1,MATCH($C$2,S$1:AD$1,0))-1,0) -> 0 | AH57: {=INDEX(#REF!,MATCH($C57,#REF!,0),MATCH(AH$1,#REF!,0))} -> #REF! | AI57: {=INDEX(#REF!,MATCH($C57,#REF!,0),MATCH(AI$1,#REF!,0))} -> #REF! | AJ57: {=INDEX(#REF!,MATCH($C57,#REF!,0),MATCH(AJ$1,#REF!,0))} -> #REF! | AK57: {=INDEX(#REF!,MATCH($C57,#REF!,0),MATCH(AK$1,#REF!,0))} -> #REF! | AL57: {=INDEX(#REF!,MATCH($C57,#REF!,0),MATCH(AL$1,#REF!,0))} -> #REF! | AM57: {=INDEX(#REF!,MATCH($C57,#REF!,0),MATCH(AM$1,#REF!,0))} -> #REF! | AN57: {=INDEX(#REF!,MATCH($C57,#REF!,0),MATCH(AN$1,#REF!,0))} -> #REF! | AO57: {=INDEX(#REF!,MATCH($C57,#REF!,0),MATCH(AO$1,#REF!,0))} -> #REF! | ... AS57: {=INDEX(#REF!,MATCH($C57,#REF!,0),MATCH(AS$1,#REF!,0))} -> #REF! | AT57: =INDEX($E57:$P57,1,MATCH($C$2,$E$1:$P$1,0))-INDEX(AH57:AS57,1,MATCH(EDATE($C$2,-12),AH$1:AS$1,0)) -> #REF! | AU57: =IFERROR(INDEX($E57:$P57,1,MATCH($C$2,$E$1:$P$1,0))/INDEX(AH57:AS57,1,MATCH(EDATE($C$2,-12),AH$1:AS$1,0))-1,0) -> 0 | AW57: =SUMIF(E$1:P$1,"<="&AW$2,E57:P57) -> #REF! | AX57: =AW57/AW$38 -> #REF! | BA57: =SUMIF(S$1:AD$1,"<="&BA$2,S57:AD57) -> #REF! | BB57: =BA57/BA$38 -> #REF! | BC57: =$AW57-BA57 -> #REF! | BD57: =($AX57-BB57)*100 -> #REF! | BG57: =SUMIF(AH$1:AS$1,"<="&BG$2,AH57:AS57) -> #REF! | BH57: =BG57/BG$38 -> #REF! | BI57: =$AW57-BG57 -> #REF! | BJ57: =($AX57-BH57)*100 -> #REF!
A58: Despesa | C58: Fee plataformas | E58: {=INDEX(#REF!,MATCH($C58,#REF!,0),MATCH(E$1,#REF!,0))} -> #REF! | F58: {=INDEX(#REF!,MATCH($C58,#REF!,0),MATCH(F$1,#REF!,0))} -> #REF! | G58: {=INDEX(#REF!,MATCH($C58,#REF!,0),MATCH(G$1,#REF!,0))} -> #REF! | H58: {=INDEX(#REF!,MATCH($C58,#REF!,0),MATCH(H$1,#REF!,0))} -> #REF! | I58: {=INDEX(#REF!,MATCH($C58,#REF!,0),MATCH(I$1,#REF!,0))} -> #REF! | J58: {=INDEX(#REF!,MATCH($C58,#REF!,0),MATCH(J$1,#REF!,0))} -> #REF! | K58: {=INDEX(#REF!,MATCH($C58,#REF!,0),MATCH(K$1,#REF!,0))} -> #REF! | L58: {=INDEX(#REF!,MATCH($C58,#REF!,0),MATCH(L$1,#REF!,0))} -> #REF! | ... P58: {=INDEX(#REF!,MATCH($C58,#REF!,0),MATCH(P$1,#REF!,0))} -> #REF! | Q58: =IFERROR(INDEX($E58:$P58,1,MATCH($C$2,$E$1:$P$1,0))/INDEX($E$38:$P$38,1,MATCH($C$2,$E$1:$P$1,0)),0) -> 0 | S58: {=INDEX(#REF!,MATCH($C58,#REF!,0),MATCH(S$1,#REF!,0))} -> #REF! | T58: {=INDEX(#REF!,MATCH($C58,#REF!,0),MATCH(T$1,#REF!,0))} -> #REF! | U58: {=INDEX(#REF!,MATCH($C58,#REF!,0),MATCH(U$1,#REF!,0))} -> #REF! | V58: {=INDEX(#REF!,MATCH($C58,#REF!,0),MATCH(V$1,#REF!,0))} -> #REF! | W58: {=INDEX(#REF!,MATCH($C58,#REF!,0),MATCH(W$1,#REF!,0))} -> #REF! | X58: {=INDEX(#REF!,MATCH($C58,#REF!,0),MATCH(X$1,#REF!,0))} -> #REF! | Y58: {=INDEX(#REF!,MATCH($C58,#REF!,0),MATCH(Y$1,#REF!,0))} -> #REF! | Z58: {=INDEX(#REF!,MATCH($C58,#REF!,0),MATCH(Z$1,#REF!,0))} -> #REF! | ... AD58: {=INDEX(#REF!,MATCH($C58,#REF!,0),MATCH(AD$1,#REF!,0))} -> #REF! | AE58: =INDEX($E58:$P58,1,MATCH($C$2,$E$1:$P$1,0))-INDEX(S58:AD58,1,MATCH($C$2,S$1:AD$1,0)) -> #REF! | AF58: =IFERROR(INDEX($E58:$P58,1,MATCH($C$2,$E$1:$P$1,0))/INDEX($S58:$AD58,1,MATCH($C$2,S$1:AD$1,0))-1,0) -> 0 | AH58: {=INDEX(#REF!,MATCH($C58,#REF!,0),MATCH(AH$1,#REF!,0))} -> #REF! | AI58: {=INDEX(#REF!,MATCH($C58,#REF!,0),MATCH(AI$1,#REF!,0))} -> #REF! | AJ58: {=INDEX(#REF!,MATCH($C58,#REF!,0),MATCH(AJ$1,#REF!,0))} -> #REF! | AK58: {=INDEX(#REF!,MATCH($C58,#REF!,0),MATCH(AK$1,#REF!,0))} -> #REF! | AL58: {=INDEX(#REF!,MATCH($C58,#REF!,0),MATCH(AL$1,#REF!,0))} -> #REF! | AM58: {=INDEX(#REF!,MATCH($C58,#REF!,0),MATCH(AM$1,#REF!,0))} -> #REF! | AN58: {=INDEX(#REF!,MATCH($C58,#REF!,0),MATCH(AN$1,#REF!,0))} -> #REF! | AO58: {=INDEX(#REF!,MATCH($C58,#REF!,0),MATCH(AO$1,#REF!,0))} -> #REF! | ... AS58: {=INDEX(#REF!,MATCH($C58,#REF!,0),MATCH(AS$1,#REF!,0))} -> #REF! | AT58: =INDEX($E58:$P58,1,MATCH($C$2,$E$1:$P$1,0))-INDEX(AH58:AS58,1,MATCH(EDATE($C$2,-12),AH$1:AS$1,0)) -> #REF! | AU58: =IFERROR(INDEX($E58:$P58,1,MATCH($C$2,$E$1:$P$1,0))/INDEX(AH58:AS58,1,MATCH(EDATE($C$2,-12),AH$1:AS$1,0))-1,0) -> 0 | AW58: =SUMIF(E$1:P$1,"<="&AW$2,E58:P58) -> #REF! | AX58: =AW58/AW$38 -> #REF! | BA58: =SUMIF(S$1:AD$1,"<="&BA$2,S58:AD58) -> #REF! | BB58: =BA58/BA$38 -> #REF! | BC58: =$AW58-BA58 -> #REF! | BD58: =($AX58-BB58)*100 -> #REF! | BG58: =SUMIF(AH$1:AS$1,"<="&BG$2,AH58:AS58) -> #REF! | BH58: =BG58/BG$38 -> #REF! | BI58: =$AW58-BG58 -> #REF! | BJ58: =($AX58-BH58)*100 -> #REF!
A59: Despesa | C59: Despesas de marketing | E59: =E60+E64+E68+E73+E78 -> #REF! | F59: =F60+F64+F68+F73+F78 -> #REF! | G59: =G60+G64+G68+G73+G78 -> #REF! | H59: =H60+H64+H68+H73+H78 -> #REF! | I59: =I60+I64+I68+I73+I78 -> #REF! | J59: =J60+J64+J68+J73+J78 -> #REF! | K59: =K60+K64+K68+K73+K78 -> #REF! | L59: =L60+L64+L68+L73+L78 -> #REF! | ... P59: =P60+P64+P68+P73+P78 -> #REF! | Q59: =IFERROR(INDEX($E59:$P59,1,MATCH($C$2,$E$1:$P$1,0))/INDEX($E$38:$P$38,1,MATCH($C$2,$E$1:$P$1,0)),0) -> 0 | S59: =S60+S64+S68+S73+S78 -> #REF! | T59: =T60+T64+T68+T73+T78 -> #REF! | U59: =U60+U64+U68+U73+U78 -> #REF! | V59: =V60+V64+V68+V73+V78 -> #REF! | W59: =W60+W64+W68+W73+W78 -> #REF! | X59: =X60+X64+X68+X73+X78 -> #REF! | Y59: =Y60+Y64+Y68+Y73+Y78 -> #REF! | Z59: =Z60+Z64+Z68+Z73+Z78 -> #REF! | ... AD59: =AD60+AD64+AD68+AD73+AD78 -> #REF! | AE59: =INDEX($E59:$P59,1,MATCH($C$2,$E$1:$P$1,0))-INDEX(S59:AD59,1,MATCH($C$2,S$1:AD$1,0)) -> #REF! | AF59: {=IFERROR(1*--(INDEX($S59:$AD59,1,MATCH($C$2,S$1:AD$1,0))<0)+INDEX($E59:$P59,1,MATCH($C$2,$E$1:$P$1,0))/INDEX($S59:$AD59,1,MATCH($C$2,S$1:AD$1,0))-1*--(INDEX($S59:$AD59,1,MATCH($C$2,S$1:AD$1,0))>=0),0)} -> 0 | AH59: =AH60+AH64+AH68+AH73+AH78 -> #REF! | AI59: =AI60+AI64+AI68+AI73+AI78 -> #REF! | AJ59: =AJ60+AJ64+AJ68+AJ73+AJ78 -> #REF! | AK59: =AK60+AK64+AK68+AK73+AK78 -> #REF! | AL59: =AL60+AL64+AL68+AL73+AL78 -> #REF! | AM59: =AM60+AM64+AM68+AM73+AM78 -> #REF! | AN59: =AN60+AN64+AN68+AN73+AN78 -> #REF! | AO59: =AO60+AO64+AO68+AO73+AO78 -> #REF! | ... AS59: =AS60+AS64+AS68+AS73+AS78 -> #REF! | AT59: =INDEX($E59:$P59,1,MATCH($C$2,$E$1:$P$1,0))-INDEX(AH59:AS59,1,MATCH(EDATE($C$2,-12),AH$1:AS$1,0)) -> #REF! | AU59: =IFERROR(INDEX($E59:$P59,1,MATCH($C$2,$E$1:$P$1,0))/INDEX(AH59:AS59,1,MATCH(EDATE($C$2,-12),AH$1:AS$1,0))-1,0) -> 0 | AW59: =AW60+AW64+AW68+AW73+AW78 -> #REF! | AX59: =AW59/AW$38 -> #REF! | BA59: =BA60+BA64+BA68+BA73+BA78 -> #REF! | BB59: =BA59/BA$38 -> #REF! | BC59: =$AW59-BA59 -> #REF! | BD59: =($AX59-BB59)*100 -> #REF! | BG59: =BG60+BG64+BG68+BG73+BG78 -> #REF! | BH59: =BG59/BG$38 -> #REF! | BI59: =$AW59-BG59 -> #REF! | BJ59: =($AX59-BH59)*100 -> #REF!
A60: Despesa | C60: Mídia online | E60: =SUM(E61:E63) -> #REF! | F60: =SUM(F61:F63) -> #REF! | G60: =SUM(G61:G63) -> #REF! | H60: =SUM(H61:H63) -> #REF! | I60: =SUM(I61:I63) -> #REF! | J60: =SUM(J61:J63) -> #REF! | K60: =SUM(K61:K63) -> #REF! | L60: =SUM(L61:L63) -> #REF! | ... P60: =SUM(P61:P63) -> #REF! | Q60: =IFERROR(INDEX($E60:$P60,1,MATCH($C$2,$E$1:$P$1,0))/INDEX($E$38:$P$38,1,MATCH($C$2,$E$1:$P$1,0)),0) -> 0 | S60: =SUM(S61:S63) -> #REF! | T60: =SUM(T61:T63) -> #REF! | U60: =SUM(U61:U63) -> #REF! | V60: =SUM(V61:V63) -> #REF! | W60: =SUM(W61:W63) -> #REF! | X60: =SUM(X61:X63) -> #REF! | Y60: =SUM(Y61:Y63) -> #REF! | Z60: =SUM(Z61:Z63) -> #REF! | ... AD60: =SUM(AD61:AD63) -> #REF! | AE60: =INDEX($E60:$P60,1,MATCH($C$2,$E$1:$P$1,0))-INDEX(S60:AD60,1,MATCH($C$2,S$1:AD$1,0)) -> #REF! | AF60: =IFERROR(INDEX($E60:$P60,1,MATCH($C$2,$E$1:$P$1,0))/INDEX($S60:$AD60,1,MATCH($C$2,S$1:AD$1,0))-1,0) -> 0 | AH60: =SUM(AH61:AH63) -> #REF! | AI60: =SUM(AI61:AI63) -> #REF! | AJ60: =SUM(AJ61:AJ63) -> #REF! | AK60: =SUM(AK61:AK63) -> #REF! | AL60: =SUM(AL61:AL63) -> #REF! | AM60: =SUM(AM61:AM63) -> #REF! | AN60: =SUM(AN61:AN63) -> #REF! | AO60: =SUM(AO61:AO63) -> #REF! | ... AS60: =SUM(AS61:AS63) -> #REF! | AT60: =INDEX($E60:$P60,1,MATCH($C$2,$E$1:$P$1,0))-INDEX(AH60:AS60,1,MATCH(EDATE($C$2,-12),AH$1:AS$1,0)) -> #REF! | AU60: =IFERROR(INDEX($E60:$P60,1,MATCH($C$2,$E$1:$P$1,0))/INDEX(AH60:AS60,1,MATCH(EDATE($C$2,-12),AH$1:AS$1,0))-1,0) -> 0 | AW60: =SUM(AW61:AW63) -> #REF! | AX60: =AW60/AW$38 -> #REF! | BA60: =SUM(BA61:BA63) -> #REF! | BB60: =BA60/BA$38 -> #REF! | BC60: =$AW60-BA60 -> #REF! | BD60: =($AX60-BB60)*100 -> #REF! | BG60: =SUM(BG61:BG63) -> #REF! | BH60: =BG60/BG$38 -> #REF! | BI60: =$AW60-BG60 -> #REF! | BJ60: =($AX60-BH60)*100 -> #REF!
A61: Despesa | C61: Facebook | E61: {=INDEX(#REF!,MATCH($C61,#REF!,0),MATCH(E$1,#REF!,0))} -> #REF! | F61: {=INDEX(#REF!,MATCH($C61,#REF!,0),MATCH(F$1,#REF!,0))} -> #REF! | G61: {=INDEX(#REF!,MATCH($C61,#REF!,0),MATCH(G$1,#REF!,0))} -> #REF! | H61: {=INDEX(#REF!,MATCH($C61,#REF!,0),MATCH(H$1,#REF!,0))} -> #REF! | I61: {=INDEX(#REF!,MATCH($C61,#REF!,0),MATCH(I$1,#REF!,0))} -> #REF! | J61: {=INDEX(#REF!,MATCH($C61,#REF!,0),MATCH(J$1,#REF!,0))} -> #REF! | K61: {=INDEX(#REF!,MATCH($C61,#REF!,0),MATCH(K$1,#REF!,0))} -> #REF! | L61: {=INDEX(#REF!,MATCH($C61,#REF!,0),MATCH(L$1,#REF!,0))} -> #REF! | ... P61: {=INDEX(#REF!,MATCH($C61,#REF!,0),MATCH(P$1,#REF!,0))} -> #REF! | Q61: =IFERROR(INDEX($E61:$P61,1,MATCH($C$2,$E$1:$P$1,0))/INDEX($E$38:$P$38,1,MATCH($C$2,$E$1:$P$1,0)),0) -> 0 | S61: {=INDEX(#REF!,MATCH($C61,#REF!,0),MATCH(S$1,#REF!,0))} -> #REF! | T61: {=INDEX(#REF!,MATCH($C61,#REF!,0),MATCH(T$1,#REF!,0))} -> #REF! | U61: {=INDEX(#REF!,MATCH($C61,#REF!,0),MATCH(U$1,#REF!,0))} -> #REF! | V61: {=INDEX(#REF!,MATCH($C61,#REF!,0),MATCH(V$1,#REF!,0))} -> #REF! | W61: {=INDEX(#REF!,MATCH($C61,#REF!,0),MATCH(W$1,#REF!,0))} -> #REF! | X61: {=INDEX(#REF!,MATCH($C61,#REF!,0),MATCH(X$1,#REF!,0))} -> #REF! | Y61: {=INDEX(#REF!,MATCH($C61,#REF!,0),MATCH(Y$1,#REF!,0))} -> #REF! | Z61: {=INDEX(#REF!,MATCH($C61,#REF!,0),MATCH(Z$1,#REF!,0))} -> #REF! | ... AD61: {=INDEX(#REF!,MATCH($C61,#REF!,0),MATCH(AD$1,#REF!,0))} -> #REF! | AE61: =INDEX($E61:$P61,1,MATCH($C$2,$E$1:$P$1,0))-INDEX(S61:AD61,1,MATCH($C$2,S$1:AD$1,0)) -> #REF! | AF61: =IFERROR(INDEX($E61:$P61,1,MATCH($C$2,$E$1:$P$1,0))/INDEX($S61:$AD61,1,MATCH($C$2,S$1:AD$1,0))-1,0) -> 0 | AH61: {=INDEX(#REF!,MATCH($C61,#REF!,0),MATCH(AH$1,#REF!,0))} -> #REF! | AI61: {=INDEX(#REF!,MATCH($C61,#REF!,0),MATCH(AI$1,#REF!,0))} -> #REF! | AJ61: {=INDEX(#REF!,MATCH($C61,#REF!,0),MATCH(AJ$1,#REF!,0))} -> #REF! | AK61: {=INDEX(#REF!,MATCH($C61,#REF!,0),MATCH(AK$1,#REF!,0))} -> #REF! | AL61: {=INDEX(#REF!,MATCH($C61,#REF!,0),MATCH(AL$1,#REF!,0))} -> #REF! | AM61: {=INDEX(#REF!,MATCH($C61,#REF!,0),MATCH(AM$1,#REF!,0))} -> #REF! | AN61: {=INDEX(#REF!,MATCH($C61,#REF!,0),MATCH(AN$1,#REF!,0))} -> #REF! | AO61: {=INDEX(#REF!,MATCH($C61,#REF!,0),MATCH(AO$1,#REF!,0))} -> #REF! | ... AS61: {=INDEX(#REF!,MATCH($C61,#REF!,0),MATCH(AS$1,#REF!,0))} -> #REF! | AT61: =INDEX($E61:$P61,1,MATCH($C$2,$E$1:$P$1,0))-INDEX(AH61:AS61,1,MATCH(EDATE($C$2,-12),AH$1:AS$1,0)) -> #REF! | AU61: =IFERROR(INDEX($E61:$P61,1,MATCH($C$2,$E$1:$P$1,0))/INDEX(AH61:AS61,1,MATCH(EDATE($C$2,-12),AH$1:AS$1,0))-1,0) -> 0 | AW61: =SUMIF(E$1:P$1,"<="&AW$2,E61:P61) -> #REF! | AX61: =AW61/AW$38 -> #REF! | BA61: =SUMIF(S$1:AD$1,"<="&BA$2,S61:AD61) -> #REF! | BB61: =BA61/BA$38 -> #REF! | BC61: =$AW61-BA61 -> #REF! | BD61: =($AX61-BB61)*100 -> #REF! | BG61: =SUMIF(AH$1:AS$1,"<="&BG$2,AH61:AS61) -> #REF! | BH61: =BG61/BG$38 -> #REF! | BI61: =$AW61-BG61 -> #REF! | BJ61: =($AX61-BH61)*100 -> #REF!
A62: Despesa | C62: Google | E62: {=INDEX(#REF!,MATCH($C62,#REF!,0),MATCH(E$1,#REF!,0))} -> #REF! | F62: {=INDEX(#REF!,MATCH($C62,#REF!,0),MATCH(F$1,#REF!,0))} -> #REF! | G62: {=INDEX(#REF!,MATCH($C62,#REF!,0),MATCH(G$1,#REF!,0))} -> #REF! | H62: {=INDEX(#REF!,MATCH($C62,#REF!,0),MATCH(H$1,#REF!,0))} -> #REF! | I62: {=INDEX(#REF!,MATCH($C62,#REF!,0),MATCH(I$1,#REF!,0))} -> #REF! | J62: {=INDEX(#REF!,MATCH($C62,#REF!,0),MATCH(J$1,#REF!,0))} -> #REF! | K62: {=INDEX(#REF!,MATCH($C62,#REF!,0),MATCH(K$1,#REF!,0))} -> #REF! | L62: {=INDEX(#REF!,MATCH($C62,#REF!,0),MATCH(L$1,#REF!,0))} -> #REF! | ... P62: {=INDEX(#REF!,MATCH($C62,#REF!,0),MATCH(P$1,#REF!,0))} -> #REF! | Q62: =IFERROR(INDEX($E62:$P62,1,MATCH($C$2,$E$1:$P$1,0))/INDEX($E$38:$P$38,1,MATCH($C$2,$E$1:$P$1,0)),0) -> 0 | S62: {=INDEX(#REF!,MATCH($C62,#REF!,0),MATCH(S$1,#REF!,0))} -> #REF! | T62: {=INDEX(#REF!,MATCH($C62,#REF!,0),MATCH(T$1,#REF!,0))} -> #REF! | U62: {=INDEX(#REF!,MATCH($C62,#REF!,0),MATCH(U$1,#REF!,0))} -> #REF! | V62: {=INDEX(#REF!,MATCH($C62,#REF!,0),MATCH(V$1,#REF!,0))} -> #REF! | W62: {=INDEX(#REF!,MATCH($C62,#REF!,0),MATCH(W$1,#REF!,0))} -> #REF! | X62: {=INDEX(#REF!,MATCH($C62,#REF!,0),MATCH(X$1,#REF!,0))} -> #REF! | Y62: {=INDEX(#REF!,MATCH($C62,#REF!,0),MATCH(Y$1,#REF!,0))} -> #REF! | Z62: {=INDEX(#REF!,MATCH($C62,#REF!,0),MATCH(Z$1,#REF!,0))} -> #REF! | ... AD62: {=INDEX(#REF!,MATCH($C62,#REF!,0),MATCH(AD$1,#REF!,0))} -> #REF! | AE62: =INDEX($E62:$P62,1,MATCH($C$2,$E$1:$P$1,0))-INDEX(S62:AD62,1,MATCH($C$2,S$1:AD$1,0)) -> #REF! | AF62: =IFERROR(INDEX($E62:$P62,1,MATCH($C$2,$E$1:$P$1,0))/INDEX($S62:$AD62,1,MATCH($C$2,S$1:AD$1,0))-1,0) -> 0 | AH62: {=INDEX(#REF!,MATCH($C62,#REF!,0),MATCH(AH$1,#REF!,0))} -> #REF! | AI62: {=INDEX(#REF!,MATCH($C62,#REF!,0),MATCH(AI$1,#REF!,0))} -> #REF! | AJ62: {=INDEX(#REF!,MATCH($C62,#REF!,0),MATCH(AJ$1,#REF!,0))} -> #REF! | AK62: {=INDEX(#REF!,MATCH($C62,#REF!,0),MATCH(AK$1,#REF!,0))} -> #REF! | AL62: {=INDEX(#REF!,MATCH($C62,#REF!,0),MATCH(AL$1,#REF!,0))} -> #REF! | AM62: {=INDEX(#REF!,MATCH($C62,#REF!,0),MATCH(AM$1,#REF!,0))} -> #REF! | AN62: {=INDEX(#REF!,MATCH($C62,#REF!,0),MATCH(AN$1,#REF!,0))} -> #REF! | AO62: {=INDEX(#REF!,MATCH($C62,#REF!,0),MATCH(AO$1,#REF!,0))} -> #REF! | ... AS62: {=INDEX(#REF!,MATCH($C62,#REF!,0),MATCH(AS$1,#REF!,0))} -> #REF! | AT62: =INDEX($E62:$P62,1,MATCH($C$2,$E$1:$P$1,0))-INDEX(AH62:AS62,1,MATCH(EDATE($C$2,-12),AH$1:AS$1,0)) -> #REF! | AU62: =IFERROR(INDEX($E62:$P62,1,MATCH($C$2,$E$1:$P$1,0))/INDEX(AH62:AS62,1,MATCH(EDATE($C$2,-12),AH$1:AS$1,0))-1,0) -> 0 | AW62: =SUMIF(E$1:P$1,"<="&AW$2,E62:P62) -> #REF! | AX62: =AW62/AW$38 -> #REF! | BA62: =SUMIF(S$1:AD$1,"<="&BA$2,S62:AD62) -> #REF! | BB62: =BA62/BA$38 -> #REF! | BC62: =$AW62-BA62 -> #REF! | BD62: =($AX62-BB62)*100 -> #REF! | BG62: =SUMIF(AH$1:AS$1,"<="&BG$2,AH62:AS62) -> #REF! | BH62: =BG62/BG$38 -> #REF! | BI62: =$AW62-BG62 -> #REF! | BJ62: =($AX62-BH62)*100 -> #REF!
A63: Despesa | C63: Pinterest | E63: {=INDEX(#REF!,MATCH($C63,#REF!,0),MATCH(E$1,#REF!,0))} -> #REF! | F63: {=INDEX(#REF!,MATCH($C63,#REF!,0),MATCH(F$1,#REF!,0))} -> #REF! | G63: {=INDEX(#REF!,MATCH($C63,#REF!,0),MATCH(G$1,#REF!,0))} -> #REF! | H63: {=INDEX(#REF!,MATCH($C63,#REF!,0),MATCH(H$1,#REF!,0))} -> #REF! | I63: {=INDEX(#REF!,MATCH($C63,#REF!,0),MATCH(I$1,#REF!,0))} -> #REF! | J63: {=INDEX(#REF!,MATCH($C63,#REF!,0),MATCH(J$1,#REF!,0))} -> #REF! | K63: {=INDEX(#REF!,MATCH($C63,#REF!,0),MATCH(K$1,#REF!,0))} -> #REF! | L63: {=INDEX(#REF!,MATCH($C63,#REF!,0),MATCH(L$1,#REF!,0))} -> #REF! | ... P63: {=INDEX(#REF!,MATCH($C63,#REF!,0),MATCH(P$1,#REF!,0))} -> #REF! | Q63: =IFERROR(INDEX($E63:$P63,1,MATCH($C$2,$E$1:$P$1,0))/INDEX($E$38:$P$38,1,MATCH($C$2,$E$1:$P$1,0)),0) -> 0 | S63: {=INDEX(#REF!,MATCH($C63,#REF!,0),MATCH(S$1,#REF!,0))} -> #REF! | T63: {=INDEX(#REF!,MATCH($C63,#REF!,0),MATCH(T$1,#REF!,0))} -> #REF! | U63: {=INDEX(#REF!,MATCH($C63,#REF!,0),MATCH(U$1,#REF!,0))} -> #REF! | V63: {=INDEX(#REF!,MATCH($C63,#REF!,0),MATCH(V$1,#REF!,0))} -> #REF! | W63: {=INDEX(#REF!,MATCH($C63,#REF!,0),MATCH(W$1,#REF!,0))} -> #REF! | X63: {=INDEX(#REF!,MATCH($C63,#REF!,0),MATCH(X$1,#REF!,0))} -> #REF! | Y63: {=INDEX(#REF!,MATCH($C63,#REF!,0),MATCH(Y$1,#REF!,0))} -> #REF! | Z63: {=INDEX(#REF!,MATCH($C63,#REF!,0),MATCH(Z$1,#REF!,0))} -> #REF! | ... AD63: {=INDEX(#REF!,MATCH($C63,#REF!,0),MATCH(AD$1,#REF!,0))} -> #REF! | AE63: =INDEX($E63:$P63,1,MATCH($C$2,$E$1:$P$1,0))-INDEX(S63:AD63,1,MATCH($C$2,S$1:AD$1,0)) -> #REF! | AF63: =IFERROR(INDEX($E63:$P63,1,MATCH($C$2,$E$1:$P$1,0))/INDEX($S63:$AD63,1,MATCH($C$2,S$1:AD$1,0))-1,0) -> 0 | AH63: {=INDEX(#REF!,MATCH($C63,#REF!,0),MATCH(AH$1,#REF!,0))} -> #REF! | AI63: {=INDEX(#REF!,MATCH($C63,#REF!,0),MATCH(AI$1,#REF!,0))} -> #REF! | AJ63: {=INDEX(#REF!,MATCH($C63,#REF!,0),MATCH(AJ$1,#REF!,0))} -> #REF! | AK63: {=INDEX(#REF!,MATCH($C63,#REF!,0),MATCH(AK$1,#REF!,0))} -> #REF! | AL63: {=INDEX(#REF!,MATCH($C63,#REF!,0),MATCH(AL$1,#REF!,0))} -> #REF! | AM63: {=INDEX(#REF!,MATCH($C63,#REF!,0),MATCH(AM$1,#REF!,0))} -> #REF! | AN63: {=INDEX(#REF!,MATCH($C63,#REF!,0),MATCH(AN$1,#REF!,0))} -> #REF! | AO63: {=INDEX(#REF!,MATCH($C63,#REF!,0),MATCH(AO$1,#REF!,0))} -> #REF! | ... AS63: {=INDEX(#REF!,MATCH($C63,#REF!,0),MATCH(AS$1,#REF!,0))} -> #REF! | AT63: =INDEX($E63:$P63,1,MATCH($C$2,$E$1:$P$1,0))-INDEX(AH63:AS63,1,MATCH(EDATE($C$2,-12),AH$1:AS$1,0)) -> #REF! | AU63: =IFERROR(INDEX($E63:$P63,1,MATCH($C$2,$E$1:$P$1,0))/INDEX(AH63:AS63,1,MATCH(EDATE($C$2,-12),AH$1:AS$1,0))-1,0) -> 0 | AW63: =SUMIF(E$1:P$1,"<="&AW$2,E63:P63) -> #REF! | AX63: =AW63/AW$38 -> #REF! | BA63: =SUMIF(S$1:AD$1,"<="&BA$2,S63:AD63) -> #REF! | BB63: =BA63/BA$38 -> #REF! | BC63: =$AW63-BA63 -> #REF! | BD63: =($AX63-BB63)*100 -> #REF! | BG63: =SUMIF(AH$1:AS$1,"<="&BG$2,AH63:AS63) -> #REF! | BH63: =BG63/BG$38 -> #REF! | BI63: =$AW63-BG63 -> #REF! | BJ63: =($AX63-BH63)*100 -> #REF!
A64: Despesa | C64: Seeding | E64: =SUM(E65:E67) -> #REF! | F64: =SUM(F65:F67) -> #REF! | G64: =SUM(G65:G67) -> #REF! | H64: =SUM(H65:H67) -> #REF! | I64: =SUM(I65:I67) -> #REF! | J64: =SUM(J65:J67) -> #REF! | K64: =SUM(K65:K67) -> #REF! | L64: =SUM(L65:L67) -> #REF! | ... P64: =SUM(P65:P67) -> #REF! | Q64: =IFERROR(INDEX($E64:$P64,1,MATCH($C$2,$E$1:$P$1,0))/INDEX($E$38:$P$38,1,MATCH($C$2,$E$1:$P$1,0)),0) -> 0 | S64: =SUM(S65:S67) -> #REF! | T64: =SUM(T65:T67) -> #REF! | U64: =SUM(U65:U67) -> #REF! | V64: =SUM(V65:V67) -> #REF! | W64: =SUM(W65:W67) -> #REF! | X64: =SUM(X65:X67) -> #REF! | Y64: =SUM(Y65:Y67) -> #REF! | Z64: =SUM(Z65:Z67) -> #REF! | ... AD64: =SUM(AD65:AD67) -> #REF! | AE64: =INDEX($E64:$P64,1,MATCH($C$2,$E$1:$P$1,0))-INDEX(S64:AD64,1,MATCH($C$2,S$1:AD$1,0)) -> #REF! | AF64: =IFERROR(INDEX($E64:$P64,1,MATCH($C$2,$E$1:$P$1,0))/INDEX($S64:$AD64,1,MATCH($C$2,S$1:AD$1,0))-1,0) -> 0 | AH64: =SUM(AH65:AH67) -> #REF! | AI64: =SUM(AI65:AI67) -> #REF! | AJ64: =SUM(AJ65:AJ67) -> #REF! | AK64: =SUM(AK65:AK67) -> #REF! | AL64: =SUM(AL65:AL67) -> #REF! | AM64: =SUM(AM65:AM67) -> #REF! | AN64: =SUM(AN65:AN67) -> #REF! | AO64: =SUM(AO65:AO67) -> #REF! | ... AS64: =SUM(AS65:AS67) -> #REF! | AT64: =INDEX($E64:$P64,1,MATCH($C$2,$E$1:$P$1,0))-INDEX(AH64:AS64,1,MATCH(EDATE($C$2,-12),AH$1:AS$1,0)) -> #REF! | AU64: =IFERROR(INDEX($E64:$P64,1,MATCH($C$2,$E$1:$P$1,0))/INDEX(AH64:AS64,1,MATCH(EDATE($C$2,-12),AH$1:AS$1,0))-1,0) -> 0 | AW64: =SUM(AW65:AW67) -> #REF! | AX64: =AW64/AW$38 -> #REF! | BA64: =SUM(BA65:BA67) -> #REF! | BB64: =BA64/BA$38 -> #REF! | BC64: =$AW64-BA64 -> #REF! | BD64: =($AX64-BB64)*100 -> #REF! | BG64: =SUM(BG65:BG67) -> #REF! | BH64: =BG64/BG$38 -> #REF! | BI64: =$AW64-BG64 -> #REF! | BJ64: =($AX64-BH64)*100 -> #REF!
A65: Despesa | C65: Produtos para seeding | E65: {=INDEX(#REF!,MATCH($C65,#REF!,0),MATCH(E$1,#REF!,0))} -> #REF! | F65: {=INDEX(#REF!,MATCH($C65,#REF!,0),MATCH(F$1,#REF!,0))} -> #REF! | G65: {=INDEX(#REF!,MATCH($C65,#REF!,0),MATCH(G$1,#REF!,0))} -> #REF! | H65: {=INDEX(#REF!,MATCH($C65,#REF!,0),MATCH(H$1,#REF!,0))} -> #REF! | I65: {=INDEX(#REF!,MATCH($C65,#REF!,0),MATCH(I$1,#REF!,0))} -> #REF! | J65: {=INDEX(#REF!,MATCH($C65,#REF!,0),MATCH(J$1,#REF!,0))} -> #REF! | K65: {=INDEX(#REF!,MATCH($C65,#REF!,0),MATCH(K$1,#REF!,0))} -> #REF! | L65: {=INDEX(#REF!,MATCH($C65,#REF!,0),MATCH(L$1,#REF!,0))} -> #REF! | ... P65: {=INDEX(#REF!,MATCH($C65,#REF!,0),MATCH(P$1,#REF!,0))} -> #REF! | Q65: =IFERROR(INDEX($E65:$P65,1,MATCH($C$2,$E$1:$P$1,0))/INDEX($E$38:$P$38,1,MATCH($C$2,$E$1:$P$1,0)),0) -> 0 | S65: {=INDEX(#REF!,MATCH($C65,#REF!,0),MATCH(S$1,#REF!,0))} -> #REF! | T65: {=INDEX(#REF!,MATCH($C65,#REF!,0),MATCH(T$1,#REF!,0))} -> #REF! | U65: {=INDEX(#REF!,MATCH($C65,#REF!,0),MATCH(U$1,#REF!,0))} -> #REF! | V65: {=INDEX(#REF!,MATCH($C65,#REF!,0),MATCH(V$1,#REF!,0))} -> #REF! | W65: {=INDEX(#REF!,MATCH($C65,#REF!,0),MATCH(W$1,#REF!,0))} -> #REF! | X65: {=INDEX(#REF!,MATCH($C65,#REF!,0),MATCH(X$1,#REF!,0))} -> #REF! | Y65: {=INDEX(#REF!,MATCH($C65,#REF!,0),MATCH(Y$1,#REF!,0))} -> #REF! | Z65: {=INDEX(#REF!,MATCH($C65,#REF!,0),MATCH(Z$1,#REF!,0))} -> #REF! | ... AD65: {=INDEX(#REF!,MATCH($C65,#REF!,0),MATCH(AD$1,#REF!,0))} -> #REF! | AE65: =INDEX($E65:$P65,1,MATCH($C$2,$E$1:$P$1,0))-INDEX(S65:AD65,1,MATCH($C$2,S$1:AD$1,0)) -> #REF! | AF65: =IFERROR(INDEX($E65:$P65,1,MATCH($C$2,$E$1:$P$1,0))/INDEX($S65:$AD65,1,MATCH($C$2,S$1:AD$1,0))-1,0) -> 0 | AH65: {=INDEX(#REF!,MATCH($C65,#REF!,0),MATCH(AH$1,#REF!,0))} -> #REF! | AI65: {=INDEX(#REF!,MATCH($C65,#REF!,0),MATCH(AI$1,#REF!,0))} -> #REF! | AJ65: {=INDEX(#REF!,MATCH($C65,#REF!,0),MATCH(AJ$1,#REF!,0))} -> #REF! | AK65: {=INDEX(#REF!,MATCH($C65,#REF!,0),MATCH(AK$1,#REF!,0))} -> #REF! | AL65: {=INDEX(#REF!,MATCH($C65,#REF!,0),MATCH(AL$1,#REF!,0))} -> #REF! | AM65: {=INDEX(#REF!,MATCH($C65,#REF!,0),MATCH(AM$1,#REF!,0))} -> #REF! | AN65: {=INDEX(#REF!,MATCH($C65,#REF!,0),MATCH(AN$1,#REF!,0))} -> #REF! | AO65: {=INDEX(#REF!,MATCH($C65,#REF!,0),MATCH(AO$1,#REF!,0))} -> #REF! | ... AS65: {=INDEX(#REF!,MATCH($C65,#REF!,0),MATCH(AS$1,#REF!,0))} -> #REF! | AT65: =INDEX($E65:$P65,1,MATCH($C$2,$E$1:$P$1,0))-INDEX(AH65:AS65,1,MATCH(EDATE($C$2,-12),AH$1:AS$1,0)) -> #REF! | AU65: =IFERROR(INDEX($E65:$P65,1,MATCH($C$2,$E$1:$P$1,0))/INDEX(AH65:AS65,1,MATCH(EDATE($C$2,-12),AH$1:AS$1,0))-1,0) -> 0 | AW65: =SUMIF(E$1:P$1,"<="&AW$2,E65:P65) -> #REF! | AX65: =AW65/AW$38 -> #REF! | BA65: =SUMIF(S$1:AD$1,"<="&BA$2,S65:AD65) -> #REF! | BB65: =BA65/BA$38 -> #REF! | BC65: =$AW65-BA65 -> #REF! | BD65: =($AX65-BB65)*100 -> #REF! | BG65: =SUMIF(AH$1:AS$1,"<="&BG$2,AH65:AS65) -> #REF! | BH65: =BG65/BG$38 -> #REF! | BI65: =$AW65-BG65 -> #REF! | BJ65: =($AX65-BH65)*100 -> #REF!
A66: Despesa | C66: Embalagens para seeding | E66: {=INDEX(#REF!,MATCH($C66,#REF!,0),MATCH(E$1,#REF!,0))} -> #REF! | F66: {=INDEX(#REF!,MATCH($C66,#REF!,0),MATCH(F$1,#REF!,0))} -> #REF! | G66: {=INDEX(#REF!,MATCH($C66,#REF!,0),MATCH(G$1,#REF!,0))} -> #REF! | H66: {=INDEX(#REF!,MATCH($C66,#REF!,0),MATCH(H$1,#REF!,0))} -> #REF! | I66: {=INDEX(#REF!,MATCH($C66,#REF!,0),MATCH(I$1,#REF!,0))} -> #REF! | J66: {=INDEX(#REF!,MATCH($C66,#REF!,0),MATCH(J$1,#REF!,0))} -> #REF! | K66: {=INDEX(#REF!,MATCH($C66,#REF!,0),MATCH(K$1,#REF!,0))} -> #REF! | L66: {=INDEX(#REF!,MATCH($C66,#REF!,0),MATCH(L$1,#REF!,0))} -> #REF! | ... P66: {=INDEX(#REF!,MATCH($C66,#REF!,0),MATCH(P$1,#REF!,0))} -> #REF! | Q66: =IFERROR(INDEX($E66:$P66,1,MATCH($C$2,$E$1:$P$1,0))/INDEX($E$38:$P$38,1,MATCH($C$2,$E$1:$P$1,0)),0) -> 0 | S66: {=INDEX(#REF!,MATCH($C66,#REF!,0),MATCH(S$1,#REF!,0))} -> #REF! | T66: {=INDEX(#REF!,MATCH($C66,#REF!,0),MATCH(T$1,#REF!,0))} -> #REF! | U66: {=INDEX(#REF!,MATCH($C66,#REF!,0),MATCH(U$1,#REF!,0))} -> #REF! | V66: {=INDEX(#REF!,MATCH($C66,#REF!,0),MATCH(V$1,#REF!,0))} -> #REF! | W66: {=INDEX(#REF!,MATCH($C66,#REF!,0),MATCH(W$1,#REF!,0))} -> #REF! | X66: {=INDEX(#REF!,MATCH($C66,#REF!,0),MATCH(X$1,#REF!,0))} -> #REF! | Y66: {=INDEX(#REF!,MATCH($C66,#REF!,0),MATCH(Y$1,#REF!,0))} -> #REF! | Z66: {=INDEX(#REF!,MATCH($C66,#REF!,0),MATCH(Z$1,#REF!,0))} -> #REF! | ... AD66: {=INDEX(#REF!,MATCH($C66,#REF!,0),MATCH(AD$1,#REF!,0))} -> #REF! | AE66: =INDEX($E66:$P66,1,MATCH($C$2,$E$1:$P$1,0))-INDEX(S66:AD66,1,MATCH($C$2,S$1:AD$1,0)) -> #REF! | AF66: =IFERROR(INDEX($E66:$P66,1,MATCH($C$2,$E$1:$P$1,0))/INDEX($S66:$AD66,1,MATCH($C$2,S$1:AD$1,0))-1,0) -> 0 | AH66: {=INDEX(#REF!,MATCH($C66,#REF!,0),MATCH(AH$1,#REF!,0))} -> #REF! | AI66: {=INDEX(#REF!,MATCH($C66,#REF!,0),MATCH(AI$1,#REF!,0))} -> #REF! | AJ66: {=INDEX(#REF!,MATCH($C66,#REF!,0),MATCH(AJ$1,#REF!,0))} -> #REF! | AK66: {=INDEX(#REF!,MATCH($C66,#REF!,0),MATCH(AK$1,#REF!,0))} -> #REF! | AL66: {=INDEX(#REF!,MATCH($C66,#REF!,0),MATCH(AL$1,#REF!,0))} -> #REF! | AM66: {=INDEX(#REF!,MATCH($C66,#REF!,0),MATCH(AM$1,#REF!,0))} -> #REF! | AN66: {=INDEX(#REF!,MATCH($C66,#REF!,0),MATCH(AN$1,#REF!,0))} -> #REF! | AO66: {=INDEX(#REF!,MATCH($C66,#REF!,0),MATCH(AO$1,#REF!,0))} -> #REF! | ... AS66: {=INDEX(#REF!,MATCH($C66,#REF!,0),MATCH(AS$1,#REF!,0))} -> #REF! | AT66: =INDEX($E66:$P66,1,MATCH($C$2,$E$1:$P$1,0))-INDEX(AH66:AS66,1,MATCH(EDATE($C$2,-12),AH$1:AS$1,0)) -> #REF! | AU66: =IFERROR(INDEX($E66:$P66,1,MATCH($C$2,$E$1:$P$1,0))/INDEX(AH66:AS66,1,MATCH(EDATE($C$2,-12),AH$1:AS$1,0))-1,0) -> 0 | AW66: =SUMIF(E$1:P$1,"<="&AW$2,E66:P66) -> #REF! | AX66: =AW66/AW$38 -> #REF! | BA66: =SUMIF(S$1:AD$1,"<="&BA$2,S66:AD66) -> #REF! | BB66: =BA66/BA$38 -> #REF! | BC66: =$AW66-BA66 -> #REF! | BD66: =($AX66-BB66)*100 -> #REF! | BG66: =SUMIF(AH$1:AS$1,"<="&BG$2,AH66:AS66) -> #REF! | BH66: =BG66/BG$38 -> #REF! | BI66: =$AW66-BG66 -> #REF! | BJ66: =($AX66-BH66)*100 -> #REF!
A67: Despesa | C67: Envios | E67: {=INDEX(#REF!,MATCH($C67,#REF!,0),MATCH(E$1,#REF!,0))} -> #REF! | F67: {=INDEX(#REF!,MATCH($C67,#REF!,0),MATCH(F$1,#REF!,0))} -> #REF! | G67: {=INDEX(#REF!,MATCH($C67,#REF!,0),MATCH(G$1,#REF!,0))} -> #REF! | H67: {=INDEX(#REF!,MATCH($C67,#REF!,0),MATCH(H$1,#REF!,0))} -> #REF! | I67: {=INDEX(#REF!,MATCH($C67,#REF!,0),MATCH(I$1,#REF!,0))} -> #REF! | J67: {=INDEX(#REF!,MATCH($C67,#REF!,0),MATCH(J$1,#REF!,0))} -> #REF! | K67: {=INDEX(#REF!,MATCH($C67,#REF!,0),MATCH(K$1,#REF!,0))} -> #REF! | L67: {=INDEX(#REF!,MATCH($C67,#REF!,0),MATCH(L$1,#REF!,0))} -> #REF! | ... P67: {=INDEX(#REF!,MATCH($C67,#REF!,0),MATCH(P$1,#REF!,0))} -> #REF! | Q67: =IFERROR(INDEX($E67:$P67,1,MATCH($C$2,$E$1:$P$1,0))/INDEX($E$38:$P$38,1,MATCH($C$2,$E$1:$P$1,0)),0) -> 0 | S67: {=INDEX(#REF!,MATCH($C67,#REF!,0),MATCH(S$1,#REF!,0))} -> #REF! | T67: {=INDEX(#REF!,MATCH($C67,#REF!,0),MATCH(T$1,#REF!,0))} -> #REF! | U67: {=INDEX(#REF!,MATCH($C67,#REF!,0),MATCH(U$1,#REF!,0))} -> #REF! | V67: {=INDEX(#REF!,MATCH($C67,#REF!,0),MATCH(V$1,#REF!,0))} -> #REF! | W67: {=INDEX(#REF!,MATCH($C67,#REF!,0),MATCH(W$1,#REF!,0))} -> #REF! | X67: {=INDEX(#REF!,MATCH($C67,#REF!,0),MATCH(X$1,#REF!,0))} -> #REF! | Y67: {=INDEX(#REF!,MATCH($C67,#REF!,0),MATCH(Y$1,#REF!,0))} -> #REF! | Z67: {=INDEX(#REF!,MATCH($C67,#REF!,0),MATCH(Z$1,#REF!,0))} -> #REF! | ... AD67: {=INDEX(#REF!,MATCH($C67,#REF!,0),MATCH(AD$1,#REF!,0))} -> #REF! | AE67: =INDEX($E67:$P67,1,MATCH($C$2,$E$1:$P$1,0))-INDEX(S67:AD67,1,MATCH($C$2,S$1:AD$1,0)) -> #REF! | AF67: =IFERROR(INDEX($E67:$P67,1,MATCH($C$2,$E$1:$P$1,0))/INDEX($S67:$AD67,1,MATCH($C$2,S$1:AD$1,0))-1,0) -> 0 | AH67: {=INDEX(#REF!,MATCH($C67,#REF!,0),MATCH(AH$1,#REF!,0))} -> #REF! | AI67: {=INDEX(#REF!,MATCH($C67,#REF!,0),MATCH(AI$1,#REF!,0))} -> #REF! | AJ67: {=INDEX(#REF!,MATCH($C67,#REF!,0),MATCH(AJ$1,#REF!,0))} -> #REF! | AK67: {=INDEX(#REF!,MATCH($C67,#REF!,0),MATCH(AK$1,#REF!,0))} -> #REF! | AL67: {=INDEX(#REF!,MATCH($C67,#REF!,0),MATCH(AL$1,#REF!,0))} -> #REF! | AM67: {=INDEX(#REF!,MATCH($C67,#REF!,0),MATCH(AM$1,#REF!,0))} -> #REF! | AN67: {=INDEX(#REF!,MATCH($C67,#REF!,0),MATCH(AN$1,#REF!,0))} -> #REF! | AO67: {=INDEX(#REF!,MATCH($C67,#REF!,0),MATCH(AO$1,#REF!,0))} -> #REF! | ... AS67: {=INDEX(#REF!,MATCH($C67,#REF!,0),MATCH(AS$1,#REF!,0))} -> #REF! | AT67: =INDEX($E67:$P67,1,MATCH($C$2,$E$1:$P$1,0))-INDEX(AH67:AS67,1,MATCH(EDATE($C$2,-12),AH$1:AS$1,0)) -> #REF! | AU67: =IFERROR(INDEX($E67:$P67,1,MATCH($C$2,$E$1:$P$1,0))/INDEX(AH67:AS67,1,MATCH(EDATE($C$2,-12),AH$1:AS$1,0))-1,0) -> 0 | AW67: =SUMIF(E$1:P$1,"<="&AW$2,E67:P67) -> #REF! | AX67: =AW67/AW$38 -> #REF! | BA67: =SUMIF(S$1:AD$1,"<="&BA$2,S67:AD67) -> #REF! | BB67: =BA67/BA$38 -> #REF! | BC67: =$AW67-BA67 -> #REF! | BD67: =($AX67-BB67)*100 -> #REF! | BG67: =SUMIF(AH$1:AS$1,"<="&BG$2,AH67:AS67) -> #REF! | BH67: =BG67/BG$38 -> #REF! | BI67: =$AW67-BG67 -> #REF! | BJ67: =($AX67-BH67)*100 -> #REF!
A68: Despesa | C68: Branding | E68: =SUM(E69:E72) -> #REF! | F68: =SUM(F69:F72) -> #REF! | G68: =SUM(G69:G72) -> #REF! | H68: =SUM(H69:H72) -> #REF! | I68: =SUM(I69:I72) -> #REF! | J68: =SUM(J69:J72) -> #REF! | K68: =SUM(K69:K72) -> #REF! | L68: =SUM(L69:L72) -> #REF! | ... P68: =SUM(P69:P72) -> #REF! | Q68: =IFERROR(INDEX($E68:$P68,1,MATCH($C$2,$E$1:$P$1,0))/INDEX($E$38:$P$38,1,MATCH($C$2,$E$1:$P$1,0)),0) -> 0 | S68: =SUM(S69:S72) -> #REF! | T68: =SUM(T69:T72) -> #REF! | U68: =SUM(U69:U72) -> #REF! | V68: =SUM(V69:V72) -> #REF! | W68: =SUM(W69:W72) -> #REF! | X68: =SUM(X69:X72) -> #REF! | Y68: =SUM(Y69:Y72) -> #REF! | Z68: =SUM(Z69:Z72) -> #REF! | ... AD68: =SUM(AD69:AD72) -> #REF! | AE68: =INDEX($E68:$P68,1,MATCH($C$2,$E$1:$P$1,0))-INDEX(S68:AD68,1,MATCH($C$2,S$1:AD$1,0)) -> #REF! | AF68: =IFERROR(INDEX($E68:$P68,1,MATCH($C$2,$E$1:$P$1,0))/INDEX($S68:$AD68,1,MATCH($C$2,S$1:AD$1,0))-1,0) -> 0 | AH68: =SUM(AH69:AH72) -> #REF! | AI68: =SUM(AI69:AI72) -> #REF! | AJ68: =SUM(AJ69:AJ72) -> #REF! | AK68: =SUM(AK69:AK72) -> #REF! | AL68: =SUM(AL69:AL72) -> #REF! | AM68: =SUM(AM69:AM72) -> #REF! | AN68: =SUM(AN69:AN72) -> #REF! | AO68: =SUM(AO69:AO72) -> #REF! | ... AS68: =SUM(AS69:AS72) -> #REF! | AT68: =INDEX($E68:$P68,1,MATCH($C$2,$E$1:$P$1,0))-INDEX(AH68:AS68,1,MATCH(EDATE($C$2,-12),AH$1:AS$1,0)) -> #REF! | AU68: =IFERROR(INDEX($E68:$P68,1,MATCH($C$2,$E$1:$P$1,0))/INDEX(AH68:AS68,1,MATCH(EDATE($C$2,-12),AH$1:AS$1,0))-1,0) -> 0 | AW68: =SUM(AW69:AW72) -> #REF! | AX68: =AW68/AW$38 -> #REF! | BA68: =SUM(BA69:BA72) -> #REF! | BB68: =BA68/BA$38 -> #REF! | BC68: =$AW68-BA68 -> #REF! | BD68: =($AX68-BB68)*100 -> #REF! | BG68: =SUM(BG69:BG72) -> #REF! | BH68: =BG68/BG$38 -> #REF! | BI68: =$AW68-BG68 -> #REF! | BJ68: =($AX68-BH68)*100 -> #REF!
A69: Despesa | C69: Conteúdo | E69: {=INDEX(#REF!,MATCH($C69,#REF!,0),MATCH(E$1,#REF!,0))} -> #REF! | F69: {=INDEX(#REF!,MATCH($C69,#REF!,0),MATCH(F$1,#REF!,0))} -> #REF! | G69: {=INDEX(#REF!,MATCH($C69,#REF!,0),MATCH(G$1,#REF!,0))} -> #REF! | H69: {=INDEX(#REF!,MATCH($C69,#REF!,0),MATCH(H$1,#REF!,0))} -> #REF! | I69: {=INDEX(#REF!,MATCH($C69,#REF!,0),MATCH(I$1,#REF!,0))} -> #REF! | J69: {=INDEX(#REF!,MATCH($C69,#REF!,0),MATCH(J$1,#REF!,0))} -> #REF! | K69: {=INDEX(#REF!,MATCH($C69,#REF!,0),MATCH(K$1,#REF!,0))} -> #REF! | L69: {=INDEX(#REF!,MATCH($C69,#REF!,0),MATCH(L$1,#REF!,0))} -> #REF! | ... P69: {=INDEX(#REF!,MATCH($C69,#REF!,0),MATCH(P$1,#REF!,0))} -> #REF! | Q69: =IFERROR(INDEX($E69:$P69,1,MATCH($C$2,$E$1:$P$1,0))/INDEX($E$38:$P$38,1,MATCH($C$2,$E$1:$P$1,0)),0) -> 0 | S69: {=INDEX(#REF!,MATCH($C69,#REF!,0),MATCH(S$1,#REF!,0))} -> #REF! | T69: {=INDEX(#REF!,MATCH($C69,#REF!,0),MATCH(T$1,#REF!,0))} -> #REF! | U69: {=INDEX(#REF!,MATCH($C69,#REF!,0),MATCH(U$1,#REF!,0))} -> #REF! | V69: {=INDEX(#REF!,MATCH($C69,#REF!,0),MATCH(V$1,#REF!,0))} -> #REF! | W69: {=INDEX(#REF!,MATCH($C69,#REF!,0),MATCH(W$1,#REF!,0))} -> #REF! | X69: {=INDEX(#REF!,MATCH($C69,#REF!,0),MATCH(X$1,#REF!,0))} -> #REF! | Y69: {=INDEX(#REF!,MATCH($C69,#REF!,0),MATCH(Y$1,#REF!,0))} -> #REF! | Z69: {=INDEX(#REF!,MATCH($C69,#REF!,0),MATCH(Z$1,#REF!,0))} -> #REF! | ... AD69: {=INDEX(#REF!,MATCH($C69,#REF!,0),MATCH(AD$1,#REF!,0))} -> #REF! | AE69: =INDEX($E69:$P69,1,MATCH($C$2,$E$1:$P$1,0))-INDEX(S69:AD69,1,MATCH($C$2,S$1:AD$1,0)) -> #REF! | AF69: =IFERROR(INDEX($E69:$P69,1,MATCH($C$2,$E$1:$P$1,0))/INDEX($S69:$AD69,1,MATCH($C$2,S$1:AD$1,0))-1,0) -> 0 | AH69: {=INDEX(#REF!,MATCH($C69,#REF!,0),MATCH(AH$1,#REF!,0))} -> #REF! | AI69: {=INDEX(#REF!,MATCH($C69,#REF!,0),MATCH(AI$1,#REF!,0))} -> #REF! | AJ69: {=INDEX(#REF!,MATCH($C69,#REF!,0),MATCH(AJ$1,#REF!,0))} -> #REF! | AK69: {=INDEX(#REF!,MATCH($C69,#REF!,0),MATCH(AK$1,#REF!,0))} -> #REF! | AL69: {=INDEX(#REF!,MATCH($C69,#REF!,0),MATCH(AL$1,#REF!,0))} -> #REF! | AM69: {=INDEX(#REF!,MATCH($C69,#REF!,0),MATCH(AM$1,#REF!,0))} -> #REF! | AN69: {=INDEX(#REF!,MATCH($C69,#REF!,0),MATCH(AN$1,#REF!,0))} -> #REF! | AO69: {=INDEX(#REF!,MATCH($C69,#REF!,0),MATCH(AO$1,#REF!,0))} -> #REF! | ... AS69: {=INDEX(#REF!,MATCH($C69,#REF!,0),MATCH(AS$1,#REF!,0))} -> #REF! | AT69: =INDEX($E69:$P69,1,MATCH($C$2,$E$1:$P$1,0))-INDEX(AH69:AS69,1,MATCH(EDATE($C$2,-12),AH$1:AS$1,0)) -> #REF! | AU69: =IFERROR(INDEX($E69:$P69,1,MATCH($C$2,$E$1:$P$1,0))/INDEX(AH69:AS69,1,MATCH(EDATE($C$2,-12),AH$1:AS$1,0))-1,0) -> 0 | AW69: =SUMIF(E$1:P$1,"<="&AW$2,E69:P69) -> #REF! | AX69: =AW69/AW$38 -> #REF! | BA69: =SUMIF(S$1:AD$1,"<="&BA$2,S69:AD69) -> #REF! | BB69: =BA69/BA$38 -> #REF! | BC69: =$AW69-BA69 -> #REF! | BD69: =($AX69-BB69)*100 -> #REF! | BG69: =SUMIF(AH$1:AS$1,"<="&BG$2,AH69:AS69) -> #REF! | BH69: =BG69/BG$38 -> #REF! | BI69: =$AW69-BG69 -> #REF! | BJ69: =($AX69-BH69)*100 -> #REF!
A70: Despesa | C70: Design | E70: {=INDEX(#REF!,MATCH($C70,#REF!,0),MATCH(E$1,#REF!,0))} -> #REF! | F70: {=INDEX(#REF!,MATCH($C70,#REF!,0),MATCH(F$1,#REF!,0))} -> #REF! | G70: {=INDEX(#REF!,MATCH($C70,#REF!,0),MATCH(G$1,#REF!,0))} -> #REF! | H70: {=INDEX(#REF!,MATCH($C70,#REF!,0),MATCH(H$1,#REF!,0))} -> #REF! | I70: {=INDEX(#REF!,MATCH($C70,#REF!,0),MATCH(I$1,#REF!,0))} -> #REF! | J70: {=INDEX(#REF!,MATCH($C70,#REF!,0),MATCH(J$1,#REF!,0))} -> #REF! | K70: {=INDEX(#REF!,MATCH($C70,#REF!,0),MATCH(K$1,#REF!,0))} -> #REF! | L70: {=INDEX(#REF!,MATCH($C70,#REF!,0),MATCH(L$1,#REF!,0))} -> #REF! | ... P70: {=INDEX(#REF!,MATCH($C70,#REF!,0),MATCH(P$1,#REF!,0))} -> #REF! | Q70: =IFERROR(INDEX($E70:$P70,1,MATCH($C$2,$E$1:$P$1,0))/INDEX($E$38:$P$38,1,MATCH($C$2,$E$1:$P$1,0)),0) -> 0 | S70: {=INDEX(#REF!,MATCH($C70,#REF!,0),MATCH(S$1,#REF!,0))} -> #REF! | T70: {=INDEX(#REF!,MATCH($C70,#REF!,0),MATCH(T$1,#REF!,0))} -> #REF! | U70: {=INDEX(#REF!,MATCH($C70,#REF!,0),MATCH(U$1,#REF!,0))} -> #REF! | V70: {=INDEX(#REF!,MATCH($C70,#REF!,0),MATCH(V$1,#REF!,0))} -> #REF! | W70: {=INDEX(#REF!,MATCH($C70,#REF!,0),MATCH(W$1,#REF!,0))} -> #REF! | X70: {=INDEX(#REF!,MATCH($C70,#REF!,0),MATCH(X$1,#REF!,0))} -> #REF! | Y70: {=INDEX(#REF!,MATCH($C70,#REF!,0),MATCH(Y$1,#REF!,0))} -> #REF! | Z70: {=INDEX(#REF!,MATCH($C70,#REF!,0),MATCH(Z$1,#REF!,0))} -> #REF! | ... AD70: {=INDEX(#REF!,MATCH($C70,#REF!,0),MATCH(AD$1,#REF!,0))} -> #REF! | AE70: =INDEX($E70:$P70,1,MATCH($C$2,$E$1:$P$1,0))-INDEX(S70:AD70,1,MATCH($C$2,S$1:AD$1,0)) -> #REF! | AF70: =IFERROR(INDEX($E70:$P70,1,MATCH($C$2,$E$1:$P$1,0))/INDEX($S70:$AD70,1,MATCH($C$2,S$1:AD$1,0))-1,0) -> 0 | AH70: {=INDEX(#REF!,MATCH($C70,#REF!,0),MATCH(AH$1,#REF!,0))} -> #REF! | AI70: {=INDEX(#REF!,MATCH($C70,#REF!,0),MATCH(AI$1,#REF!,0))} -> #REF! | AJ70: {=INDEX(#REF!,MATCH($C70,#REF!,0),MATCH(AJ$1,#REF!,0))} -> #REF! | AK70: {=INDEX(#REF!,MATCH($C70,#REF!,0),MATCH(AK$1,#REF!,0))} -> #REF! | AL70: {=INDEX(#REF!,MATCH($C70,#REF!,0),MATCH(AL$1,#REF!,0))} -> #REF! | AM70: {=INDEX(#REF!,MATCH($C70,#REF!,0),MATCH(AM$1,#REF!,0))} -> #REF! | AN70: {=INDEX(#REF!,MATCH($C70,#REF!,0),MATCH(AN$1,#REF!,0))} -> #REF! | AO70: {=INDEX(#REF!,MATCH($C70,#REF!,0),MATCH(AO$1,#REF!,0))} -> #REF! | ... AS70: {=INDEX(#REF!,MATCH($C70,#REF!,0),MATCH(AS$1,#REF!,0))} -> #REF! | AT70: =INDEX($E70:$P70,1,MATCH($C$2,$E$1:$P$1,0))-INDEX(AH70:AS70,1,MATCH(EDATE($C$2,-12),AH$1:AS$1,0)) -> #REF! | AU70: =IFERROR(INDEX($E70:$P70,1,MATCH($C$2,$E$1:$P$1,0))/INDEX(AH70:AS70,1,MATCH(EDATE($C$2,-12),AH$1:AS$1,0))-1,0) -> 0 | AW70: =SUMIF(E$1:P$1,"<="&AW$2,E70:P70) -> #REF! | AX70: =AW70/AW$38 -> #REF! | BA70: =SUMIF(S$1:AD$1,"<="&BA$2,S70:AD70) -> #REF! | BB70: =BA70/BA$38 -> #REF! | BC70: =$AW70-BA70 -> #REF! | BD70: =($AX70-BB70)*100 -> #REF! | BG70: =SUMIF(AH$1:AS$1,"<="&BG$2,AH70:AS70) -> #REF! | BH70: =BG70/BG$38 -> #REF! | BI70: =$AW70-BG70 -> #REF! | BJ70: =($AX70-BH70)*100 -> #REF!
A71: Despesa | C71: Eventos | E71: {=INDEX(#REF!,MATCH($C71,#REF!,0),MATCH(E$1,#REF!,0))} -> #REF! | F71: {=INDEX(#REF!,MATCH($C71,#REF!,0),MATCH(F$1,#REF!,0))} -> #REF! | G71: {=INDEX(#REF!,MATCH($C71,#REF!,0),MATCH(G$1,#REF!,0))} -> #REF! | H71: {=INDEX(#REF!,MATCH($C71,#REF!,0),MATCH(H$1,#REF!,0))} -> #REF! | I71: {=INDEX(#REF!,MATCH($C71,#REF!,0),MATCH(I$1,#REF!,0))} -> #REF! | J71: {=INDEX(#REF!,MATCH($C71,#REF!,0),MATCH(J$1,#REF!,0))} -> #REF! | K71: {=INDEX(#REF!,MATCH($C71,#REF!,0),MATCH(K$1,#REF!,0))} -> #REF! | L71: {=INDEX(#REF!,MATCH($C71,#REF!,0),MATCH(L$1,#REF!,0))} -> #REF! | ... P71: {=INDEX(#REF!,MATCH($C71,#REF!,0),MATCH(P$1,#REF!,0))} -> #REF! | Q71: =IFERROR(INDEX($E71:$P71,1,MATCH($C$2,$E$1:$P$1,0))/INDEX($E$38:$P$38,1,MATCH($C$2,$E$1:$P$1,0)),0) -> 0 | S71: {=INDEX(#REF!,MATCH($C71,#REF!,0),MATCH(S$1,#REF!,0))} -> #REF! | T71: {=INDEX(#REF!,MATCH($C71,#REF!,0),MATCH(T$1,#REF!,0))} -> #REF! | U71: {=INDEX(#REF!,MATCH($C71,#REF!,0),MATCH(U$1,#REF!,0))} -> #REF! | V71: {=INDEX(#REF!,MATCH($C71,#REF!,0),MATCH(V$1,#REF!,0))} -> #REF! | W71: {=INDEX(#REF!,MATCH($C71,#REF!,0),MATCH(W$1,#REF!,0))} -> #REF! | X71: {=INDEX(#REF!,MATCH($C71,#REF!,0),MATCH(X$1,#REF!,0))} -> #REF! | Y71: {=INDEX(#REF!,MATCH($C71,#REF!,0),MATCH(Y$1,#REF!,0))} -> #REF! | Z71: {=INDEX(#REF!,MATCH($C71,#REF!,0),MATCH(Z$1,#REF!,0))} -> #REF! | ... AD71: {=INDEX(#REF!,MATCH($C71,#REF!,0),MATCH(AD$1,#REF!,0))} -> #REF! | AE71: =INDEX($E71:$P71,1,MATCH($C$2,$E$1:$P$1,0))-INDEX(S71:AD71,1,MATCH($C$2,S$1:AD$1,0)) -> #REF! | AF71: =IFERROR(INDEX($E71:$P71,1,MATCH($C$2,$E$1:$P$1,0))/INDEX($S71:$AD71,1,MATCH($C$2,S$1:AD$1,0))-1,0) -> 0 | AH71: {=INDEX(#REF!,MATCH($C71,#REF!,0),MATCH(AH$1,#REF!,0))} -> #REF! | AI71: {=INDEX(#REF!,MATCH($C71,#REF!,0),MATCH(AI$1,#REF!,0))} -> #REF! | AJ71: {=INDEX(#REF!,MATCH($C71,#REF!,0),MATCH(AJ$1,#REF!,0))} -> #REF! | AK71: {=INDEX(#REF!,MATCH($C71,#REF!,0),MATCH(AK$1,#REF!,0))} -> #REF! | AL71: {=INDEX(#REF!,MATCH($C71,#REF!,0),MATCH(AL$1,#REF!,0))} -> #REF! | AM71: {=INDEX(#REF!,MATCH($C71,#REF!,0),MATCH(AM$1,#REF!,0))} -> #REF! | AN71: {=INDEX(#REF!,MATCH($C71,#REF!,0),MATCH(AN$1,#REF!,0))} -> #REF! | AO71: {=INDEX(#REF!,MATCH($C71,#REF!,0),MATCH(AO$1,#REF!,0))} -> #REF! | ... AS71: {=INDEX(#REF!,MATCH($C71,#REF!,0),MATCH(AS$1,#REF!,0))} -> #REF! | AT71: =INDEX($E71:$P71,1,MATCH($C$2,$E$1:$P$1,0))-INDEX(AH71:AS71,1,MATCH(EDATE($C$2,-12),AH$1:AS$1,0)) -> #REF! | AU71: =IFERROR(INDEX($E71:$P71,1,MATCH($C$2,$E$1:$P$1,0))/INDEX(AH71:AS71,1,MATCH(EDATE($C$2,-12),AH$1:AS$1,0))-1,0) -> 0 | AW71: =SUMIF(E$1:P$1,"<="&AW$2,E71:P71) -> #REF! | AX71: =AW71/AW$38 -> #REF! | BA71: =SUMIF(S$1:AD$1,"<="&BA$2,S71:AD71) -> #REF! | BB71: =BA71/BA$38 -> #REF! | BC71: =$AW71-BA71 -> #REF! | BD71: =($AX71-BB71)*100 -> #REF! | BG71: =SUMIF(AH$1:AS$1,"<="&BG$2,AH71:AS71) -> #REF! | BH71: =BG71/BG$38 -> #REF! | BI71: =$AW71-BG71 -> #REF! | BJ71: =($AX71-BH71)*100 -> #REF!
A72: Despesa | C72: Produção | E72: {=INDEX(#REF!,MATCH($C72,#REF!,0),MATCH(E$1,#REF!,0))} -> #REF! | F72: {=INDEX(#REF!,MATCH($C72,#REF!,0),MATCH(F$1,#REF!,0))} -> #REF! | G72: {=INDEX(#REF!,MATCH($C72,#REF!,0),MATCH(G$1,#REF!,0))} -> #REF! | H72: {=INDEX(#REF!,MATCH($C72,#REF!,0),MATCH(H$1,#REF!,0))} -> #REF! | I72: {=INDEX(#REF!,MATCH($C72,#REF!,0),MATCH(I$1,#REF!,0))} -> #REF! | J72: {=INDEX(#REF!,MATCH($C72,#REF!,0),MATCH(J$1,#REF!,0))} -> #REF! | K72: {=INDEX(#REF!,MATCH($C72,#REF!,0),MATCH(K$1,#REF!,0))} -> #REF! | L72: {=INDEX(#REF!,MATCH($C72,#REF!,0),MATCH(L$1,#REF!,0))} -> #REF! | ... P72: {=INDEX(#REF!,MATCH($C72,#REF!,0),MATCH(P$1,#REF!,0))} -> #REF! | Q72: =IFERROR(INDEX($E72:$P72,1,MATCH($C$2,$E$1:$P$1,0))/INDEX($E$38:$P$38,1,MATCH($C$2,$E$1:$P$1,0)),0) -> 0 | S72: {=INDEX(#REF!,MATCH($C72,#REF!,0),MATCH(S$1,#REF!,0))} -> #REF! | T72: {=INDEX(#REF!,MATCH($C72,#REF!,0),MATCH(T$1,#REF!,0))} -> #REF! | U72: {=INDEX(#REF!,MATCH($C72,#REF!,0),MATCH(U$1,#REF!,0))} -> #REF! | V72: {=INDEX(#REF!,MATCH($C72,#REF!,0),MATCH(V$1,#REF!,0))} -> #REF! | W72: {=INDEX(#REF!,MATCH($C72,#REF!,0),MATCH(W$1,#REF!,0))} -> #REF! | X72: {=INDEX(#REF!,MATCH($C72,#REF!,0),MATCH(X$1,#REF!,0))} -> #REF! | Y72: {=INDEX(#REF!,MATCH($C72,#REF!,0),MATCH(Y$1,#REF!,0))} -> #REF! | Z72: {=INDEX(#REF!,MATCH($C72,#REF!,0),MATCH(Z$1,#REF!,0))} -> #REF! | ... AD72: {=INDEX(#REF!,MATCH($C72,#REF!,0),MATCH(AD$1,#REF!,0))} -> #REF! | AE72: =INDEX($E72:$P72,1,MATCH($C$2,$E$1:$P$1,0))-INDEX(S72:AD72,1,MATCH($C$2,S$1:AD$1,0)) -> #REF! | AF72: =IFERROR(INDEX($E72:$P72,1,MATCH($C$2,$E$1:$P$1,0))/INDEX($S72:$AD72,1,MATCH($C$2,S$1:AD$1,0))-1,0) -> 0 | AH72: {=INDEX(#REF!,MATCH($C72,#REF!,0),MATCH(AH$1,#REF!,0))} -> #REF! | AI72: {=INDEX(#REF!,MATCH($C72,#REF!,0),MATCH(AI$1,#REF!,0))} -> #REF! | AJ72: {=INDEX(#REF!,MATCH($C72,#REF!,0),MATCH(AJ$1,#REF!,0))} -> #REF! | AK72: {=INDEX(#REF!,MATCH($C72,#REF!,0),MATCH(AK$1,#REF!,0))} -> #REF! | AL72: {=INDEX(#REF!,MATCH($C72,#REF!,0),MATCH(AL$1,#REF!,0))} -> #REF! | AM72: {=INDEX(#REF!,MATCH($C72,#REF!,0),MATCH(AM$1,#REF!,0))} -> #REF! | AN72: {=INDEX(#REF!,MATCH($C72,#REF!,0),MATCH(AN$1,#REF!,0))} -> #REF! | AO72: {=INDEX(#REF!,MATCH($C72,#REF!,0),MATCH(AO$1,#REF!,0))} -> #REF! | ... AS72: {=INDEX(#REF!,MATCH($C72,#REF!,0),MATCH(AS$1,#REF!,0))} -> #REF! | AT72: =INDEX($E72:$P72,1,MATCH($C$2,$E$1:$P$1,0))-INDEX(AH72:AS72,1,MATCH(EDATE($C$2,-12),AH$1:AS$1,0)) -> #REF! | AU72: =IFERROR(INDEX($E72:$P72,1,MATCH($C$2,$E$1:$P$1,0))/INDEX(AH72:AS72,1,MATCH(EDATE($C$2,-12),AH$1:AS$1,0))-1,0) -> 0 | AW72: =SUMIF(E$1:P$1,"<="&AW$2,E72:P72) -> #REF! | AX72: =AW72/AW$38 -> #REF! | BA72: =SUMIF(S$1:AD$1,"<="&BA$2,S72:AD72) -> #REF! | BB72: =BA72/BA$38 -> #REF! | BC72: =$AW72-BA72 -> #REF! | BD72: =($AX72-BB72)*100 -> #REF! | BG72: =SUMIF(AH$1:AS$1,"<="&BG$2,AH72:AS72) -> #REF! | BH72: =BG72/BG$38 -> #REF! | BI72: =$AW72-BG72 -> #REF! | BJ72: =($AX72-BH72)*100 -> #REF!
A73: Despesa | C73: Trade marketing | E73: =SUM(E74:E77) -> #REF! | F73: =SUM(F74:F77) -> #REF! | G73: =SUM(G74:G77) -> #REF! | H73: =SUM(H74:H77) -> #REF! | I73: =SUM(I74:I77) -> #REF! | J73: =SUM(J74:J77) -> #REF! | K73: =SUM(K74:K77) -> #REF! | L73: =SUM(L74:L77) -> #REF! | ... P73: =SUM(P74:P77) -> #REF! | Q73: =IFERROR(INDEX($E73:$P73,1,MATCH($C$2,$E$1:$P$1,0))/INDEX($E$38:$P$38,1,MATCH($C$2,$E$1:$P$1,0)),0) -> 0 | S73: =SUM(S74:S77) -> #REF! | T73: =SUM(T74:T77) -> #REF! | U73: =SUM(U74:U77) -> #REF! | V73: =SUM(V74:V77) -> #REF! | W73: =SUM(W74:W77) -> #REF! | X73: =SUM(X74:X77) -> #REF! | Y73: =SUM(Y74:Y77) -> #REF! | Z73: =SUM(Z74:Z77) -> #REF! | ... AD73: =SUM(AD74:AD77) -> #REF! | AE73: =INDEX($E73:$P73,1,MATCH($C$2,$E$1:$P$1,0))-INDEX(S73:AD73,1,MATCH($C$2,S$1:AD$1,0)) -> #REF! | AF73: =IFERROR(INDEX($E73:$P73,1,MATCH($C$2,$E$1:$P$1,0))/INDEX($S73:$AD73,1,MATCH($C$2,S$1:AD$1,0))-1,0) -> 0 | AH73: =SUM(AH74:AH77) -> #REF! | AI73: =SUM(AI74:AI77) -> #REF! | AJ73: =SUM(AJ74:AJ77) -> #REF! | AK73: =SUM(AK74:AK77) -> #REF! | AL73: =SUM(AL74:AL77) -> #REF! | AM73: =SUM(AM74:AM77) -> #REF! | AN73: =SUM(AN74:AN77) -> #REF! | AO73: =SUM(AO74:AO77) -> #REF! | ... AS73: =SUM(AS74:AS77) -> #REF! | AT73: =INDEX($E73:$P73,1,MATCH($C$2,$E$1:$P$1,0))-INDEX(AH73:AS73,1,MATCH(EDATE($C$2,-12),AH$1:AS$1,0)) -> #REF! | AU73: =IFERROR(INDEX($E73:$P73,1,MATCH($C$2,$E$1:$P$1,0))/INDEX(AH73:AS73,1,MATCH(EDATE($C$2,-12),AH$1:AS$1,0))-1,0) -> 0 | AW73: =SUM(AW74:AW77) -> #REF! | AX73: =AW73/AW$38 -> #REF! | BA73: =SUM(BA74:BA77) -> #REF! | BB73: =BA73/BA$38 -> #REF! | BC73: =$AW73-BA73 -> #REF! | BD73: =($AX73-BB73)*100 -> #REF! | BG73: =SUM(BG74:BG77) -> #REF! | BH73: =BG73/BG$38 -> #REF! | BI73: =$AW73-BG73 -> #REF! | BJ73: =($AX73-BH73)*100 -> #REF!
A74: Despesa | C74: Material para PDVs próprios | E74: {=INDEX(#REF!,MATCH($C74,#REF!,0),MATCH(E$1,#REF!,0))} -> #REF! | F74: {=INDEX(#REF!,MATCH($C74,#REF!,0),MATCH(F$1,#REF!,0))} -> #REF! | G74: {=INDEX(#REF!,MATCH($C74,#REF!,0),MATCH(G$1,#REF!,0))} -> #REF! | H74: {=INDEX(#REF!,MATCH($C74,#REF!,0),MATCH(H$1,#REF!,0))} -> #REF! | I74: {=INDEX(#REF!,MATCH($C74,#REF!,0),MATCH(I$1,#REF!,0))} -> #REF! | J74: {=INDEX(#REF!,MATCH($C74,#REF!,0),MATCH(J$1,#REF!,0))} -> #REF! | K74: {=INDEX(#REF!,MATCH($C74,#REF!,0),MATCH(K$1,#REF!,0))} -> #REF! | L74: {=INDEX(#REF!,MATCH($C74,#REF!,0),MATCH(L$1,#REF!,0))} -> #REF! | ... P74: {=INDEX(#REF!,MATCH($C74,#REF!,0),MATCH(P$1,#REF!,0))} -> #REF! | Q74: =IFERROR(INDEX($E74:$P74,1,MATCH($C$2,$E$1:$P$1,0))/INDEX($E$38:$P$38,1,MATCH($C$2,$E$1:$P$1,0)),0) -> 0 | S74: {=INDEX(#REF!,MATCH($C74,#REF!,0),MATCH(S$1,#REF!,0))} -> #REF! | T74: {=INDEX(#REF!,MATCH($C74,#REF!,0),MATCH(T$1,#REF!,0))} -> #REF! | U74: {=INDEX(#REF!,MATCH($C74,#REF!,0),MATCH(U$1,#REF!,0))} -> #REF! | V74: {=INDEX(#REF!,MATCH($C74,#REF!,0),MATCH(V$1,#REF!,0))} -> #REF! | W74: {=INDEX(#REF!,MATCH($C74,#REF!,0),MATCH(W$1,#REF!,0))} -> #REF! | X74: {=INDEX(#REF!,MATCH($C74,#REF!,0),MATCH(X$1,#REF!,0))} -> #REF! | Y74: {=INDEX(#REF!,MATCH($C74,#REF!,0),MATCH(Y$1,#REF!,0))} -> #REF! | Z74: {=INDEX(#REF!,MATCH($C74,#REF!,0),MATCH(Z$1,#REF!,0))} -> #REF! | ... AD74: {=INDEX(#REF!,MATCH($C74,#REF!,0),MATCH(AD$1,#REF!,0))} -> #REF! | AE74: =INDEX($E74:$P74,1,MATCH($C$2,$E$1:$P$1,0))-INDEX(S74:AD74,1,MATCH($C$2,S$1:AD$1,0)) -> #REF! | AF74: =IFERROR(INDEX($E74:$P74,1,MATCH($C$2,$E$1:$P$1,0))/INDEX($S74:$AD74,1,MATCH($C$2,S$1:AD$1,0))-1,0) -> 0 | AH74: {=INDEX(#REF!,MATCH($C74,#REF!,0),MATCH(AH$1,#REF!,0))} -> #REF! | AI74: {=INDEX(#REF!,MATCH($C74,#REF!,0),MATCH(AI$1,#REF!,0))} -> #REF! | AJ74: {=INDEX(#REF!,MATCH($C74,#REF!,0),MATCH(AJ$1,#REF!,0))} -> #REF! | AK74: {=INDEX(#REF!,MATCH($C74,#REF!,0),MATCH(AK$1,#REF!,0))} -> #REF! | AL74: {=INDEX(#REF!,MATCH($C74,#REF!,0),MATCH(AL$1,#REF!,0))} -> #REF! | AM74: {=INDEX(#REF!,MATCH($C74,#REF!,0),MATCH(AM$1,#REF!,0))} -> #REF! | AN74: {=INDEX(#REF!,MATCH($C74,#REF!,0),MATCH(AN$1,#REF!,0))} -> #REF! | AO74: {=INDEX(#REF!,MATCH($C74,#REF!,0),MATCH(AO$1,#REF!,0))} -> #REF! | ... AS74: {=INDEX(#REF!,MATCH($C74,#REF!,0),MATCH(AS$1,#REF!,0))} -> #REF! | AT74: =INDEX($E74:$P74,1,MATCH($C$2,$E$1:$P$1,0))-INDEX(AH74:AS74,1,MATCH(EDATE($C$2,-12),AH$1:AS$1,0)) -> #REF! | AU74: =IFERROR(INDEX($E74:$P74,1,MATCH($C$2,$E$1:$P$1,0))/INDEX(AH74:AS74,1,MATCH(EDATE($C$2,-12),AH$1:AS$1,0))-1,0) -> 0 | AW74: =SUMIF(E$1:P$1,"<="&AW$2,E74:P74) -> #REF! | AX74: =AW74/AW$38 -> #REF! | BA74: =SUMIF(S$1:AD$1,"<="&BA$2,S74:AD74) -> #REF! | BB74: =BA74/BA$38 -> #REF! | BC74: =$AW74-BA74 -> #REF! | BD74: =($AX74-BB74)*100 -> #REF! | BG74: =SUMIF(AH$1:AS$1,"<="&BG$2,AH74:AS74) -> #REF! | BH74: =BG74/BG$38 -> #REF! | BI74: =$AW74-BG74 -> #REF! | BJ74: =($AX74-BH74)*100 -> #REF!
A75: Despesa | C75: Material para PDVs B2B | E75: {=INDEX(#REF!,MATCH($C75,#REF!,0),MATCH(E$1,#REF!,0))} -> #REF! | F75: {=INDEX(#REF!,MATCH($C75,#REF!,0),MATCH(F$1,#REF!,0))} -> #REF! | G75: {=INDEX(#REF!,MATCH($C75,#REF!,0),MATCH(G$1,#REF!,0))} -> #REF! | H75: {=INDEX(#REF!,MATCH($C75,#REF!,0),MATCH(H$1,#REF!,0))} -> #REF! | I75: {=INDEX(#REF!,MATCH($C75,#REF!,0),MATCH(I$1,#REF!,0))} -> #REF! | J75: {=INDEX(#REF!,MATCH($C75,#REF!,0),MATCH(J$1,#REF!,0))} -> #REF! | K75: {=INDEX(#REF!,MATCH($C75,#REF!,0),MATCH(K$1,#REF!,0))} -> #REF! | L75: {=INDEX(#REF!,MATCH($C75,#REF!,0),MATCH(L$1,#REF!,0))} -> #REF! | ... P75: {=INDEX(#REF!,MATCH($C75,#REF!,0),MATCH(P$1,#REF!,0))} -> #REF! | Q75: =IFERROR(INDEX($E75:$P75,1,MATCH($C$2,$E$1:$P$1,0))/INDEX($E$38:$P$38,1,MATCH($C$2,$E$1:$P$1,0)),0) -> 0 | S75: {=INDEX(#REF!,MATCH($C75,#REF!,0),MATCH(S$1,#REF!,0))} -> #REF! | T75: {=INDEX(#REF!,MATCH($C75,#REF!,0),MATCH(T$1,#REF!,0))} -> #REF! | U75: {=INDEX(#REF!,MATCH($C75,#REF!,0),MATCH(U$1,#REF!,0))} -> #REF! | V75: {=INDEX(#REF!,MATCH($C75,#REF!,0),MATCH(V$1,#REF!,0))} -> #REF! | W75: {=INDEX(#REF!,MATCH($C75,#REF!,0),MATCH(W$1,#REF!,0))} -> #REF! | X75: {=INDEX(#REF!,MATCH($C75,#REF!,0),MATCH(X$1,#REF!,0))} -> #REF! | Y75: {=INDEX(#REF!,MATCH($C75,#REF!,0),MATCH(Y$1,#REF!,0))} -> #REF! | Z75: {=INDEX(#REF!,MATCH($C75,#REF!,0),MATCH(Z$1,#REF!,0))} -> #REF! | ... AD75: {=INDEX(#REF!,MATCH($C75,#REF!,0),MATCH(AD$1,#REF!,0))} -> #REF! | AE75: =INDEX($E75:$P75,1,MATCH($C$2,$E$1:$P$1,0))-INDEX(S75:AD75,1,MATCH($C$2,S$1:AD$1,0)) -> #REF! | AF75: =IFERROR(INDEX($E75:$P75,1,MATCH($C$2,$E$1:$P$1,0))/INDEX($S75:$AD75,1,MATCH($C$2,S$1:AD$1,0))-1,0) -> 0 | AH75: {=INDEX(#REF!,MATCH($C75,#REF!,0),MATCH(AH$1,#REF!,0))} -> #REF! | AI75: {=INDEX(#REF!,MATCH($C75,#REF!,0),MATCH(AI$1,#REF!,0))} -> #REF! | AJ75: {=INDEX(#REF!,MATCH($C75,#REF!,0),MATCH(AJ$1,#REF!,0))} -> #REF! | AK75: {=INDEX(#REF!,MATCH($C75,#REF!,0),MATCH(AK$1,#REF!,0))} -> #REF! | AL75: {=INDEX(#REF!,MATCH($C75,#REF!,0),MATCH(AL$1,#REF!,0))} -> #REF! | AM75: {=INDEX(#REF!,MATCH($C75,#REF!,0),MATCH(AM$1,#REF!,0))} -> #REF! | AN75: {=INDEX(#REF!,MATCH($C75,#REF!,0),MATCH(AN$1,#REF!,0))} -> #REF! | AO75: {=INDEX(#REF!,MATCH($C75,#REF!,0),MATCH(AO$1,#REF!,0))} -> #REF! | ... AS75: {=INDEX(#REF!,MATCH($C75,#REF!,0),MATCH(AS$1,#REF!,0))} -> #REF! | AT75: =INDEX($E75:$P75,1,MATCH($C$2,$E$1:$P$1,0))-INDEX(AH75:AS75,1,MATCH(EDATE($C$2,-12),AH$1:AS$1,0)) -> #REF! | AU75: =IFERROR(INDEX($E75:$P75,1,MATCH($C$2,$E$1:$P$1,0))/INDEX(AH75:AS75,1,MATCH(EDATE($C$2,-12),AH$1:AS$1,0))-1,0) -> 0 | AW75: =SUMIF(E$1:P$1,"<="&AW$2,E75:P75) -> #REF! | AX75: =AW75/AW$38 -> #REF! | BA75: =SUMIF(S$1:AD$1,"<="&BA$2,S75:AD75) -> #REF! | BB75: =BA75/BA$38 -> #REF! | BC75: =$AW75-BA75 -> #REF! | BD75: =($AX75-BB75)*100 -> #REF! | BG75: =SUMIF(AH$1:AS$1,"<="&BG$2,AH75:AS75) -> #REF! | BH75: =BG75/BG$38 -> #REF! | BI75: =$AW75-BG75 -> #REF! | BJ75: =($AX75-BH75)*100 -> #REF!
A76: Despesa | C76: Brindes compre e ganhe | E76: {=INDEX(#REF!,MATCH($C76,#REF!,0),MATCH(E$1,#REF!,0))} -> #REF! | F76: {=INDEX(#REF!,MATCH($C76,#REF!,0),MATCH(F$1,#REF!,0))} -> #REF! | G76: {=INDEX(#REF!,MATCH($C76,#REF!,0),MATCH(G$1,#REF!,0))} -> #REF! | H76: {=INDEX(#REF!,MATCH($C76,#REF!,0),MATCH(H$1,#REF!,0))} -> #REF! | I76: {=INDEX(#REF!,MATCH($C76,#REF!,0),MATCH(I$1,#REF!,0))} -> #REF! | J76: {=INDEX(#REF!,MATCH($C76,#REF!,0),MATCH(J$1,#REF!,0))} -> #REF! | K76: {=INDEX(#REF!,MATCH($C76,#REF!,0),MATCH(K$1,#REF!,0))} -> #REF! | L76: {=INDEX(#REF!,MATCH($C76,#REF!,0),MATCH(L$1,#REF!,0))} -> #REF! | ... P76: {=INDEX(#REF!,MATCH($C76,#REF!,0),MATCH(P$1,#REF!,0))} -> #REF! | Q76: =IFERROR(INDEX($E76:$P76,1,MATCH($C$2,$E$1:$P$1,0))/INDEX($E$38:$P$38,1,MATCH($C$2,$E$1:$P$1,0)),0) -> 0 | S76: {=INDEX(#REF!,MATCH($C76,#REF!,0),MATCH(S$1,#REF!,0))} -> #REF! | T76: {=INDEX(#REF!,MATCH($C76,#REF!,0),MATCH(T$1,#REF!,0))} -> #REF! | U76: {=INDEX(#REF!,MATCH($C76,#REF!,0),MATCH(U$1,#REF!,0))} -> #REF! | V76: {=INDEX(#REF!,MATCH($C76,#REF!,0),MATCH(V$1,#REF!,0))} -> #REF! | W76: {=INDEX(#REF!,MATCH($C76,#REF!,0),MATCH(W$1,#REF!,0))} -> #REF! | X76: {=INDEX(#REF!,MATCH($C76,#REF!,0),MATCH(X$1,#REF!,0))} -> #REF! | Y76: {=INDEX(#REF!,MATCH($C76,#REF!,0),MATCH(Y$1,#REF!,0))} -> #REF! | Z76: {=INDEX(#REF!,MATCH($C76,#REF!,0),MATCH(Z$1,#REF!,0))} -> #REF! | ... AD76: {=INDEX(#REF!,MATCH($C76,#REF!,0),MATCH(AD$1,#REF!,0))} -> #REF! | AE76: =INDEX($E76:$P76,1,MATCH($C$2,$E$1:$P$1,0))-INDEX(S76:AD76,1,MATCH($C$2,S$1:AD$1,0)) -> #REF! | AF76: =IFERROR(INDEX($E76:$P76,1,MATCH($C$2,$E$1:$P$1,0))/INDEX($S76:$AD76,1,MATCH($C$2,S$1:AD$1,0))-1,0) -> 0 | AH76: {=INDEX(#REF!,MATCH($C76,#REF!,0),MATCH(AH$1,#REF!,0))} -> #REF! | AI76: {=INDEX(#REF!,MATCH($C76,#REF!,0),MATCH(AI$1,#REF!,0))} -> #REF! | AJ76: {=INDEX(#REF!,MATCH($C76,#REF!,0),MATCH(AJ$1,#REF!,0))} -> #REF! | AK76: {=INDEX(#REF!,MATCH($C76,#REF!,0),MATCH(AK$1,#REF!,0))} -> #REF! | AL76: {=INDEX(#REF!,MATCH($C76,#REF!,0),MATCH(AL$1,#REF!,0))} -> #REF! | AM76: {=INDEX(#REF!,MATCH($C76,#REF!,0),MATCH(AM$1,#REF!,0))} -> #REF! | AN76: {=INDEX(#REF!,MATCH($C76,#REF!,0),MATCH(AN$1,#REF!,0))} -> #REF! | AO76: {=INDEX(#REF!,MATCH($C76,#REF!,0),MATCH(AO$1,#REF!,0))} -> #REF! | ... AS76: {=INDEX(#REF!,MATCH($C76,#REF!,0),MATCH(AS$1,#REF!,0))} -> #REF! | AT76: =INDEX($E76:$P76,1,MATCH($C$2,$E$1:$P$1,0))-INDEX(AH76:AS76,1,MATCH(EDATE($C$2,-12),AH$1:AS$1,0)) -> #REF! | AU76: =IFERROR(INDEX($E76:$P76,1,MATCH($C$2,$E$1:$P$1,0))/INDEX(AH76:AS76,1,MATCH(EDATE($C$2,-12),AH$1:AS$1,0))-1,0) -> 0 | AW76: =SUMIF(E$1:P$1,"<="&AW$2,E76:P76) -> #REF! | AX76: =AW76/AW$38 -> #REF! | BA76: =SUMIF(S$1:AD$1,"<="&BA$2,S76:AD76) -> #REF! | BB76: =BA76/BA$38 -> #REF! | BC76: =$AW76-BA76 -> #REF! | BD76: =($AX76-BB76)*100 -> #REF! | BG76: =SUMIF(AH$1:AS$1,"<="&BG$2,AH76:AS76) -> #REF! | BH76: =BG76/BG$38 -> #REF! | BI76: =$AW76-BG76 -> #REF! | BJ76: =($AX76-BH76)*100 -> #REF!
A77: Despesa | C77: Ações de marketing lojas | E77: {=INDEX(#REF!,MATCH($C77,#REF!,0),MATCH(E$1,#REF!,0))} -> #REF! | F77: {=INDEX(#REF!,MATCH($C77,#REF!,0),MATCH(F$1,#REF!,0))} -> #REF! | G77: {=INDEX(#REF!,MATCH($C77,#REF!,0),MATCH(G$1,#REF!,0))} -> #REF! | H77: {=INDEX(#REF!,MATCH($C77,#REF!,0),MATCH(H$1,#REF!,0))} -> #REF! | I77: {=INDEX(#REF!,MATCH($C77,#REF!,0),MATCH(I$1,#REF!,0))} -> #REF! | J77: {=INDEX(#REF!,MATCH($C77,#REF!,0),MATCH(J$1,#REF!,0))} -> #REF! | K77: {=INDEX(#REF!,MATCH($C77,#REF!,0),MATCH(K$1,#REF!,0))} -> #REF! | L77: {=INDEX(#REF!,MATCH($C77,#REF!,0),MATCH(L$1,#REF!,0))} -> #REF! | ... P77: {=INDEX(#REF!,MATCH($C77,#REF!,0),MATCH(P$1,#REF!,0))} -> #REF! | Q77: =IFERROR(INDEX($E77:$P77,1,MATCH($C$2,$E$1:$P$1,0))/INDEX($E$38:$P$38,1,MATCH($C$2,$E$1:$P$1,0)),0) -> 0 | S77: {=INDEX(#REF!,MATCH($C77,#REF!,0),MATCH(S$1,#REF!,0))} -> #REF! | T77: {=INDEX(#REF!,MATCH($C77,#REF!,0),MATCH(T$1,#REF!,0))} -> #REF! | U77: {=INDEX(#REF!,MATCH($C77,#REF!,0),MATCH(U$1,#REF!,0))} -> #REF! | V77: {=INDEX(#REF!,MATCH($C77,#REF!,0),MATCH(V$1,#REF!,0))} -> #REF! | W77: {=INDEX(#REF!,MATCH($C77,#REF!,0),MATCH(W$1,#REF!,0))} -> #REF! | X77: {=INDEX(#REF!,MATCH($C77,#REF!,0),MATCH(X$1,#REF!,0))} -> #REF! | Y77: {=INDEX(#REF!,MATCH($C77,#REF!,0),MATCH(Y$1,#REF!,0))} -> #REF! | Z77: {=INDEX(#REF!,MATCH($C77,#REF!,0),MATCH(Z$1,#REF!,0))} -> #REF! | ... AD77: {=INDEX(#REF!,MATCH($C77,#REF!,0),MATCH(AD$1,#REF!,0))} -> #REF! | AE77: =INDEX($E77:$P77,1,MATCH($C$2,$E$1:$P$1,0))-INDEX(S77:AD77,1,MATCH($C$2,S$1:AD$1,0)) -> #REF! | AF77: =IFERROR(INDEX($E77:$P77,1,MATCH($C$2,$E$1:$P$1,0))/INDEX($S77:$AD77,1,MATCH($C$2,S$1:AD$1,0))-1,0) -> 0 | AH77: {=INDEX(#REF!,MATCH($C77,#REF!,0),MATCH(AH$1,#REF!,0))} -> #REF! | AI77: {=INDEX(#REF!,MATCH($C77,#REF!,0),MATCH(AI$1,#REF!,0))} -> #REF! | AJ77: {=INDEX(#REF!,MATCH($C77,#REF!,0),MATCH(AJ$1,#REF!,0))} -> #REF! | AK77: {=INDEX(#REF!,MATCH($C77,#REF!,0),MATCH(AK$1,#REF!,0))} -> #REF! | AL77: {=INDEX(#REF!,MATCH($C77,#REF!,0),MATCH(AL$1,#REF!,0))} -> #REF! | AM77: {=INDEX(#REF!,MATCH($C77,#REF!,0),MATCH(AM$1,#REF!,0))} -> #REF! | AN77: {=INDEX(#REF!,MATCH($C77,#REF!,0),MATCH(AN$1,#REF!,0))} -> #REF! | AO77: {=INDEX(#REF!,MATCH($C77,#REF!,0),MATCH(AO$1,#REF!,0))} -> #REF! | ... AS77: {=INDEX(#REF!,MATCH($C77,#REF!,0),MATCH(AS$1,#REF!,0))} -> #REF! | AT77: =INDEX($E77:$P77,1,MATCH($C$2,$E$1:$P$1,0))-INDEX(AH77:AS77,1,MATCH(EDATE($C$2,-12),AH$1:AS$1,0)) -> #REF! | AU77: =IFERROR(INDEX($E77:$P77,1,MATCH($C$2,$E$1:$P$1,0))/INDEX(AH77:AS77,1,MATCH(EDATE($C$2,-12),AH$1:AS$1,0))-1,0) -> 0 | AW77: =SUMIF(E$1:P$1,"<="&AW$2,E77:P77) -> #REF! | AX77: =AW77/AW$38 -> #REF! | BA77: =SUMIF(S$1:AD$1,"<="&BA$2,S77:AD77) -> #REF! | BB77: =BA77/BA$38 -> #REF! | BC77: =$AW77-BA77 -> #REF! | BD77: =($AX77-BB77)*100 -> #REF! | BG77: =SUMIF(AH$1:AS$1,"<="&BG$2,AH77:AS77) -> #REF! | BH77: =BG77/BG$38 -> #REF! | BI77: =$AW77-BG77 -> #REF! | BJ77: =($AX77-BH77)*100 -> #REF!
A78: Despesa | C78: Influência | E78: =SUM(E79:E81) -> #REF! | F78: =SUM(F79:F81) -> #REF! | G78: =SUM(G79:G81) -> #REF! | H78: =SUM(H79:H81) -> #REF! | I78: =SUM(I79:I81) -> #REF! | J78: =SUM(J79:J81) -> #REF! | K78: =SUM(K79:K81) -> #REF! | L78: =SUM(L79:L81) -> #REF! | ... P78: =SUM(P79:P81) -> #REF! | Q78: =IFERROR(INDEX($E78:$P78,1,MATCH($C$2,$E$1:$P$1,0))/INDEX($E$38:$P$38,1,MATCH($C$2,$E$1:$P$1,0)),0) -> 0 | S78: =SUM(S79:S81) -> #REF! | T78: =SUM(T79:T81) -> #REF! | U78: =SUM(U79:U81) -> #REF! | V78: =SUM(V79:V81) -> #REF! | W78: =SUM(W79:W81) -> #REF! | X78: =SUM(X79:X81) -> #REF! | Y78: =SUM(Y79:Y81) -> #REF! | Z78: =SUM(Z79:Z81) -> #REF! | ... AD78: =SUM(AD79:AD81) -> #REF! | AE78: =INDEX($E78:$P78,1,MATCH($C$2,$E$1:$P$1,0))-INDEX(S78:AD78,1,MATCH($C$2,S$1:AD$1,0)) -> #REF! | AF78: =IFERROR(INDEX($E78:$P78,1,MATCH($C$2,$E$1:$P$1,0))/INDEX($S78:$AD78,1,MATCH($C$2,S$1:AD$1,0))-1,0) -> 0 | AH78: =SUM(AH79:AH81) -> #REF! | AI78: =SUM(AI79:AI81) -> #REF! | AJ78: =SUM(AJ79:AJ81) -> #REF! | AK78: =SUM(AK79:AK81) -> #REF! | AL78: =SUM(AL79:AL81) -> #REF! | AM78: =SUM(AM79:AM81) -> #REF! | AN78: =SUM(AN79:AN81) -> #REF! | AO78: =SUM(AO79:AO81) -> #REF! | ... AS78: =SUM(AS79:AS81) -> #REF! | AT78: =INDEX($E78:$P78,1,MATCH($C$2,$E$1:$P$1,0))-INDEX(AH78:AS78,1,MATCH(EDATE($C$2,-12),AH$1:AS$1,0)) -> #REF! | AU78: =IFERROR(INDEX($E78:$P78,1,MATCH($C$2,$E$1:$P$1,0))/INDEX(AH78:AS78,1,MATCH(EDATE($C$2,-12),AH$1:AS$1,0))-1,0) -> 0 | AW78: =SUM(AW79:AW81) -> #REF! | AX78: =AW78/AW$38 -> #REF! | BA78: =SUM(BA79:BA81) -> #REF! | BB78: =BA78/BA$38 -> #REF! | BC78: =$AW78-BA78 -> #REF! | BD78: =($AX78-BB78)*100 -> #REF! | BG78: =SUM(BG79:BG81) -> #REF! | BH78: =BG78/BG$38 -> #REF! | BI78: =$AW78-BG78 -> #REF! | BJ78: =($AX78-BH78)*100 -> #REF!
A79: Despesa | C79: Awareness | E79: {=INDEX(#REF!,MATCH($C79,#REF!,0),MATCH(E$1,#REF!,0))} -> #REF! | F79: {=INDEX(#REF!,MATCH($C79,#REF!,0),MATCH(F$1,#REF!,0))} -> #REF! | G79: {=INDEX(#REF!,MATCH($C79,#REF!,0),MATCH(G$1,#REF!,0))} -> #REF! | H79: {=INDEX(#REF!,MATCH($C79,#REF!,0),MATCH(H$1,#REF!,0))} -> #REF! | I79: {=INDEX(#REF!,MATCH($C79,#REF!,0),MATCH(I$1,#REF!,0))} -> #REF! | J79: {=INDEX(#REF!,MATCH($C79,#REF!,0),MATCH(J$1,#REF!,0))} -> #REF! | K79: {=INDEX(#REF!,MATCH($C79,#REF!,0),MATCH(K$1,#REF!,0))} -> #REF! | L79: {=INDEX(#REF!,MATCH($C79,#REF!,0),MATCH(L$1,#REF!,0))} -> #REF! | ... P79: {=INDEX(#REF!,MATCH($C79,#REF!,0),MATCH(P$1,#REF!,0))} -> #REF! | Q79: =IFERROR(INDEX($E79:$P79,1,MATCH($C$2,$E$1:$P$1,0))/INDEX($E$38:$P$38,1,MATCH($C$2,$E$1:$P$1,0)),0) -> 0 | S79: {=INDEX(#REF!,MATCH($C79,#REF!,0),MATCH(S$1,#REF!,0))} -> #REF! | T79: {=INDEX(#REF!,MATCH($C79,#REF!,0),MATCH(T$1,#REF!,0))} -> #REF! | U79: {=INDEX(#REF!,MATCH($C79,#REF!,0),MATCH(U$1,#REF!,0))} -> #REF! | V79: {=INDEX(#REF!,MATCH($C79,#REF!,0),MATCH(V$1,#REF!,0))} -> #REF! | W79: {=INDEX(#REF!,MATCH($C79,#REF!,0),MATCH(W$1,#REF!,0))} -> #REF! | X79: {=INDEX(#REF!,MATCH($C79,#REF!,0),MATCH(X$1,#REF!,0))} -> #REF! | Y79: {=INDEX(#REF!,MATCH($C79,#REF!,0),MATCH(Y$1,#REF!,0))} -> #REF! | Z79: {=INDEX(#REF!,MATCH($C79,#REF!,0),MATCH(Z$1,#REF!,0))} -> #REF! | ... AD79: {=INDEX(#REF!,MATCH($C79,#REF!,0),MATCH(AD$1,#REF!,0))} -> #REF! | AE79: =INDEX($E79:$P79,1,MATCH($C$2,$E$1:$P$1,0))-INDEX(S79:AD79,1,MATCH($C$2,S$1:AD$1,0)) -> #REF! | AF79: =IFERROR(INDEX($E79:$P79,1,MATCH($C$2,$E$1:$P$1,0))/INDEX($S79:$AD79,1,MATCH($C$2,S$1:AD$1,0))-1,0) -> 0 | AH79: {=INDEX(#REF!,MATCH($C79,#REF!,0),MATCH(AH$1,#REF!,0))} -> #REF! | AI79: {=INDEX(#REF!,MATCH($C79,#REF!,0),MATCH(AI$1,#REF!,0))} -> #REF! | AJ79: {=INDEX(#REF!,MATCH($C79,#REF!,0),MATCH(AJ$1,#REF!,0))} -> #REF! | AK79: {=INDEX(#REF!,MATCH($C79,#REF!,0),MATCH(AK$1,#REF!,0))} -> #REF! | AL79: {=INDEX(#REF!,MATCH($C79,#REF!,0),MATCH(AL$1,#REF!,0))} -> #REF! | AM79: {=INDEX(#REF!,MATCH($C79,#REF!,0),MATCH(AM$1,#REF!,0))} -> #REF! | AN79: {=INDEX(#REF!,MATCH($C79,#REF!,0),MATCH(AN$1,#REF!,0))} -> #REF! | AO79: {=INDEX(#REF!,MATCH($C79,#REF!,0),MATCH(AO$1,#REF!,0))} -> #REF! | ... AS79: {=INDEX(#REF!,MATCH($C79,#REF!,0),MATCH(AS$1,#REF!,0))} -> #REF! | AT79: =INDEX($E79:$P79,1,MATCH($C$2,$E$1:$P$1,0))-INDEX(AH79:AS79,1,MATCH(EDATE($C$2,-12),AH$1:AS$1,0)) -> #REF! | AU79: =IFERROR(INDEX($E79:$P79,1,MATCH($C$2,$E$1:$P$1,0))/INDEX(AH79:AS79,1,MATCH(EDATE($C$2,-12),AH$1:AS$1,0))-1,0) -> 0 | AW79: =SUMIF(E$1:P$1,"<="&AW$2,E79:P79) -> #REF! | AX79: =AW79/AW$38 -> #REF! | BA79: =SUMIF(S$1:AD$1,"<="&BA$2,S79:AD79) -> #REF! | BB79: =BA79/BA$38 -> #REF! | BC79: =$AW79-BA79 -> #REF! | BD79: =($AX79-BB79)*100 -> #REF! | BG79: =SUMIF(AH$1:AS$1,"<="&BG$2,AH79:AS79) -> #REF! | BH79: =BG79/BG$38 -> #REF! | BI79: =$AW79-BG79 -> #REF! | BJ79: =($AX79-BH79)*100 -> #REF!
A80: Despesa | C80: Consideração | E80: {=INDEX(#REF!,MATCH($C80,#REF!,0),MATCH(E$1,#REF!,0))} -> #REF! | F80: {=INDEX(#REF!,MATCH($C80,#REF!,0),MATCH(F$1,#REF!,0))} -> #REF! | G80: {=INDEX(#REF!,MATCH($C80,#REF!,0),MATCH(G$1,#REF!,0))} -> #REF! | H80: {=INDEX(#REF!,MATCH($C80,#REF!,0),MATCH(H$1,#REF!,0))} -> #REF! | I80: {=INDEX(#REF!,MATCH($C80,#REF!,0),MATCH(I$1,#REF!,0))} -> #REF! | J80: {=INDEX(#REF!,MATCH($C80,#REF!,0),MATCH(J$1,#REF!,0))} -> #REF! | K80: {=INDEX(#REF!,MATCH($C80,#REF!,0),MATCH(K$1,#REF!,0))} -> #REF! | L80: {=INDEX(#REF!,MATCH($C80,#REF!,0),MATCH(L$1,#REF!,0))} -> #REF! | ... P80: {=INDEX(#REF!,MATCH($C80,#REF!,0),MATCH(P$1,#REF!,0))} -> #REF! | Q80: =IFERROR(INDEX($E80:$P80,1,MATCH($C$2,$E$1:$P$1,0))/INDEX($E$38:$P$38,1,MATCH($C$2,$E$1:$P$1,0)),0) -> 0 | S80: {=INDEX(#REF!,MATCH($C80,#REF!,0),MATCH(S$1,#REF!,0))} -> #REF! | T80: {=INDEX(#REF!,MATCH($C80,#REF!,0),MATCH(T$1,#REF!,0))} -> #REF! | U80: {=INDEX(#REF!,MATCH($C80,#REF!,0),MATCH(U$1,#REF!,0))} -> #REF! | V80: {=INDEX(#REF!,MATCH($C80,#REF!,0),MATCH(V$1,#REF!,0))} -> #REF! | W80: {=INDEX(#REF!,MATCH($C80,#REF!,0),MATCH(W$1,#REF!,0))} -> #REF! | X80: {=INDEX(#REF!,MATCH($C80,#REF!,0),MATCH(X$1,#REF!,0))} -> #REF! | Y80: {=INDEX(#REF!,MATCH($C80,#REF!,0),MATCH(Y$1,#REF!,0))} -> #REF! | Z80: {=INDEX(#REF!,MATCH($C80,#REF!,0),MATCH(Z$1,#REF!,0))} -> #REF! | ... AD80: {=INDEX(#REF!,MATCH($C80,#REF!,0),MATCH(AD$1,#REF!,0))} -> #REF! | AE80: =INDEX($E80:$P80,1,MATCH($C$2,$E$1:$P$1,0))-INDEX(S80:AD80,1,MATCH($C$2,S$1:AD$1,0)) -> #REF! | AF80: =IFERROR(INDEX($E80:$P80,1,MATCH($C$2,$E$1:$P$1,0))/INDEX($S80:$AD80,1,MATCH($C$2,S$1:AD$1,0))-1,0) -> 0 | AH80: {=INDEX(#REF!,MATCH($C80,#REF!,0),MATCH(AH$1,#REF!,0))} -> #REF! | AI80: {=INDEX(#REF!,MATCH($C80,#REF!,0),MATCH(AI$1,#REF!,0))} -> #REF! | AJ80: {=INDEX(#REF!,MATCH($C80,#REF!,0),MATCH(AJ$1,#REF!,0))} -> #REF! | AK80: {=INDEX(#REF!,MATCH($C80,#REF!,0),MATCH(AK$1,#REF!,0))} -> #REF! | AL80: {=INDEX(#REF!,MATCH($C80,#REF!,0),MATCH(AL$1,#REF!,0))} -> #REF! | AM80: {=INDEX(#REF!,MATCH($C80,#REF!,0),MATCH(AM$1,#REF!,0))} -> #REF! | AN80: {=INDEX(#REF!,MATCH($C80,#REF!,0),MATCH(AN$1,#REF!,0))} -> #REF! | AO80: {=INDEX(#REF!,MATCH($C80,#REF!,0),MATCH(AO$1,#REF!,0))} -> #REF! | ... AS80: {=INDEX(#REF!,MATCH($C80,#REF!,0),MATCH(AS$1,#REF!,0))} -> #REF! | AT80: =INDEX($E80:$P80,1,MATCH($C$2,$E$1:$P$1,0))-INDEX(AH80:AS80,1,MATCH(EDATE($C$2,-12),AH$1:AS$1,0)) -> #REF! | AU80: =IFERROR(INDEX($E80:$P80,1,MATCH($C$2,$E$1:$P$1,0))/INDEX(AH80:AS80,1,MATCH(EDATE($C$2,-12),AH$1:AS$1,0))-1,0) -> 0 | AW80: =SUMIF(E$1:P$1,"<="&AW$2,E80:P80) -> #REF! | AX80: =AW80/AW$38 -> #REF! | BA80: =SUMIF(S$1:AD$1,"<="&BA$2,S80:AD80) -> #REF! | BB80: =BA80/BA$38 -> #REF! | BC80: =$AW80-BA80 -> #REF! | BD80: =($AX80-BB80)*100 -> #REF! | BG80: =SUMIF(AH$1:AS$1,"<="&BG$2,AH80:AS80) -> #REF! | BH80: =BG80/BG$38 -> #REF! | BI80: =$AW80-BG80 -> #REF! | BJ80: =($AX80-BH80)*100 -> #REF!
