Workbook

Sheet Parametros
A1: SIMULADOR DE ANTECIPAÇÃO DE RECEBÍVEIS — GE Beauty
A2: Cash & Funding · controle de o que descontar, quando e com quem
A4: Data de hoje (editável) | B4: =TODAY() -> 46239 | C4: ← usada para 'dias até vencimento'. Troque por data fixa se quiser congelar.
A6: PARÂMETROS DOS FUNDERS (editáveis)
A7: Funder | B7: Taxa a.m. | C7: IOF diário | D7: IOF fixo | E7: Tarifa / parcela | F7: Tenor máx (dias) | G7: Teto (R$)
A8: Itaú | B8: 0.0172 | C8: 8.2e-05 | D8: 0.0038 | E8: 0 | F8: 210 | G8: 650000
A9: Ghia | B9: 0.02 | C9: 0 | D9: 0 | E9: 0 | F9: 120 | G9: 500000
A11: Notas: Itaú IOF = 0,0082%/dia + 0,38% fixo (crédito PJ). Ghia (FIDC true-sale) IOF assumido 0 e tarifas não quantificadas — CUSTO GHIA É ESTIMATIVA. Ajuste ao confirmar.
A12: Custo estimado por parcela = valor×(taxa a.m./30)×dias + valor×(IOF diário×dias + IOF fixo) + tarifa.

Sheet Entregas
A1: ENTREGAS NEGOCIADAS — preencha as células amarelas
A2: ID | B2: Cliente | C2: Produto | D2: Qtd | E2: Preço unit. | F2: Total | G2: Nº parcelas | H2: 1ª parcela (dias) | I2: Intervalo (dias) | J2: Calendário | K2: Data entrega | L2: Status
A3: E01 | B3: UAUBox | C3: Shampoo a Seco (Março) | D3: 17000 | E3: 17.19 | F3: =IF(D3="","",D3*E3) -> 292230 | G3: 4 | H3: 30 | I3: 30 | J3: Corrido | K3: 46068 | L3: Faturado
A4: E02 | B4: UAUBox | C4: Booster Hidratante (Maio) | D4: 17000 | E4: 18.29 | F4: =IF(D4="","",D4*E4) -> 310930 | G4: 4 | H4: 30 | I4: 30 | J4: Corrido | K4: 46127 | L4: Parcial
A5: E03 | B5: UAUBox | C5: Booster Definição (Nov, revisado) | D5: 26500 | E5: 21.83 | F5: =IF(D5="","",D5*E5) -> 578495 | G5: 5 | H5: 30 | I5: 30 | J5: Corrido | K5: 46310 | L5: 4x faturadas; 5ª a faturar
A6: E04 | B6: B4A | C6: Shampoo sem sulfato 60ml (ajuda custo) | D6: 15000 | E6: 7 | F6: =IF(D6="","",D6*E6) -> 105000 | G6: 4 | H6: 30 | I6: 30 | J6: Terça 3-25 | K6: 46239 | L6: Contrato 28/07 · dia estimado
A7: E05 | B7: B4A | C7: Máscara condicionadora 50ml (ajuda custo) | D7: 15000 | E7: 7 | F7: =IF(D7="","",D7*E7) -> 105000 | G7: 4 | H7: 30 | I7: 30 | J7: Terça 3-25 | K7: 46239 | L7: Contrato 28/07 · dia estimado
A8: E06 | B8: B4A | C8: Leave-in 150ml (ajuda custo) | D8: 15000 | E8: 12 | F8: =IF(D8="","",D8*E8) -> 180000 | G8: 4 | H8: 30 | I8: 30 | J8: Terça 3-25 | K8: 46300 | L8: Contrato 28/07 · dia estimado
A9: E07 | B9: B4A | C9: Shampoo a seco 150ml (ajuda custo) | D9: 15000 | E9: 14 | F9: =IF(D9="","",D9*E9) -> 210000 | G9: 4 | H9: 30 | I9: 30 | J9: Terça 3-25 | K9: 46331 | L9: Contrato 28/07 · dia estimado
A10: E08 | B10: B4A | C10: Booster Antifrizz 15ml (ajuda custo) | D10: 20000 | E10: 12 | F10: =IF(D10="","",D10*E10) -> 240000 | G10: 4 | H10: 30 | I10: 30 | J10: Terça 3-25 | K10: 46361 | L10: Contrato 28/07 · dia estimado
A11: E09 | F11: =IF(D11="","",D11*E11) | J11: Terça 3-25
A12: E10 | F12: =IF(D12="","",D12*E12) | J12: Terça 3-25
A13: E11 | F13: =IF(D13="","",D13*E13) | J13: Terça 3-25
A14: E12 | F14: =IF(D14="","",D14*E14) | J14: Terça 3-25
A16: Total negociado: | F16: =SUM(F3:F14) -> 2021655

Sheet Parcelas
A1: PARCELAS — vencimentos calculados; edite Data desconto e Funder (amarelo)
A2: Entrega | B2: Parc nº | C2: Cliente | D2: Produto | E2: Valor parcela | F2: Venc. nominal | G2: helper T0 | H2: helper 1ºdia m+1 | I2: helper Terça m+1 | J2: Vencimento | K2: Dias p/ venc (hoje) | L2: Data desconto | M2: Funder | N2: Tenor (dias) | O2: Tenor OK? | P2: Custo estim. | Q2: Valor líquido
A3: E01 | B3: 1 | C3: =IF($T3=1,INDEX(Entregas!$B$3:$B$14,$S3),"") -> UAUBox | D3: =IF($T3=1,INDEX(Entregas!$C$3:$C$14,$S3),"") -> Shampoo a Seco (Março) | E3: =IF($T3=1,INDEX(Entregas!$F$3:$F$14,$S3)/INDEX(Entregas!$G$3:$G$14,$S3),"") -> 73057.5 | F3: =IF($T3=1,INDEX(Entregas!$K$3:$K$14,$S3)+INDEX(Entregas!$H$3:$H$14,$S3),"") -> 46098 | G3: =IF($T3=1,F3+MOD(1-WEEKDAY(F3,3)+7,7),"") -> 46098 | H3: =IF($T3=1,EOMONTH(F3,0)+1,"") -> 46113 | I3: =IF($T3=1,IF(DAY(H3+MOD(1-WEEKDAY(H3,3)+7,7))<3,H3+MOD(1-WEEKDAY(H3,3)+7,7)+7,H3+MOD(1-WEEKDAY(H3,3)+7,7)),"") -> 46119 | J3: =IF($T3=1,IF(INDEX(Entregas!$J$3:$J$14,$S3)="Corrido",F3,IF(DAY(G3)>25,I3,IF(DAY(G3)<3,G3+7,G3))),"") -> 46098 | K3: =IF($T3=1,J3-Parametros!$B$4,"") -> -141 | N3: =IF(AND($T3=1,L3<>"",M3<>""),J3-L3,"") | O3: =IF(N3="","",IF(N3<0,"desc>venc",IF(N3>INDEX(Parametros!$F$8:$F$9,MATCH(M3,Parametros!$A$8:$A$9,0)),"EXCEDE","ok"))) | P3: =IF(OR(N3="",N3<0),"",E3*(INDEX(Parametros!$B$8:$B$9,MATCH(M3,Parametros!$A$8:$A$9,0))/30)*N3+E3*(INDEX(Parametros!$C$8:$C$9,MATCH(M3,Parametros!$A$8:$A$9,0))*N3+INDEX(Parametros!$D$8:$D$9,MATCH(M3,Parametros!$A$8:$A$9,0)))+INDEX(Parametros!$E$8:$E$9,MATCH(M3,Parametros!$A$8:$A$9,0))) | Q3: =IF(P3="","",E3-P3) | S3: =IFERROR(MATCH($A3,Entregas!$A$3:$A$14,0),"") -> 1 | T3: =IF($S3="",0,IF(AND(INDEX(Entregas!$F$3:$F$14,$S3)<>"",INDEX(Entregas!$F$3:$F$14,$S3)>0,$B3<=INDEX(Entregas!$G$3:$G$14,$S3)),1,0)) -> 1
A4: E01 | B4: 2 | C4: =IF($T4=1,INDEX(Entregas!$B$3:$B$14,$S4),"") -> UAUBox | D4: =IF($T4=1,INDEX(Entregas!$C$3:$C$14,$S4),"") -> Shampoo a Seco (Março) | E4: =IF($T4=1,INDEX(Entregas!$F$3:$F$14,$S4)/INDEX(Entregas!$G$3:$G$14,$S4),"") -> 73057.5 | F4: =IF($T4=1,J3+INDEX(Entregas!$I$3:$I$14,$S4),"") -> 46128 | G4: =IF($T4=1,F4+MOD(1-WEEKDAY(F4,3)+7,7),"") -> 46133 | H4: =IF($T4=1,EOMONTH(F4,0)+1,"") -> 46143 | I4: =IF($T4=1,IF(DAY(H4+MOD(1-WEEKDAY(H4,3)+7,7))<3,H4+MOD(1-WEEKDAY(H4,3)+7,7)+7,H4+MOD(1-WEEKDAY(H4,3)+7,7)),"") -> 46147 | J4: =IF($T4=1,IF(INDEX(Entregas!$J$3:$J$14,$S4)="Corrido",F4,IF(DAY(G4)>25,I4,IF(DAY(G4)<3,G4+7,G4))),"") -> 46128 | K4: =IF($T4=1,J4-Parametros!$B$4,"") -> -111 | N4: =IF(AND($T4=1,L4<>"",M4<>""),J4-L4,"") | O4: =IF(N4="","",IF(N4<0,"desc>venc",IF(N4>INDEX(Parametros!$F$8:$F$9,MATCH(M4,Parametros!$A$8:$A$9,0)),"EXCEDE","ok"))) | P4: =IF(OR(N4="",N4<0),"",E4*(INDEX(Parametros!$B$8:$B$9,MATCH(M4,Parametros!$A$8:$A$9,0))/30)*N4+E4*(INDEX(Parametros!$C$8:$C$9,MATCH(M4,Parametros!$A$8:$A$9,0))*N4+INDEX(Parametros!$D$8:$D$9,MATCH(M4,Parametros!$A$8:$A$9,0)))+INDEX(Parametros!$E$8:$E$9,MATCH(M4,Parametros!$A$8:$A$9,0))) | Q4: =IF(P4="","",E4-P4) | S4: =IFERROR(MATCH($A4,Entregas!$A$3:$A$14,0),"") -> 1 | T4: =IF($S4="",0,IF(AND(INDEX(Entregas!$F$3:$F$14,$S4)<>"",INDEX(Entregas!$F$3:$F$14,$S4)>0,$B4<=INDEX(Entregas!$G$3:$G$14,$S4)),1,0)) -> 1
A5: E01 | B5: 3 | C5: =IF($T5=1,INDEX(Entregas!$B$3:$B$14,$S5),"") -> UAUBox | D5: =IF($T5=1,INDEX(Entregas!$C$3:$C$14,$S5),"") -> Shampoo a Seco (Março) | E5: =IF($T5=1,INDEX(Entregas!$F$3:$F$14,$S5)/INDEX(Entregas!$G$3:$G$14,$S5),"") -> 73057.5 | F5: =IF($T5=1,J4+INDEX(Entregas!$I$3:$I$14,$S5),"") -> 46158 | G5: =IF($T5=1,F5+MOD(1-WEEKDAY(F5,3)+7,7),"") -> 46161 | H5: =IF($T5=1,EOMONTH(F5,0)+1,"") -> 46174 | I5: =IF($T5=1,IF(DAY(H5+MOD(1-WEEKDAY(H5,3)+7,7))<3,H5+MOD(1-WEEKDAY(H5,3)+7,7)+7,H5+MOD(1-WEEKDAY(H5,3)+7,7)),"") -> 46182 | J5: =IF($T5=1,IF(INDEX(Entregas!$J$3:$J$14,$S5)="Corrido",F5,IF(DAY(G5)>25,I5,IF(DAY(G5)<3,G5+7,G5))),"") -> 46158 | K5: =IF($T5=1,J5-Parametros!$B$4,"") -> -81 | N5: =IF(AND($T5=1,L5<>"",M5<>""),J5-L5,"") | O5: =IF(N5="","",IF(N5<0,"desc>venc",IF(N5>INDEX(Parametros!$F$8:$F$9,MATCH(M5,Parametros!$A$8:$A$9,0)),"EXCEDE","ok"))) | P5: =IF(OR(N5="",N5<0),"",E5*(INDEX(Parametros!$B$8:$B$9,MATCH(M5,Parametros!$A$8:$A$9,0))/30)*N5+E5*(INDEX(Parametros!$C$8:$C$9,MATCH(M5,Parametros!$A$8:$A$9,0))*N5+INDEX(Parametros!$D$8:$D$9,MATCH(M5,Parametros!$A$8:$A$9,0)))+INDEX(Parametros!$E$8:$E$9,MATCH(M5,Parametros!$A$8:$A$9,0))) | Q5: =IF(P5="","",E5-P5) | S5: =IFERROR(MATCH($A5,Entregas!$A$3:$A$14,0),"") -> 1 | T5: =IF($S5="",0,IF(AND(INDEX(Entregas!$F$3:$F$14,$S5)<>"",INDEX(Entregas!$F$3:$F$14,$S5)>0,$B5<=INDEX(Entregas!$G$3:$G$14,$S5)),1,0)) -> 1
A6: E01 | B6: 4 | C6: =IF($T6=1,INDEX(Entregas!$B$3:$B$14,$S6),"") -> UAUBox | D6: =IF($T6=1,INDEX(Entregas!$C$3:$C$14,$S6),"") -> Shampoo a Seco (Março) | E6: =IF($T6=1,INDEX(Entregas!$F$3:$F$14,$S6)/INDEX(Entregas!$G$3:$G$14,$S6),"") -> 73057.5 | F6: =IF($T6=1,J5+INDEX(Entregas!$I$3:$I$14,$S6),"") -> 46188 | G6: =IF($T6=1,F6+MOD(1-WEEKDAY(F6,3)+7,7),"") -> 46189 | H6: =IF($T6=1,EOMONTH(F6,0)+1,"") -> 46204 | I6: =IF($T6=1,IF(DAY(H6+MOD(1-WEEKDAY(H6,3)+7,7))<3,H6+MOD(1-WEEKDAY(H6,3)+7,7)+7,H6+MOD(1-WEEKDAY(H6,3)+7,7)),"") -> 46210 | J6: =IF($T6=1,IF(INDEX(Entregas!$J$3:$J$14,$S6)="Corrido",F6,IF(DAY(G6)>25,I6,IF(DAY(G6)<3,G6+7,G6))),"") -> 46188 | K6: =IF($T6=1,J6-Parametros!$B$4,"") -> -51 | N6: =IF(AND($T6=1,L6<>"",M6<>""),J6-L6,"") | O6: =IF(N6="","",IF(N6<0,"desc>venc",IF(N6>INDEX(Parametros!$F$8:$F$9,MATCH(M6,Parametros!$A$8:$A$9,0)),"EXCEDE","ok"))) | P6: =IF(OR(N6="",N6<0),"",E6*(INDEX(Parametros!$B$8:$B$9,MATCH(M6,Parametros!$A$8:$A$9,0))/30)*N6+E6*(INDEX(Parametros!$C$8:$C$9,MATCH(M6,Parametros!$A$8:$A$9,0))*N6+INDEX(Parametros!$D$8:$D$9,MATCH(M6,Parametros!$A$8:$A$9,0)))+INDEX(Parametros!$E$8:$E$9,MATCH(M6,Parametros!$A$8:$A$9,0))) | Q6: =IF(P6="","",E6-P6) | S6: =IFERROR(MATCH($A6,Entregas!$A$3:$A$14,0),"") -> 1 | T6: =IF($S6="",0,IF(AND(INDEX(Entregas!$F$3:$F$14,$S6)<>"",INDEX(Entregas!$F$3:$F$14,$S6)>0,$B6<=INDEX(Entregas!$G$3:$G$14,$S6)),1,0)) -> 1
A7: E01 | B7: 5 | C7: =IF($T7=1,INDEX(Entregas!$B$3:$B$14,$S7),"") | D7: =IF($T7=1,INDEX(Entregas!$C$3:$C$14,$S7),"") | E7: =IF($T7=1,INDEX(Entregas!$F$3:$F$14,$S7)/INDEX(Entregas!$G$3:$G$14,$S7),"") | F7: =IF($T7=1,J6+INDEX(Entregas!$I$3:$I$14,$S7),"") | G7: =IF($T7=1,F7+MOD(1-WEEKDAY(F7,3)+7,7),"") | H7: =IF($T7=1,EOMONTH(F7,0)+1,"") | I7: =IF($T7=1,IF(DAY(H7+MOD(1-WEEKDAY(H7,3)+7,7))<3,H7+MOD(1-WEEKDAY(H7,3)+7,7)+7,H7+MOD(1-WEEKDAY(H7,3)+7,7)),"") | J7: =IF($T7=1,IF(INDEX(Entregas!$J$3:$J$14,$S7)="Corrido",F7,IF(DAY(G7)>25,I7,IF(DAY(G7)<3,G7+7,G7))),"") | K7: =IF($T7=1,J7-Parametros!$B$4,"") | N7: =IF(AND($T7=1,L7<>"",M7<>""),J7-L7,"") | O7: =IF(N7="","",IF(N7<0,"desc>venc",IF(N7>INDEX(Parametros!$F$8:$F$9,MATCH(M7,Parametros!$A$8:$A$9,0)),"EXCEDE","ok"))) | P7: =IF(OR(N7="",N7<0),"",E7*(INDEX(Parametros!$B$8:$B$9,MATCH(M7,Parametros!$A$8:$A$9,0))/30)*N7+E7*(INDEX(Parametros!$C$8:$C$9,MATCH(M7,Parametros!$A$8:$A$9,0))*N7+INDEX(Parametros!$D$8:$D$9,MATCH(M7,Parametros!$A$8:$A$9,0)))+INDEX(Parametros!$E$8:$E$9,MATCH(M7,Parametros!$A$8:$A$9,0))) | Q7: =IF(P7="","",E7-P7) | S7: =IFERROR(MATCH($A7,Entregas!$A$3:$A$14,0),"") -> 1 | T7: =IF($S7="",0,IF(AND(INDEX(Entregas!$F$3:$F$14,$S7)<>"",INDEX(Entregas!$F$3:$F$14,$S7)>0,$B7<=INDEX(Entregas!$G$3:$G$14,$S7)),1,0)) -> 0
A8: E02 | B8: 1 | C8: =IF($T8=1,INDEX(Entregas!$B$3:$B$14,$S8),"") -> UAUBox | D8: =IF($T8=1,INDEX(Entregas!$C$3:$C$14,$S8),"") -> Booster Hidratante (Maio) | E8: =IF($T8=1,INDEX(Entregas!$F$3:$F$14,$S8)/INDEX(Entregas!$G$3:$G$14,$S8),"") -> 77732.5 | F8: =IF($T8=1,INDEX(Entregas!$K$3:$K$14,$S8)+INDEX(Entregas!$H$3:$H$14,$S8),"") -> 46157 | G8: =IF($T8=1,F8+MOD(1-WEEKDAY(F8,3)+7,7),"") -> 46161 | H8: =IF($T8=1,EOMONTH(F8,0)+1,"") -> 46174 | I8: =IF($T8=1,IF(DAY(H8+MOD(1-WEEKDAY(H8,3)+7,7))<3,H8+MOD(1-WEEKDAY(H8,3)+7,7)+7,H8+MOD(1-WEEKDAY(H8,3)+7,7)),"") -> 46182 | J8: =IF($T8=1,IF(INDEX(Entregas!$J$3:$J$14,$S8)="Corrido",F8,IF(DAY(G8)>25,I8,IF(DAY(G8)<3,G8+7,G8))),"") -> 46157 | K8: =IF($T8=1,J8-Parametros!$B$4,"") -> -82 | N8: =IF(AND($T8=1,L8<>"",M8<>""),J8-L8,"") | O8: =IF(N8="","",IF(N8<0,"desc>venc",IF(N8>INDEX(Parametros!$F$8:$F$9,MATCH(M8,Parametros!$A$8:$A$9,0)),"EXCEDE","ok"))) | P8: =IF(OR(N8="",N8<0),"",E8*(INDEX(Parametros!$B$8:$B$9,MATCH(M8,Parametros!$A$8:$A$9,0))/30)*N8+E8*(INDEX(Parametros!$C$8:$C$9,MATCH(M8,Parametros!$A$8:$A$9,0))*N8+INDEX(Parametros!$D$8:$D$9,MATCH(M8,Parametros!$A$8:$A$9,0)))+INDEX(Parametros!$E$8:$E$9,MATCH(M8,Parametros!$A$8:$A$9,0))) | Q8: =IF(P8="","",E8-P8) | S8: =IFERROR(MATCH($A8,Entregas!$A$3:$A$14,0),"") -> 2 | T8: =IF($S8="",0,IF(AND(INDEX(Entregas!$F$3:$F$14,$S8)<>"",INDEX(Entregas!$F$3:$F$14,$S8)>0,$B8<=INDEX(Entregas!$G$3:$G$14,$S8)),1,0)) -> 1
A9: E02 | B9: 2 | C9: =IF($T9=1,INDEX(Entregas!$B$3:$B$14,$S9),"") -> UAUBox | D9: =IF($T9=1,INDEX(Entregas!$C$3:$C$14,$S9),"") -> Booster Hidratante (Maio) | E9: =IF($T9=1,INDEX(Entregas!$F$3:$F$14,$S9)/INDEX(Entregas!$G$3:$G$14,$S9),"") -> 77732.5 | F9: =IF($T9=1,J8+INDEX(Entregas!$I$3:$I$14,$S9),"") -> 46187 | G9: =IF($T9=1,F9+MOD(1-WEEKDAY(F9,3)+7,7),"") -> 46189 | H9: =IF($T9=1,EOMONTH(F9,0)+1,"") -> 46204 | I9: =IF($T9=1,IF(DAY(H9+MOD(1-WEEKDAY(H9,3)+7,7))<3,H9+MOD(1-WEEKDAY(H9,3)+7,7)+7,H9+MOD(1-WEEKDAY(H9,3)+7,7)),"") -> 46210 | J9: =IF($T9=1,IF(INDEX(Entregas!$J$3:$J$14,$S9)="Corrido",F9,IF(DAY(G9)>25,I9,IF(DAY(G9)<3,G9+7,G9))),"") -> 46187 | K9: =IF($T9=1,J9-Parametros!$B$4,"") -> -52 | N9: =IF(AND($T9=1,L9<>"",M9<>""),J9-L9,"") | O9: =IF(N9="","",IF(N9<0,"desc>venc",IF(N9>INDEX(Parametros!$F$8:$F$9,MATCH(M9,Parametros!$A$8:$A$9,0)),"EXCEDE","ok"))) | P9: =IF(OR(N9="",N9<0),"",E9*(INDEX(Parametros!$B$8:$B$9,MATCH(M9,Parametros!$A$8:$A$9,0))/30)*N9+E9*(INDEX(Parametros!$C$8:$C$9,MATCH(M9,Parametros!$A$8:$A$9,0))*N9+INDEX(Parametros!$D$8:$D$9,MATCH(M9,Parametros!$A$8:$A$9,0)))+INDEX(Parametros!$E$8:$E$9,MATCH(M9,Parametros!$A$8:$A$9,0))) | Q9: =IF(P9="","",E9-P9) | S9: =IFERROR(MATCH($A9,Entregas!$A$3:$A$14,0),"") -> 2 | T9: =IF($S9="",0,IF(AND(INDEX(Entregas!$F$3:$F$14,$S9)<>"",INDEX(Entregas!$F$3:$F$14,$S9)>0,$B9<=INDEX(Entregas!$G$3:$G$14,$S9)),1,0)) -> 1
A10: E02 | B10: 3 | C10: =IF($T10=1,INDEX(Entregas!$B$3:$B$14,$S10),"") -> UAUBox | D10: =IF($T10=1,INDEX(Entregas!$C$3:$C$14,$S10),"") -> Booster Hidratante (Maio) | E10: =IF($T10=1,INDEX(Entregas!$F$3:$F$14,$S10)/INDEX(Entregas!$G$3:$G$14,$S10),"") -> 77732.5 | F10: =IF($T10=1,J9+INDEX(Entregas!$I$3:$I$14,$S10),"") -> 46217 | G10: =IF($T10=1,F10+MOD(1-WEEKDAY(F10,3)+7,7),"") -> 46217 | H10: =IF($T10=1,EOMONTH(F10,0)+1,"") -> 46235 | I10: =IF($T10=1,IF(DAY(H10+MOD(1-WEEKDAY(H10,3)+7,7))<3,H10+MOD(1-WEEKDAY(H10,3)+7,7)+7,H10+MOD(1-WEEKDAY(H10,3)+7,7)),"") -> 46238 | J10: =IF($T10=1,IF(INDEX(Entregas!$J$3:$J$14,$S10)="Corrido",F10,IF(DAY(G10)>25,I10,IF(DAY(G10)<3,G10+7,G10))),"") -> 46217 | K10: =IF($T10=1,J10-Parametros!$B$4,"") -> -22 | N10: =IF(AND($T10=1,L10<>"",M10<>""),J10-L10,"") | O10: =IF(N10="","",IF(N10<0,"desc>venc",IF(N10>INDEX(Parametros!$F$8:$F$9,MATCH(M10,Parametros!$A$8:$A$9,0)),"EXCEDE","ok"))) | P10: =IF(OR(N10="",N10<0),"",E10*(INDEX(Parametros!$B$8:$B$9,MATCH(M10,Parametros!$A$8:$A$9,0))/30)*N10+E10*(INDEX(Parametros!$C$8:$C$9,MATCH(M10,Parametros!$A$8:$A$9,0))*N10+INDEX(Parametros!$D$8:$D$9,MATCH(M10,Parametros!$A$8:$A$9,0)))+INDEX(Parametros!$E$8:$E$9,MATCH(M10,Parametros!$A$8:$A$9,0))) | Q10: =IF(P10="","",E10-P10) | S10: =IFERROR(MATCH($A10,Entregas!$A$3:$A$14,0),"") -> 2 | T10: =IF($S10="",0,IF(AND(INDEX(Entregas!$F$3:$F$14,$S10)<>"",INDEX(Entregas!$F$3:$F$14,$S10)>0,$B10<=INDEX(Entregas!$G$3:$G$14,$S10)),1,0)) -> 1
A11: E02 | B11: 4 | C11: =IF($T11=1,INDEX(Entregas!$B$3:$B$14,$S11),"") -> UAUBox | D11: =IF($T11=1,INDEX(Entregas!$C$3:$C$14,$S11),"") -> Booster Hidratante (Maio) | E11: =IF($T11=1,INDEX(Entregas!$F$3:$F$14,$S11)/INDEX(Entregas!$G$3:$G$14,$S11),"") -> 77732.5 | F11: =IF($T11=1,J10+INDEX(Entregas!$I$3:$I$14,$S11),"") -> 46247 | G11: =IF($T11=1,F11+MOD(1-WEEKDAY(F11,3)+7,7),"") -> 46252 | H11: =IF($T11=1,EOMONTH(F11,0)+1,"") -> 46266 | I11: =IF($T11=1,IF(DAY(H11+MOD(1-WEEKDAY(H11,3)+7,7))<3,H11+MOD(1-WEEKDAY(H11,3)+7,7)+7,H11+MOD(1-WEEKDAY(H11,3)+7,7)),"") -> 46273 | J11: =IF($T11=1,IF(INDEX(Entregas!$J$3:$J$14,$S11)="Corrido",F11,IF(DAY(G11)>25,I11,IF(DAY(G11)<3,G11+7,G11))),"") -> 46247 | K11: =IF($T11=1,J11-Parametros!$B$4,"") -> 8 | N11: =IF(AND($T11=1,L11<>"",M11<>""),J11-L11,"") | O11: =IF(N11="","",IF(N11<0,"desc>venc",IF(N11>INDEX(Parametros!$F$8:$F$9,MATCH(M11,Parametros!$A$8:$A$9,0)),"EXCEDE","ok"))) | P11: =IF(OR(N11="",N11<0),"",E11*(INDEX(Parametros!$B$8:$B$9,MATCH(M11,Parametros!$A$8:$A$9,0))/30)*N11+E11*(INDEX(Parametros!$C$8:$C$9,MATCH(M11,Parametros!$A$8:$A$9,0))*N11+INDEX(Parametros!$D$8:$D$9,MATCH(M11,Parametros!$A$8:$A$9,0)))+INDEX(Parametros!$E$8:$E$9,MATCH(M11,Parametros!$A$8:$A$9,0))) | Q11: =IF(P11="","",E11-P11) | S11: =IFERROR(MATCH($A11,Entregas!$A$3:$A$14,0),"") -> 2 | T11: =IF($S11="",0,IF(AND(INDEX(Entregas!$F$3:$F$14,$S11)<>"",INDEX(Entregas!$F$3:$F$14,$S11)>0,$B11<=INDEX(Entregas!$G$3:$G$14,$S11)),1,0)) -> 1
A12: E02 | B12: 5 | C12: =IF($T12=1,INDEX(Entregas!$B$3:$B$14,$S12),"") | D12: =IF($T12=1,INDEX(Entregas!$C$3:$C$14,$S12),"") | E12: =IF($T12=1,INDEX(Entregas!$F$3:$F$14,$S12)/INDEX(Entregas!$G$3:$G$14,$S12),"") | F12: =IF($T12=1,J11+INDEX(Entregas!$I$3:$I$14,$S12),"") | G12: =IF($T12=1,F12+MOD(1-WEEKDAY(F12,3)+7,7),"") | H12: =IF($T12=1,EOMONTH(F12,0)+1,"") | I12: =IF($T12=1,IF(DAY(H12+MOD(1-WEEKDAY(H12,3)+7,7))<3,H12+MOD(1-WEEKDAY(H12,3)+7,7)+7,H12+MOD(1-WEEKDAY(H12,3)+7,7)),"") | J12: =IF($T12=1,IF(INDEX(Entregas!$J$3:$J$14,$S12)="Corrido",F12,IF(DAY(G12)>25,I12,IF(DAY(G12)<3,G12+7,G12))),"") | K12: =IF($T12=1,J12-Parametros!$B$4,"") | N12: =IF(AND($T12=1,L12<>"",M12<>""),J12-L12,"") | O12: =IF(N12="","",IF(N12<0,"desc>venc",IF(N12>INDEX(Parametros!$F$8:$F$9,MATCH(M12,Parametros!$A$8:$A$9,0)),"EXCEDE","ok"))) | P12: =IF(OR(N12="",N12<0),"",E12*(INDEX(Parametros!$B$8:$B$9,MATCH(M12,Parametros!$A$8:$A$9,0))/30)*N12+E12*(INDEX(Parametros!$C$8:$C$9,MATCH(M12,Parametros!$A$8:$A$9,0))*N12+INDEX(Parametros!$D$8:$D$9,MATCH(M12,Parametros!$A$8:$A$9,0)))+INDEX(Parametros!$E$8:$E$9,MATCH(M12,Parametros!$A$8:$A$9,0))) | Q12: =IF(P12="","",E12-P12) | S12: =IFERROR(MATCH($A12,Entregas!$A$3:$A$14,0),"") -> 2 | T12: =IF($S12="",0,IF(AND(INDEX(Entregas!$F$3:$F$14,$S12)<>"",INDEX(Entregas!$F$3:$F$14,$S12)>0,$B12<=INDEX(Entregas!$G$3:$G$14,$S12)),1,0)) -> 0
A13: E03 | B13: 1 | C13: =IF($T13=1,INDEX(Entregas!$B$3:$B$14,$S13),"") -> UAUBox | D13: =IF($T13=1,INDEX(Entregas!$C$3:$C$14,$S13),"") -> Booster Definição (Nov, revisado) | E13: =IF($T13=1,INDEX(Entregas!$F$3:$F$14,$S13)/INDEX(Entregas!$G$3:$G$14,$S13),"") -> 115699 | F13: =IF($T13=1,INDEX(Entregas!$K$3:$K$14,$S13)+INDEX(Entregas!$H$3:$H$14,$S13),"") -> 46340 | G13: =IF($T13=1,F13+MOD(1-WEEKDAY(F13,3)+7,7),"") -> 46343 | H13: =IF($T13=1,EOMONTH(F13,0)+1,"") -> 46357 | I13: =IF($T13=1,IF(DAY(H13+MOD(1-WEEKDAY(H13,3)+7,7))<3,H13+MOD(1-WEEKDAY(H13,3)+7,7)+7,H13+MOD(1-WEEKDAY(H13,3)+7,7)),"") -> 46364 | J13: =IF($T13=1,IF(INDEX(Entregas!$J$3:$J$14,$S13)="Corrido",F13,IF(DAY(G13)>25,I13,IF(DAY(G13)<3,G13+7,G13))),"") -> 46340 | K13: =IF($T13=1,J13-Parametros!$B$4,"") -> 101 | N13: =IF(AND($T13=1,L13<>"",M13<>""),J13-L13,"") | O13: =IF(N13="","",IF(N13<0,"desc>venc",IF(N13>INDEX(Parametros!$F$8:$F$9,MATCH(M13,Parametros!$A$8:$A$9,0)),"EXCEDE","ok"))) | P13: =IF(OR(N13="",N13<0),"",E13*(INDEX(Parametros!$B$8:$B$9,MATCH(M13,Parametros!$A$8:$A$9,0))/30)*N13+E13*(INDEX(Parametros!$C$8:$C$9,MATCH(M13,Parametros!$A$8:$A$9,0))*N13+INDEX(Parametros!$D$8:$D$9,MATCH(M13,Parametros!$A$8:$A$9,0)))+INDEX(Parametros!$E$8:$E$9,MATCH(M13,Parametros!$A$8:$A$9,0))) | Q13: =IF(P13="","",E13-P13) | S13: =IFERROR(MATCH($A13,Entregas!$A$3:$A$14,0),"") -> 3 | T13: =IF($S13="",0,IF(AND(INDEX(Entregas!$F$3:$F$14,$S13)<>"",INDEX(Entregas!$F$3:$F$14,$S13)>0,$B13<=INDEX(Entregas!$G$3:$G$14,$S13)),1,0)) -> 1
A14: E03 | B14: 2 | C14: =IF($T14=1,INDEX(Entregas!$B$3:$B$14,$S14),"") -> UAUBox | D14: =IF($T14=1,INDEX(Entregas!$C$3:$C$14,$S14),"") -> Booster Definição (Nov, revisado) | E14: =IF($T14=1,INDEX(Entregas!$F$3:$F$14,$S14)/INDEX(Entregas!$G$3:$G$14,$S14),"") -> 115699 | F14: =IF($T14=1,J13+INDEX(Entregas!$I$3:$I$14,$S14),"") -> 46370 | G14: =IF($T14=1,F14+MOD(1-WEEKDAY(F14,3)+7,7),"") -> 46371 | H14: =IF($T14=1,EOMONTH(F14,0)+1,"") -> 46388 | I14: =IF($T14=1,IF(DAY(H14+MOD(1-WEEKDAY(H14,3)+7,7))<3,H14+MOD(1-WEEKDAY(H14,3)+7,7)+7,H14+MOD(1-WEEKDAY(H14,3)+7,7)),"") -> 46392 | J14: =IF($T14=1,IF(INDEX(Entregas!$J$3:$J$14,$S14)="Corrido",F14,IF(DAY(G14)>25,I14,IF(DAY(G14)<3,G14+7,G14))),"") -> 46370 | K14: =IF($T14=1,J14-Parametros!$B$4,"") -> 131 | N14: =IF(AND($T14=1,L14<>"",M14<>""),J14-L14,"") | O14: =IF(N14="","",IF(N14<0,"desc>venc",IF(N14>INDEX(Parametros!$F$8:$F$9,MATCH(M14,Parametros!$A$8:$A$9,0)),"EXCEDE","ok"))) | P14: =IF(OR(N14="",N14<0),"",E14*(INDEX(Parametros!$B$8:$B$9,MATCH(M14,Parametros!$A$8:$A$9,0))/30)*N14+E14*(INDEX(Parametros!$C$8:$C$9,MATCH(M14,Parametros!$A$8:$A$9,0))*N14+INDEX(Parametros!$D$8:$D$9,MATCH(M14,Parametros!$A$8:$A$9,0)))+INDEX(Parametros!$E$8:$E$9,MATCH(M14,Parametros!$A$8:$A$9,0))) | Q14: =IF(P14="","",E14-P14) | S14: =IFERROR(MATCH($A14,Entregas!$A$3:$A$14,0),"") -> 3 | T14: =IF($S14="",0,IF(AND(INDEX(Entregas!$F$3:$F$14,$S14)<>"",INDEX(Entregas!$F$3:$F$14,$S14)>0,$B14<=INDEX(Entregas!$G$3:$G$14,$S14)),1,0)) -> 1
A15: E03 | B15: 3 | C15: =IF($T15=1,INDEX(Entregas!$B$3:$B$14,$S15),"") -> UAUBox | D15: =IF($T15=1,INDEX(Entregas!$C$3:$C$14,$S15),"") -> Booster Definição (Nov, revisado) | E15: =IF($T15=1,INDEX(Entregas!$F$3:$F$14,$S15)/INDEX(Entregas!$G$3:$G$14,$S15),"") -> 115699 | F15: =IF($T15=1,J14+INDEX(Entregas!$I$3:$I$14,$S15),"") -> 46400 | G15: =IF($T15=1,F15+MOD(1-WEEKDAY(F15,3)+7,7),"") -> 46406 | H15: =IF($T15=1,EOMONTH(F15,0)+1,"") -> 46419 | I15: =IF($T15=1,IF(DAY(H15+MOD(1-WEEKDAY(H15,3)+7,7))<3,H15+MOD(1-WEEKDAY(H15,3)+7,7)+7,H15+MOD(1-WEEKDAY(H15,3)+7,7)),"") -> 46427 | J15: =IF($T15=1,IF(INDEX(Entregas!$J$3:$J$14,$S15)="Corrido",F15,IF(DAY(G15)>25,I15,IF(DAY(G15)<3,G15+7,G15))),"") -> 46400 | K15: =IF($T15=1,J15-Parametros!$B$4,"") -> 161 | N15: =IF(AND($T15=1,L15<>"",M15<>""),J15-L15,"") | O15: =IF(N15="","",IF(N15<0,"desc>venc",IF(N15>INDEX(Parametros!$F$8:$F$9,MATCH(M15,Parametros!$A$8:$A$9,0)),"EXCEDE","ok"))) | P15: =IF(OR(N15="",N15<0),"",E15*(INDEX(Parametros!$B$8:$B$9,MATCH(M15,Parametros!$A$8:$A$9,0))/30)*N15+E15*(INDEX(Parametros!$C$8:$C$9,MATCH(M15,Parametros!$A$8:$A$9,0))*N15+INDEX(Parametros!$D$8:$D$9,MATCH(M15,Parametros!$A$8:$A$9,0)))+INDEX(Parametros!$E$8:$E$9,MATCH(M15,Parametros!$A$8:$A$9,0))) | Q15: =IF(P15="","",E15-P15) | S15: =IFERROR(MATCH($A15,Entregas!$A$3:$A$14,0),"") -> 3 | T15: =IF($S15="",0,IF(AND(INDEX(Entregas!$F$3:$F$14,$S15)<>"",INDEX(Entregas!$F$3:$F$14,$S15)>0,$B15<=INDEX(Entregas!$G$3:$G$14,$S15)),1,0)) -> 1
A16: E03 | B16: 4 | C16: =IF($T16=1,INDEX(Entregas!$B$3:$B$14,$S16),"") -> UAUBox | D16: =IF($T16=1,INDEX(Entregas!$C$3:$C$14,$S16),"") -> Booster Definição (Nov, revisado) | E16: =IF($T16=1,INDEX(Entregas!$F$3:$F$14,$S16)/INDEX(Entregas!$G$3:$G$14,$S16),"") -> 115699 | F16: =IF($T16=1,J15+INDEX(Entregas!$I$3:$I$14,$S16),"") -> 46430 | G16: =IF($T16=1,F16+MOD(1-WEEKDAY(F16,3)+7,7),"") -> 46434 | H16: =IF($T16=1,EOMONTH(F16,0)+1,"") -> 46447 | I16: =IF($T16=1,IF(DAY(H16+MOD(1-WEEKDAY(H16,3)+7,7))<3,H16+MOD(1-WEEKDAY(H16,3)+7,7)+7,H16+MOD(1-WEEKDAY(H16,3)+7,7)),"") -> 46455 | J16: =IF($T16=1,IF(INDEX(Entregas!$J$3:$J$14,$S16)="Corrido",F16,IF(DAY(G16)>25,I16,IF(DAY(G16)<3,G16+7,G16))),"") -> 46430 | K16: =IF($T16=1,J16-Parametros!$B$4,"") -> 191 | N16: =IF(AND($T16=1,L16<>"",M16<>""),J16-L16,"") | O16: =IF(N16="","",IF(N16<0,"desc>venc",IF(N16>INDEX(Parametros!$F$8:$F$9,MATCH(M16,Parametros!$A$8:$A$9,0)),"EXCEDE","ok"))) | P16: =IF(OR(N16="",N16<0),"",E16*(INDEX(Parametros!$B$8:$B$9,MATCH(M16,Parametros!$A$8:$A$9,0))/30)*N16+E16*(INDEX(Parametros!$C$8:$C$9,MATCH(M16,Parametros!$A$8:$A$9,0))*N16+INDEX(Parametros!$D$8:$D$9,MATCH(M16,Parametros!$A$8:$A$9,0)))+INDEX(Parametros!$E$8:$E$9,MATCH(M16,Parametros!$A$8:$A$9,0))) | Q16: =IF(P16="","",E16-P16) | S16: =IFERROR(MATCH($A16,Entregas!$A$3:$A$14,0),"") -> 3 | T16: =IF($S16="",0,IF(AND(INDEX(Entregas!$F$3:$F$14,$S16)<>"",INDEX(Entregas!$F$3:$F$14,$S16)>0,$B16<=INDEX(Entregas!$G$3:$G$14,$S16)),1,0)) -> 1
A17: E03 | B17: 5 | C17: =IF($T17=1,INDEX(Entregas!$B$3:$B$14,$S17),"") -> UAUBox | D17: =IF($T17=1,INDEX(Entregas!$C$3:$C$14,$S17),"") -> Booster Definição (Nov, revisado) | E17: =IF($T17=1,INDEX(Entregas!$F$3:$F$14,$S17)/INDEX(Entregas!$G$3:$G$14,$S17),"") -> 115699 | F17: =IF($T17=1,J16+INDEX(Entregas!$I$3:$I$14,$S17),"") -> 46460 | G17: =IF($T17=1,F17+MOD(1-WEEKDAY(F17,3)+7,7),"") -> 46462 | H17: =IF($T17=1,EOMONTH(F17,0)+1,"") -> 46478 | I17: =IF($T17=1,IF(DAY(H17+MOD(1-WEEKDAY(H17,3)+7,7))<3,H17+MOD(1-WEEKDAY(H17,3)+7,7)+7,H17+MOD(1-WEEKDAY(H17,3)+7,7)),"") -> 46483 | J17: =IF($T17=1,IF(INDEX(Entregas!$J$3:$J$14,$S17)="Corrido",F17,IF(DAY(G17)>25,I17,IF(DAY(G17)<3,G17+7,G17))),"") -> 46460 | K17: =IF($T17=1,J17-Parametros!$B$4,"") -> 221 | N17: =IF(AND($T17=1,L17<>"",M17<>""),J17-L17,"") | O17: =IF(N17="","",IF(N17<0,"desc>venc",IF(N17>INDEX(Parametros!$F$8:$F$9,MATCH(M17,Parametros!$A$8:$A$9,0)),"EXCEDE","ok"))) | P17: =IF(OR(N17="",N17<0),"",E17*(INDEX(Parametros!$B$8:$B$9,MATCH(M17,Parametros!$A$8:$A$9,0))/30)*N17+E17*(INDEX(Parametros!$C$8:$C$9,MATCH(M17,Parametros!$A$8:$A$9,0))*N17+INDEX(Parametros!$D$8:$D$9,MATCH(M17,Parametros!$A$8:$A$9,0)))+INDEX(Parametros!$E$8:$E$9,MATCH(M17,Parametros!$A$8:$A$9,0))) | Q17: =IF(P17="","",E17-P17) | S17: =IFERROR(MATCH($A17,Entregas!$A$3:$A$14,0),"") -> 3 | T17: =IF($S17="",0,IF(AND(INDEX(Entregas!$F$3:$F$14,$S17)<>"",INDEX(Entregas!$F$3:$F$14,$S17)>0,$B17<=INDEX(Entregas!$G$3:$G$14,$S17)),1,0)) -> 1
A18: E04 | B18: 1 | C18: =IF($T18=1,INDEX(Entregas!$B$3:$B$14,$S18),"") -> B4A | D18: =IF($T18=1,INDEX(Entregas!$C$3:$C$14,$S18),"") -> Shampoo sem sulfato 60ml (ajuda custo) | E18: =IF($T18=1,INDEX(Entregas!$F$3:$F$14,$S18)/INDEX(Entregas!$G$3:$G$14,$S18),"") -> 26250 | F18: =IF($T18=1,INDEX(Entregas!$K$3:$K$14,$S18)+INDEX(Entregas!$H$3:$H$14,$S18),"") -> 46269 | G18: =IF($T18=1,F18+MOD(1-WEEKDAY(F18,3)+7,7),"") -> 46273 | H18: =IF($T18=1,EOMONTH(F18,0)+1,"") -> 46296 | I18: =IF($T18=1,IF(DAY(H18+MOD(1-WEEKDAY(H18,3)+7,7))<3,H18+MOD(1-WEEKDAY(H18,3)+7,7)+7,H18+MOD(1-WEEKDAY(H18,3)+7,7)),"") -> 46301 | J18: =IF($T18=1,IF(INDEX(Entregas!$J$3:$J$14,$S18)="Corrido",F18,IF(DAY(G18)>25,I18,IF(DAY(G18)<3,G18+7,G18))),"") -> 46273 | K18: =IF($T18=1,J18-Parametros!$B$4,"") -> 34 | N18: =IF(AND($T18=1,L18<>"",M18<>""),J18-L18,"") | O18: =IF(N18="","",IF(N18<0,"desc>venc",IF(N18>INDEX(Parametros!$F$8:$F$9,MATCH(M18,Parametros!$A$8:$A$9,0)),"EXCEDE","ok"))) | P18: =IF(OR(N18="",N18<0),"",E18*(INDEX(Parametros!$B$8:$B$9,MATCH(M18,Parametros!$A$8:$A$9,0))/30)*N18+E18*(INDEX(Parametros!$C$8:$C$9,MATCH(M18,Parametros!$A$8:$A$9,0))*N18+INDEX(Parametros!$D$8:$D$9,MATCH(M18,Parametros!$A$8:$A$9,0)))+INDEX(Parametros!$E$8:$E$9,MATCH(M18,Parametros!$A$8:$A$9,0))) | Q18: =IF(P18="","",E18-P18) | S18: =IFERROR(MATCH($A18,Entregas!$A$3:$A$14,0),"") -> 4 | T18: =IF($S18="",0,IF(AND(INDEX(Entregas!$F$3:$F$14,$S18)<>"",INDEX(Entregas!$F$3:$F$14,$S18)>0,$B18<=INDEX(Entregas!$G$3:$G$14,$S18)),1,0)) -> 1
A19: E04 | B19: 2 | C19: =IF($T19=1,INDEX(Entregas!$B$3:$B$14,$S19),"") -> B4A | D19: =IF($T19=1,INDEX(Entregas!$C$3:$C$14,$S19),"") -> Shampoo sem sulfato 60ml (ajuda custo) | E19: =IF($T19=1,INDEX(Entregas!$F$3:$F$14,$S19)/INDEX(Entregas!$G$3:$G$14,$S19),"") -> 26250 | F19: =IF($T19=1,J18+INDEX(Entregas!$I$3:$I$14,$S19),"") -> 46303 | G19: =IF($T19=1,F19+MOD(1-WEEKDAY(F19,3)+7,7),"") -> 46308 | H19: =IF($T19=1,EOMONTH(F19,0)+1,"") -> 46327 | I19: =IF($T19=1,IF(DAY(H19+MOD(1-WEEKDAY(H19,3)+7,7))<3,H19+MOD(1-WEEKDAY(H19,3)+7,7)+7,H19+MOD(1-WEEKDAY(H19,3)+7,7)),"") -> 46329 | J19: =IF($T19=1,IF(INDEX(Entregas!$J$3:$J$14,$S19)="Corrido",F19,IF(DAY(G19)>25,I19,IF(DAY(G19)<3,G19+7,G19))),"") -> 46308 | K19: =IF($T19=1,J19-Parametros!$B$4,"") -> 69 | N19: =IF(AND($T19=1,L19<>"",M19<>""),J19-L19,"") | O19: =IF(N19="","",IF(N19<0,"desc>venc",IF(N19>INDEX(Parametros!$F$8:$F$9,MATCH(M19,Parametros!$A$8:$A$9,0)),"EXCEDE","ok"))) | P19: =IF(OR(N19="",N19<0),"",E19*(INDEX(Parametros!$B$8:$B$9,MATCH(M19,Parametros!$A$8:$A$9,0))/30)*N19+E19*(INDEX(Parametros!$C$8:$C$9,MATCH(M19,Parametros!$A$8:$A$9,0))*N19+INDEX(Parametros!$D$8:$D$9,MATCH(M19,Parametros!$A$8:$A$9,0)))+INDEX(Parametros!$E$8:$E$9,MATCH(M19,Parametros!$A$8:$A$9,0))) | Q19: =IF(P19="","",E19-P19) | S19: =IFERROR(MATCH($A19,Entregas!$A$3:$A$14,0),"") -> 4 | T19: =IF($S19="",0,IF(AND(INDEX(Entregas!$F$3:$F$14,$S19)<>"",INDEX(Entregas!$F$3:$F$14,$S19)>0,$B19<=INDEX(Entregas!$G$3:$G$14,$S19)),1,0)) -> 1
A20: E04 | B20: 3 | C20: =IF($T20=1,INDEX(Entregas!$B$3:$B$14,$S20),"") -> B4A | D20: =IF($T20=1,INDEX(Entregas!$C$3:$C$14,$S20),"") -> Shampoo sem sulfato 60ml (ajuda custo) | E20: =IF($T20=1,INDEX(Entregas!$F$3:$F$14,$S20)/INDEX(Entregas!$G$3:$G$14,$S20),"") -> 26250 | F20: =IF($T20=1,J19+INDEX(Entregas!$I$3:$I$14,$S20),"") -> 46338 | G20: =IF($T20=1,F20+MOD(1-WEEKDAY(F20,3)+7,7),"") -> 46343 | H20: =IF($T20=1,EOMONTH(F20,0)+1,"") -> 46357 | I20: =IF($T20=1,IF(DAY(H20+MOD(1-WEEKDAY(H20,3)+7,7))<3,H20+MOD(1-WEEKDAY(H20,3)+7,7)+7,H20+MOD(1-WEEKDAY(H20,3)+7,7)),"") -> 46364 | J20: =IF($T20=1,IF(INDEX(Entregas!$J$3:$J$14,$S20)="Corrido",F20,IF(DAY(G20)>25,I20,IF(DAY(G20)<3,G20+7,G20))),"") -> 46343 | K20: =IF($T20=1,J20-Parametros!$B$4,"") -> 104 | N20: =IF(AND($T20=1,L20<>"",M20<>""),J20-L20,"") | O20: =IF(N20="","",IF(N20<0,"desc>venc",IF(N20>INDEX(Parametros!$F$8:$F$9,MATCH(M20,Parametros!$A$8:$A$9,0)),"EXCEDE","ok"))) | P20: =IF(OR(N20="",N20<0),"",E20*(INDEX(Parametros!$B$8:$B$9,MATCH(M20,Parametros!$A$8:$A$9,0))/30)*N20+E20*(INDEX(Parametros!$C$8:$C$9,MATCH(M20,Parametros!$A$8:$A$9,0))*N20+INDEX(Parametros!$D$8:$D$9,MATCH(M20,Parametros!$A$8:$A$9,0)))+INDEX(Parametros!$E$8:$E$9,MATCH(M20,Parametros!$A$8:$A$9,0))) | Q20: =IF(P20="","",E20-P20) | S20: =IFERROR(MATCH($A20,Entregas!$A$3:$A$14,0),"") -> 4 | T20: =IF($S20="",0,IF(AND(INDEX(Entregas!$F$3:$F$14,$S20)<>"",INDEX(Entregas!$F$3:$F$14,$S20)>0,$B20<=INDEX(Entregas!$G$3:$G$14,$S20)),1,0)) -> 1
A21: E04 | B21: 4 | C21: =IF($T21=1,INDEX(Entregas!$B$3:$B$14,$S21),"") -> B4A | D21: =IF($T21=1,INDEX(Entregas!$C$3:$C$14,$S21),"") -> Shampoo sem sulfato 60ml (ajuda custo) | E21: =IF($T21=1,INDEX(Entregas!$F$3:$F$14,$S21)/INDEX(Entregas!$G$3:$G$14,$S21),"") -> 26250 | F21: =IF($T21=1,J20+INDEX(Entregas!$I$3:$I$14,$S21),"") -> 46373 | G21: =IF($T21=1,F21+MOD(1-WEEKDAY(F21,3)+7,7),"") -> 46378 | H21: =IF($T21=1,EOMONTH(F21,0)+1,"") -> 46388 | I21: =IF($T21=1,IF(DAY(H21+MOD(1-WEEKDAY(H21,3)+7,7))<3,H21+MOD(1-WEEKDAY(H21,3)+7,7)+7,H21+MOD(1-WEEKDAY(H21,3)+7,7)),"") -> 46392 | J21: =IF($T21=1,IF(INDEX(Entregas!$J$3:$J$14,$S21)="Corrido",F21,IF(DAY(G21)>25,I21,IF(DAY(G21)<3,G21+7,G21))),"") -> 46378 | K21: =IF($T21=1,J21-Parametros!$B$4,"") -> 139 | N21: =IF(AND($T21=1,L21<>"",M21<>""),J21-L21,"") | O21: =IF(N21="","",IF(N21<0,"desc>venc",IF(N21>INDEX(Parametros!$F$8:$F$9,MATCH(M21,Parametros!$A$8:$A$9,0)),"EXCEDE","ok"))) | P21: =IF(OR(N21="",N21<0),"",E21*(INDEX(Parametros!$B$8:$B$9,MATCH(M21,Parametros!$A$8:$A$9,0))/30)*N21+E21*(INDEX(Parametros!$C$8:$C$9,MATCH(M21,Parametros!$A$8:$A$9,0))*N21+INDEX(Parametros!$D$8:$D$9,MATCH(M21,Parametros!$A$8:$A$9,0)))+INDEX(Parametros!$E$8:$E$9,MATCH(M21,Parametros!$A$8:$A$9,0))) | Q21: =IF(P21="","",E21-P21) | S21: =IFERROR(MATCH($A21,Entregas!$A$3:$A$14,0),"") -> 4 | T21: =IF($S21="",0,IF(AND(INDEX(Entregas!$F$3:$F$14,$S21)<>"",INDEX(Entregas!$F$3:$F$14,$S21)>0,$B21<=INDEX(Entregas!$G$3:$G$14,$S21)),1,0)) -> 1
A22: E04 | B22: 5 | C22: =IF($T22=1,INDEX(Entregas!$B$3:$B$14,$S22),"") | D22: =IF($T22=1,INDEX(Entregas!$C$3:$C$14,$S22),"") | E22: =IF($T22=1,INDEX(Entregas!$F$3:$F$14,$S22)/INDEX(Entregas!$G$3:$G$14,$S22),"") | F22: =IF($T22=1,J21+INDEX(Entregas!$I$3:$I$14,$S22),"") | G22: =IF($T22=1,F22+MOD(1-WEEKDAY(F22,3)+7,7),"") | H22: =IF($T22=1,EOMONTH(F22,0)+1,"") | I22: =IF($T22=1,IF(DAY(H22+MOD(1-WEEKDAY(H22,3)+7,7))<3,H22+MOD(1-WEEKDAY(H22,3)+7,7)+7,H22+MOD(1-WEEKDAY(H22,3)+7,7)),"") | J22: =IF($T22=1,IF(INDEX(Entregas!$J$3:$J$14,$S22)="Corrido",F22,IF(DAY(G22)>25,I22,IF(DAY(G22)<3,G22+7,G22))),"") | K22: =IF($T22=1,J22-Parametros!$B$4,"") | N22: =IF(AND($T22=1,L22<>"",M22<>""),J22-L22,"") | O22: =IF(N22="","",IF(N22<0,"desc>venc",IF(N22>INDEX(Parametros!$F$8:$F$9,MATCH(M22,Parametros!$A$8:$A$9,0)),"EXCEDE","ok"))) | P22: =IF(OR(N22="",N22<0),"",E22*(INDEX(Parametros!$B$8:$B$9,MATCH(M22,Parametros!$A$8:$A$9,0))/30)*N22+E22*(INDEX(Parametros!$C$8:$C$9,MATCH(M22,Parametros!$A$8:$A$9,0))*N22+INDEX(Parametros!$D$8:$D$9,MATCH(M22,Parametros!$A$8:$A$9,0)))+INDEX(Parametros!$E$8:$E$9,MATCH(M22,Parametros!$A$8:$A$9,0))) | Q22: =IF(P22="","",E22-P22) | S22: =IFERROR(MATCH($A22,Entregas!$A$3:$A$14,0),"") -> 4 | T22: =IF($S22="",0,IF(AND(INDEX(Entregas!$F$3:$F$14,$S22)<>"",INDEX(Entregas!$F$3:$F$14,$S22)>0,$B22<=INDEX(Entregas!$G$3:$G$14,$S22)),1,0)) -> 0
A23: E05 | B23: 1 | C23: =IF($T23=1,INDEX(Entregas!$B$3:$B$14,$S23),"") -> B4A | D23: =IF($T23=1,INDEX(Entregas!$C$3:$C$14,$S23),"") -> Máscara condicionadora 50ml (ajuda custo) | E23: =IF($T23=1,INDEX(Entregas!$F$3:$F$14,$S23)/INDEX(Entregas!$G$3:$G$14,$S23),"") -> 26250 | F23: =IF($T23=1,INDEX(Entregas!$K$3:$K$14,$S23)+INDEX(Entregas!$H$3:$H$14,$S23),"") -> 46269 | G23: =IF($T23=1,F23+MOD(1-WEEKDAY(F23,3)+7,7),"") -> 46273 | H23: =IF($T23=1,EOMONTH(F23,0)+1,"") -> 46296 | I23: =IF($T23=1,IF(DAY(H23+MOD(1-WEEKDAY(H23,3)+7,7))<3,H23+MOD(1-WEEKDAY(H23,3)+7,7)+7,H23+MOD(1-WEEKDAY(H23,3)+7,7)),"") -> 46301 | J23: =IF($T23=1,IF(INDEX(Entregas!$J$3:$J$14,$S23)="Corrido",F23,IF(DAY(G23)>25,I23,IF(DAY(G23)<3,G23+7,G23))),"") -> 46273 | K23: =IF($T23=1,J23-Parametros!$B$4,"") -> 34 | N23: =IF(AND($T23=1,L23<>"",M23<>""),J23-L23,"") | O23: =IF(N23="","",IF(N23<0,"desc>venc",IF(N23>INDEX(Parametros!$F$8:$F$9,MATCH(M23,Parametros!$A$8:$A$9,0)),"EXCEDE","ok"))) | P23: =IF(OR(N23="",N23<0),"",E23*(INDEX(Parametros!$B$8:$B$9,MATCH(M23,Parametros!$A$8:$A$9,0))/30)*N23+E23*(INDEX(Parametros!$C$8:$C$9,MATCH(M23,Parametros!$A$8:$A$9,0))*N23+INDEX(Parametros!$D$8:$D$9,MATCH(M23,Parametros!$A$8:$A$9,0)))+INDEX(Parametros!$E$8:$E$9,MATCH(M23,Parametros!$A$8:$A$9,0))) | Q23: =IF(P23="","",E23-P23) | S23: =IFERROR(MATCH($A23,Entregas!$A$3:$A$14,0),"") -> 5 | T23: =IF($S23="",0,IF(AND(INDEX(Entregas!$F$3:$F$14,$S23)<>"",INDEX(Entregas!$F$3:$F$14,$S23)>0,$B23<=INDEX(Entregas!$G$3:$G$14,$S23)),1,0)) -> 1
A24: E05 | B24: 2 | C24: =IF($T24=1,INDEX(Entregas!$B$3:$B$14,$S24),"") -> B4A | D24: =IF($T24=1,INDEX(Entregas!$C$3:$C$14,$S24),"") -> Máscara condicionadora 50ml (ajuda custo) | E24: =IF($T24=1,INDEX(Entregas!$F$3:$F$14,$S24)/INDEX(Entregas!$G$3:$G$14,$S24),"") -> 26250 | F24: =IF($T24=1,J23+INDEX(Entregas!$I$3:$I$14,$S24),"") -> 46303 | G24: =IF($T24=1,F24+MOD(1-WEEKDAY(F24,3)+7,7),"") -> 46308 | H24: =IF($T24=1,EOMONTH(F24,0)+1,"") -> 46327 | I24: =IF($T24=1,IF(DAY(H24+MOD(1-WEEKDAY(H24,3)+7,7))<3,H24+MOD(1-WEEKDAY(H24,3)+7,7)+7,H24+MOD(1-WEEKDAY(H24,3)+7,7)),"") -> 46329 | J24: =IF($T24=1,IF(INDEX(Entregas!$J$3:$J$14,$S24)="Corrido",F24,IF(DAY(G24)>25,I24,IF(DAY(G24)<3,G24+7,G24))),"") -> 46308 | K24: =IF($T24=1,J24-Parametros!$B$4,"") -> 69 | N24: =IF(AND($T24=1,L24<>"",M24<>""),J24-L24,"") | O24: =IF(N24="","",IF(N24<0,"desc>venc",IF(N24>INDEX(Parametros!$F$8:$F$9,MATCH(M24,Parametros!$A$8:$A$9,0)),"EXCEDE","ok"))) | P24: =IF(OR(N24="",N24<0),"",E24*(INDEX(Parametros!$B$8:$B$9,MATCH(M24,Parametros!$A$8:$A$9,0))/30)*N24+E24*(INDEX(Parametros!$C$8:$C$9,MATCH(M24,Parametros!$A$8:$A$9,0))*N24+INDEX(Parametros!$D$8:$D$9,MATCH(M24,Parametros!$A$8:$A$9,0)))+INDEX(Parametros!$E$8:$E$9,MATCH(M24,Parametros!$A$8:$A$9,0))) | Q24: =IF(P24="","",E24-P24) | S24: =IFERROR(MATCH($A24,Entregas!$A$3:$A$14,0),"") -> 5 | T24: =IF($S24="",0,IF(AND(INDEX(Entregas!$F$3:$F$14,$S24)<>"",INDEX(Entregas!$F$3:$F$14,$S24)>0,$B24<=INDEX(Entregas!$G$3:$G$14,$S24)),1,0)) -> 1
A25: E05 | B25: 3 | C25: =IF($T25=1,INDEX(Entregas!$B$3:$B$14,$S25),"") -> B4A | D25: =IF($T25=1,INDEX(Entregas!$C$3:$C$14,$S25),"") -> Máscara condicionadora 50ml (ajuda custo) | E25: =IF($T25=1,INDEX(Entregas!$F$3:$F$14,$S25)/INDEX(Entregas!$G$3:$G$14,$S25),"") -> 26250 | F25: =IF($T25=1,J24+INDEX(Entregas!$I$3:$I$14,$S25),"") -> 46338 | G25: =IF($T25=1,F25+MOD(1-WEEKDAY(F25,3)+7,7),"") -> 46343 | H25: =IF($T25=1,EOMONTH(F25,0)+1,"") -> 46357 | I25: =IF($T25=1,IF(DAY(H25+MOD(1-WEEKDAY(H25,3)+7,7))<3,H25+MOD(1-WEEKDAY(H25,3)+7,7)+7,H25+MOD(1-WEEKDAY(H25,3)+7,7)),"") -> 46364 | J25: =IF($T25=1,IF(INDEX(Entregas!$J$3:$J$14,$S25)="Corrido",F25,IF(DAY(G25)>25,I25,IF(DAY(G25)<3,G25+7,G25))),"") -> 46343 | K25: =IF($T25=1,J25-Parametros!$B$4,"") -> 104 | N25: =IF(AND($T25=1,L25<>"",M25<>""),J25-L25,"") | O25: =IF(N25="","",IF(N25<0,"desc>venc",IF(N25>INDEX(Parametros!$F$8:$F$9,MATCH(M25,Parametros!$A$8:$A$9,0)),"EXCEDE","ok"))) | P25: =IF(OR(N25="",N25<0),"",E25*(INDEX(Parametros!$B$8:$B$9,MATCH(M25,Parametros!$A$8:$A$9,0))/30)*N25+E25*(INDEX(Parametros!$C$8:$C$9,MATCH(M25,Parametros!$A$8:$A$9,0))*N25+INDEX(Parametros!$D$8:$D$9,MATCH(M25,Parametros!$A$8:$A$9,0)))+INDEX(Parametros!$E$8:$E$9,MATCH(M25,Parametros!$A$8:$A$9,0))) | Q25: =IF(P25="","",E25-P25) | S25: =IFERROR(MATCH($A25,Entregas!$A$3:$A$14,0),"") -> 5 | T25: =IF($S25="",0,IF(AND(INDEX(Entregas!$F$3:$F$14,$S25)<>"",INDEX(Entregas!$F$3:$F$14,$S25)>0,$B25<=INDEX(Entregas!$G$3:$G$14,$S25)),1,0)) -> 1
A26: E05 | B26: 4 | C26: =IF($T26=1,INDEX(Entregas!$B$3:$B$14,$S26),"") -> B4A | D26: =IF($T26=1,INDEX(Entregas!$C$3:$C$14,$S26),"") -> Máscara condicionadora 50ml (ajuda custo) | E26: =IF($T26=1,INDEX(Entregas!$F$3:$F$14,$S26)/INDEX(Entregas!$G$3:$G$14,$S26),"") -> 26250 | F26: =IF($T26=1,J25+INDEX(Entregas!$I$3:$I$14,$S26),"") -> 46373 | G26: =IF($T26=1,F26+MOD(1-WEEKDAY(F26,3)+7,7),"") -> 46378 | H26: =IF($T26=1,EOMONTH(F26,0)+1,"") -> 46388 | I26: =IF($T26=1,IF(DAY(H26+MOD(1-WEEKDAY(H26,3)+7,7))<3,H26+MOD(1-WEEKDAY(H26,3)+7,7)+7,H26+MOD(1-WEEKDAY(H26,3)+7,7)),"") -> 46392 | J26: =IF($T26=1,IF(INDEX(Entregas!$J$3:$J$14,$S26)="Corrido",F26,IF(DAY(G26)>25,I26,IF(DAY(G26)<3,G26+7,G26))),"") -> 46378 | K26: =IF($T26=1,J26-Parametros!$B$4,"") -> 139 | N26: =IF(AND($T26=1,L26<>"",M26<>""),J26-L26,"") | O26: =IF(N26="","",IF(N26<0,"desc>venc",IF(N26>INDEX(Parametros!$F$8:$F$9,MATCH(M26,Parametros!$A$8:$A$9,0)),"EXCEDE","ok"))) | P26: =IF(OR(N26="",N26<0),"",E26*(INDEX(Parametros!$B$8:$B$9,MATCH(M26,Parametros!$A$8:$A$9,0))/30)*N26+E26*(INDEX(Parametros!$C$8:$C$9,MATCH(M26,Parametros!$A$8:$A$9,0))*N26+INDEX(Parametros!$D$8:$D$9,MATCH(M26,Parametros!$A$8:$A$9,0)))+INDEX(Parametros!$E$8:$E$9,MATCH(M26,Parametros!$A$8:$A$9,0))) | Q26: =IF(P26="","",E26-P26) | S26: =IFERROR(MATCH($A26,Entregas!$A$3:$A$14,0),"") -> 5 | T26: =IF($S26="",0,IF(AND(INDEX(Entregas!$F$3:$F$14,$S26)<>"",INDEX(Entregas!$F$3:$F$14,$S26)>0,$B26<=INDEX(Entregas!$G$3:$G$14,$S26)),1,0)) -> 1
A27: E05 | B27: 5 | C27: =IF($T27=1,INDEX(Entregas!$B$3:$B$14,$S27),"") | D27: =IF($T27=1,INDEX(Entregas!$C$3:$C$14,$S27),"") | E27: =IF($T27=1,INDEX(Entregas!$F$3:$F$14,$S27)/INDEX(Entregas!$G$3:$G$14,$S27),"") | F27: =IF($T27=1,J26+INDEX(Entregas!$I$3:$I$14,$S27),"") | G27: =IF($T27=1,F27+MOD(1-WEEKDAY(F27,3)+7,7),"") | H27: =IF($T27=1,EOMONTH(F27,0)+1,"") | I27: =IF($T27=1,IF(DAY(H27+MOD(1-WEEKDAY(H27,3)+7,7))<3,H27+MOD(1-WEEKDAY(H27,3)+7,7)+7,H27+MOD(1-WEEKDAY(H27,3)+7,7)),"") | J27: =IF($T27=1,IF(INDEX(Entregas!$J$3:$J$14,$S27)="Corrido",F27,IF(DAY(G27)>25,I27,IF(DAY(G27)<3,G27+7,G27))),"") | K27: =IF($T27=1,J27-Parametros!$B$4,"") | N27: =IF(AND($T27=1,L27<>"",M27<>""),J27-L27,"") | O27: =IF(N27="","",IF(N27<0,"desc>venc",IF(N27>INDEX(Parametros!$F$8:$F$9,MATCH(M27,Parametros!$A$8:$A$9,0)),"EXCEDE","ok"))) | P27: =IF(OR(N27="",N27<0),"",E27*(INDEX(Parametros!$B$8:$B$9,MATCH(M27,Parametros!$A$8:$A$9,0))/30)*N27+E27*(INDEX(Parametros!$C$8:$C$9,MATCH(M27,Parametros!$A$8:$A$9,0))*N27+INDEX(Parametros!$D$8:$D$9,MATCH(M27,Parametros!$A$8:$A$9,0)))+INDEX(Parametros!$E$8:$E$9,MATCH(M27,Parametros!$A$8:$A$9,0))) | Q27: =IF(P27="","",E27-P27) | S27: =IFERROR(MATCH($A27,Entregas!$A$3:$A$14,0),"") -> 5 | T27: =IF($S27="",0,IF(AND(INDEX(Entregas!$F$3:$F$14,$S27)<>"",INDEX(Entregas!$F$3:$F$14,$S27)>0,$B27<=INDEX(Entregas!$G$3:$G$14,$S27)),1,0)) -> 0
A28: E06 | B28: 1 | C28: =IF($T28=1,INDEX(Entregas!$B$3:$B$14,$S28),"") -> B4A | D28: =IF($T28=1,INDEX(Entregas!$C$3:$C$14,$S28),"") -> Leave-in 150ml (ajuda custo) | E28: =IF($T28=1,INDEX(Entregas!$F$3:$F$14,$S28)/INDEX(Entregas!$G$3:$G$14,$S28),"") -> 45000 | F28: =IF($T28=1,INDEX(Entregas!$K$3:$K$14,$S28)+INDEX(Entregas!$H$3:$H$14,$S28),"") -> 46330 | G28: =IF($T28=1,F28+MOD(1-WEEKDAY(F28,3)+7,7),"") -> 46336 | H28: =IF($T28=1,EOMONTH(F28,0)+1,"") -> 46357 | I28: =IF($T28=1,IF(DAY(H28+MOD(1-WEEKDAY(H28,3)+7,7))<3,H28+MOD(1-WEEKDAY(H28,3)+7,7)+7,H28+MOD(1-WEEKDAY(H28,3)+7,7)),"") -> 46364 | J28: =IF($T28=1,IF(INDEX(Entregas!$J$3:$J$14,$S28)="Corrido",F28,IF(DAY(G28)>25,I28,IF(DAY(G28)<3,G28+7,G28))),"") -> 46336 | K28: =IF($T28=1,J28-Parametros!$B$4,"") -> 97 | N28: =IF(AND($T28=1,L28<>"",M28<>""),J28-L28,"") | O28: =IF(N28="","",IF(N28<0,"desc>venc",IF(N28>INDEX(Parametros!$F$8:$F$9,MATCH(M28,Parametros!$A$8:$A$9,0)),"EXCEDE","ok"))) | P28: =IF(OR(N28="",N28<0),"",E28*(INDEX(Parametros!$B$8:$B$9,MATCH(M28,Parametros!$A$8:$A$9,0))/30)*N28+E28*(INDEX(Parametros!$C$8:$C$9,MATCH(M28,Parametros!$A$8:$A$9,0))*N28+INDEX(Parametros!$D$8:$D$9,MATCH(M28,Parametros!$A$8:$A$9,0)))+INDEX(Parametros!$E$8:$E$9,MATCH(M28,Parametros!$A$8:$A$9,0))) | Q28: =IF(P28="","",E28-P28) | S28: =IFERROR(MATCH($A28,Entregas!$A$3:$A$14,0),"") -> 6 | T28: =IF($S28="",0,IF(AND(INDEX(Entregas!$F$3:$F$14,$S28)<>"",INDEX(Entregas!$F$3:$F$14,$S28)>0,$B28<=INDEX(Entregas!$G$3:$G$14,$S28)),1,0)) -> 1
A29: E06 | B29: 2 | C29: =IF($T29=1,INDEX(Entregas!$B$3:$B$14,$S29),"") -> B4A | D29: =IF($T29=1,INDEX(Entregas!$C$3:$C$14,$S29),"") -> Leave-in 150ml (ajuda custo) | E29: =IF($T29=1,INDEX(Entregas!$F$3:$F$14,$S29)/INDEX(Entregas!$G$3:$G$14,$S29),"") -> 45000 | F29: =IF($T29=1,J28+INDEX(Entregas!$I$3:$I$14,$S29),"") -> 46366 | G29: =IF($T29=1,F29+MOD(1-WEEKDAY(F29,3)+7,7),"") -> 46371 | H29: =IF($T29=1,EOMONTH(F29,0)+1,"") -> 46388 | I29: =IF($T29=1,IF(DAY(H29+MOD(1-WEEKDAY(H29,3)+7,7))<3,H29+MOD(1-WEEKDAY(H29,3)+7,7)+7,H29+MOD(1-WEEKDAY(H29,3)+7,7)),"") -> 46392 | J29: =IF($T29=1,IF(INDEX(Entregas!$J$3:$J$14,$S29)="Corrido",F29,IF(DAY(G29)>25,I29,IF(DAY(G29)<3,G29+7,G29))),"") -> 46371 | K29: =IF($T29=1,J29-Parametros!$B$4,"") -> 132 | N29: =IF(AND($T29=1,L29<>"",M29<>""),J29-L29,"") | O29: =IF(N29="","",IF(N29<0,"desc>venc",IF(N29>INDEX(Parametros!$F$8:$F$9,MATCH(M29,Parametros!$A$8:$A$9,0)),"EXCEDE","ok"))) | P29: =IF(OR(N29="",N29<0),"",E29*(INDEX(Parametros!$B$8:$B$9,MATCH(M29,Parametros!$A$8:$A$9,0))/30)*N29+E29*(INDEX(Parametros!$C$8:$C$9,MATCH(M29,Parametros!$A$8:$A$9,0))*N29+INDEX(Parametros!$D$8:$D$9,MATCH(M29,Parametros!$A$8:$A$9,0)))+INDEX(Parametros!$E$8:$E$9,MATCH(M29,Parametros!$A$8:$A$9,0))) | Q29: =IF(P29="","",E29-P29) | S29: =IFERROR(MATCH($A29,Entregas!$A$3:$A$14,0),"") -> 6 | T29: =IF($S29="",0,IF(AND(INDEX(Entregas!$F$3:$F$14,$S29)<>"",INDEX(Entregas!$F$3:$F$14,$S29)>0,$B29<=INDEX(Entregas!$G$3:$G$14,$S29)),1,0)) -> 1
A30: E06 | B30: 3 | C30: =IF($T30=1,INDEX(Entregas!$B$3:$B$14,$S30),"") -> B4A | D30: =IF($T30=1,INDEX(Entregas!$C$3:$C$14,$S30),"") -> Leave-in 150ml (ajuda custo) | E30: =IF($T30=1,INDEX(Entregas!$F$3:$F$14,$S30)/INDEX(Entregas!$G$3:$G$14,$S30),"") -> 45000 | F30: =IF($T30=1,J29+INDEX(Entregas!$I$3:$I$14,$S30),"") -> 46401 | G30: =IF($T30=1,F30+MOD(1-WEEKDAY(F30,3)+7,7),"") -> 46406 | H30: =IF($T30=1,EOMONTH(F30,0)+1,"") -> 46419 | I30: =IF($T30=1,IF(DAY(H30+MOD(1-WEEKDAY(H30,3)+7,7))<3,H30+MOD(1-WEEKDAY(H30,3)+7,7)+7,H30+MOD(1-WEEKDAY(H30,3)+7,7)),"") -> 46427 | J30: =IF($T30=1,IF(INDEX(Entregas!$J$3:$J$14,$S30)="Corrido",F30,IF(DAY(G30)>25,I30,IF(DAY(G30)<3,G30+7,G30))),"") -> 46406 | K30: =IF($T30=1,J30-Parametros!$B$4,"") -> 167 | N30: =IF(AND($T30=1,L30<>"",M30<>""),J30-L30,"") | O30: =IF(N30="","",IF(N30<0,"desc>venc",IF(N30>INDEX(Parametros!$F$8:$F$9,MATCH(M30,Parametros!$A$8:$A$9,0)),"EXCEDE","ok"))) | P30: =IF(OR(N30="",N30<0),"",E30*(INDEX(Parametros!$B$8:$B$9,MATCH(M30,Parametros!$A$8:$A$9,0))/30)*N30+E30*(INDEX(Parametros!$C$8:$C$9,MATCH(M30,Parametros!$A$8:$A$9,0))*N30+INDEX(Parametros!$D$8:$D$9,MATCH(M30,Parametros!$A$8:$A$9,0)))+INDEX(Parametros!$E$8:$E$9,MATCH(M30,Parametros!$A$8:$A$9,0))) | Q30: =IF(P30="","",E30-P30) | S30: =IFERROR(MATCH($A30,Entregas!$A$3:$A$14,0),"") -> 6 | T30: =IF($S30="",0,IF(AND(INDEX(Entregas!$F$3:$F$14,$S30)<>"",INDEX(Entregas!$F$3:$F$14,$S30)>0,$B30<=INDEX(Entregas!$G$3:$G$14,$S30)),1,0)) -> 1
A31: E06 | B31: 4 | C31: =IF($T31=1,INDEX(Entregas!$B$3:$B$14,$S31),"") -> B4A | D31: =IF($T31=1,INDEX(Entregas!$C$3:$C$14,$S31),"") -> Leave-in 150ml (ajuda custo) | E31: =IF($T31=1,INDEX(Entregas!$F$3:$F$14,$S31)/INDEX(Entregas!$G$3:$G$14,$S31),"") -> 45000 | F31: =IF($T31=1,J30+INDEX(Entregas!$I$3:$I$14,$S31),"") -> 46436 | G31: =IF($T31=1,F31+MOD(1-WEEKDAY(F31,3)+7,7),"") -> 46441 | H31: =IF($T31=1,EOMONTH(F31,0)+1,"") -> 46447 | I31: =IF($T31=1,IF(DAY(H31+MOD(1-WEEKDAY(H31,3)+7,7))<3,H31+MOD(1-WEEKDAY(H31,3)+7,7)+7,H31+MOD(1-WEEKDAY(H31,3)+7,7)),"") -> 46455 | J31: =IF($T31=1,IF(INDEX(Entregas!$J$3:$J$14,$S31)="Corrido",F31,IF(DAY(G31)>25,I31,IF(DAY(G31)<3,G31+7,G31))),"") -> 46441 | K31: =IF($T31=1,J31-Parametros!$B$4,"") -> 202 | N31: =IF(AND($T31=1,L31<>"",M31<>""),J31-L31,"") | O31: =IF(N31="","",IF(N31<0,"desc>venc",IF(N31>INDEX(Parametros!$F$8:$F$9,MATCH(M31,Parametros!$A$8:$A$9,0)),"EXCEDE","ok"))) | P31: =IF(OR(N31="",N31<0),"",E31*(INDEX(Parametros!$B$8:$B$9,MATCH(M31,Parametros!$A$8:$A$9,0))/30)*N31+E31*(INDEX(Parametros!$C$8:$C$9,MATCH(M31,Parametros!$A$8:$A$9,0))*N31+INDEX(Parametros!$D$8:$D$9,MATCH(M31,Parametros!$A$8:$A$9,0)))+INDEX(Parametros!$E$8:$E$9,MATCH(M31,Parametros!$A$8:$A$9,0))) | Q31: =IF(P31="","",E31-P31) | S31: =IFERROR(MATCH($A31,Entregas!$A$3:$A$14,0),"") -> 6 | T31: =IF($S31="",0,IF(AND(INDEX(Entregas!$F$3:$F$14,$S31)<>"",INDEX(Entregas!$F$3:$F$14,$S31)>0,$B31<=INDEX(Entregas!$G$3:$G$14,$S31)),1,0)) -> 1
A32: E06 | B32: 5 | C32: =IF($T32=1,INDEX(Entregas!$B$3:$B$14,$S32),"") | D32: =IF($T32=1,INDEX(Entregas!$C$3:$C$14,$S32),"") | E32: =IF($T32=1,INDEX(Entregas!$F$3:$F$14,$S32)/INDEX(Entregas!$G$3:$G$14,$S32),"") | F32: =IF($T32=1,J31+INDEX(Entregas!$I$3:$I$14,$S32),"") | G32: =IF($T32=1,F32+MOD(1-WEEKDAY(F32,3)+7,7),"") | H32: =IF($T32=1,EOMONTH(F32,0)+1,"") | I32: =IF($T32=1,IF(DAY(H32+MOD(1-WEEKDAY(H32,3)+7,7))<3,H32+MOD(1-WEEKDAY(H32,3)+7,7)+7,H32+MOD(1-WEEKDAY(H32,3)+7,7)),"") | J32: =IF($T32=1,IF(INDEX(Entregas!$J$3:$J$14,$S32)="Corrido",F32,IF(DAY(G32)>25,I32,IF(DAY(G32)<3,G32+7,G32))),"") | K32: =IF($T32=1,J32-Parametros!$B$4,"") | N32: =IF(AND($T32=1,L32<>"",M32<>""),J32-L32,"") | O32: =IF(N32="","",IF(N32<0,"desc>venc",IF(N32>INDEX(Parametros!$F$8:$F$9,MATCH(M32,Parametros!$A$8:$A$9,0)),"EXCEDE","ok"))) | P32: =IF(OR(N32="",N32<0),"",E32*(INDEX(Parametros!$B$8:$B$9,MATCH(M32,Parametros!$A$8:$A$9,0))/30)*N32+E32*(INDEX(Parametros!$C$8:$C$9,MATCH(M32,Parametros!$A$8:$A$9,0))*N32+INDEX(Parametros!$D$8:$D$9,MATCH(M32,Parametros!$A$8:$A$9,0)))+INDEX(Parametros!$E$8:$E$9,MATCH(M32,Parametros!$A$8:$A$9,0))) | Q32: =IF(P32="","",E32-P32) | S32: =IFERROR(MATCH($A32,Entregas!$A$3:$A$14,0),"") -> 6 | T32: =IF($S32="",0,IF(AND(INDEX(Entregas!$F$3:$F$14,$S32)<>"",INDEX(Entregas!$F$3:$F$14,$S32)>0,$B32<=INDEX(Entregas!$G$3:$G$14,$S32)),1,0)) -> 0
A33: E07 | B33: 1 | C33: =IF($T33=1,INDEX(Entregas!$B$3:$B$14,$S33),"") -> B4A | D33: =IF($T33=1,INDEX(Entregas!$C$3:$C$14,$S33),"") -> Shampoo a seco 150ml (ajuda custo) | E33: =IF($T33=1,INDEX(Entregas!$F$3:$F$14,$S33)/INDEX(Entregas!$G$3:$G$14,$S33),"") -> 52500 | F33: =IF($T33=1,INDEX(Entregas!$K$3:$K$14,$S33)+INDEX(Entregas!$H$3:$H$14,$S33),"") -> 46361 | G33: =IF($T33=1,F33+MOD(1-WEEKDAY(F33,3)+7,7),"") -> 46364 | H33: =IF($T33=1,EOMONTH(F33,0)+1,"") -> 46388 | I33: =IF($T33=1,IF(DAY(H33+MOD(1-WEEKDAY(H33,3)+7,7))<3,H33+MOD(1-WEEKDAY(H33,3)+7,7)+7,H33+MOD(1-WEEKDAY(H33,3)+7,7)),"") -> 46392 | J33: =IF($T33=1,IF(INDEX(Entregas!$J$3:$J$14,$S33)="Corrido",F33,IF(DAY(G33)>25,I33,IF(DAY(G33)<3,G33+7,G33))),"") -> 46364 | K33: =IF($T33=1,J33-Parametros!$B$4,"") -> 125 | N33: =IF(AND($T33=1,L33<>"",M33<>""),J33-L33,"") | O33: =IF(N33="","",IF(N33<0,"desc>venc",IF(N33>INDEX(Parametros!$F$8:$F$9,MATCH(M33,Parametros!$A$8:$A$9,0)),"EXCEDE","ok"))) | P33: =IF(OR(N33="",N33<0),"",E33*(INDEX(Parametros!$B$8:$B$9,MATCH(M33,Parametros!$A$8:$A$9,0))/30)*N33+E33*(INDEX(Parametros!$C$8:$C$9,MATCH(M33,Parametros!$A$8:$A$9,0))*N33+INDEX(Parametros!$D$8:$D$9,MATCH(M33,Parametros!$A$8:$A$9,0)))+INDEX(Parametros!$E$8:$E$9,MATCH(M33,Parametros!$A$8:$A$9,0))) | Q33: =IF(P33="","",E33-P33) | S33: =IFERROR(MATCH($A33,Entregas!$A$3:$A$14,0),"") -> 7 | T33: =IF($S33="",0,IF(AND(INDEX(Entregas!$F$3:$F$14,$S33)<>"",INDEX(Entregas!$F$3:$F$14,$S33)>0,$B33<=INDEX(Entregas!$G$3:$G$14,$S33)),1,0)) -> 1
A34: E07 | B34: 2 | C34: =IF($T34=1,INDEX(Entregas!$B$3:$B$14,$S34),"") -> B4A | D34: =IF($T34=1,INDEX(Entregas!$C$3:$C$14,$S34),"") -> Shampoo a seco 150ml (ajuda custo) | E34: =IF($T34=1,INDEX(Entregas!$F$3:$F$14,$S34)/INDEX(Entregas!$G$3:$G$14,$S34),"") -> 52500 | F34: =IF($T34=1,J33+INDEX(Entregas!$I$3:$I$14,$S34),"") -> 46394 | G34: =IF($T34=1,F34+MOD(1-WEEKDAY(F34,3)+7,7),"") -> 46399 | H34: =IF($T34=1,EOMONTH(F34,0)+1,"") -> 46419 | I34: =IF($T34=1,IF(DAY(H34+MOD(1-WEEKDAY(H34,3)+7,7))<3,H34+MOD(1-WEEKDAY(H34,3)+7,7)+7,H34+MOD(1-WEEKDAY(H34,3)+7,7)),"") -> 46427 | J34: =IF($T34=1,IF(INDEX(Entregas!$J$3:$J$14,$S34)="Corrido",F34,IF(DAY(G34)>25,I34,IF(DAY(G34)<3,G34+7,G34))),"") -> 46399 | K34: =IF($T34=1,J34-Parametros!$B$4,"") -> 160 | N34: =IF(AND($T34=1,L34<>"",M34<>""),J34-L34,"") | O34: =IF(N34="","",IF(N34<0,"desc>venc",IF(N34>INDEX(Parametros!$F$8:$F$9,MATCH(M34,Parametros!$A$8:$A$9,0)),"EXCEDE","ok"))) | P34: =IF(OR(N34="",N34<0),"",E34*(INDEX(Parametros!$B$8:$B$9,MATCH(M34,Parametros!$A$8:$A$9,0))/30)*N34+E34*(INDEX(Parametros!$C$8:$C$9,MATCH(M34,Parametros!$A$8:$A$9,0))*N34+INDEX(Parametros!$D$8:$D$9,MATCH(M34,Parametros!$A$8:$A$9,0)))+INDEX(Parametros!$E$8:$E$9,MATCH(M34,Parametros!$A$8:$A$9,0))) | Q34: =IF(P34="","",E34-P34) | S34: =IFERROR(MATCH($A34,Entregas!$A$3:$A$14,0),"") -> 7 | T34: =IF($S34="",0,IF(AND(INDEX(Entregas!$F$3:$F$14,$S34)<>"",INDEX(Entregas!$F$3:$F$14,$S34)>0,$B34<=INDEX(Entregas!$G$3:$G$14,$S34)),1,0)) -> 1
A35: E07 | B35: 3 | C35: =IF($T35=1,INDEX(Entregas!$B$3:$B$14,$S35),"") -> B4A | D35: =IF($T35=1,INDEX(Entregas!$C$3:$C$14,$S35),"") -> Shampoo a seco 150ml (ajuda custo) | E35: =IF($T35=1,INDEX(Entregas!$F$3:$F$14,$S35)/INDEX(Entregas!$G$3:$G$14,$S35),"") -> 52500 | F35: =IF($T35=1,J34+INDEX(Entregas!$I$3:$I$14,$S35),"") -> 46429 | G35: =IF($T35=1,F35+MOD(1-WEEKDAY(F35,3)+7,7),"") -> 46434 | H35: =IF($T35=1,EOMONTH(F35,0)+1,"") -> 46447 | I35: =IF($T35=1,IF(DAY(H35+MOD(1-WEEKDAY(H35,3)+7,7))<3,H35+MOD(1-WEEKDAY(H35,3)+7,7)+7,H35+MOD(1-WEEKDAY(H35,3)+7,7)),"") -> 46455 | J35: =IF($T35=1,IF(INDEX(Entregas!$J$3:$J$14,$S35)="Corrido",F35,IF(DAY(G35)>25,I35,IF(DAY(G35)<3,G35+7,G35))),"") -> 46434 | K35: =IF($T35=1,J35-Parametros!$B$4,"") -> 195 | N35: =IF(AND($T35=1,L35<>"",M35<>""),J35-L35,"") | O35: =IF(N35="","",IF(N35<0,"desc>venc",IF(N35>INDEX(Parametros!$F$8:$F$9,MATCH(M35,Parametros!$A$8:$A$9,0)),"EXCEDE","ok"))) | P35: =IF(OR(N35="",N35<0),"",E35*(INDEX(Parametros!$B$8:$B$9,MATCH(M35,Parametros!$A$8:$A$9,0))/30)*N35+E35*(INDEX(Parametros!$C$8:$C$9,MATCH(M35,Parametros!$A$8:$A$9,0))*N35+INDEX(Parametros!$D$8:$D$9,MATCH(M35,Parametros!$A$8:$A$9,0)))+INDEX(Parametros!$E$8:$E$9,MATCH(M35,Parametros!$A$8:$A$9,0))) | Q35: =IF(P35="","",E35-P35) | S35: =IFERROR(MATCH($A35,Entregas!$A$3:$A$14,0),"") -> 7 | T35: =IF($S35="",0,IF(AND(INDEX(Entregas!$F$3:$F$14,$S35)<>"",INDEX(Entregas!$F$3:$F$14,$S35)>0,$B35<=INDEX(Entregas!$G$3:$G$14,$S35)),1,0)) -> 1
A36: E07 | B36: 4 | C36: =IF($T36=1,INDEX(Entregas!$B$3:$B$14,$S36),"") -> B4A | D36: =IF($T36=1,INDEX(Entregas!$C$3:$C$14,$S36),"") -> Shampoo a seco 150ml (ajuda custo) | E36: =IF($T36=1,INDEX(Entregas!$F$3:$F$14,$S36)/INDEX(Entregas!$G$3:$G$14,$S36),"") -> 52500 | F36: =IF($T36=1,J35+INDEX(Entregas!$I$3:$I$14,$S36),"") -> 46464 | G36: =IF($T36=1,F36+MOD(1-WEEKDAY(F36,3)+7,7),"") -> 46469 | H36: =IF($T36=1,EOMONTH(F36,0)+1,"") -> 46478 | I36: =IF($T36=1,IF(DAY(H36+MOD(1-WEEKDAY(H36,3)+7,7))<3,H36+MOD(1-WEEKDAY(H36,3)+7,7)+7,H36+MOD(1-WEEKDAY(H36,3)+7,7)),"") -> 46483 | J36: =IF($T36=1,IF(INDEX(Entregas!$J$3:$J$14,$S36)="Corrido",F36,IF(DAY(G36)>25,I36,IF(DAY(G36)<3,G36+7,G36))),"") -> 46469 | K36: =IF($T36=1,J36-Parametros!$B$4,"") -> 230 | N36: =IF(AND($T36=1,L36<>"",M36<>""),J36-L36,"") | O36: =IF(N36="","",IF(N36<0,"desc>venc",IF(N36>INDEX(Parametros!$F$8:$F$9,MATCH(M36,Parametros!$A$8:$A$9,0)),"EXCEDE","ok"))) | P36: =IF(OR(N36="",N36<0),"",E36*(INDEX(Parametros!$B$8:$B$9,MATCH(M36,Parametros!$A$8:$A$9,0))/30)*N36+E36*(INDEX(Parametros!$C$8:$C$9,MATCH(M36,Parametros!$A$8:$A$9,0))*N36+INDEX(Parametros!$D$8:$D$9,MATCH(M36,Parametros!$A$8:$A$9,0)))+INDEX(Parametros!$E$8:$E$9,MATCH(M36,Parametros!$A$8:$A$9,0))) | Q36: =IF(P36="","",E36-P36) | S36: =IFERROR(MATCH($A36,Entregas!$A$3:$A$14,0),"") -> 7 | T36: =IF($S36="",0,IF(AND(INDEX(Entregas!$F$3:$F$14,$S36)<>"",INDEX(Entregas!$F$3:$F$14,$S36)>0,$B36<=INDEX(Entregas!$G$3:$G$14,$S36)),1,0)) -> 1
A37: E07 | B37: 5 | C37: =IF($T37=1,INDEX(Entregas!$B$3:$B$14,$S37),"") | D37: =IF($T37=1,INDEX(Entregas!$C$3:$C$14,$S37),"") | E37: =IF($T37=1,INDEX(Entregas!$F$3:$F$14,$S37)/INDEX(Entregas!$G$3:$G$14,$S37),"") | F37: =IF($T37=1,J36+INDEX(Entregas!$I$3:$I$14,$S37),"") | G37: =IF($T37=1,F37+MOD(1-WEEKDAY(F37,3)+7,7),"") | H37: =IF($T37=1,EOMONTH(F37,0)+1,"") | I37: =IF($T37=1,IF(DAY(H37+MOD(1-WEEKDAY(H37,3)+7,7))<3,H37+MOD(1-WEEKDAY(H37,3)+7,7)+7,H37+MOD(1-WEEKDAY(H37,3)+7,7)),"") | J37: =IF($T37=1,IF(INDEX(Entregas!$J$3:$J$14,$S37)="Corrido",F37,IF(DAY(G37)>25,I37,IF(DAY(G37)<3,G37+7,G37))),"") | K37: =IF($T37=1,J37-Parametros!$B$4,"") | N37: =IF(AND($T37=1,L37<>"",M37<>""),J37-L37,"") | O37: =IF(N37="","",IF(N37<0,"desc>venc",IF(N37>INDEX(Parametros!$F$8:$F$9,MATCH(M37,Parametros!$A$8:$A$9,0)),"EXCEDE","ok"))) | P37: =IF(OR(N37="",N37<0),"",E37*(INDEX(Parametros!$B$8:$B$9,MATCH(M37,Parametros!$A$8:$A$9,0))/30)*N37+E37*(INDEX(Parametros!$C$8:$C$9,MATCH(M37,Parametros!$A$8:$A$9,0))*N37+INDEX(Parametros!$D$8:$D$9,MATCH(M37,Parametros!$A$8:$A$9,0)))+INDEX(Parametros!$E$8:$E$9,MATCH(M37,Parametros!$A$8:$A$9,0))) | Q37: =IF(P37="","",E37-P37) | S37: =IFERROR(MATCH($A37,Entregas!$A$3:$A$14,0),"") -> 7 | T37: =IF($S37="",0,IF(AND(INDEX(Entregas!$F$3:$F$14,$S37)<>"",INDEX(Entregas!$F$3:$F$14,$S37)>0,$B37<=INDEX(Entregas!$G$3:$G$14,$S37)),1,0)) -> 0
A38: E08 | B38: 1 | C38: =IF($T38=1,INDEX(Entregas!$B$3:$B$14,$S38),"") -> B4A | D38: =IF($T38=1,INDEX(Entregas!$C$3:$C$14,$S38),"") -> Booster Antifrizz 15ml (ajuda custo) | E38: =IF($T38=1,INDEX(Entregas!$F$3:$F$14,$S38)/INDEX(Entregas!$G$3:$G$14,$S38),"") -> 60000 | F38: =IF($T38=1,INDEX(Entregas!$K$3:$K$14,$S38)+INDEX(Entregas!$H$3:$H$14,$S38),"") -> 46391 | G38: =IF($T38=1,F38+MOD(1-WEEKDAY(F38,3)+7,7),"") -> 46392 | H38: =IF($T38=1,EOMONTH(F38,0)+1,"") -> 46419 | I38: =IF($T38=1,IF(DAY(H38+MOD(1-WEEKDAY(H38,3)+7,7))<3,H38+MOD(1-WEEKDAY(H38,3)+7,7)+7,H38+MOD(1-WEEKDAY(H38,3)+7,7)),"") -> 46427 | J38: =IF($T38=1,IF(INDEX(Entregas!$J$3:$J$14,$S38)="Corrido",F38,IF(DAY(G38)>25,I38,IF(DAY(G38)<3,G38+7,G38))),"") -> 46392 | K38: =IF($T38=1,J38-Parametros!$B$4,"") -> 153 | N38: =IF(AND($T38=1,L38<>"",M38<>""),J38-L38,"") | O38: =IF(N38="","",IF(N38<0,"desc>venc",IF(N38>INDEX(Parametros!$F$8:$F$9,MATCH(M38,Parametros!$A$8:$A$9,0)),"EXCEDE","ok"))) | P38: =IF(OR(N38="",N38<0),"",E38*(INDEX(Parametros!$B$8:$B$9,MATCH(M38,Parametros!$A$8:$A$9,0))/30)*N38+E38*(INDEX(Parametros!$C$8:$C$9,MATCH(M38,Parametros!$A$8:$A$9,0))*N38+INDEX(Parametros!$D$8:$D$9,MATCH(M38,Parametros!$A$8:$A$9,0)))+INDEX(Parametros!$E$8:$E$9,MATCH(M38,Parametros!$A$8:$A$9,0))) | Q38: =IF(P38="","",E38-P38) | S38: =IFERROR(MATCH($A38,Entregas!$A$3:$A$14,0),"") -> 8 | T38: =IF($S38="",0,IF(AND(INDEX(Entregas!$F$3:$F$14,$S38)<>"",INDEX(Entregas!$F$3:$F$14,$S38)>0,$B38<=INDEX(Entregas!$G$3:$G$14,$S38)),1,0)) -> 1
A39: E08 | B39: 2 | C39: =IF($T39=1,INDEX(Entregas!$B$3:$B$14,$S39),"") -> B4A | D39: =IF($T39=1,INDEX(Entregas!$C$3:$C$14,$S39),"") -> Booster Antifrizz 15ml (ajuda custo) | E39: =IF($T39=1,INDEX(Entregas!$F$3:$F$14,$S39)/INDEX(Entregas!$G$3:$G$14,$S39),"") -> 60000 | F39: =IF($T39=1,J38+INDEX(Entregas!$I$3:$I$14,$S39),"") -> 46422 | G39: =IF($T39=1,F39+MOD(1-WEEKDAY(F39,3)+7,7),"") -> 46427 | H39: =IF($T39=1,EOMONTH(F39,0)+1,"") -> 46447 | I39: =IF($T39=1,IF(DAY(H39+MOD(1-WEEKDAY(H39,3)+7,7))<3,H39+MOD(1-WEEKDAY(H39,3)+7,7)+7,H39+MOD(1-WEEKDAY(H39,3)+7,7)),"") -> 46455 | J39: =IF($T39=1,IF(INDEX(Entregas!$J$3:$J$14,$S39)="Corrido",F39,IF(DAY(G39)>25,I39,IF(DAY(G39)<3,G39+7,G39))),"") -> 46427 | K39: =IF($T39=1,J39-Parametros!$B$4,"") -> 188 | N39: =IF(AND($T39=1,L39<>"",M39<>""),J39-L39,"") | O39: =IF(N39="","",IF(N39<0,"desc>venc",IF(N39>INDEX(Parametros!$F$8:$F$9,MATCH(M39,Parametros!$A$8:$A$9,0)),"EXCEDE","ok"))) | P39: =IF(OR(N39="",N39<0),"",E39*(INDEX(Parametros!$B$8:$B$9,MATCH(M39,Parametros!$A$8:$A$9,0))/30)*N39+E39*(INDEX(Parametros!$C$8:$C$9,MATCH(M39,Parametros!$A$8:$A$9,0))*N39+INDEX(Parametros!$D$8:$D$9,MATCH(M39,Parametros!$A$8:$A$9,0)))+INDEX(Parametros!$E$8:$E$9,MATCH(M39,Parametros!$A$8:$A$9,0))) | Q39: =IF(P39="","",E39-P39) | S39: =IFERROR(MATCH($A39,Entregas!$A$3:$A$14,0),"") -> 8 | T39: =IF($S39="",0,IF(AND(INDEX(Entregas!$F$3:$F$14,$S39)<>"",INDEX(Entregas!$F$3:$F$14,$S39)>0,$B39<=INDEX(Entregas!$G$3:$G$14,$S39)),1,0)) -> 1
A40: E08 | B40: 3 | C40: =IF($T40=1,INDEX(Entregas!$B$3:$B$14,$S40),"") -> B4A | D40: =IF($T40=1,INDEX(Entregas!$C$3:$C$14,$S40),"") -> Booster Antifrizz 15ml (ajuda custo) | E40: =IF($T40=1,INDEX(Entregas!$F$3:$F$14,$S40)/INDEX(Entregas!$G$3:$G$14,$S40),"") -> 60000 | F40: =IF($T40=1,J39+INDEX(Entregas!$I$3:$I$14,$S40),"") -> 46457 | G40: =IF($T40=1,F40+MOD(1-WEEKDAY(F40,3)+7,7),"") -> 46462 | H40: =IF($T40=1,EOMONTH(F40,0)+1,"") -> 46478 | I40: =IF($T40=1,IF(DAY(H40+MOD(1-WEEKDAY(H40,3)+7,7))<3,H40+MOD(1-WEEKDAY(H40,3)+7,7)+7,H40+MOD(1-WEEKDAY(H40,3)+7,7)),"") -> 46483 | J40: =IF($T40=1,IF(INDEX(Entregas!$J$3:$J$14,$S40)="Corrido",F40,IF(DAY(G40)>25,I40,IF(DAY(G40)<3,G40+7,G40))),"") -> 46462 | K40: =IF($T40=1,J40-Parametros!$B$4,"") -> 223 | N40: =IF(AND($T40=1,L40<>"",M40<>""),J40-L40,"") | O40: =IF(N40="","",IF(N40<0,"desc>venc",IF(N40>INDEX(Parametros!$F$8:$F$9,MATCH(M40,Parametros!$A$8:$A$9,0)),"EXCEDE","ok"))) | P40: =IF(OR(N40="",N40<0),"",E40*(INDEX(Parametros!$B$8:$B$9,MATCH(M40,Parametros!$A$8:$A$9,0))/30)*N40+E40*(INDEX(Parametros!$C$8:$C$9,MATCH(M40,Parametros!$A$8:$A$9,0))*N40+INDEX(Parametros!$D$8:$D$9,MATCH(M40,Parametros!$A$8:$A$9,0)))+INDEX(Parametros!$E$8:$E$9,MATCH(M40,Parametros!$A$8:$A$9,0))) | Q40: =IF(P40="","",E40-P40) | S40: =IFERROR(MATCH($A40,Entregas!$A$3:$A$14,0),"") -> 8 | T40: =IF($S40="",0,IF(AND(INDEX(Entregas!$F$3:$F$14,$S40)<>"",INDEX(Entregas!$F$3:$F$14,$S40)>0,$B40<=INDEX(Entregas!$G$3:$G$14,$S40)),1,0)) -> 1
A41: E08 | B41: 4 | C41: =IF($T41=1,INDEX(Entregas!$B$3:$B$14,$S41),"") -> B4A | D41: =IF($T41=1,INDEX(Entregas!$C$3:$C$14,$S41),"") -> Booster Antifrizz 15ml (ajuda custo) | E41: =IF($T41=1,INDEX(Entregas!$F$3:$F$14,$S41)/INDEX(Entregas!$G$3:$G$14,$S41),"") -> 60000 | F41: =IF($T41=1,J40+INDEX(Entregas!$I$3:$I$14,$S41),"") -> 46492 | G41: =IF($T41=1,F41+MOD(1-WEEKDAY(F41,3)+7,7),"") -> 46497 | H41: =IF($T41=1,EOMONTH(F41,0)+1,"") -> 46508 | I41: =IF($T41=1,IF(DAY(H41+MOD(1-WEEKDAY(H41,3)+7,7))<3,H41+MOD(1-WEEKDAY(H41,3)+7,7)+7,H41+MOD(1-WEEKDAY(H41,3)+7,7)),"") -> 46511 | J41: =IF($T41=1,IF(INDEX(Entregas!$J$3:$J$14,$S41)="Corrido",F41,IF(DAY(G41)>25,I41,IF(DAY(G41)<3,G41+7,G41))),"") -> 46497 | K41: =IF($T41=1,J41-Parametros!$B$4,"") -> 258 | N41: =IF(AND($T41=1,L41<>"",M41<>""),J41-L41,"") | O41: =IF(N41="","",IF(N41<0,"desc>venc",IF(N41>INDEX(Parametros!$F$8:$F$9,MATCH(M41,Parametros!$A$8:$A$9,0)),"EXCEDE","ok"))) | P41: =IF(OR(N41="",N41<0),"",E41*(INDEX(Parametros!$B$8:$B$9,MATCH(M41,Parametros!$A$8:$A$9,0))/30)*N41+E41*(INDEX(Parametros!$C$8:$C$9,MATCH(M41,Parametros!$A$8:$A$9,0))*N41+INDEX(Parametros!$D$8:$D$9,MATCH(M41,Parametros!$A$8:$A$9,0)))+INDEX(Parametros!$E$8:$E$9,MATCH(M41,Parametros!$A$8:$A$9,0))) | Q41: =IF(P41="","",E41-P41) | S41: =IFERROR(MATCH($A41,Entregas!$A$3:$A$14,0),"") -> 8 | T41: =IF($S41="",0,IF(AND(INDEX(Entregas!$F$3:$F$14,$S41)<>"",INDEX(Entregas!$F$3:$F$14,$S41)>0,$B41<=INDEX(Entregas!$G$3:$G$14,$S41)),1,0)) -> 1
A42: E08 | B42: 5 | C42: =IF($T42=1,INDEX(Entregas!$B$3:$B$14,$S42),"") | D42: =IF($T42=1,INDEX(Entregas!$C$3:$C$14,$S42),"") | E42: =IF($T42=1,INDEX(Entregas!$F$3:$F$14,$S42)/INDEX(Entregas!$G$3:$G$14,$S42),"") | F42: =IF($T42=1,J41+INDEX(Entregas!$I$3:$I$14,$S42),"") | G42: =IF($T42=1,F42+MOD(1-WEEKDAY(F42,3)+7,7),"") | H42: =IF($T42=1,EOMONTH(F42,0)+1,"") | I42: =IF($T42=1,IF(DAY(H42+MOD(1-WEEKDAY(H42,3)+7,7))<3,H42+MOD(1-WEEKDAY(H42,3)+7,7)+7,H42+MOD(1-WEEKDAY(H42,3)+7,7)),"") | J42: =IF($T42=1,IF(INDEX(Entregas!$J$3:$J$14,$S42)="Corrido",F42,IF(DAY(G42)>25,I42,IF(DAY(G42)<3,G42+7,G42))),"") | K42: =IF($T42=1,J42-Parametros!$B$4,"") | N42: =IF(AND($T42=1,L42<>"",M42<>""),J42-L42,"") | O42: =IF(N42="","",IF(N42<0,"desc>venc",IF(N42>INDEX(Parametros!$F$8:$F$9,MATCH(M42,Parametros!$A$8:$A$9,0)),"EXCEDE","ok"))) | P42: =IF(OR(N42="",N42<0),"",E42*(INDEX(Parametros!$B$8:$B$9,MATCH(M42,Parametros!$A$8:$A$9,0))/30)*N42+E42*(INDEX(Parametros!$C$8:$C$9,MATCH(M42,Parametros!$A$8:$A$9,0))*N42+INDEX(Parametros!$D$8:$D$9,MATCH(M42,Parametros!$A$8:$A$9,0)))+INDEX(Parametros!$E$8:$E$9,MATCH(M42,Parametros!$A$8:$A$9,0))) | Q42: =IF(P42="","",E42-P42) | S42: =IFERROR(MATCH($A42,Entregas!$A$3:$A$14,0),"") -> 8 | T42: =IF($S42="",0,IF(AND(INDEX(Entregas!$F$3:$F$14,$S42)<>"",INDEX(Entregas!$F$3:$F$14,$S42)>0,$B42<=INDEX(Entregas!$G$3:$G$14,$S42)),1,0)) -> 0
A43: E09 | B43: 1 | C43: =IF($T43=1,INDEX(Entregas!$B$3:$B$14,$S43),"") | D43: =IF($T43=1,INDEX(Entregas!$C$3:$C$14,$S43),"") | E43: =IF($T43=1,INDEX(Entregas!$F$3:$F$14,$S43)/INDEX(Entregas!$G$3:$G$14,$S43),"") | F43: =IF($T43=1,INDEX(Entregas!$K$3:$K$14,$S43)+INDEX(Entregas!$H$3:$H$14,$S43),"") | G43: =IF($T43=1,F43+MOD(1-WEEKDAY(F43,3)+7,7),"") | H43: =IF($T43=1,EOMONTH(F43,0)+1,"") | I43: =IF($T43=1,IF(DAY(H43+MOD(1-WEEKDAY(H43,3)+7,7))<3,H43+MOD(1-WEEKDAY(H43,3)+7,7)+7,H43+MOD(1-WEEKDAY(H43,3)+7,7)),"") | J43: =IF($T43=1,IF(INDEX(Entregas!$J$3:$J$14,$S43)="Corrido",F43,IF(DAY(G43)>25,I43,IF(DAY(G43)<3,G43+7,G43))),"") | K43: =IF($T43=1,J43-Parametros!$B$4,"") | N43: =IF(AND($T43=1,L43<>"",M43<>""),J43-L43,"") | O43: =IF(N43="","",IF(N43<0,"desc>venc",IF(N43>INDEX(Parametros!$F$8:$F$9,MATCH(M43,Parametros!$A$8:$A$9,0)),"EXCEDE","ok"))) | P43: =IF(OR(N43="",N43<0),"",E43*(INDEX(Parametros!$B$8:$B$9,MATCH(M43,Parametros!$A$8:$A$9,0))/30)*N43+E43*(INDEX(Parametros!$C$8:$C$9,MATCH(M43,Parametros!$A$8:$A$9,0))*N43+INDEX(Parametros!$D$8:$D$9,MATCH(M43,Parametros!$A$8:$A$9,0)))+INDEX(Parametros!$E$8:$E$9,MATCH(M43,Parametros!$A$8:$A$9,0))) | Q43: =IF(P43="","",E43-P43) | S43: =IFERROR(MATCH($A43,Entregas!$A$3:$A$14,0),"") -> 9 | T43: =IF($S43="",0,IF(AND(INDEX(Entregas!$F$3:$F$14,$S43)<>"",INDEX(Entregas!$F$3:$F$14,$S43)>0,$B43<=INDEX(Entregas!$G$3:$G$14,$S43)),1,0)) -> 0
A44: E09 | B44: 2 | C44: =IF($T44=1,INDEX(Entregas!$B$3:$B$14,$S44),"") | D44: =IF($T44=1,INDEX(Entregas!$C$3:$C$14,$S44),"") | E44: =IF($T44=1,INDEX(Entregas!$F$3:$F$14,$S44)/INDEX(Entregas!$G$3:$G$14,$S44),"") | F44: =IF($T44=1,J43+INDEX(Entregas!$I$3:$I$14,$S44),"") | G44: =IF($T44=1,F44+MOD(1-WEEKDAY(F44,3)+7,7),"") | H44: =IF($T44=1,EOMONTH(F44,0)+1,"") | I44: =IF($T44=1,IF(DAY(H44+MOD(1-WEEKDAY(H44,3)+7,7))<3,H44+MOD(1-WEEKDAY(H44,3)+7,7)+7,H44+MOD(1-WEEKDAY(H44,3)+7,7)),"") | J44: =IF($T44=1,IF(INDEX(Entregas!$J$3:$J$14,$S44)="Corrido",F44,IF(DAY(G44)>25,I44,IF(DAY(G44)<3,G44+7,G44))),"") | K44: =IF($T44=1,J44-Parametros!$B$4,"") | N44: =IF(AND($T44=1,L44<>"",M44<>""),J44-L44,"") | O44: =IF(N44="","",IF(N44<0,"desc>venc",IF(N44>INDEX(Parametros!$F$8:$F$9,MATCH(M44,Parametros!$A$8:$A$9,0)),"EXCEDE","ok"))) | P44: =IF(OR(N44="",N44<0),"",E44*(INDEX(Parametros!$B$8:$B$9,MATCH(M44,Parametros!$A$8:$A$9,0))/30)*N44+E44*(INDEX(Parametros!$C$8:$C$9,MATCH(M44,Parametros!$A$8:$A$9,0))*N44+INDEX(Parametros!$D$8:$D$9,MATCH(M44,Parametros!$A$8:$A$9,0)))+INDEX(Parametros!$E$8:$E$9,MATCH(M44,Parametros!$A$8:$A$9,0))) | Q44: =IF(P44="","",E44-P44) | S44: =IFERROR(MATCH($A44,Entregas!$A$3:$A$14,0),"") -> 9 | T44: =IF($S44="",0,IF(AND(INDEX(Entregas!$F$3:$F$14,$S44)<>"",INDEX(Entregas!$F$3:$F$14,$S44)>0,$B44<=INDEX(Entregas!$G$3:$G$14,$S44)),1,0)) -> 0
A45: E09 | B45: 3 | C45: =IF($T45=1,INDEX(Entregas!$B$3:$B$14,$S45),"") | D45: =IF($T45=1,INDEX(Entregas!$C$3:$C$14,$S45),"") | E45: =IF($T45=1,INDEX(Entregas!$F$3:$F$14,$S45)/INDEX(Entregas!$G$3:$G$14,$S45),"") | F45: =IF($T45=1,J44+INDEX(Entregas!$I$3:$I$14,$S45),"") | G45: =IF($T45=1,F45+MOD(1-WEEKDAY(F45,3)+7,7),"") | H45: =IF($T45=1,EOMONTH(F45,0)+1,"") | I45: =IF($T45=1,IF(DAY(H45+MOD(1-WEEKDAY(H45,3)+7,7))<3,H45+MOD(1-WEEKDAY(H45,3)+7,7)+7,H45+MOD(1-WEEKDAY(H45,3)+7,7)),"") | J45: =IF($T45=1,IF(INDEX(Entregas!$J$3:$J$14,$S45)="Corrido",F45,IF(DAY(G45)>25,I45,IF(DAY(G45)<3,G45+7,G45))),"") | K45: =IF($T45=1,J45-Parametros!$B$4,"") | N45: =IF(AND($T45=1,L45<>"",M45<>""),J45-L45,"") | O45: =IF(N45="","",IF(N45<0,"desc>venc",IF(N45>INDEX(Parametros!$F$8:$F$9,MATCH(M45,Parametros!$A$8:$A$9,0)),"EXCEDE","ok"))) | P45: =IF(OR(N45="",N45<0),"",E45*(INDEX(Parametros!$B$8:$B$9,MATCH(M45,Parametros!$A$8:$A$9,0))/30)*N45+E45*(INDEX(Parametros!$C$8:$C$9,MATCH(M45,Parametros!$A$8:$A$9,0))*N45+INDEX(Parametros!$D$8:$D$9,MATCH(M45,Parametros!$A$8:$A$9,0)))+INDEX(Parametros!$E$8:$E$9,MATCH(M45,Parametros!$A$8:$A$9,0))) | Q45: =IF(P45="","",E45-P45) | S45: =IFERROR(MATCH($A45,Entregas!$A$3:$A$14,0),"") -> 9 | T45: =IF($S45="",0,IF(AND(INDEX(Entregas!$F$3:$F$14,$S45)<>"",INDEX(Entregas!$F$3:$F$14,$S45)>0,$B45<=INDEX(Entregas!$G$3:$G$14,$S45)),1,0)) -> 0
A46: E09 | B46: 4 | C46: =IF($T46=1,INDEX(Entregas!$B$3:$B$14,$S46),"") | D46: =IF($T46=1,INDEX(Entregas!$C$3:$C$14,$S46),"") | E46: =IF($T46=1,INDEX(Entregas!$F$3:$F$14,$S46)/INDEX(Entregas!$G$3:$G$14,$S46),"") | F46: =IF($T46=1,J45+INDEX(Entregas!$I$3:$I$14,$S46),"") | G46: =IF($T46=1,F46+MOD(1-WEEKDAY(F46,3)+7,7),"") | H46: =IF($T46=1,EOMONTH(F46,0)+1,"") | I46: =IF($T46=1,IF(DAY(H46+MOD(1-WEEKDAY(H46,3)+7,7))<3,H46+MOD(1-WEEKDAY(H46,3)+7,7)+7,H46+MOD(1-WEEKDAY(H46,3)+7,7)),"") | J46: =IF($T46=1,IF(INDEX(Entregas!$J$3:$J$14,$S46)="Corrido",F46,IF(DAY(G46)>25,I46,IF(DAY(G46)<3,G46+7,G46))),"") | K46: =IF($T46=1,J46-Parametros!$B$4,"") | N46: =IF(AND($T46=1,L46<>"",M46<>""),J46-L46,"") | O46: =IF(N46="","",IF(N46<0,"desc>venc",IF(N46>INDEX(Parametros!$F$8:$F$9,MATCH(M46,Parametros!$A$8:$A$9,0)),"EXCEDE","ok"))) | P46: =IF(OR(N46="",N46<0),"",E46*(INDEX(Parametros!$B$8:$B$9,MATCH(M46,Parametros!$A$8:$A$9,0))/30)*N46+E46*(INDEX(Parametros!$C$8:$C$9,MATCH(M46,Parametros!$A$8:$A$9,0))*N46+INDEX(Parametros!$D$8:$D$9,MATCH(M46,Parametros!$A$8:$A$9,0)))+INDEX(Parametros!$E$8:$E$9,MATCH(M46,Parametros!$A$8:$A$9,0))) | Q46: =IF(P46="","",E46-P46) | S46: =IFERROR(MATCH($A46,Entregas!$A$3:$A$14,0),"") -> 9 | T46: =IF($S46="",0,IF(AND(INDEX(Entregas!$F$3:$F$14,$S46)<>"",INDEX(Entregas!$F$3:$F$14,$S46)>0,$B46<=INDEX(Entregas!$G$3:$G$14,$S46)),1,0)) -> 0
A47: E09 | B47: 5 | C47: =IF($T47=1,INDEX(Entregas!$B$3:$B$14,$S47),"") | D47: =IF($T47=1,INDEX(Entregas!$C$3:$C$14,$S47),"") | E47: =IF($T47=1,INDEX(Entregas!$F$3:$F$14,$S47)/INDEX(Entregas!$G$3:$G$14,$S47),"") | F47: =IF($T47=1,J46+INDEX(Entregas!$I$3:$I$14,$S47),"") | G47: =IF($T47=1,F47+MOD(1-WEEKDAY(F47,3)+7,7),"") | H47: =IF($T47=1,EOMONTH(F47,0)+1,"") | I47: =IF($T47=1,IF(DAY(H47+MOD(1-WEEKDAY(H47,3)+7,7))<3,H47+MOD(1-WEEKDAY(H47,3)+7,7)+7,H47+MOD(1-WEEKDAY(H47,3)+7,7)),"") | J47: =IF($T47=1,IF(INDEX(Entregas!$J$3:$J$14,$S47)="Corrido",F47,IF(DAY(G47)>25,I47,IF(DAY(G47)<3,G47+7,G47))),"") | K47: =IF($T47=1,J47-Parametros!$B$4,"") | N47: =IF(AND($T47=1,L47<>"",M47<>""),J47-L47,"") | O47: =IF(N47="","",IF(N47<0,"desc>venc",IF(N47>INDEX(Parametros!$F$8:$F$9,MATCH(M47,Parametros!$A$8:$A$9,0)),"EXCEDE","ok"))) | P47: =IF(OR(N47="",N47<0),"",E47*(INDEX(Parametros!$B$8:$B$9,MATCH(M47,Parametros!$A$8:$A$9,0))/30)*N47+E47*(INDEX(Parametros!$C$8:$C$9,MATCH(M47,Parametros!$A$8:$A$9,0))*N47+INDEX(Parametros!$D$8:$D$9,MATCH(M47,Parametros!$A$8:$A$9,0)))+INDEX(Parametros!$E$8:$E$9,MATCH(M47,Parametros!$A$8:$A$9,0))) | Q47: =IF(P47="","",E47-P47) | S47: =IFERROR(MATCH($A47,Entregas!$A$3:$A$14,0),"") -> 9 | T47: =IF($S47="",0,IF(AND(INDEX(Entregas!$F$3:$F$14,$S47)<>"",INDEX(Entregas!$F$3:$F$14,$S47)>0,$B47<=INDEX(Entregas!$G$3:$G$14,$S47)),1,0)) -> 0
A48: E10 | B48: 1 | C48: =IF($T48=1,INDEX(Entregas!$B$3:$B$14,$S48),"") | D48: =IF($T48=1,INDEX(Entregas!$C$3:$C$14,$S48),"") | E48: =IF($T48=1,INDEX(Entregas!$F$3:$F$14,$S48)/INDEX(Entregas!$G$3:$G$14,$S48),"") | F48: =IF($T48=1,INDEX(Entregas!$K$3:$K$14,$S48)+INDEX(Entregas!$H$3:$H$14,$S48),"") | G48: =IF($T48=1,F48+MOD(1-WEEKDAY(F48,3)+7,7),"") | H48: =IF($T48=1,EOMONTH(F48,0)+1,"") | I48: =IF($T48=1,IF(DAY(H48+MOD(1-WEEKDAY(H48,3)+7,7))<3,H48+MOD(1-WEEKDAY(H48,3)+7,7)+7,H48+MOD(1-WEEKDAY(H48,3)+7,7)),"") | J48: =IF($T48=1,IF(INDEX(Entregas!$J$3:$J$14,$S48)="Corrido",F48,IF(DAY(G48)>25,I48,IF(DAY(G48)<3,G48+7,G48))),"") | K48: =IF($T48=1,J48-Parametros!$B$4,"") | N48: =IF(AND($T48=1,L48<>"",M48<>""),J48-L48,"") | O48: =IF(N48="","",IF(N48<0,"desc>venc",IF(N48>INDEX(Parametros!$F$8:$F$9,MATCH(M48,Parametros!$A$8:$A$9,0)),"EXCEDE","ok"))) | P48: =IF(OR(N48="",N48<0),"",E48*(INDEX(Parametros!$B$8:$B$9,MATCH(M48,Parametros!$A$8:$A$9,0))/30)*N48+E48*(INDEX(Parametros!$C$8:$C$9,MATCH(M48,Parametros!$A$8:$A$9,0))*N48+INDEX(Parametros!$D$8:$D$9,MATCH(M48,Parametros!$A$8:$A$9,0)))+INDEX(Parametros!$E$8:$E$9,MATCH(M48,Parametros!$A$8:$A$9,0))) | Q48: =IF(P48="","",E48-P48) | S48: =IFERROR(MATCH($A48,Entregas!$A$3:$A$14,0),"") -> 10 | T48: =IF($S48="",0,IF(AND(INDEX(Entregas!$F$3:$F$14,$S48)<>"",INDEX(Entregas!$F$3:$F$14,$S48)>0,$B48<=INDEX(Entregas!$G$3:$G$14,$S48)),1,0)) -> 0
A49: E10 | B49: 2 | C49: =IF($T49=1,INDEX(Entregas!$B$3:$B$14,$S49),"") | D49: =IF($T49=1,INDEX(Entregas!$C$3:$C$14,$S49),"") | E49: =IF($T49=1,INDEX(Entregas!$F$3:$F$14,$S49)/INDEX(Entregas!$G$3:$G$14,$S49),"") | F49: =IF($T49=1,J48+INDEX(Entregas!$I$3:$I$14,$S49),"") | G49: =IF($T49=1,F49+MOD(1-WEEKDAY(F49,3)+7,7),"") | H49: =IF($T49=1,EOMONTH(F49,0)+1,"") | I49: =IF($T49=1,IF(DAY(H49+MOD(1-WEEKDAY(H49,3)+7,7))<3,H49+MOD(1-WEEKDAY(H49,3)+7,7)+7,H49+MOD(1-WEEKDAY(H49,3)+7,7)),"") | J49: =IF($T49=1,IF(INDEX(Entregas!$J$3:$J$14,$S49)="Corrido",F49,IF(DAY(G49)>25,I49,IF(DAY(G49)<3,G49+7,G49))),"") | K49: =IF($T49=1,J49-Parametros!$B$4,"") | N49: =IF(AND($T49=1,L49<>"",M49<>""),J49-L49,"") | O49: =IF(N49="","",IF(N49<0,"desc>venc",IF(N49>INDEX(Parametros!$F$8:$F$9,MATCH(M49,Parametros!$A$8:$A$9,0)),"EXCEDE","ok"))) | P49: =IF(OR(N49="",N49<0),"",E49*(INDEX(Parametros!$B$8:$B$9,MATCH(M49,Parametros!$A$8:$A$9,0))/30)*N49+E49*(INDEX(Parametros!$C$8:$C$9,MATCH(M49,Parametros!$A$8:$A$9,0))*N49+INDEX(Parametros!$D$8:$D$9,MATCH(M49,Parametros!$A$8:$A$9,0)))+INDEX(Parametros!$E$8:$E$9,MATCH(M49,Parametros!$A$8:$A$9,0))) | Q49: =IF(P49="","",E49-P49) | S49: =IFERROR(MATCH($A49,Entregas!$A$3:$A$14,0),"") -> 10 | T49: =IF($S49="",0,IF(AND(INDEX(Entregas!$F$3:$F$14,$S49)<>"",INDEX(Entregas!$F$3:$F$14,$S49)>0,$B49<=INDEX(Entregas!$G$3:$G$14,$S49)),1,0)) -> 0
A50: E10 | B50: 3 | C50: =IF($T50=1,INDEX(Entregas!$B$3:$B$14,$S50),"") | D50: =IF($T50=1,INDEX(Entregas!$C$3:$C$14,$S50),"") | E50: =IF($T50=1,INDEX(Entregas!$F$3:$F$14,$S50)/INDEX(Entregas!$G$3:$G$14,$S50),"") | F50: =IF($T50=1,J49+INDEX(Entregas!$I$3:$I$14,$S50),"") | G50: =IF($T50=1,F50+MOD(1-WEEKDAY(F50,3)+7,7),"") | H50: =IF($T50=1,EOMONTH(F50,0)+1,"") | I50: =IF($T50=1,IF(DAY(H50+MOD(1-WEEKDAY(H50,3)+7,7))<3,H50+MOD(1-WEEKDAY(H50,3)+7,7)+7,H50+MOD(1-WEEKDAY(H50,3)+7,7)),"") | J50: =IF($T50=1,IF(INDEX(Entregas!$J$3:$J$14,$S50)="Corrido",F50,IF(DAY(G50)>25,I50,IF(DAY(G50)<3,G50+7,G50))),"") | K50: =IF($T50=1,J50-Parametros!$B$4,"") | N50: =IF(AND($T50=1,L50<>"",M50<>""),J50-L50,"") | O50: =IF(N50="","",IF(N50<0,"desc>venc",IF(N50>INDEX(Parametros!$F$8:$F$9,MATCH(M50,Parametros!$A$8:$A$9,0)),"EXCEDE","ok"))) | P50: =IF(OR(N50="",N50<0),"",E50*(INDEX(Parametros!$B$8:$B$9,MATCH(M50,Parametros!$A$8:$A$9,0))/30)*N50+E50*(INDEX(Parametros!$C$8:$C$9,MATCH(M50,Parametros!$A$8:$A$9,0))*N50+INDEX(Parametros!$D$8:$D$9,MATCH(M50,Parametros!$A$8:$A$9,0)))+INDEX(Parametros!$E$8:$E$9,MATCH(M50,Parametros!$A$8:$A$9,0))) | Q50: =IF(P50="","",E50-P50) | S50: =IFERROR(MATCH($A50,Entregas!$A$3:$A$14,0),"") -> 10 | T50: =IF($S50="",0,IF(AND(INDEX(Entregas!$F$3:$F$14,$S50)<>"",INDEX(Entregas!$F$3:$F$14,$S50)>0,$B50<=INDEX(Entregas!$G$3:$G$14,$S50)),1,0)) -> 0
A51: E10 | B51: 4 | C51: =IF($T51=1,INDEX(Entregas!$B$3:$B$14,$S51),"") | D51: =IF($T51=1,INDEX(Entregas!$C$3:$C$14,$S51),"") | E51: =IF($T51=1,INDEX(Entregas!$F$3:$F$14,$S51)/INDEX(Entregas!$G$3:$G$14,$S51),"") | F51: =IF($T51=1,J50+INDEX(Entregas!$I$3:$I$14,$S51),"") | G51: =IF($T51=1,F51+MOD(1-WEEKDAY(F51,3)+7,7),"") | H51: =IF($T51=1,EOMONTH(F51,0)+1,"") | I51: =IF($T51=1,IF(DAY(H51+MOD(1-WEEKDAY(H51,3)+7,7))<3,H51+MOD(1-WEEKDAY(H51,3)+7,7)+7,H51+MOD(1-WEEKDAY(H51,3)+7,7)),"") | J51: =IF($T51=1,IF(INDEX(Entregas!$J$3:$J$14,$S51)="Corrido",F51,IF(DAY(G51)>25,I51,IF(DAY(G51)<3,G51+7,G51))),"") | K51: =IF($T51=1,J51-Parametros!$B$4,"") | N51: =IF(AND($T51=1,L51<>"",M51<>""),J51-L51,"") | O51: =IF(N51="","",IF(N51<0,"desc>venc",IF(N51>INDEX(Parametros!$F$8:$F$9,MATCH(M51,Parametros!$A$8:$A$9,0)),"EXCEDE","ok"))) | P51: =IF(OR(N51="",N51<0),"",E51*(INDEX(Parametros!$B$8:$B$9,MATCH(M51,Parametros!$A$8:$A$9,0))/30)*N51+E51*(INDEX(Parametros!$C$8:$C$9,MATCH(M51,Parametros!$A$8:$A$9,0))*N51+INDEX(Parametros!$D$8:$D$9,MATCH(M51,Parametros!$A$8:$A$9,0)))+INDEX(Parametros!$E$8:$E$9,MATCH(M51,Parametros!$A$8:$A$9,0))) | Q51: =IF(P51="","",E51-P51) | S51: =IFERROR(MATCH($A51,Entregas!$A$3:$A$14,0),"") -> 10 | T51: =IF($S51="",0,IF(AND(INDEX(Entregas!$F$3:$F$14,$S51)<>"",INDEX(Entregas!$F$3:$F$14,$S51)>0,$B51<=INDEX(Entregas!$G$3:$G$14,$S51)),1,0)) -> 0
A52: E10 | B52: 5 | C52: =IF($T52=1,INDEX(Entregas!$B$3:$B$14,$S52),"") | D52: =IF($T52=1,INDEX(Entregas!$C$3:$C$14,$S52),"") | E52: =IF($T52=1,INDEX(Entregas!$F$3:$F$14,$S52)/INDEX(Entregas!$G$3:$G$14,$S52),"") | F52: =IF($T52=1,J51+INDEX(Entregas!$I$3:$I$14,$S52),"") | G52: =IF($T52=1,F52+MOD(1-WEEKDAY(F52,3)+7,7),"") | H52: =IF($T52=1,EOMONTH(F52,0)+1,"") | I52: =IF($T52=1,IF(DAY(H52+MOD(1-WEEKDAY(H52,3)+7,7))<3,H52+MOD(1-WEEKDAY(H52,3)+7,7)+7,H52+MOD(1-WEEKDAY(H52,3)+7,7)),"") | J52: =IF($T52=1,IF(INDEX(Entregas!$J$3:$J$14,$S52)="Corrido",F52,IF(DAY(G52)>25,I52,IF(DAY(G52)<3,G52+7,G52))),"") | K52: =IF($T52=1,J52-Parametros!$B$4,"") | N52: =IF(AND($T52=1,L52<>"",M52<>""),J52-L52,"") | O52: =IF(N52="","",IF(N52<0,"desc>venc",IF(N52>INDEX(Parametros!$F$8:$F$9,MATCH(M52,Parametros!$A$8:$A$9,0)),"EXCEDE","ok"))) | P52: =IF(OR(N52="",N52<0),"",E52*(INDEX(Parametros!$B$8:$B$9,MATCH(M52,Parametros!$A$8:$A$9,0))/30)*N52+E52*(INDEX(Parametros!$C$8:$C$9,MATCH(M52,Parametros!$A$8:$A$9,0))*N52+INDEX(Parametros!$D$8:$D$9,MATCH(M52,Parametros!$A$8:$A$9,0)))+INDEX(Parametros!$E$8:$E$9,MATCH(M52,Parametros!$A$8:$A$9,0))) | Q52: =IF(P52="","",E52-P52) | S52: =IFERROR(MATCH($A52,Entregas!$A$3:$A$14,0),"") -> 10 | T52: =IF($S52="",0,IF(AND(INDEX(Entregas!$F$3:$F$14,$S52)<>"",INDEX(Entregas!$F$3:$F$14,$S52)>0,$B52<=INDEX(Entregas!$G$3:$G$14,$S52)),1,0)) -> 0
A53: E11 | B53: 1 | C53: =IF($T53=1,INDEX(Entregas!$B$3:$B$14,$S53),"") | D53: =IF($T53=1,INDEX(Entregas!$C$3:$C$14,$S53),"") | E53: =IF($T53=1,INDEX(Entregas!$F$3:$F$14,$S53)/INDEX(Entregas!$G$3:$G$14,$S53),"") | F53: =IF($T53=1,INDEX(Entregas!$K$3:$K$14,$S53)+INDEX(Entregas!$H$3:$H$14,$S53),"") | G53: =IF($T53=1,F53+MOD(1-WEEKDAY(F53,3)+7,7),"") | H53: =IF($T53=1,EOMONTH(F53,0)+1,"") | I53: =IF($T53=1,IF(DAY(H53+MOD(1-WEEKDAY(H53,3)+7,7))<3,H53+MOD(1-WEEKDAY(H53,3)+7,7)+7,H53+MOD(1-WEEKDAY(H53,3)+7,7)),"") | J53: =IF($T53=1,IF(INDEX(Entregas!$J$3:$J$14,$S53)="Corrido",F53,IF(DAY(G53)>25,I53,IF(DAY(G53)<3,G53+7,G53))),"") | K53: =IF($T53=1,J53-Parametros!$B$4,"") | N53: =IF(AND($T53=1,L53<>"",M53<>""),J53-L53,"") | O53: =IF(N53="","",IF(N53<0,"desc>venc",IF(N53>INDEX(Parametros!$F$8:$F$9,MATCH(M53,Parametros!$A$8:$A$9,0)),"EXCEDE","ok"))) | P53: =IF(OR(N53="",N53<0),"",E53*(INDEX(Parametros!$B$8:$B$9,MATCH(M53,Parametros!$A$8:$A$9,0))/30)*N53+E53*(INDEX(Parametros!$C$8:$C$9,MATCH(M53,Parametros!$A$8:$A$9,0))*N53+INDEX(Parametros!$D$8:$D$9,MATCH(M53,Parametros!$A$8:$A$9,0)))+INDEX(Parametros!$E$8:$E$9,MATCH(M53,Parametros!$A$8:$A$9,0))) | Q53: =IF(P53="","",E53-P53) | S53: =IFERROR(MATCH($A53,Entregas!$A$3:$A$14,0),"") -> 11 | T53: =IF($S53="",0,IF(AND(INDEX(Entregas!$F$3:$F$14,$S53)<>"",INDEX(Entregas!$F$3:$F$14,$S53)>0,$B53<=INDEX(Entregas!$G$3:$G$14,$S53)),1,0)) -> 0
A54: E11 | B54: 2 | C54: =IF($T54=1,INDEX(Entregas!$B$3:$B$14,$S54),"") | D54: =IF($T54=1,INDEX(Entregas!$C$3:$C$14,$S54),"") | E54: =IF($T54=1,INDEX(Entregas!$F$3:$F$14,$S54)/INDEX(Entregas!$G$3:$G$14,$S54),"") | F54: =IF($T54=1,J53+INDEX(Entregas!$I$3:$I$14,$S54),"") | G54: =IF($T54=1,F54+MOD(1-WEEKDAY(F54,3)+7,7),"") | H54: =IF($T54=1,EOMONTH(F54,0)+1,"") | I54: =IF($T54=1,IF(DAY(H54+MOD(1-WEEKDAY(H54,3)+7,7))<3,H54+MOD(1-WEEKDAY(H54,3)+7,7)+7,H54+MOD(1-WEEKDAY(H54,3)+7,7)),"") | J54: =IF($T54=1,IF(INDEX(Entregas!$J$3:$J$14,$S54)="Corrido",F54,IF(DAY(G54)>25,I54,IF(DAY(G54)<3,G54+7,G54))),"") | K54: =IF($T54=1,J54-Parametros!$B$4,"") | N54: =IF(AND($T54=1,L54<>"",M54<>""),J54-L54,"") | O54: =IF(N54="","",IF(N54<0,"desc>venc",IF(N54>INDEX(Parametros!$F$8:$F$9,MATCH(M54,Parametros!$A$8:$A$9,0)),"EXCEDE","ok"))) | P54: =IF(OR(N54="",N54<0),"",E54*(INDEX(Parametros!$B$8:$B$9,MATCH(M54,Parametros!$A$8:$A$9,0))/30)*N54+E54*(INDEX(Parametros!$C$8:$C$9,MATCH(M54,Parametros!$A$8:$A$9,0))*N54+INDEX(Parametros!$D$8:$D$9,MATCH(M54,Parametros!$A$8:$A$9,0)))+INDEX(Parametros!$E$8:$E$9,MATCH(M54,Parametros!$A$8:$A$9,0))) | Q54: =IF(P54="","",E54-P54) | S54: =IFERROR(MATCH($A54,Entregas!$A$3:$A$14,0),"") -> 11 | T54: =IF($S54="",0,IF(AND(INDEX(Entregas!$F$3:$F$14,$S54)<>"",INDEX(Entregas!$F$3:$F$14,$S54)>0,$B54<=INDEX(Entregas!$G$3:$G$14,$S54)),1,0)) -> 0
A55: E11 | B55: 3 | C55: =IF($T55=1,INDEX(Entregas!$B$3:$B$14,$S55),"") | D55: =IF($T55=1,INDEX(Entregas!$C$3:$C$14,$S55),"") | E55: =IF($T55=1,INDEX(Entregas!$F$3:$F$14,$S55)/INDEX(Entregas!$G$3:$G$14,$S55),"") | F55: =IF($T55=1,J54+INDEX(Entregas!$I$3:$I$14,$S55),"") | G55: =IF($T55=1,F55+MOD(1-WEEKDAY(F55,3)+7,7),"") | H55: =IF($T55=1,EOMONTH(F55,0)+1,"") | I55: =IF($T55=1,IF(DAY(H55+MOD(1-WEEKDAY(H55,3)+7,7))<3,H55+MOD(1-WEEKDAY(H55,3)+7,7)+7,H55+MOD(1-WEEKDAY(H55,3)+7,7)),"") | J55: =IF($T55=1,IF(INDEX(Entregas!$J$3:$J$14,$S55)="Corrido",F55,IF(DAY(G55)>25,I55,IF(DAY(G55)<3,G55+7,G55))),"") | K55: =IF($T55=1,J55-Parametros!$B$4,"") | N55: =IF(AND($T55=1,L55<>"",M55<>""),J55-L55,"") | O55: =IF(N55="","",IF(N55<0,"desc>venc",IF(N55>INDEX(Parametros!$F$8:$F$9,MATCH(M55,Parametros!$A$8:$A$9,0)),"EXCEDE","ok"))) | P55: =IF(OR(N55="",N55<0),"",E55*(INDEX(Parametros!$B$8:$B$9,MATCH(M55,Parametros!$A$8:$A$9,0))/30)*N55+E55*(INDEX(Parametros!$C$8:$C$9,MATCH(M55,Parametros!$A$8:$A$9,0))*N55+INDEX(Parametros!$D$8:$D$9,MATCH(M55,Parametros!$A$8:$A$9,0)))+INDEX(Parametros!$E$8:$E$9,MATCH(M55,Parametros!$A$8:$A$9,0))) | Q55: =IF(P55="","",E55-P55) | S55: =IFERROR(MATCH($A55,Entregas!$A$3:$A$14,0),"") -> 11 | T55: =IF($S55="",0,IF(AND(INDEX(Entregas!$F$3:$F$14,$S55)<>"",INDEX(Entregas!$F$3:$F$14,$S55)>0,$B55<=INDEX(Entregas!$G$3:$G$14,$S55)),1,0)) -> 0
A56: E11 | B56: 4 | C56: =IF($T56=1,INDEX(Entregas!$B$3:$B$14,$S56),"") | D56: =IF($T56=1,INDEX(Entregas!$C$3:$C$14,$S56),"") | E56: =IF($T56=1,INDEX(Entregas!$F$3:$F$14,$S56)/INDEX(Entregas!$G$3:$G$14,$S56),"") | F56: =IF($T56=1,J55+INDEX(Entregas!$I$3:$I$14,$S56),"") | G56: =IF($T56=1,F56+MOD(1-WEEKDAY(F56,3)+7,7),"") | H56: =IF($T56=1,EOMONTH(F56,0)+1,"") | I56: =IF($T56=1,IF(DAY(H56+MOD(1-WEEKDAY(H56,3)+7,7))<3,H56+MOD(1-WEEKDAY(H56,3)+7,7)+7,H56+MOD(1-WEEKDAY(H56,3)+7,7)),"") | J56: =IF($T56=1,IF(INDEX(Entregas!$J$3:$J$14,$S56)="Corrido",F56,IF(DAY(G56)>25,I56,IF(DAY(G56)<3,G56+7,G56))),"") | K56: =IF($T56=1,J56-Parametros!$B$4,"") | N56: =IF(AND($T56=1,L56<>"",M56<>""),J56-L56,"") | O56: =IF(N56="","",IF(N56<0,"desc>venc",IF(N56>INDEX(Parametros!$F$8:$F$9,MATCH(M56,Parametros!$A$8:$A$9,0)),"EXCEDE","ok"))) | P56: =IF(OR(N56="",N56<0),"",E56*(INDEX(Parametros!$B$8:$B$9,MATCH(M56,Parametros!$A$8:$A$9,0))/30)*N56+E56*(INDEX(Parametros!$C$8:$C$9,MATCH(M56,Parametros!$A$8:$A$9,0))*N56+INDEX(Parametros!$D$8:$D$9,MATCH(M56,Parametros!$A$8:$A$9,0)))+INDEX(Parametros!$E$8:$E$9,MATCH(M56,Parametros!$A$8:$A$9,0))) | Q56: =IF(P56="","",E56-P56) | S56: =IFERROR(MATCH($A56,Entregas!$A$3:$A$14,0),"") -> 11 | T56: =IF($S56="",0,IF(AND(INDEX(Entregas!$F$3:$F$14,$S56)<>"",INDEX(Entregas!$F$3:$F$14,$S56)>0,$B56<=INDEX(Entregas!$G$3:$G$14,$S56)),1,0)) -> 0
A57: E11 | B57: 5 | C57: =IF($T57=1,INDEX(Entregas!$B$3:$B$14,$S57),"") | D57: =IF($T57=1,INDEX(Entregas!$C$3:$C$14,$S57),"") | E57: =IF($T57=1,INDEX(Entregas!$F$3:$F$14,$S57)/INDEX(Entregas!$G$3:$G$14,$S57),"") | F57: =IF($T57=1,J56+INDEX(Entregas!$I$3:$I$14,$S57),"") | G57: =IF($T57=1,F57+MOD(1-WEEKDAY(F57,3)+7,7),"") | H57: =IF($T57=1,EOMONTH(F57,0)+1,"") | I57: =IF($T57=1,IF(DAY(H57+MOD(1-WEEKDAY(H57,3)+7,7))<3,H57+MOD(1-WEEKDAY(H57,3)+7,7)+7,H57+MOD(1-WEEKDAY(H57,3)+7,7)),"") | J57: =IF($T57=1,IF(INDEX(Entregas!$J$3:$J$14,$S57)="Corrido",F57,IF(DAY(G57)>25,I57,IF(DAY(G57)<3,G57+7,G57))),"") | K57: =IF($T57=1,J57-Parametros!$B$4,"") | N57: =IF(AND($T57=1,L57<>"",M57<>""),J57-L57,"") | O57: =IF(N57="","",IF(N57<0,"desc>venc",IF(N57>INDEX(Parametros!$F$8:$F$9,MATCH(M57,Parametros!$A$8:$A$9,0)),"EXCEDE","ok"))) | P57: =IF(OR(N57="",N57<0),"",E57*(INDEX(Parametros!$B$8:$B$9,MATCH(M57,Parametros!$A$8:$A$9,0))/30)*N57+E57*(INDEX(Parametros!$C$8:$C$9,MATCH(M57,Parametros!$A$8:$A$9,0))*N57+INDEX(Parametros!$D$8:$D$9,MATCH(M57,Parametros!$A$8:$A$9,0)))+INDEX(Parametros!$E$8:$E$9,MATCH(M57,Parametros!$A$8:$A$9,0))) | Q57: =IF(P57="","",E57-P57) | S57: =IFERROR(MATCH($A57,Entregas!$A$3:$A$14,0),"") -> 11 | T57: =IF($S57="",0,IF(AND(INDEX(Entregas!$F$3:$F$14,$S57)<>"",INDEX(Entregas!$F$3:$F$14,$S57)>0,$B57<=INDEX(Entregas!$G$3:$G$14,$S57)),1,0)) -> 0
A58: E12 | B58: 1 | C58: =IF($T58=1,INDEX(Entregas!$B$3:$B$14,$S58),"") | D58: =IF($T58=1,INDEX(Entregas!$C$3:$C$14,$S58),"") | E58: =IF($T58=1,INDEX(Entregas!$F$3:$F$14,$S58)/INDEX(Entregas!$G$3:$G$14,$S58),"") | F58: =IF($T58=1,INDEX(Entregas!$K$3:$K$14,$S58)+INDEX(Entregas!$H$3:$H$14,$S58),"") | G58: =IF($T58=1,F58+MOD(1-WEEKDAY(F58,3)+7,7),"") | H58: =IF($T58=1,EOMONTH(F58,0)+1,"") | I58: =IF($T58=1,IF(DAY(H58+MOD(1-WEEKDAY(H58,3)+7,7))<3,H58+MOD(1-WEEKDAY(H58,3)+7,7)+7,H58+MOD(1-WEEKDAY(H58,3)+7,7)),"") | J58: =IF($T58=1,IF(INDEX(Entregas!$J$3:$J$14,$S58)="Corrido",F58,IF(DAY(G58)>25,I58,IF(DAY(G58)<3,G58+7,G58))),"") | K58: =IF($T58=1,J58-Parametros!$B$4,"") | N58: =IF(AND($T58=1,L58<>"",M58<>""),J58-L58,"") | O58: =IF(N58="","",IF(N58<0,"desc>venc",IF(N58>INDEX(Parametros!$F$8:$F$9,MATCH(M58,Parametros!$A$8:$A$9,0)),"EXCEDE","ok"))) | P58: =IF(OR(N58="",N58<0),"",E58*(INDEX(Parametros!$B$8:$B$9,MATCH(M58,Parametros!$A$8:$A$9,0))/30)*N58+E58*(INDEX(Parametros!$C$8:$C$9,MATCH(M58,Parametros!$A$8:$A$9,0))*N58+INDEX(Parametros!$D$8:$D$9,MATCH(M58,Parametros!$A$8:$A$9,0)))+INDEX(Parametros!$E$8:$E$9,MATCH(M58,Parametros!$A$8:$A$9,0))) | Q58: =IF(P58="","",E58-P58) | S58: =IFERROR(MATCH($A58,Entregas!$A$3:$A$14,0),"") -> 12 | T58: =IF($S58="",0,IF(AND(INDEX(Entregas!$F$3:$F$14,$S58)<>"",INDEX(Entregas!$F$3:$F$14,$S58)>0,$B58<=INDEX(Entregas!$G$3:$G$14,$S58)),1,0)) -> 0
A59: E12 | B59: 2 | C59: =IF($T59=1,INDEX(Entregas!$B$3:$B$14,$S59),"") | D59: =IF($T59=1,INDEX(Entregas!$C$3:$C$14,$S59),"") | E59: =IF($T59=1,INDEX(Entregas!$F$3:$F$14,$S59)/INDEX(Entregas!$G$3:$G$14,$S59),"") | F59: =IF($T59=1,J58+INDEX(Entregas!$I$3:$I$14,$S59),"") | G59: =IF($T59=1,F59+MOD(1-WEEKDAY(F59,3)+7,7),"") | H59: =IF($T59=1,EOMONTH(F59,0)+1,"") | I59: =IF($T59=1,IF(DAY(H59+MOD(1-WEEKDAY(H59,3)+7,7))<3,H59+MOD(1-WEEKDAY(H59,3)+7,7)+7,H59+MOD(1-WEEKDAY(H59,3)+7,7)),"") | J59: =IF($T59=1,IF(INDEX(Entregas!$J$3:$J$14,$S59)="Corrido",F59,IF(DAY(G59)>25,I59,IF(DAY(G59)<3,G59+7,G59))),"") | K59: =IF($T59=1,J59-Parametros!$B$4,"") | N59: =IF(AND($T59=1,L59<>"",M59<>""),J59-L59,"") | O59: =IF(N59="","",IF(N59<0,"desc>venc",IF(N59>INDEX(Parametros!$F$8:$F$9,MATCH(M59,Parametros!$A$8:$A$9,0)),"EXCEDE","ok"))) | P59: =IF(OR(N59="",N59<0),"",E59*(INDEX(Parametros!$B$8:$B$9,MATCH(M59,Parametros!$A$8:$A$9,0))/30)*N59+E59*(INDEX(Parametros!$C$8:$C$9,MATCH(M59,Parametros!$A$8:$A$9,0))*N59+INDEX(Parametros!$D$8:$D$9,MATCH(M59,Parametros!$A$8:$A$9,0)))+INDEX(Parametros!$E$8:$E$9,MATCH(M59,Parametros!$A$8:$A$9,0))) | Q59: =IF(P59="","",E59-P59) | S59: =IFERROR(MATCH($A59,Entregas!$A$3:$A$14,0),"") -> 12 | T59: =IF($S59="",0,IF(AND(INDEX(Entregas!$F$3:$F$14,$S59)<>"",INDEX(Entregas!$F$3:$F$14,$S59)>0,$B59<=INDEX(Entregas!$G$3:$G$14,$S59)),1,0)) -> 0
A60: E12 | B60: 3 | C60: =IF($T60=1,INDEX(Entregas!$B$3:$B$14,$S60),"") | D60: =IF($T60=1,INDEX(Entregas!$C$3:$C$14,$S60),"") | E60: =IF($T60=1,INDEX(Entregas!$F$3:$F$14,$S60)/INDEX(Entregas!$G$3:$G$14,$S60),"") | F60: =IF($T60=1,J59+INDEX(Entregas!$I$3:$I$14,$S60),"") | G60: =IF($T60=1,F60+MOD(1-WEEKDAY(F60,3)+7,7),"") | H60: =IF($T60=1,EOMONTH(F60,0)+1,"") | I60: =IF($T60=1,IF(DAY(H60+MOD(1-WEEKDAY(H60,3)+7,7))<3,H60+MOD(1-WEEKDAY(H60,3)+7,7)+7,H60+MOD(1-WEEKDAY(H60,3)+7,7)),"") | J60: =IF($T60=1,IF(INDEX(Entregas!$J$3:$J$14,$S60)="Corrido",F60,IF(DAY(G60)>25,I60,IF(DAY(G60)<3,G60+7,G60))),"") | K60: =IF($T60=1,J60-Parametros!$B$4,"") | N60: =IF(AND($T60=1,L60<>"",M60<>""),J60-L60,"") | O60: =IF(N60="","",IF(N60<0,"desc>venc",IF(N60>INDEX(Parametros!$F$8:$F$9,MATCH(M60,Parametros!$A$8:$A$9,0)),"EXCEDE","ok"))) | P60: =IF(OR(N60="",N60<0),"",E60*(INDEX(Parametros!$B$8:$B$9,MATCH(M60,Parametros!$A$8:$A$9,0))/30)*N60+E60*(INDEX(Parametros!$C$8:$C$9,MATCH(M60,Parametros!$A$8:$A$9,0))*N60+INDEX(Parametros!$D$8:$D$9,MATCH(M60,Parametros!$A$8:$A$9,0)))+INDEX(Parametros!$E$8:$E$9,MATCH(M60,Parametros!$A$8:$A$9,0))) | Q60: =IF(P60="","",E60-P60) | S60: =IFERROR(MATCH($A60,Entregas!$A$3:$A$14,0),"") -> 12 | T60: =IF($S60="",0,IF(AND(INDEX(Entregas!$F$3:$F$14,$S60)<>"",INDEX(Entregas!$F$3:$F$14,$S60)>0,$B60<=INDEX(Entregas!$G$3:$G$14,$S60)),1,0)) -> 0
A61: E12 | B61: 4 | C61: =IF($T61=1,INDEX(Entregas!$B$3:$B$14,$S61),"") | D61: =IF($T61=1,INDEX(Entregas!$C$3:$C$14,$S61),"") | E61: =IF($T61=1,INDEX(Entregas!$F$3:$F$14,$S61)/INDEX(Entregas!$G$3:$G$14,$S61),"") | F61: =IF($T61=1,J60+INDEX(Entregas!$I$3:$I$14,$S61),"") | G61: =IF($T61=1,F61+MOD(1-WEEKDAY(F61,3)+7,7),"") | H61: =IF($T61=1,EOMONTH(F61,0)+1,"") | I61: =IF($T61=1,IF(DAY(H61+MOD(1-WEEKDAY(H61,3)+7,7))<3,H61+MOD(1-WEEKDAY(H61,3)+7,7)+7,H61+MOD(1-WEEKDAY(H61,3)+7,7)),"") | J61: =IF($T61=1,IF(INDEX(Entregas!$J$3:$J$14,$S61)="Corrido",F61,IF(DAY(G61)>25,I61,IF(DAY(G61)<3,G61+7,G61))),"") | K61: =IF($T61=1,J61-Parametros!$B$4,"") | N61: =IF(AND($T61=1,L61<>"",M61<>""),J61-L61,"") | O61: =IF(N61="","",IF(N61<0,"desc>venc",IF(N61>INDEX(Parametros!$F$8:$F$9,MATCH(M61,Parametros!$A$8:$A$9,0)),"EXCEDE","ok"))) | P61: =IF(OR(N61="",N61<0),"",E61*(INDEX(Parametros!$B$8:$B$9,MATCH(M61,Parametros!$A$8:$A$9,0))/30)*N61+E61*(INDEX(Parametros!$C$8:$C$9,MATCH(M61,Parametros!$A$8:$A$9,0))*N61+INDEX(Parametros!$D$8:$D$9,MATCH(M61,Parametros!$A$8:$A$9,0)))+INDEX(Parametros!$E$8:$E$9,MATCH(M61,Parametros!$A$8:$A$9,0))) | Q61: =IF(P61="","",E61-P61) | S61: =IFERROR(MATCH($A61,Entregas!$A$3:$A$14,0),"") -> 12 | T61: =IF($S61="",0,IF(AND(INDEX(Entregas!$F$3:$F$14,$S61)<>"",INDEX(Entregas!$F$3:$F$14,$S61)>0,$B61<=INDEX(Entregas!$G$3:$G$14,$S61)),1,0)) -> 0
A62: E12 | B62: 5 | C62: =IF($T62=1,INDEX(Entregas!$B$3:$B$14,$S62),"") | D62: =IF($T62=1,INDEX(Entregas!$C$3:$C$14,$S62),"") | E62: =IF($T62=1,INDEX(Entregas!$F$3:$F$14,$S62)/INDEX(Entregas!$G$3:$G$14,$S62),"") | F62: =IF($T62=1,J61+INDEX(Entregas!$I$3:$I$14,$S62),"") | G62: =IF($T62=1,F62+MOD(1-WEEKDAY(F62,3)+7,7),"") | H62: =IF($T62=1,EOMONTH(F62,0)+1,"") | I62: =IF($T62=1,IF(DAY(H62+MOD(1-WEEKDAY(H62,3)+7,7))<3,H62+MOD(1-WEEKDAY(H62,3)+7,7)+7,H62+MOD(1-WEEKDAY(H62,3)+7,7)),"") | J62: =IF($T62=1,IF(INDEX(Entregas!$J$3:$J$14,$S62)="Corrido",F62,IF(DAY(G62)>25,I62,IF(DAY(G62)<3,G62+7,G62))),"") | K62: =IF($T62=1,J62-Parametros!$B$4,"") | N62: =IF(AND($T62=1,L62<>"",M62<>""),J62-L62,"") | O62: =IF(N62="","",IF(N62<0,"desc>venc",IF(N62>INDEX(Parametros!$F$8:$F$9,MATCH(M62,Parametros!$A$8:$A$9,0)),"EXCEDE","ok"))) | P62: =IF(OR(N62="",N62<0),"",E62*(INDEX(Parametros!$B$8:$B$9,MATCH(M62,Parametros!$A$8:$A$9,0))/30)*N62+E62*(INDEX(Parametros!$C$8:$C$9,MATCH(M62,Parametros!$A$8:$A$9,0))*N62+INDEX(Parametros!$D$8:$D$9,MATCH(M62,Parametros!$A$8:$A$9,0)))+INDEX(Parametros!$E$8:$E$9,MATCH(M62,Parametros!$A$8:$A$9,0))) | Q62: =IF(P62="","",E62-P62) | S62: =IFERROR(MATCH($A62,Entregas!$A$3:$A$14,0),"") -> 12 | T62: =IF($S62="",0,IF(AND(INDEX(Entregas!$F$3:$F$14,$S62)<>"",INDEX(Entregas!$F$3:$F$14,$S62)>0,$B62<=INDEX(Entregas!$G$3:$G$14,$S62)),1,0)) -> 0
D64: TOTAIS → | E64: =SUM(E3:E62) -> 2021655 | P64: =SUM(P3:P62) -> 0 | Q64: =SUM(Q3:Q62) -> 0

Sheet Resumo
A1: RESUMO
A3: Por funder
A4: Funder | B4: Face descontada | C4: Valor líquido | D4: Teto | E4: Utilização
A5: Itaú | B5: =SUMIFS(Parcelas!$E$3:$E$62,Parcelas!$M$3:$M$62,A5) -> 0 | C5: =SUMIFS(Parcelas!$Q$3:$Q$62,Parcelas!$M$3:$M$62,A5) -> 0 | D5: =INDEX(Parametros!$G$8:$G$9,MATCH(A5,Parametros!$A$8:$A$9,0)) -> 650000 | E5: =IF(D5=0,"",B5/D5) -> 0
A6: Ghia | B6: =SUMIFS(Parcelas!$E$3:$E$62,Parcelas!$M$3:$M$62,A6) -> 0 | C6: =SUMIFS(Parcelas!$Q$3:$Q$62,Parcelas!$M$3:$M$62,A6) -> 0 | D6: =INDEX(Parametros!$G$8:$G$9,MATCH(A6,Parametros!$A$8:$A$9,0)) -> 500000 | E6: =IF(D6=0,"",B6/D6) -> 0
A8: Total negociado | B8: =Entregas!F16 -> 2021655
A9: Total descontado (face) | B9: =SUM(B5:B6) -> 0
A10: Total líquido a receber | B10: =SUM(C5:C6) -> 0

Sheet Leia-me
A1: COMO USAR
A3: Células AMARELAS = editáveis. As demais são fórmulas — não edite.
A5: 1) Aba ENTREGAS: uma linha por entrega negociada (E01..E12).
A6: Preencha: Cliente, Produto, Qtd, Preço unit., Nº parcelas, 1ª parcela (dias),
A7: Intervalo (dias), Calendário, Data entrega, Status. 'Total' é calculado.
A8: Calendário = 'Corrido' (vence exatamente em entrega+prazo) ou
A9: 'Terça 3-25' (vencimento cai na 1ª terça-feira, entre dias 3 e 25; se passar do 25,
A10: empurra p/ 1ª terça do mês seguinte). UAUBox = Corrido; B4A = Terça 3-25.
A12: 2) Aba PARCELAS: gerada automaticamente (5 linhas por entrega; sobra some sozinha).
A13: Vencimento é calculado de Data entrega + prazos + Calendário.
A14: Edite só: Data desconto e Funder (amarelo). O resto calcula:
A15: Tenor (dias desconto→vencimento), Tenor OK? (vs limite do funder),
... A28: Teto/uso Itaú ainda não verificados. Vencimentos assumem regra informada, não o contrato.
